Workbook

Sheet CrossfireHiddenWorksheet
A3: 7f9cd215-a3a3-4337-9d33-54c7f7ced498 | B3: d0c5ccc1-ca05-4a09-8a05-3d3e017a4a48 | C3: fb462344-2b2e-4473-8e11-78fc35a5a303 | D3: af0d0bab-9df8-47f4-a1b4-6d5c796d9b40 | E3: d4b1939f-8d75-468e-9394-92558626264e
A4: 1 | B4: 7 | C4: 25 | D4: 31 | E4: 109
A5: =IS!$10:$10 -> 0 | B5: 1 | C5: =IS!$C:$C -> 0 | D5: 1249 | E5: =IS!$B$3 -> 77712 - Wentworth (Vacaville, CA) | F5: 418 | G5: =BS!$10:$10 -> 0 | H5: 1 | I5: =BS!$H:$H -> 0 | J5: 19 | K5: =BS!$B$3 -> 77712 - Wentworth (Vacaville, CA) | L5: 16 | Y5: =YOY!$10:$10 -> 0 | Z5: 1 | AA5: =YOY!$E:$E -> 0 | AB5: 64 | AC5: =YOY!$B$3 -> 77712 - Wentworth (Vacaville, CA) | AD5: 62 | AE5: ='Act v Bud'!$10:$10 -> 0 | AF5: 1 | AG5: ='Act v Bud'!$D:$D -> 0 | AH5: 30 | AI5: ='Act v Bud'!$B$3 -> 77712 - Wentworth (Vacaville, CA) | AJ5: 35 | DE5: ='IS.BS.Detail'!$49:$49 -> 0 | DF5: 1 | DG5: ='IS.BS.Detail'!$B:$B -> 0 | DH5: 238 | DI5: ='IS.BS.Detail'!$A$3 -> 77712 - Wentworth (Vacaville, CA) | DJ5: 250
A6: =IS!$11:$11 -> 0 | B6: 2 | C6: =IS!$D:$D -> 0 | D6: 1250 | E6: =IS!$B$4 -> 1/31/2026 | F6: 503 | G6: =BS!$11:$11 -> 0 | H6: 2 | I6: =BS!$E:$E -> 0 | J6: 20 | K6: =BS!$B$4 -> 1/31/2026 | L6: 23 | Y6: =YOY!$11:$11 -> 0 | Z6: 2 | AA6: =YOY!$D:$D -> MTD | AB6: 65 | AC6: =YOY!$B$4 -> 1/31/2026 | AD6: 63 | AE6: ='Act v Bud'!$11:$11 -> 0 | AF6: 2 | AG6: ='Act v Bud'!$I:$I -> QTD | AH6: 31 | AI6: ='Act v Bud'!$B$4 -> 1/31/2026 | AJ6: 36 | DE6: ='IS.BS.Detail'!$64:$64 -> 0 | DF6: 2 | DG6: ='IS.BS.Detail'!$C:$C -> Mar-2025 | DH6: 239 | DI6: ='IS.BS.Detail'!$A$4 -> 1/31/2026 | DJ6: 252
A7: =IS!$12:$12 -> 0 | B7: 3 | C7: =IS!$E:$E -> Apr-2025 | D7: 1251 | E7: =IS!$C$7 -> Feb-2025 | F7: 1261 | G7: =BS!$12:$12 -> 0 | H7: 3 | I7: =BS!$I:$I -> Dec-2025 | J7: 21 | K7: =BS!$D$7 -> Jan-2026 | L7: 24 | Y7: =YOY!$12:$12 -> 0 | Z7: 3 | AA7: =YOY!$I:$I -> Jan-2026 | AB7: 66 | AC7: =YOY!$D$7 -> Jan-2026 | AD7: 70 | AE7: ='Act v Bud'!$12:$12 -> 0 | AF7: 3 | AG7: ='Act v Bud'!$N:$N -> Actual | AH7: 33 | DE7: ='IS.BS.Detail'!$59:$59 -> 0 | DF7: 3 | DG7: ='IS.BS.Detail'!$D:$D -> 0 | DH7: 240 | DI7: ='IS.BS.Detail'!$B$6 -> Feb-2025 | DJ7: 289
A8: =IS!$13:$13 -> 0 | B8: 4 | C8: =IS!$F:$F -> 0 | D8: 1252 | E8: =IS!$D$7 -> Mar-2025 | F8: 1262 | G8: =BS!$13:$13 -> 0 | H8: 4 | I8: =BS!$D:$D -> 0 | J8: 22 | K8: =BS!$E$7 -> Dec-2025 | L8: 25 | Y8: =YOY!$13:$13 -> 0 | Z8: 4 | AA8: =YOY!$N:$N -> 0 | AB8: 77 | AC8: =YOY!$E$7 -> Jan-2025 | AD8: 71 | AE8: ='Act v Bud'!$13:$13 -> 0 | AF8: 4 | AG8: ='Act v Bud'!$O:$O -> 0 | AH8: 34 | DE8: ='IS.BS.Detail'!$57:$57 -> 0 | DF8: 4 | DG8: ='IS.BS.Detail'!$E:$E -> 109356.15 | DH8: 241 | DI8: ='IS.BS.Detail'!$C$6 -> Mar-2025 | DJ8: 290
A9: =IS!$17:$17 -> 0 | B9: 759 | C9: =IS!$G:$G -> 0 | D9: 1253 | E9: =IS!$E$7 -> Apr-2025 | F9: 1263 | G9: =BS!$14:$14 -> 0 | H9: 5 | K9: =BS!$H$7 -> Jan-2026 | L9: 26 | Y9: =YOY!$17:$17 -> 0 | Z9: 5 | AA9: =YOY!$J:$J -> 0 | AB9: 78 | AC9: =YOY!$I$7 -> Jan-2026 | AD9: 72 | AE9: ='Act v Bud'!$17:$17 -> 0 | AF9: 5 | AG9: ='Act v Bud'!$E:$E -> 0 | AH9: 45 | DE9: ='IS.BS.Detail'!$13:$13 -> 0 | DF9: 5 | DG9: ='IS.BS.Detail'!$F:$F -> 101771.71 | DH9: 242 | DI9: ='IS.BS.Detail'!$D$6 -> Apr-2025 | DJ9: 291
A10: =IS!$18:$18 -> 0 | B10: 760 | C10: =IS!$H:$H -> 72813.54 | D10: 1254 | E10: =IS!$F$7 -> May-2025 | F10: 1264 | G10: =BS!$15:$15 -> 0 | H10: 6 | K10: =BS!$I$7 -> Dec-2025 | L10: 27 | Y10: =YOY!$18:$18 -> 0 | Z10: 6 | AA10: =YOY!$O:$O -> 34544.2 | AB10: 79 | AC10: =YOY!$J$7 -> Jan-2025 | AD10: 73 | AE10: ='Act v Bud'!$18:$18 -> 0 | AF10: 6 | AG10: ='Act v Bud'!$J:$J -> 87063.195 | AH10: 46 | DE10: ='IS.BS.Detail'!$10:$10 -> 0 | DF10: 6 | DG10: ='IS.BS.Detail'!$G:$G -> 2227.33 | DH10: 243 | DI10: ='IS.BS.Detail'!$E$6 -> May-2025 | DJ10: 292
A11: =IS!$19:$19 -> 0 | B11: 761 | C11: =IS!$I:$I -> 3144 | D11: 1255 | E11: =IS!$G$7 -> Jun-2025 | F11: 1265 | G11: =BS!$16:$16 -> 0 | H11: 7 | Y11: =YOY!$19:$19 -> 0 | Z11: 7 | AC11: =YOY!$N$7 -> Jan-2026 | AD11: 74 | AE11: ='Act v Bud'!$19:$19 -> 0 | AF11: 7 | DE11: ='IS.BS.Detail'!$8:$8 -> 0 | DF11: 7 | DG11: ='IS.BS.Detail'!$H:$H -> 1700.32 | DH11: 244 | DI11: ='IS.BS.Detail'!$F$6 -> Jun-2025 | DJ11: 293
A12: =IS!$23:$23 -> 0 | B12: 762 | C12: =IS!$J:$J -> 619.78 | D12: 1256 | E12: =IS!$H$7 -> Jul-2025 | F12: 1266 | G12: =BS!$20:$20 -> 0 | H12: 8 | Y12: =YOY!$23:$23 -> 0 | Z12: 8 | AC12: =YOY!$O$7 -> Jan-2025 | AD12: 75 | AE12: ='Act v Bud'!$23:$23 -> 0 | AF12: 8 | DE12: ='IS.BS.Detail'!$77:$77 -> 0 | DF12: 8 | DG12: ='IS.BS.Detail'!$I:$I -> 221.36 | DH12: 245 | DI12: ='IS.BS.Detail'!$G$6 -> Jul-2025 | DJ12: 294
A13: =IS!$24:$24 -> 0 | B13: 763 | C13: =IS!$K:$K -> 4286.87 | D13: 1257 | E13: =IS!$I$7 -> Aug-2025 | F13: 1267 | G13: =BS!$21:$21 -> 0 | H13: 9 | Y13: =YOY!$24:$24 -> 0 | Z13: 9 | AE13: ='Act v Bud'!$24:$24 -> 0 | AF13: 9 | DE13: ='IS.BS.Detail'!$80:$80 -> 0 | DF13: 9 | DG13: ='IS.BS.Detail'!$J:$J -> 3694.97 | DH13: 246 | DI13: ='IS.BS.Detail'!$H$6 -> Aug-2025 | DJ13: 295
A14: =IS!$25:$25 -> 0 | B14: 764 | C14: =IS!$L:$L -> 91791.12 | D14: 1258 | E14: =IS!$J$7 -> Sep-2025 | F14: 1268 | G14: =BS!$22:$22 -> 0 | H14: 10 | Y14: =YOY!$25:$25 -> 0 | Z14: 10 | AE14: ='Act v Bud'!$25:$25 -> 0 | AF14: 10 | DE14: ='IS.BS.Detail'!$82:$82 -> 0 | DF14: 10 | DG14: ='IS.BS.Detail'!$K:$K -> 1925.32 | DH14: 247 | DI14: ='IS.BS.Detail'!$I$6 -> Sep-2025 | DJ14: 296
A15: =IS!$27:$27 -> 0 | B15: 765 | C15: =IS!$M:$M -> 0 | D15: 1259 | E15: =IS!$K$7 -> Oct-2025 | F15: 1269 | G15: =BS!$23:$23 -> 0 | H15: 11 | Y15: =YOY!$27:$27 -> 0 | Z15: 11 | AE15: ='Act v Bud'!$27:$27 -> 0 | AF15: 11 | DE15: ='IS.BS.Detail'!$85:$85 -> 0 | DF15: 13 | DG15: ='IS.BS.Detail'!$L:$L -> 605.39 | DH15: 248 | DI15: ='IS.BS.Detail'!$J$6 -> Oct-2025 | DJ15: 297
A16: =IS!$28:$28 -> 0 | B16: 766 | C16: =IS!$N:$N -> 0 | D16: 1260 | E16: =IS!$L$7 -> Nov-2025 | F16: 1270 | G16: =BS!$25:$25 -> 0 | H16: 12 | Y16: =YOY!$28:$28 -> 0 | Z16: 12 | AE16: ='Act v Bud'!$28:$28 -> 0 | AF16: 12 | DE16: ='IS.BS.Detail'!$94:$94 -> 0 | DF16: 14 | DG16: ='IS.BS.Detail'!$M:$M -> 1287.44 | DH16: 249 | DI16: ='IS.BS.Detail'!$K$6 -> Nov-2025 | DJ16: 298
A17: =IS!$29:$29 -> 0 | B17: 767 | C17: =IS!$O:$O -> 299 | D17: 1276 | E17: =IS!$M$7 -> Dec-2025 | F17: 1271 | G17: =BS!$29:$29 -> 0 | H17: 13 | Y17: =YOY!$29:$29 -> 0 | Z17: 13 | AE17: ='Act v Bud'!$29:$29 -> 0 | AF17: 13 | DE17: ='IS.BS.Detail'!$121:$121 -> 0 | DF17: 15 | DI17: ='IS.BS.Detail'!$L$6 -> Dec-2025 | DJ17: 299
A18: =IS!$30:$30 -> 0 | B18: 768 | E18: =IS!$N$7 -> Jan-2026 | F18: 1272 | G18: =BS!$30:$30 -> 0 | H18: 14 | Y18: =YOY!$30:$30 -> 0 | Z18: 14 | AE18: ='Act v Bud'!$30:$30 -> 0 | AF18: 14 | DE18: ='IS.BS.Detail'!$124:$124 -> 0 | DF18: 16 | DI18: ='IS.BS.Detail'!$M$6 -> Jan-2026 | DJ18: 300
A19: =IS!$31:$31 -> 0 | B19: 769 | E19: =IS!$O$7 -> Jan-2026 YTD | F19: 1277 | G19: =BS!$31:$31 -> 0 | H19: 15 | Y19: =YOY!$31:$31 -> 0 | Z19: 15 | AE19: ='Act v Bud'!$31:$31 -> 0 | AF19: 15 | DE19: ='IS.BS.Detail'!$129:$129 -> 0 | DF19: 17
A20: =IS!$32:$32 -> 0 | B20: 770 | Y20: =YOY!$32:$32 -> 0 | Z20: 16 | AE20: ='Act v Bud'!$32:$32 -> 0 | AF20: 16 | DE20: ='IS.BS.Detail'!$165:$165 -> 0 | DF20: 18
A21: =IS!$33:$33 -> 0 | B21: 771 | Y21: =YOY!$33:$33 -> 0 | Z21: 17 | AE21: ='Act v Bud'!$33:$33 -> 0 | AF21: 17 | DE21: ='IS.BS.Detail'!$168:$168 -> 0 | DF21: 19
A22: =IS!$34:$34 -> 0 | B22: 772 | Y22: =YOY!$34:$34 -> 0 | Z22: 18 | AE22: ='Act v Bud'!$34:$34 -> 0 | AF22: 18 | DE22: ='IS.BS.Detail'!$173:$173 -> 0 | DF22: 20
A23: =IS!$35:$35 -> 0 | B23: 773 | Y23: =YOY!$35:$35 -> 0 | Z23: 19 | AE23: ='Act v Bud'!$35:$35 -> 0 | AF23: 19 | DE23: ='IS.BS.Detail'!$175:$175 -> 0 | DF23: 21
A24: =IS!$36:$36 -> 0 | B24: 774 | Y24: =YOY!$36:$36 -> 0 | Z24: 20 | AE24: ='Act v Bud'!$36:$36 -> 0 | AF24: 20 | DE24: ='IS.BS.Detail'!$178:$178 -> 0 | DF24: 22
A25: =IS!$44:$44 -> 0 | B25: 875 | Y25: =YOY!$44:$44 -> 0 | Z25: 21 | AE25: ='Act v Bud'!$44:$44 -> 0 | AF25: 21 | DE25: ='IS.BS.Detail'!$180:$180 -> 0 | DF25: 23
A26: =IS!$45:$45 -> 0 | B26: 876 | Y26: =YOY!$45:$45 -> 0 | Z26: 22 | AE26: ='Act v Bud'!$45:$45 -> 0 | AF26: 22 | DE26: ='IS.BS.Detail'!$182:$182 -> 0 | DF26: 24
A27: =IS!$46:$46 -> 0 | B27: 877 | Y27: =YOY!$46:$46 -> 0 | Z27: 23 | AE27: ='Act v Bud'!$46:$46 -> 0 | AF27: 23 | DE27: ='IS.BS.Detail'!$189:$189 -> 0 | DF27: 25
A28: =IS!$47:$47 -> 0 | B28: 878 | Y28: =YOY!$47:$47 -> 0 | Z28: 24 | AE28: ='Act v Bud'!$47:$47 -> 0 | AF28: 24 | DE28: ='IS.BS.Detail'!$191:$191 -> 0 | DF28: 26
A29: =IS!$48:$48 -> 0 | B29: 879 | Y29: =YOY!$48:$48 -> 0 | Z29: 25 | AE29: ='Act v Bud'!$48:$48 -> 0 | AF29: 25 | DE29: ='IS.BS.Detail'!$20:$20 -> 0 | DF29: 28
A30: =IS!$49:$49 -> 0 | B30: 880 | Y30: =YOY!$49:$49 -> 0 | Z30: 26 | AE30: ='Act v Bud'!$49:$49 -> 0 | AF30: 26 | DE30: ='IS.BS.Detail'!$19:$19 -> 0 | DF30: 29
A31: =IS!$50:$50 -> 0 | B31: 881 | Y31: =YOY!$50:$50 -> 0 | Z31: 27 | AE31: ='Act v Bud'!$50:$50 -> 0 | AF31: 27 | DE31: ='IS.BS.Detail'!$18:$18 -> 0 | DF31: 30
A32: =IS!$51:$51 -> 0 | B32: 882 | Y32: =YOY!$51:$51 -> 0 | Z32: 28 | AE32: ='Act v Bud'!$51:$51 -> 0 | AF32: 28 | DE32: ='IS.BS.Detail'!$38:$38 -> 0 | DF32: 31
A33: =IS!$62:$62 -> 0 | B33: 883 | Y33: =YOY!$26:$26 -> 0 | Z33: 76 | AE33: ='Act v Bud'!$26:$26 -> 0 | AF33: 43 | DE33: ='IS.BS.Detail'!$35:$35 -> 0 | DF33: 32
A34: =IS!$63:$63 -> 0 | B34: 884 | DE34: ='IS.BS.Detail'!$36:$36 -> 0 | DF34: 33
A35: =IS!$64:$64 -> 0 | B35: 885 | DE35: ='IS.BS.Detail'!$45:$45 -> 0 | DF35: 36
A36: =IS!$65:$65 -> 0 | B36: 886 | DE36: ='IS.BS.Detail'!$43:$43 -> 0 | DF36: 37
A37: =IS!$66:$66 -> 0 | B37: 887 | DE37: ='IS.BS.Detail'!$194:$194 -> 0 | DF37: 38
A38: =IS!$67:$67 -> 0 | B38: 888 | DE38: ='IS.BS.Detail'!$195:$195 -> 0 | DF38: 39
A39: =IS!$69:$69 -> 0 | B39: 890 | DE39: ='IS.BS.Detail'!$197:$197 -> 0 | DF39: 40
A40: =IS!$72:$72 -> 0 | B40: 891 | DE40: ='IS.BS.Detail'!$198:$198 -> 0 | DF40: 41
A41: =IS!$71:$71 -> 0 | B41: 892 | DE41: ='IS.BS.Detail'!$199:$199 -> 0 | DF41: 42
A42: =IS!$26:$26 -> 0 | B42: 893 | DE42: ='IS.BS.Detail'!$201:$201 -> 0 | DF42: 43
A43: =IS!$68:$68 -> 0 | B43: 1571 | DE43: ='IS.BS.Detail'!$202:$202 -> 0 | DF43: 44
DE44: ='IS.BS.Detail'!$203:$203 -> 0 | DF44: 45
DE45: ='IS.BS.Detail'!$17:$17 -> 0 | DF45: 46
DE46: ='IS.BS.Detail'!$34:$34 -> 0 | DF46: 48
DE47: ='IS.BS.Detail'!$25:$25 -> 0 | DF47: 53
DE48: ='IS.BS.Detail'!$40:$40 -> 0 | DF48: 56
DE49: ='IS.BS.Detail'!$192:$192 -> 0 | DF49: 7635
DE50: ='IS.BS.Detail'!$183:$183 -> 0 | DF50: 7636
DE51: ='IS.BS.Detail'!$184:$184 -> 0 | DF51: 7637
DE52: ='IS.BS.Detail'!$185:$185 -> 0 | DF52: 7638
DE53: ='IS.BS.Detail'!$186:$186 -> 0 | DF53: 7639
DE54: ='IS.BS.Detail'!$187:$187 -> 0 | DF54: 7640
DE55: ='IS.BS.Detail'!$188:$188 -> 0 | DF55: 7641
DE56: ='IS.BS.Detail'!$196:$196 -> 0 | DF56: 7642
DE57: ='IS.BS.Detail'!$176:$176 -> 0 | DF57: 7643
DE58: ='IS.BS.Detail'!$177:$177 -> 0 | DF58: 7644
DE59: ='IS.BS.Detail'!$181:$181 -> 0 | DF59: 7645
DE60: ='IS.BS.Detail'!$179:$179 -> 0 | DF60: 7646
DE61: ='IS.BS.Detail'!$174:$174 -> 0 | DF61: 7647
DE62: ='IS.BS.Detail'!$169:$169 -> 0 | DF62: 7648
DE63: ='IS.BS.Detail'!$170:$170 -> 0 | DF63: 7649
DE64: ='IS.BS.Detail'!$171:$171 -> 0 | DF64: 7650
DE65: ='IS.BS.Detail'!$172:$172 -> 0 | DF65: 7651
DE66: ='IS.BS.Detail'!$122:$122 -> 0 | DF66: 7652
DE67: ='IS.BS.Detail'!$123:$123 -> 0 | DF67: 7653
DE68: ='IS.BS.Detail'!$166:$166 -> 0 | DF68: 7654
DE69: ='IS.BS.Detail'!$167:$167 -> 0 | DF69: 7655
DE70: ='IS.BS.Detail'!$130:$130 -> 0 | DF70: 7656
DE71: ='IS.BS.Detail'!$131:$131 -> 0 | DF71: 7657
DE72: ='IS.BS.Detail'!$132:$132 -> 0 | DF72: 7658
DE73: ='IS.BS.Detail'!$133:$133 -> 0 | DF73: 7659
DE74: ='IS.BS.Detail'!$134:$134 -> 0 | DF74: 7660
DE75: ='IS.BS.Detail'!$135:$135 -> 0 | DF75: 7661
DE76: ='IS.BS.Detail'!$136:$136 -> 0 | DF76: 7662
DE77: ='IS.BS.Detail'!$137:$137 -> 0 | DF77: 7663
DE78: ='IS.BS.Detail'!$138:$138 -> 0 | DF78: 7664
DE79: ='IS.BS.Detail'!$139:$139 -> 0 | DF79: 7665
DE80: ='IS.BS.Detail'!$140:$140 -> 0 | DF80: 7666
DE81: ='IS.BS.Detail'!$141:$141 -> 0 | DF81: 7667
DE82: ='IS.BS.Detail'!$142:$142 -> 0 | DF82: 7668
DE83: ='IS.BS.Detail'!$143:$143 -> 0 | DF83: 7669
DE84: ='IS.BS.Detail'!$144:$144 -> 0 | DF84: 7670
DE85: ='IS.BS.Detail'!$145:$145 -> 0 | DF85: 7671
DE86: ='IS.BS.Detail'!$146:$146 -> 0 | DF86: 7672
DE87: ='IS.BS.Detail'!$147:$147 -> 0 | DF87: 7673
DE88: ='IS.BS.Detail'!$148:$148 -> 0 | DF88: 7674
DE89: ='IS.BS.Detail'!$149:$149 -> 0 | DF89: 7675
DE90: ='IS.BS.Detail'!$150:$150 -> 0 | DF90: 7676
DE91: ='IS.BS.Detail'!$151:$151 -> 0 | DF91: 7677
DE92: ='IS.BS.Detail'!$152:$152 -> 0 | DF92: 7678
DE93: ='IS.BS.Detail'!$153:$153 -> 0 | DF93: 7679
DE94: ='IS.BS.Detail'!$154:$154 -> 0 | DF94: 7680
DE95: ='IS.BS.Detail'!$155:$155 -> 0 | DF95: 7681
DE96: ='IS.BS.Detail'!$156:$156 -> 0 | DF96: 7682
DE97: ='IS.BS.Detail'!$157:$157 -> 0 | DF97: 7683
DE98: ='IS.BS.Detail'!$158:$158 -> 0 | DF98: 7684
DE99: ='IS.BS.Detail'!$159:$159 -> 0 | DF99: 7685
DE100: ='IS.BS.Detail'!$160:$160 -> 0 | DF100: 7686
DE101: ='IS.BS.Detail'!$161:$161 -> 0 | DF101: 7687
DE102: ='IS.BS.Detail'!$162:$162 -> 0 | DF102: 7688
...

Sheet OfficeConnectCellHighlights
A3: 7f9cd215-a3a3-4337-9d33-54c7f7ced498 | B3: af0d0bab-9df8-47f4-a1b4-6d5c796d9b40
A4: 1 | B4: 19

Sheet IS
B2: Income Statement and Distribution Computation
B3: 77712 - Wentworth (Vacaville, CA)
B4: 1/31/2026
B5: Accrual Basis
C7: Feb-2025 | D7: Mar-2025 | E7: Apr-2025 | F7: May-2025 | G7: Jun-2025 | H7: Jul-2025 | I7: Aug-2025 | J7: Sep-2025 | K7: Oct-2025 | L7: Nov-2025 | M7: Dec-2025 | N7: Jan-2026 | O7: Jan-2026 YTD | P7: TTM
B9: Revenue
B10: Rental Income | C10: 41324.65 | D10: 48906.56 | E10: 54138.43 | F10: 60857.87 | G10: 65220.38 | H10: 72813.54 | I10: 75484.5 | J10: 77101.22 | K10: 81508.51 | L10: 84146.79 | M10: 82848.56 | N10: 88458.82 | O10: 88458.82 | P10: =+SUM(C10:N10) -> 832809.83
B11: Tenant Insurance RMASA Fee | C11: 2454 | D11: 2646 | E11: 2742 | F11: 2964 | G11: 3054 | H11: 3102 | I11: 3144 | J11: 3096 | K11: 3084 | L11: 3078 | M11: 3174 | N11: 3258 | O11: 3258 | P11: =+SUM(C11:N11) -> 35796
B12: Merchandise Sales | C12: 912.96 | D12: 756.69 | E12: 843.42 | F12: 1118.63 | G12: 889.55 | H12: 760.21 | I12: 1091.8 | J12: 619.78 | K12: 696.85 | L12: 687.25 | M12: 1066.98 | N12: 787.81 | O12: 787.81 | P12: =+SUM(C12:N12) -> 10231.93
B13: Admin Fees, Late Fees, and Other Fees | C13: 2432 | D13: 2907.6 | E13: 3362.87 | F13: 3467.6 | G13: 3484.4 | H13: 2579.4 | I13: 3582.59 | J13: 3282.56 | K13: 4286.87 | L13: 3879.08 | M13: 6080.3 | N13: 4984.98 | O13: 4984.98 | P13: =+SUM(C13:N13) -> 44330.25
B14: Total Revenue | C14: =+SUM(C10:C13) -> 47123.61 | D14: =+SUM(D10:D13) -> 55216.85 | E14: =+SUM(E10:E13) -> 61086.72 | F14: =+SUM(F10:F13) -> 68408.1 | G14: =+SUM(G10:G13) -> 72648.33 | H14: =+SUM(H10:H13) -> 79255.15 | I14: =+SUM(I10:I13) -> 83302.89 | J14: =+SUM(J10:J13) -> 84099.56 | ... O14: =+SUM(O10:O13) -> 97489.61 | P14: =+SUM(C14:N14) -> 923168.01
B16: Contractually set fees
B17: Property Management Software | C17: 299 | D17: 299 | E17: 299 | F17: 299.55 | G17: 300.86 | H17: 299 | I17: 299 | J17: 300.83 | K17: 299 | L17: 299 | M17: 300.81 | N17: 299 | O17: 299 | P17: =+SUM(C17:N17) -> 3594.05
B18: Customer Care Center | C18: 549 | D18: 549 | E18: 549 | F18: 549 | G18: 549 | H18: 549 | I18: 549 | J18: 549 | K18: 549 | L18: 549 | M18: 549 | N18: 549 | O18: 549 | P18: =+SUM(C18:N18) -> 6588
B19: Management Fees | C19: 1754.77 | D19: 2058.87 | E19: 2286.18 | F19: 2694.28 | G19: 2709.73 | H19: 2950.41 | I19: 3144.77 | J19: 3149.43 | K19: 3536.17 | L19: 3345.34 | M19: 3636.85 | N19: 3727.71 | O19: 3727.71 | P19: =+SUM(C19:N19) -> 34994.51
B20: Total Contractually set fees | C20: =+SUM(C17:C19) -> 2602.77 | D20: =+SUM(D17:D19) -> 2906.87 | E20: =+SUM(E17:E19) -> 3134.18 | F20: =+SUM(F17:F19) -> 3542.83 | G20: =+SUM(G17:G19) -> 3559.59 | H20: =+SUM(H17:H19) -> 3798.41 | I20: =+SUM(I17:I19) -> 3992.77 | J20: =+SUM(J17:J19) -> 3999.26 | ... O20: =+SUM(O17:O19) -> 4575.71 | P20: =+SUM(C20:N20) -> 45176.56
B22: Other Expenses
B23: Cost of Goods Sold | C23: 352.63 | D23: 212.59 | E23: 288.38 | F23: 351.82 | G23: 237.58 | H23: 182.07 | I23: 418.25 | J23: 275.06 | K23: 299.7 | L23: 243.02 | M23: 476.19 | N23: 359.28 | O23: 359.28 | P23: =+SUM(C23:N23) -> 3696.57
B24: Payroll - Property Manager | C24: 7395.57 | D24: 5933.77 | E24: 7055.44 | F24: 8709.83 | G24: 8544.95 | H24: 7756.4 | I24: 8621.55 | J24: 8103.48 | K24: 6491.09 | L24: 6675.98 | M24: 7406.73 | N24: 6871.5 | O24: 6871.5 | P24: =+SUM(C24:N24) -> 89566.29
B25: Payroll - District Manager | C25: 1303.22 | D25: 1522.62 | E25: 726.55 | F25: 1063.15 | G25: 864.46 | H25: 899.05 | I25: 914.95 | J25: 1159.66 | K25: 779.34 | L25: 838.3 | M25: 986.78 | N25: 871.77 | O25: 871.77 | P25: =+SUM(C25:N25) -> 11929.85
B26: Utilities | C26: 835 | D26: 0 | E26: 0 | F26: 0 | G26: 0 | H26: 9037.35 | I26: 3057.52 | J26: 3231.46 | K26: 2923.38 | L26: 2871.81 | M26: 3218.15 | N26: 2948.17 | O26: 2948.17 | P26: =+SUM(C26:N26) -> 28122.84
B27: Repairs and Maintenance | C27: 1787.91 | D27: 2478.26 | E27: 1154.66 | F27: 4197.65 | G27: 4226.47 | H27: 3614.14 | I27: 5572.98 | J27: 5344.8 | K27: 1458.36 | L27: 3092.95 | M27: 4347.63 | N27: 2511.82 | O27: 2511.82 | P27: =+SUM(C27:N27) -> 39787.63
B28: Credit Card Charges | C28: 703.49 | D28: 756.68 | E28: 881.92 | F28: 1037.71 | G28: 1031.97 | H28: 1088.87 | I28: 1189.62 | J28: 1153.06 | K28: 1300.32 | L28: 1237.39 | M28: 1468.12 | N28: 1484.59 | O28: 1484.59 | P28: =+SUM(C28:N28) -> 13333.74
B29: Internet Advertising | C29: 2690.57 | D29: 3766.33 | E29: 3452.22 | F29: 4285.4 | G29: 3507.05 | H29: 2723.6 | I29: 3419.91 | J29: 3480.91 | K29: 1750.46 | L29: 1792.6 | M29: 1752.92 | N29: 2235.45 | O29: 2235.45 | P29: =+SUM(C29:N29) -> 34857.42
B30: Network Charges | C30: 260.69 | D30: 260.69 | E30: 260.69 | F30: 260.69 | G30: 260.69 | H30: 260.69 | I30: 260.77 | J30: 260.77 | K30: 260.77 | L30: 260.77 | M30: 260.77 | N30: 273.09 | O30: 273.09 | P30: =+SUM(C30:N30) -> 3141.08
B31: Bank Charges | C31: 319.16 | D31: 299.79 | E31: 330.88 | F31: 330.7 | G31: 352.63 | H31: 316.58 | I31: 344.24 | J31: 360.28 | K31: 339.2 | L31: 352.57 | M31: 343.44 | N31: 287.56 | O31: 287.56 | P31: =+SUM(C31:N31) -> 3977.03
B32: Telephone | C32: 6.21 | D32: 3303.39 | E32: 6.19 | F32: 6.16 | G32: 6.17 | H32: 3271.3 | I32: 6.04 | J32: 841.6 | K32: 977.89 | L32: 827.65 | M32: 15.49 | N32: 1645.42 | O32: 1645.42 | P32: =+SUM(C32:N32) -> 10913.51
B33: Tenant Mailings | C33: 16.04 | D33: 17.87 | E33: 18.61 | F33: 23.91 | G33: 17.03 | H33: 35.27 | I33: 38.71 | J33: 42.98 | K33: 26.43 | L33: 33.21 | M33: 31.24 | N33: 16.72 | O33: 16.72 | P33: =+SUM(C33:N33) -> 318.02
B34: Office Expense | C34: 464.39 | D34: 3.77 | E34: 162.69 | F34: 155.28 | G34: 55.44 | H34: 79.73 | I34: 477.39 | J34: 54.14 | K34: 67.58 | L34: 2.26 | M34: 43.02 | N34: 94.23 | O34: 94.23 | P34: =+SUM(C34:N34) -> 1659.92
... B36: Legal and Evictions | C36: 101.4 | D36: 264.15 | E36: 204.86 | F36: 152.38 | G36: 284.61 | H36: 42.5 | I36: 158 | J36: 50.69 | K36: 263.18 | L36: 213.33 | M36: 42.5 | N36: 163.16 | O36: 163.16 | P36: =+SUM(C36:N36) -> 1940.76
B37: Total Other Expenses | C37: =+SUM(C23:C36) -> 16236.28 | D37: =+SUM(D23:D36) -> 18819.91 | E37: =+SUM(E23:E36) -> 14543.09 | F37: =+SUM(F23:F36) -> 20574.68 | G37: =+SUM(G23:G36) -> 19389.05 | H37: =+SUM(H23:H36) -> 29307.55 | I37: =+SUM(I23:I36) -> 24479.93 | J37: =+SUM(J23:J36) -> 24358.89 | ... O37: =+SUM(O23:O36) -> 19762.76 | P37: =+SUM(C37:N37) -> 243654.91
B39: Total Operating Expenses | C39: =+C20+C37 -> 18839.05 | D39: =+D20+D37 -> 21726.78 | E39: =+E20+E37 -> 17677.27 | F39: =+F20+F37 -> 24117.51 | G39: =+G20+G37 -> 22948.64 | H39: =+H20+H37 -> 33105.96 | I39: =+I20+I37 -> 28472.7 | J39: =+J20+J37 -> 28358.15 | ... O39: =+O20+O37 -> 24338.47 | P39: =+SUM(C39:N39) -> 288831.47
B41: Net Operating Income | C41: =+C14-C39 -> 28284.56 | D41: =+D14-D39 -> 33490.07 | E41: =+E14-E39 -> 43409.45 | F41: =+F14-F39 -> 44290.59 | G41: =+G14-G39 -> 49699.69 | H41: =+H14-H39 -> 46149.19 | I41: =+I14-I39 -> 54830.19 | J41: =+J14-J39 -> 55741.41 | ... O41: =+O14-O39 -> 73151.14 | P41: =+SUM(C41:N41) -> 634336.54
B43: Other items
B44: Other Income | C44: 0 | D44: 0 | E44: 0 | F44: 0 | G44: 0 | H44: 0 | I44: 0 | J44: 0 | K44: 0 | L44: 0 | M44: 0 | N44: 0 | O44: 0 | P44: =+SUM(C44:N44) -> 0
B45: Property Insurance | C45: 0 | D45: 117.39 | E45: 0 | F45: 0 | G45: 0 | H45: 14.03 | I45: 0 | J45: 0 | K45: 0 | L45: 0 | M45: 0 | N45: 33.42 | O45: 33.42 | P45: =+SUM(C45:N45) -> 164.84
B46: Other Insurance | C46: 0 | D46: 0 | E46: 0 | F46: 0 | G46: 0 | H46: 0 | I46: 0 | J46: 0 | K46: 0 | L46: 0 | M46: 0 | N46: 0 | O46: 0 | P46: =+SUM(C46:N46) -> 0
B47: Property Tax | C47: 0 | D47: 0 | E47: 0 | F47: 0 | G47: 0 | H47: 0 | I47: 0 | J47: 0 | K47: 0 | L47: 0 | M47: 0 | N47: 0 | O47: 0 | P47: =+SUM(C47:N47) -> 0
B48: Other Taxes | C48: 0 | D48: 0 | E48: 0 | F48: 0 | G48: 0 | H48: 0 | I48: 12.96 | J48: 6.48 | K48: 6.48 | L48: 4.86 | M48: 12.96 | N48: 8.95 | O48: 8.95 | P48: =+SUM(C48:N48) -> 52.69
B49: Interest Expense | C49: 0 | D49: 0 | E49: 0 | F49: 0 | G49: 0 | H49: 0 | I49: 0 | J49: 0 | K49: 0 | L49: 0 | M49: 0 | N49: 0 | O49: 0 | P49: =+SUM(C49:N49) -> 0
B50: Association Fees | C50: 0 | D50: 0 | E50: 0 | F50: 0 | G50: 0 | H50: 0 | I50: 0 | J50: 0 | K50: 0 | L50: 0 | M50: 0 | N50: 0 | O50: 0 | P50: =+SUM(C50:N50) -> 0
B51: Professional Fees | C51: 0 | D51: 0 | E51: 0 | F51: 0 | G51: 0 | H51: 0 | I51: 0 | J51: 0 | K51: 0 | L51: 0 | M51: 0 | N51: 0 | O51: 0 | P51: =+SUM(C51:N51) -> 0
B52: Total Other items | C52: =+SUM(C44:C51) -> 0 | D52: =+SUM(D44:D51) -> 117.39 | E52: =+SUM(E44:E51) -> 0 | F52: =+SUM(F44:F51) -> 0 | G52: =+SUM(G44:G51) -> 0 | H52: =+SUM(H44:H51) -> 14.03 | I52: =+SUM(I44:I51) -> 12.96 | J52: =+SUM(J44:J51) -> 6.48 | ... O52: =+SUM(O44:O51) -> 42.37 | P52: =+SUM(C52:N52) -> 217.53
B54: Net Income | C54: =+C41-C52 -> 28284.56 | D54: =+D41-D52 -> 33372.68 | E54: =+E41-E52 -> 43409.45 | F54: =+F41-F52 -> 44290.59 | G54: =+G41-G52 -> 49699.69 | H54: =+H41-H52 -> 46135.16 | I54: =+I41-I52 -> 54817.23 | J54: =+J41-J52 -> 55734.93 | ... O54: =+O41-O52 -> 73108.77 | P54: =+SUM(C54:N54) -> 634119.01
B58: Distribution Computation
B60: Net Income | C60: =+C54 -> 28284.56 | D60: =+D54 -> 33372.68 | E60: =+E54 -> 43409.45 | F60: =+F54 -> 44290.59 | G60: =+G54 -> 49699.69 | H60: =+H54 -> 46135.16 | I60: =+I54 -> 54817.23 | J60: =+J54 -> 55734.93 | ... O60: =+O54 -> 73108.77 | P60: =+SUM(C60:N60) -> 634119.01
B61: Less other impacts to cash flow
B62: Inventory | C62: -37.81 | D62: 212.59 | E62: -77.38 | F62: 351.82 | G62: -128.18 | H62: 182.07 | I62: -1204.71 | J62: 195.1 | K62: 219.74 | L62: -213.83 | M62: 316.27 | N62: 249.33 | O62: 249.33 | P62: =+SUM(C62:N62) -> 65.01
B63: Capital Improvements | C63: 0 | D63: 0 | E63: 0 | F63: 0 | G63: 0 | H63: -2058.61 | I63: -1755 | J63: 0 | K63: 0 | L63: -2005.69 | M63: 0 | N63: -3000 | O63: -3000 | P63: =+SUM(C63:N63) -> -8819.3
B64: Prepaid and Deposit | C64: 0 | D64: 0 | E64: 0 | F64: 0 | G64: 0 | H64: 0 | I64: 0 | J64: 0 | K64: 0 | L64: 0 | M64: 0 | N64: 0 | O64: 0 | P64: =+SUM(C64:N64) -> 0
B65: A/P and Other Liabilities | C65: 0 | D65: 0 | E65: 179.25 | F65: 0 | G65: 0 | H65: 0 | I65: 1097.28 | J65: -994.63 | K65: 53.9 | L65: 0 | M65: 0 | N65: 473.15 | O65: 473.15 | P65: =+SUM(C65:N65) -> 808.95
B66: A/P Property Tax | C66: 0 | D66: 0 | E66: 0 | F66: 0 | G66: 0 | H66: 0 | I66: 0 | J66: 0 | K66: 0 | L66: 0 | M66: 0 | N66: 0 | O66: 0 | P66: =+SUM(C66:N66) -> 0
B67: Intercompany | C67: 0 | D67: 0 | E67: 0 | F67: 0 | G67: 0 | H67: 0 | I67: 0 | J67: 0 | K67: 0 | L67: 0 | M67: 0 | N67: 0 | O67: 0 | P67: =+SUM(C67:N67) -> 0
B68: Non-cash activity | C68: 0 | D68: 0 | E68: 0 | F68: 0 | G68: 0 | H68: 0 | I68: 0 | J68: 0 | K68: 0 | L68: 0 | M68: 0 | N68: 0 | O68: 0 | P68: =+SUM(C68:N68) -> 0
B69: Accrued revenue and fees | C69: -96.88 | D69: -342.51 | E69: -308.21 | F69: 2950.52 | G69: -819.21 | H69: -1304.13 | I69: -350.11 | J69: -1688.45 | K69: 3212.32 | L69: -3842.21 | M69: 2393.5 | N69: 445.67 | O69: 445.67 | P69: =+SUM(C69:N69) -> 250.3
B70: Distribution due to owner | C70: =SUM(C60:C69) -> 28149.87 | D70: =SUM(D60:D69) -> 33242.76 | E70: =SUM(E60:E69) -> 43203.11 | F70: =SUM(F60:F69) -> 47592.93 | G70: =SUM(G60:G69) -> 48752.3 | H70: =SUM(H60:H69) -> 42954.49 | I70: =SUM(I60:I69) -> 52604.69 | J70: =SUM(J60:J69) -> 53246.95 | ... O70: =SUM(O60:O69) -> 71276.92 | P70: =+SUM(C70:N70) -> 626423.97
B71: Remaining distribution from prior year | C71: 0 | D71: 0 | E71: 0 | F71: 0 | G71: 0 | H71: 0 | I71: 0 | J71: 0 | K71: 0 | L71: 0 | M71: 0 | N71: 0 | O71: 0 | P71: =+SUM(C71:N71) -> 0
B72: Distribution sent | C72: 0 | D72: 116177.51 | E72: 43203.11 | F72: 47592.93 | G72: 48752.3 | H72: 42954.49 | I72: 52604.69 | J72: 53246.95 | K72: 71323.59 | L72: 63089.35 | M72: 70987.01 | N72: 71276.92 | O72: 71276.92 | P72: =+SUM(C72:N72) -> 681208.85
B73: Variance | C73: =+C70+C71-C72 -> 28149.87 | D73: =+D70+D71-D72 -> -82934.75 | E73: =+E70+E71-E72 -> 0 | F73: =+F70+F71-F72 -> 0 | G73: =+G70+G71-G72 -> 0 | H73: =+H70+H71-H72 -> 0 | I73: =+I70+I71-I72 -> 0 | J73: =+J70+J71-J72 -> 0 | ... O73: =+O70+O71-O72 -> 0 | P73: =+SUM(C73:N73) -> -54784.88

Sheet BS
B2: Balance Sheet
B3: 77712 - Wentworth (Vacaville, CA)
B4: 1/31/2026
D6: Current Month v Prior Year End | H6: Current Month v Prior Month
D7: Jan-2026 | E7: Dec-2025 | F7: Var | H7: Jan-2026 | I7: Dec-2025 | J7: Var
B9: Assets
B10: Cash | D10: 238209.52 | E10: 136202.39 | F10: =+D10-E10 -> 102007.13 | H10: 238209.52 | I10: 136202.39 | J10: =+H10-I10 -> 102007.13
B11: Account Receivable | D11: 2775.77 | E11: 3074.62 | F11: =+D11-E11 -> -298.85 | H11: 2775.77 | I11: 3074.62 | J11: =+H11-I11 -> -298.85
B12: Inventory | D12: 3343.2 | E12: 3592.53 | F12: =+D12-E12 -> -249.33 | H12: 3343.2 | I12: 3592.53 | J12: =+H12-I12 -> -249.33
B13: Prepaid and Other | D13: 0 | E13: 0 | F13: =+D13-E13 -> 0 | H13: 0 | I13: 0 | J13: =+H13-I13 -> 0
B14: Intercompany | D14: 0 | E14: 0 | F14: =+D14-E14 -> 0 | H14: 0 | I14: 0 | J14: =+H14-I14 -> 0
B15: Other Assets | D15: 0 | E15: 0 | F15: =+D15-E15 -> 0 | H15: 0 | I15: 0 | J15: =+H15-I15 -> 0
B16: Land, Building, and Capital Improvements | D16: 13019.16 | E16: 10019.16 | F16: =+D16-E16 -> 3000 | H16: 13019.16 | I16: 10019.16 | J16: =+H16-I16 -> 3000
B17: Total Assets | D17: =+SUM(D10:D16) -> 257347.65 | E17: =+SUM(E10:E16) -> 152888.7 | F17: =+D17-E17 -> 104458.95 | H17: =+SUM(H10:H16) -> 257347.65 | I17: =+SUM(I10:I16) -> 152888.7 | J17: =+H17-I17 -> 104458.95
B19: Liabilities
B20: Accounts Payable | D20: 122481.29 | E20: 20542.79 | F20: =+D20-E20 -> 101938.5 | H20: 122481.29 | I20: 20542.79 | J20: =+H20-I20 -> 101938.5
B21: Accrued Property Tax | D21: 0 | E21: 0 | F21: =+D21-E21 -> 0 | H21: 0 | I21: 0 | J21: =+H21-I21 -> 0
B22: Accrued Liabilities | D22: 0 | E22: 0 | F22: =+D22-E22 -> 0 | H22: 0 | I22: 0 | J22: =+H22-I22 -> 0
B23: Deferred Revenue | D23: 8077.89 | E23: 7679.2 | F23: =+D23-E23 -> 398.69 | H23: 8077.89 | I23: 7679.2 | J23: =+H23-I23 -> 398.69
B24: Other liabilities | D24: 0 | E24: 0 | F24: =+D24-E24 -> 0 | H24: 0 | I24: 0 | J24: =+H24-I24 -> 0
B25: Notes Payable | D25: 0 | E25: 0 | F25: =+D25-E25 -> 0 | H25: 0 | I25: 0 | J25: =+H25-I25 -> 0
B26: Total Liabilities | D26: =+SUM(D20:D25) -> 130559.18 | E26: =+SUM(E20:E25) -> 28221.99 | F26: =+D26-E26 -> 102337.19 | H26: =+SUM(H20:H25) -> 130559.18 | I26: =+SUM(I20:I25) -> 28221.99 | J26: =+H26-I26 -> 102337.19
B28: Owner's Equity
B29: Capital Contribution and Distribution | D29: -565652.96 | E29: -494665.95 | F29: =+D29-E29 -> -70987.01 | H29: -565652.96 | I29: -494665.95 | J29: =+H29-I29 -> -70987.01
B30: Retained Earnings | D30: 619332.66 | E30: 33107.62 | F30: =+D30-E30 -> 586225.04 | H30: 619332.66 | I30: 33107.62 | J30: =+H30-I30 -> 586225.04
B31: Current Earnings | D31: 73108.77 | E31: 586225.04 | F31: =+D31-E31 -> -513116.27 | H31: 73108.77 | I31: 586225.04 | J31: =+H31-I31 -> -513116.27
B32: Total Owner's Equity | D32: =+SUM(D29:D31) -> 126788.47 | E32: =+SUM(E29:E31) -> 124666.71 | F32: =+D32-E32 -> 2121.76 | H32: =+SUM(H29:H31) -> 126788.47 | I32: =+SUM(I29:I31) -> 124666.71 | J32: =+H32-I32 -> 2121.76
B34: Total Liabilities and Owner's Equity | D34: =+D26+D32 -> 257347.65 | E34: =+E26+E32 -> 152888.7 | F34: =+D34-E34 -> 104458.95 | H34: =+H26+H32 -> 257347.65 | I34: =+I26+I32 -> 152888.7 | J34: =+H34-I34 -> 104458.95

Sheet YOY
B2: Current Year vs Prior Year
B3: 77712 - Wentworth (Vacaville, CA)
B4: 1/31/2026
D6: MTD | I6: QTD | N6: YTD
D7: Jan-2026 | E7: Jan-2025 | F7: Var | G7: Var % | I7: Jan-2026 | J7: Jan-2025 | K7: Var | L7: Var % | N7: Jan-2026 | O7: Jan-2025 | P7: Var | Q7: Var %
B9: Revenue
B10: Rental Income | D10: 88458.82 | E10: 34544.2 | F10: =+IFERROR(D10-E10,"") -> 53914.62 | G10: =+IFERROR(F10/E10,"") -> 1.560743 | I10: 88458.82 | J10: 34544.2 | K10: =+IFERROR(I10-J10,"") -> 53914.62 | L10: =+IFERROR(K10/J10,"") -> 1.560743 | N10: 88458.82 | O10: 34544.2 | P10: =+IFERROR(N10-O10,"") -> 53914.62 | Q10: =+IFERROR(P10/O10,"") -> 1.560743
B11: Tenant Insurance RMASA Fee | D11: 3258 | E11: 2322 | F11: =+IFERROR(D11-E11,"") -> 936 | G11: =+IFERROR(F11/E11,"") -> 0.40310078 | I11: 3258 | J11: 2322 | K11: =+IFERROR(I11-J11,"") -> 936 | L11: =+IFERROR(K11/J11,"") -> 0.40310078 | N11: 3258 | O11: 2322 | P11: =+IFERROR(N11-O11,"") -> 936 | Q11: =+IFERROR(P11/O11,"") -> 0.40310078
B12: Merchandise Sales | D12: 787.81 | E12: 967.88 | F12: =+IFERROR(D12-E12,"") -> -180.07 | G12: =+IFERROR(F12/E12,"") -> -0.18604579 | I12: 787.81 | J12: 967.88 | K12: =+IFERROR(I12-J12,"") -> -180.07 | L12: =+IFERROR(K12/J12,"") -> -0.18604579 | N12: 787.81 | O12: 967.88 | P12: =+IFERROR(N12-O12,"") -> -180.07 | Q12: =+IFERROR(P12/O12,"") -> -0.18604579
B13: Admin Fees, Late Fees, and Other Fees | D13: 4984.98 | E13: 3195.2 | F13: =+IFERROR(D13-E13,"") -> 1789.78 | G13: =+IFERROR(F13/E13,"") -> 0.56014647 | I13: 4984.98 | J13: 3195.2 | K13: =+IFERROR(I13-J13,"") -> 1789.78 | L13: =+IFERROR(K13/J13,"") -> 0.56014647 | N13: 4984.98 | O13: 3195.2 | P13: =+IFERROR(N13-O13,"") -> 1789.78 | Q13: =+IFERROR(P13/O13,"") -> 0.56014647
B14: Total Revenue | D14: =+SUM(D10:D13) -> 97489.61 | E14: =+SUM(E10:E13) -> 41029.28 | F14: =+IFERROR(D14-E14,"") -> 56460.33 | G14: =+IFERROR(F14/E14,"") -> 1.3760985 | I14: =+SUM(I10:I13) -> 97489.61 | J14: =+SUM(J10:J13) -> 41029.28 | K14: =+IFERROR(I14-J14,"") -> 56460.33 | L14: =+IFERROR(K14/J14,"") -> 1.3760985 | N14: =+SUM(N10:N13) -> 97489.61 | O14: =+SUM(O10:O13) -> 41029.28 | P14: =+IFERROR(N14-O14,"") -> 56460.33 | Q14: =+IFERROR(P14/O14,"") -> 1.3760985
B16: Contractually set fees
B17: Property Management Software | D17: 299 | E17: 299 | F17: =+IFERROR(D17-E17,"") -> 0 | G17: =+IFERROR(F17/E17,"") -> 0 | I17: 299 | J17: 299 | K17: =+IFERROR(I17-J17,"") -> 0 | L17: =+IFERROR(K17/J17,"") -> 0 | N17: 299 | O17: 299 | P17: =+IFERROR(N17-O17,"") -> 0 | Q17: =+IFERROR(P17/O17,"") -> 0
B18: Customer Care Center | D18: 549 | E18: 549 | F18: =+IFERROR(D18-E18,"") -> 0 | G18: =+IFERROR(F18/E18,"") -> 0 | I18: 549 | J18: 549 | K18: =+IFERROR(I18-J18,"") -> 0 | L18: =+IFERROR(K18/J18,"") -> 0 | N18: 549 | O18: 549 | P18: =+IFERROR(N18-O18,"") -> 0 | Q18: =+IFERROR(P18/O18,"") -> 0
B19: Management Fees | D19: 3727.71 | E19: 1574.8 | F19: =+IFERROR(D19-E19,"") -> 2152.91 | G19: =+IFERROR(F19/E19,"") -> 1.3671006 | I19: 3727.71 | J19: 1574.8 | K19: =+IFERROR(I19-J19,"") -> 2152.91 | L19: =+IFERROR(K19/J19,"") -> 1.3671006 | N19: 3727.71 | O19: 1574.8 | P19: =+IFERROR(N19-O19,"") -> 2152.91 | Q19: =+IFERROR(P19/O19,"") -> 1.3671006
B20: Total Contractually set fees | D20: =+SUM(D17:D19) -> 4575.71 | E20: =+SUM(E17:E19) -> 2422.8 | F20: =+IFERROR(D20-E20,"") -> 2152.91 | G20: =+IFERROR(F20/E20,"") -> 0.88860409 | I20: =+SUM(I17:I19) -> 4575.71 | J20: =+SUM(J17:J19) -> 2422.8 | K20: =+IFERROR(I20-J20,"") -> 2152.91 | L20: =+IFERROR(K20/J20,"") -> 0.88860409 | N20: =+SUM(N17:N19) -> 4575.71 | O20: =+SUM(O17:O19) -> 2422.8 | P20: =+IFERROR(N20-O20,"") -> 2152.91 | Q20: =+IFERROR(P20/O20,"") -> 0.88860409
B22: Other Expenses
B23: Cost of Goods Sold | D23: 359.28 | E23: 499.4 | F23: =+IFERROR(D23-E23,"") -> -140.12 | G23: =+IFERROR(F23/E23,"") -> -0.28057669 | I23: 359.28 | J23: 499.4 | K23: =+IFERROR(I23-J23,"") -> -140.12 | L23: =+IFERROR(K23/J23,"") -> -0.28057669 | N23: 359.28 | O23: 499.4 | P23: =+IFERROR(N23-O23,"") -> -140.12 | Q23: =+IFERROR(P23/O23,"") -> -0.28057669
B24: Payroll - Property Manager | D24: 6871.5 | E24: 4556.92 | F24: =+IFERROR(D24-E24,"") -> 2314.58 | G24: =+IFERROR(F24/E24,"") -> 0.50792641 | I24: 6871.5 | J24: 4556.92 | K24: =+IFERROR(I24-J24,"") -> 2314.58 | L24: =+IFERROR(K24/J24,"") -> 0.50792641 | N24: 6871.5 | O24: 4556.92 | P24: =+IFERROR(N24-O24,"") -> 2314.58 | Q24: =+IFERROR(P24/O24,"") -> 0.50792641
B25: Payroll - District Manager | D25: 871.77 | E25: 1144.34 | F25: =+IFERROR(D25-E25,"") -> -272.57 | G25: =+IFERROR(F25/E25,"") -> -0.2381897 | I25: 871.77 | J25: 1144.34 | K25: =+IFERROR(I25-J25,"") -> -272.57 | L25: =+IFERROR(K25/J25,"") -> -0.2381897 | N25: 871.77 | O25: 1144.34 | P25: =+IFERROR(N25-O25,"") -> -272.57 | Q25: =+IFERROR(P25/O25,"") -> -0.2381897
B26: Utilities | D26: 2948.17 | E26: 0 | F26: =+IFERROR(D26-E26,"") -> 2948.17 | G26: =+IFERROR(F26/E26,"") | I26: 2948.17 | J26: 0 | K26: =+IFERROR(I26-J26,"") -> 2948.17 | L26: =+IFERROR(K26/J26,"") | N26: 2948.17 | O26: 0 | P26: =+IFERROR(N26-O26,"") -> 2948.17 | Q26: =+IFERROR(P26/O26,"")
B27: Repairs and Maintenance | D27: 2511.82 | E27: 2119.05 | F27: =+IFERROR(D27-E27,"") -> 392.77 | G27: =+IFERROR(F27/E27,"") -> 0.18535193 | I27: 2511.82 | J27: 2119.05 | K27: =+IFERROR(I27-J27,"") -> 392.77 | L27: =+IFERROR(K27/J27,"") -> 0.18535193 | N27: 2511.82 | O27: 2119.05 | P27: =+IFERROR(N27-O27,"") -> 392.77 | Q27: =+IFERROR(P27/O27,"") -> 0.18535193
B28: Credit Card Charges | D28: 1484.59 | E28: 611.94 | F28: =+IFERROR(D28-E28,"") -> 872.65 | G28: =+IFERROR(F28/E28,"") -> 1.4260385 | I28: 1484.59 | J28: 611.94 | K28: =+IFERROR(I28-J28,"") -> 872.65 | L28: =+IFERROR(K28/J28,"") -> 1.4260385 | N28: 1484.59 | O28: 611.94 | P28: =+IFERROR(N28-O28,"") -> 872.65 | Q28: =+IFERROR(P28/O28,"") -> 1.4260385
B29: Internet Advertising | D29: 2235.45 | E29: 3717.23 | F29: =+IFERROR(D29-E29,"") -> -1481.78 | G29: =+IFERROR(F29/E29,"") -> -0.39862478 | I29: 2235.45 | J29: 3717.23 | K29: =+IFERROR(I29-J29,"") -> -1481.78 | L29: =+IFERROR(K29/J29,"") -> -0.39862478 | N29: 2235.45 | O29: 3717.23 | P29: =+IFERROR(N29-O29,"") -> -1481.78 | Q29: =+IFERROR(P29/O29,"") -> -0.39862478
B30: Network Charges | D30: 273.09 | E30: 261.8 | F30: =+IFERROR(D30-E30,"") -> 11.29 | G30: =+IFERROR(F30/E30,"") -> 0.043124523 | I30: 273.09 | J30: 261.8 | K30: =+IFERROR(I30-J30,"") -> 11.29 | L30: =+IFERROR(K30/J30,"") -> 0.043124523 | N30: 273.09 | O30: 261.8 | P30: =+IFERROR(N30-O30,"") -> 11.29 | Q30: =+IFERROR(P30/O30,"") -> 0.043124523
B31: Bank Charges | D31: 287.56 | E31: 296.05 | F31: =+IFERROR(D31-E31,"") -> -8.49 | G31: =+IFERROR(F31/E31,"") -> -0.028677588 | I31: 287.56 | J31: 296.05 | K31: =+IFERROR(I31-J31,"") -> -8.49 | L31: =+IFERROR(K31/J31,"") -> -0.028677588 | N31: 287.56 | O31: 296.05 | P31: =+IFERROR(N31-O31,"") -> -8.49 | Q31: =+IFERROR(P31/O31,"") -> -0.028677588
B32: Telephone | D32: 1645.42 | E32: 6.24 | F32: =+IFERROR(D32-E32,"") -> 1639.18 | G32: =+IFERROR(F32/E32,"") -> 262.6891 | I32: 1645.42 | J32: 6.24 | K32: =+IFERROR(I32-J32,"") -> 1639.18 | L32: =+IFERROR(K32/J32,"") -> 262.6891 | N32: 1645.42 | O32: 6.24 | P32: =+IFERROR(N32-O32,"") -> 1639.18 | Q32: =+IFERROR(P32/O32,"") -> 262.6891
B33: Tenant Mailings | D33: 16.72 | E33: 13.71 | F33: =+IFERROR(D33-E33,"") -> 3.01 | G33: =+IFERROR(F33/E33,"") -> 0.21954778 | I33: 16.72 | J33: 13.71 | K33: =+IFERROR(I33-J33,"") -> 3.01 | L33: =+IFERROR(K33/J33,"") -> 0.21954778 | N33: 16.72 | O33: 13.71 | P33: =+IFERROR(N33-O33,"") -> 3.01 | Q33: =+IFERROR(P33/O33,"") -> 0.21954778
B34: Office Expense | D34: 94.23 | E34: 122.5 | F34: =+IFERROR(D34-E34,"") -> -28.27 | G34: =+IFERROR(F34/E34,"") -> -0.23077551 | I34: 94.23 | J34: 122.5 | K34: =+IFERROR(I34-J34,"") -> -28.27 | L34: =+IFERROR(K34/J34,"") -> -0.23077551 | N34: 94.23 | O34: 122.5 | P34: =+IFERROR(N34-O34,"") -> -28.27 | Q34: =+IFERROR(P34/O34,"") -> -0.23077551
... B36: Legal and Evictions | D36: 163.16 | E36: 42.5 | F36: =+IFERROR(D36-E36,"") -> 120.66 | G36: =+IFERROR(F36/E36,"") -> 2.8390588 | I36: 163.16 | J36: 42.5 | K36: =+IFERROR(I36-J36,"") -> 120.66 | L36: =+IFERROR(K36/J36,"") -> 2.8390588 | N36: 163.16 | O36: 42.5 | P36: =+IFERROR(N36-O36,"") -> 120.66 | Q36: =+IFERROR(P36/O36,"") -> 2.8390588
B37: Total Other Expenses | D37: =+SUM(D23:D36) -> 19762.76 | E37: =+SUM(E23:E36) -> 13391.68 | F37: =+IFERROR(D37-E37,"") -> 6371.08 | G37: =+IFERROR(F37/E37,"") -> 0.47574912 | I37: =+SUM(I23:I36) -> 19762.76 | J37: =+SUM(J23:J36) -> 13391.68 | K37: =+IFERROR(I37-J37,"") -> 6371.08 | L37: =+IFERROR(K37/J37,"") -> 0.47574912 | N37: =+SUM(N23:N36) -> 19762.76 | O37: =+SUM(O23:O36) -> 13391.68 | P37: =+IFERROR(N37-O37,"") -> 6371.08 | Q37: =+IFERROR(P37/O37,"") -> 0.47574912
B39: Total Operating Expenses | D39: =+D20+D37 -> 24338.47 | E39: =+E20+E37 -> 15814.48 | F39: =+IFERROR(D39-E39,"") -> 8523.99 | G39: =+IFERROR(F39/E39,"") -> 0.53899907 | I39: =+I20+I37 -> 24338.47 | J39: =+J20+J37 -> 15814.48 | K39: =+IFERROR(I39-J39,"") -> 8523.99 | L39: =+IFERROR(K39/J39,"") -> 0.53899907 | N39: =+N20+N37 -> 24338.47 | O39: =+O20+O37 -> 15814.48 | P39: =+IFERROR(N39-O39,"") -> 8523.99 | Q39: =+IFERROR(P39/O39,"") -> 0.53899907
F40: =+IFERROR(D40-E40,"") -> 0 | G40: =+IFERROR(F40/E40,"") | K40: =+IFERROR(I40-J40,"") -> 0 | L40: =+IFERROR(K40/J40,"") | P40: =+IFERROR(N40-O40,"") -> 0 | Q40: =+IFERROR(P40/O40,"")
B41: Net Operating Income | D41: =+D14-D39 -> 73151.14 | E41: =+E14-E39 -> 25214.8 | F41: =+IFERROR(D41-E41,"") -> 47936.34 | G41: =+IFERROR(F41/E41,"") -> 1.9011192 | I41: =+I14-I39 -> 73151.14 | J41: =+J14-J39 -> 25214.8 | K41: =+IFERROR(I41-J41,"") -> 47936.34 | L41: =+IFERROR(K41/J41,"") -> 1.9011192 | N41: =+N14-N39 -> 73151.14 | O41: =+O14-O39 -> 25214.8 | P41: =+IFERROR(N41-O41,"") -> 47936.34 | Q41: =+IFERROR(P41/O41,"") -> 1.9011192
B43: Other items
B44: Other Income | D44: 0 | E44: 0 | F44: =+IFERROR(D44-E44,"") -> 0 | G44: =+IFERROR(F44/E44,"") | I44: 0 | J44: 0 | K44: =+IFERROR(I44-J44,"") -> 0 | L44: =+IFERROR(K44/J44,"") | N44: 0 | O44: 0 | P44: =+IFERROR(N44-O44,"") -> 0 | Q44: =+IFERROR(P44/O44,"")
B45: Property Insurance | D45: 33.42 | E45: 0 | F45: =+IFERROR(D45-E45,"") -> 33.42 | G45: =+IFERROR(F45/E45,"") | I45: 33.42 | J45: 0 | K45: =+IFERROR(I45-J45,"") -> 33.42 | L45: =+IFERROR(K45/J45,"") | N45: 33.42 | O45: 0 | P45: =+IFERROR(N45-O45,"") -> 33.42 | Q45: =+IFERROR(P45/O45,"")
B46: Other Insurance | D46: 0 | E46: 0 | F46: =+IFERROR(D46-E46,"") -> 0 | G46: =+IFERROR(F46/E46,"") | I46: 0 | J46: 0 | K46: =+IFERROR(I46-J46,"") -> 0 | L46: =+IFERROR(K46/J46,"") | N46: 0 | O46: 0 | P46: =+IFERROR(N46-O46,"") -> 0 | Q46: =+IFERROR(P46/O46,"")
B47: Property Tax | D47: 0 | E47: 0 | F47: =+IFERROR(D47-E47,"") -> 0 | G47: =+IFERROR(F47/E47,"") | I47: 0 | J47: 0 | K47: =+IFERROR(I47-J47,"") -> 0 | L47: =+IFERROR(K47/J47,"") | N47: 0 | O47: 0 | P47: =+IFERROR(N47-O47,"") -> 0 | Q47: =+IFERROR(P47/O47,"")
B48: Other Taxes | D48: 8.95 | E48: 0 | F48: =+IFERROR(D48-E48,"") -> 8.95 | G48: =+IFERROR(F48/E48,"") | I48: 8.95 | J48: 0 | K48: =+IFERROR(I48-J48,"") -> 8.95 | L48: =+IFERROR(K48/J48,"") | N48: 8.95 | O48: 0 | P48: =+IFERROR(N48-O48,"") -> 8.95 | Q48: =+IFERROR(P48/O48,"")
B49: Interest Expense | D49: 0 | E49: 0 | F49: =+IFERROR(D49-E49,"") -> 0 | G49: =+IFERROR(F49/E49,"") | I49: 0 | J49: 0 | K49: =+IFERROR(I49-J49,"") -> 0 | L49: =+IFERROR(K49/J49,"") | N49: 0 | O49: 0 | P49: =+IFERROR(N49-O49,"") -> 0 | Q49: =+IFERROR(P49/O49,"")
B50: Association Fees | D50: 0 | E50: 0 | F50: =+IFERROR(D50-E50,"") -> 0 | G50: =+IFERROR(F50/E50,"") | I50: 0 | J50: 0 | K50: =+IFERROR(I50-J50,"") -> 0 | L50: =+IFERROR(K50/J50,"") | N50: 0 | O50: 0 | P50: =+IFERROR(N50-O50,"") -> 0 | Q50: =+IFERROR(P50/O50,"")
B51: Professional Fees | D51: 0 | E51: 0 | F51: =+IFERROR(D51-E51,"") -> 0 | G51: =+IFERROR(F51/E51,"") | I51: 0 | J51: 0 | K51: =+IFERROR(I51-J51,"") -> 0 | L51: =+IFERROR(K51/J51,"") | N51: 0 | O51: 0 | P51: =+IFERROR(N51-O51,"") -> 0 | Q51: =+IFERROR(P51/O51,"")
B52: Total Other items | D52: =+SUM(D44:D51) -> 42.37 | E52: =+SUM(E44:E51) -> 0 | F52: =+IFERROR(D52-E52,"") -> 42.37 | G52: =+IFERROR(F52/E52,"") | I52: =+SUM(I44:I51) -> 42.37 | J52: =+SUM(J44:J51) -> 0 | K52: =+IFERROR(I52-J52,"") -> 42.37 | L52: =+IFERROR(K52/J52,"") | N52: =+SUM(N44:N51) -> 42.37 | O52: =+SUM(O44:O51) -> 0 | P52: =+IFERROR(N52-O52,"") -> 42.37 | Q52: =+IFERROR(P52/O52,"")
B54: Net Income | D54: =+D41-D52 -> 73108.77 | E54: =+E41-E52 -> 25214.8 | F54: =+IFERROR(D54-E54,"") -> 47893.97 | G54: =+IFERROR(F54/E54,"") -> 1.8994388 | I54: =+I41-I52 -> 73108.77 | J54: =+J41-J52 -> 25214.8 | K54: =+IFERROR(I54-J54,"") -> 47893.97 | L54: =+IFERROR(K54/J54,"") -> 1.8994388 | N54: =+N41-N52 -> 73108.77 | O54: =+O41-O52 -> 25214.8 | P54: =+IFERROR(N54-O54,"") -> 47893.97 | Q54: =+IFERROR(P54/O54,"") -> 1.8994388

Sheet Act v Bud
B2: Actual vs Budget
B3: 77712 - Wentworth (Vacaville, CA)
B4: 1/31/2026
D6: MTD | I6: QTD | N6: YTD
D7: Actual | E7: Budget | F7: Var | G7: Var % | I7: Actual | J7: Budget | K7: Var | L7: Var % | N7: Actual | O7: Budget | P7: Var | Q7: Var %
B9: Revenue
B10: Rental Income | D10: 88458.82 | E10: 87063.195 | F10: =+IFERROR(D10-E10,"") -> 1395.6247 | G10: =+IFERROR(F10/E10,"") -> 0.016030019 | I10: 88458.82 | J10: 87063.195 | K10: =+IFERROR(I10-J10,"") -> 1395.6247 | L10: =+IFERROR(K10/J10,"") -> 0.016030019 | N10: 88458.82 | O10: 87063.195 | P10: =+IFERROR(N10-O10,"") -> 1395.6247 | Q10: =+IFERROR(P10/O10,"") -> 0.016030019
B11: Tenant Insurance RMASA Fee | D11: 3258 | E11: 3123.9 | F11: =+IFERROR(D11-E11,"") -> 134.1 | G11: =+IFERROR(F11/E11,"") -> 0.04292711 | I11: 3258 | J11: 3123.9 | K11: =+IFERROR(I11-J11,"") -> 134.1 | L11: =+IFERROR(K11/J11,"") -> 0.04292711 | N11: 3258 | O11: 3123.9 | P11: =+IFERROR(N11-O11,"") -> 134.1 | Q11: =+IFERROR(P11/O11,"") -> 0.04292711
B12: Merchandise Sales | D12: 787.81 | E12: 700 | F12: =+IFERROR(D12-E12,"") -> 87.81 | G12: =+IFERROR(F12/E12,"") -> 0.12544286 | I12: 787.81 | J12: 700 | K12: =+IFERROR(I12-J12,"") -> 87.81 | L12: =+IFERROR(K12/J12,"") -> 0.12544286 | N12: 787.81 | O12: 700 | P12: =+IFERROR(N12-O12,"") -> 87.81 | Q12: =+IFERROR(P12/O12,"") -> 0.12544286
B13: Admin Fees, Late Fees, and Other Fees | D13: 4984.98 | E13: 2450 | F13: =+IFERROR(D13-E13,"") -> 2534.98 | G13: =+IFERROR(F13/E13,"") -> 1.0346857 | I13: 4984.98 | J13: 2450 | K13: =+IFERROR(I13-J13,"") -> 2534.98 | L13: =+IFERROR(K13/J13,"") -> 1.0346857 | N13: 4984.98 | O13: 2450 | P13: =+IFERROR(N13-O13,"") -> 2534.98 | Q13: =+IFERROR(P13/O13,"") -> 1.0346857
B14: Total Revenue | D14: =+SUM(D10:D13) -> 97489.61 | E14: =+SUM(E10:E13) -> 93337.095 | F14: =+IFERROR(D14-E14,"") -> 4152.5147 | G14: =+IFERROR(F14/E14,"") -> 0.044489436 | I14: =+SUM(I10:I13) -> 97489.61 | J14: =+SUM(J10:J13) -> 93337.095 | K14: =+IFERROR(I14-J14,"") -> 4152.5147 | L14: =+IFERROR(K14/J14,"") -> 0.044489436 | N14: =+SUM(N10:N13) -> 97489.61 | O14: =+SUM(O10:O13) -> 93337.095 | P14: =+IFERROR(N14-O14,"") -> 4152.5147 | Q14: =+IFERROR(P14/O14,"") -> 0.044489436
B16: Contractually set fees
B17: Property Management Software | D17: 299 | E17: 299 | F17: =+IFERROR(D17-E17,"") -> 0 | G17: =+IFERROR(F17/E17,"") -> 0 | I17: 299 | J17: 299 | K17: =+IFERROR(I17-J17,"") -> 0 | L17: =+IFERROR(K17/J17,"") -> 0 | N17: 299 | O17: 299 | P17: =+IFERROR(N17-O17,"") -> 0 | Q17: =+IFERROR(P17/O17,"") -> 0
B18: Customer Care Center | D18: 549 | E18: 549 | F18: =+IFERROR(D18-E18,"") -> 0 | G18: =+IFERROR(F18/E18,"") -> 0 | I18: 549 | J18: 549 | K18: =+IFERROR(I18-J18,"") -> 0 | L18: =+IFERROR(K18/J18,"") -> 0 | N18: 549 | O18: 549 | P18: =+IFERROR(N18-O18,"") -> 0 | Q18: =+IFERROR(P18/O18,"") -> 0
B19: Management Fees | D19: 3727.71 | E19: 3552.5956 | F19: =+IFERROR(D19-E19,"") -> 175.11437 | G19: =+IFERROR(F19/E19,"") -> 0.049291951 | I19: 3727.71 | J19: 3552.5956 | K19: =+IFERROR(I19-J19,"") -> 175.11437 | L19: =+IFERROR(K19/J19,"") -> 0.049291951 | N19: 3727.71 | O19: 3552.5956 | P19: =+IFERROR(N19-O19,"") -> 175.11437 | Q19: =+IFERROR(P19/O19,"") -> 0.049291951
B20: Total Contractually set fees | D20: =+SUM(D17:D19) -> 4575.71 | E20: =+SUM(E17:E19) -> 4400.5956 | F20: =+IFERROR(D20-E20,"") -> 175.11437 | G20: =+IFERROR(F20/E20,"") -> 0.039793334 | I20: =+SUM(I17:I19) -> 4575.71 | J20: =+SUM(J17:J19) -> 4400.5956 | K20: =+IFERROR(I20-J20,"") -> 175.11437 | L20: =+IFERROR(K20/J20,"") -> 0.039793334 | N20: =+SUM(N17:N19) -> 4575.71 | O20: =+SUM(O17:O19) -> 4400.5956 | P20: =+IFERROR(N20-O20,"") -> 175.11437 | Q20: =+IFERROR(P20/O20,"") -> 0.039793334
B22: Other Expenses
B23: Cost of Goods Sold | D23: 359.28 | E23: 315 | F23: =+IFERROR(D23-E23,"") -> 44.28 | G23: =+IFERROR(F23/E23,"") -> 0.14057143 | I23: 359.28 | J23: 315 | K23: =+IFERROR(I23-J23,"") -> 44.28 | L23: =+IFERROR(K23/J23,"") -> 0.14057143 | N23: 359.28 | O23: 315 | P23: =+IFERROR(N23-O23,"") -> 44.28 | Q23: =+IFERROR(P23/O23,"") -> 0.14057143
B24: Payroll - Property Manager | D24: 6871.5 | E24: 7993.6385 | F24: =+IFERROR(D24-E24,"") -> -1122.1385 | G24: =+IFERROR(F24/E24,"") -> -0.14037894 | I24: 6871.5 | J24: 7993.6385 | K24: =+IFERROR(I24-J24,"") -> -1122.1385 | L24: =+IFERROR(K24/J24,"") -> -0.14037894 | N24: 6871.5 | O24: 7993.6385 | P24: =+IFERROR(N24-O24,"") -> -1122.1385 | Q24: =+IFERROR(P24/O24,"") -> -0.14037894
B25: Payroll - District Manager | D25: 871.77 | E25: 1060.2862 | F25: =+IFERROR(D25-E25,"") -> -188.51622 | G25: =+IFERROR(F25/E25,"") -> -0.17779748 | I25: 871.77 | J25: 1060.2862 | K25: =+IFERROR(I25-J25,"") -> -188.51622 | L25: =+IFERROR(K25/J25,"") -> -0.17779748 | N25: 871.77 | O25: 1060.2862 | P25: =+IFERROR(N25-O25,"") -> -188.51622 | Q25: =+IFERROR(P25/O25,"") -> -0.17779748
B26: Utilities | D26: 2948.17 | E26: 3290.1108 | F26: =+IFERROR(D26-E26,"") -> -341.94077 | G26: =+IFERROR(F26/E26,"") -> -0.10392987 | I26: 2948.17 | J26: 3290.1108 | K26: =+IFERROR(I26-J26,"") -> -341.94077 | L26: =+IFERROR(K26/J26,"") -> -0.10392987 | N26: 2948.17 | O26: 3290.1108 | P26: =+IFERROR(N26-O26,"") -> -341.94077 | Q26: =+IFERROR(P26/O26,"") -> -0.10392987
B27: Repairs and Maintenance | D27: 2511.82 | E27: 3389.9944 | F27: =+IFERROR(D27-E27,"") -> -878.17437 | G27: =+IFERROR(F27/E27,"") -> -0.25904892 | I27: 2511.82 | J27: 3389.9944 | K27: =+IFERROR(I27-J27,"") -> -878.17437 | L27: =+IFERROR(K27/J27,"") -> -0.25904892 | N27: 2511.82 | O27: 3389.9944 | P27: =+IFERROR(N27-O27,"") -> -878.17437 | Q27: =+IFERROR(P27/O27,"") -> -0.25904892
B28: Credit Card Charges | D28: 1484.59 | E28: 1398.3045 | F28: =+IFERROR(D28-E28,"") -> 86.285473 | G28: =+IFERROR(F28/E28,"") -> 0.061707211 | I28: 1484.59 | J28: 1398.3045 | K28: =+IFERROR(I28-J28,"") -> 86.285473 | L28: =+IFERROR(K28/J28,"") -> 0.061707211 | N28: 1484.59 | O28: 1398.3045 | P28: =+IFERROR(N28-O28,"") -> 86.285473 | Q28: =+IFERROR(P28/O28,"") -> 0.061707211
B29: Internet Advertising | D29: 2235.45 | E29: 3500 | F29: =+IFERROR(D29-E29,"") -> -1264.55 | G29: =+IFERROR(F29/E29,"") -> -0.3613 | I29: 2235.45 | J29: 3500 | K29: =+IFERROR(I29-J29,"") -> -1264.55 | L29: =+IFERROR(K29/J29,"") -> -0.3613 | N29: 2235.45 | O29: 3500 | P29: =+IFERROR(N29-O29,"") -> -1264.55 | Q29: =+IFERROR(P29/O29,"") -> -0.3613
B30: Network Charges | D30: 273.09 | E30: 300 | F30: =+IFERROR(D30-E30,"") -> -26.91 | G30: =+IFERROR(F30/E30,"") -> -0.0897 | I30: 273.09 | J30: 300 | K30: =+IFERROR(I30-J30,"") -> -26.91 | L30: =+IFERROR(K30/J30,"") -> -0.0897 | N30: 273.09 | O30: 300 | P30: =+IFERROR(N30-O30,"") -> -26.91 | Q30: =+IFERROR(P30/O30,"") -> -0.0897
B31: Bank Charges | D31: 287.56 | E31: 375 | F31: =+IFERROR(D31-E31,"") -> -87.44 | G31: =+IFERROR(F31/E31,"") -> -0.23317333 | I31: 287.56 | J31: 375 | K31: =+IFERROR(I31-J31,"") -> -87.44 | L31: =+IFERROR(K31/J31,"") -> -0.23317333 | N31: 287.56 | O31: 375 | P31: =+IFERROR(N31-O31,"") -> -87.44 | Q31: =+IFERROR(P31/O31,"") -> -0.23317333
B32: Telephone | D32: 1645.42 | E32: 800 | F32: =+IFERROR(D32-E32,"") -> 845.42 | G32: =+IFERROR(F32/E32,"") -> 1.056775 | I32: 1645.42 | J32: 800 | K32: =+IFERROR(I32-J32,"") -> 845.42 | L32: =+IFERROR(K32/J32,"") -> 1.056775 | N32: 1645.42 | O32: 800 | P32: =+IFERROR(N32-O32,"") -> 845.42 | Q32: =+IFERROR(P32/O32,"") -> 1.056775
B33: Tenant Mailings | D33: 16.72 | E33: 27.136667 | F33: =+IFERROR(D33-E33,"") -> -10.416667 | G33: =+IFERROR(F33/E33,"") -> -0.38385948 | I33: 16.72 | J33: 27.136667 | K33: =+IFERROR(I33-J33,"") -> -10.416667 | L33: =+IFERROR(K33/J33,"") -> -0.38385948 | N33: 16.72 | O33: 27.136667 | P33: =+IFERROR(N33-O33,"") -> -10.416667 | Q33: =+IFERROR(P33/O33,"") -> -0.38385948
B34: Office Expense | D34: 94.23 | E34: 182.32346 | F34: =+IFERROR(D34-E34,"") -> -88.093458 | G34: =+IFERROR(F34/E34,"") -> -0.48317128 | I34: 94.23 | J34: 182.32346 | K34: =+IFERROR(I34-J34,"") -> -88.093458 | L34: =+IFERROR(K34/J34,"") -> -0.48317128 | N34: 94.23 | O34: 182.32346 | P34: =+IFERROR(N34-O34,"") -> -88.093458 | Q34: =+IFERROR(P34/O34,"") -> -0.48317128
... B36: Legal and Evictions | D36: 163.16 | E36: 175 | F36: =+IFERROR(D36-E36,"") -> -11.84 | G36: =+IFERROR(F36/E36,"") -> -0.067657143 | I36: 163.16 | J36: 175 | K36: =+IFERROR(I36-J36,"") -> -11.84 | L36: =+IFERROR(K36/J36,"") -> -0.067657143 | N36: 163.16 | O36: 175 | P36: =+IFERROR(N36-O36,"") -> -11.84 | Q36: =+IFERROR(P36/O36,"") -> -0.067657143
B37: Total Other Expenses | D37: =+SUM(D23:D36) -> 19762.76 | E37: =+SUM(E23:E36) -> 22806.795 | F37: =+IFERROR(D37-E37,"") -> -3044.0345 | G37: =+IFERROR(F37/E37,"") -> -0.13347051 | I37: =+SUM(I23:I36) -> 19762.76 | J37: =+SUM(J23:J36) -> 22806.795 | K37: =+IFERROR(I37-J37,"") -> -3044.0345 | L37: =+IFERROR(K37/J37,"") -> -0.13347051 | N37: =+SUM(N23:N36) -> 19762.76 | O37: =+SUM(O23:O36) -> 22806.795 | P37: =+IFERROR(N37-O37,"") -> -3044.0345 | Q37: =+IFERROR(P37/O37,"") -> -0.13347051
B39: Total Operating Expenses | D39: =+D20+D37 -> 24338.47 | E39: =+E20+E37 -> 27207.39 | F39: =+IFERROR(D39-E39,"") -> -2868.9201 | G39: =+IFERROR(F39/E39,"") -> -0.10544636 | I39: =+I20+I37 -> 24338.47 | J39: =+J20+J37 -> 27207.39 | K39: =+IFERROR(I39-J39,"") -> -2868.9201 | L39: =+IFERROR(K39/J39,"") -> -0.10544636 | N39: =+N20+N37 -> 24338.47 | O39: =+O20+O37 -> 27207.39 | P39: =+IFERROR(N39-O39,"") -> -2868.9201 | Q39: =+IFERROR(P39/O39,"") -> -0.10544636
F40: =+IFERROR(D40-E40,"") -> 0 | G40: =+IFERROR(F40/E40,"") | K40: =+IFERROR(I40-J40,"") -> 0 | L40: =+IFERROR(K40/J40,"") | P40: =+IFERROR(N40-O40,"") -> 0 | Q40: =+IFERROR(P40/O40,"")
B41: Net Operating Income | D41: =+D14-D39 -> 73151.14 | E41: =+E14-E39 -> 66129.705 | F41: =+IFERROR(D41-E41,"") -> 7021.4349 | G41: =+IFERROR(F41/E41,"") -> 0.10617672 | I41: =+I14-I39 -> 73151.14 | J41: =+J14-J39 -> 66129.705 | K41: =+IFERROR(I41-J41,"") -> 7021.4349 | L41: =+IFERROR(K41/J41,"") -> 0.10617672 | N41: =+N14-N39 -> 73151.14 | O41: =+O14-O39 -> 66129.705 | P41: =+IFERROR(N41-O41,"") -> 7021.4349 | Q41: =+IFERROR(P41/O41,"") -> 0.10617672
B43: Other items
B44: Other Income | D44: 0 | E44: 0 | F44: =+IFERROR(D44-E44,"") -> 0 | G44: =+IFERROR(F44/E44,"") | I44: 0 | J44: 0 | K44: =+IFERROR(I44-J44,"") -> 0 | L44: =+IFERROR(K44/J44,"") | N44: 0 | O44: 0 | P44: =+IFERROR(N44-O44,"") -> 0 | Q44: =+IFERROR(P44/O44,"")
B45: Property Insurance | D45: 33.42 | E45: 0 | F45: =+IFERROR(D45-E45,"") -> 33.42 | G45: =+IFERROR(F45/E45,"") | I45: 33.42 | J45: 0 | K45: =+IFERROR(I45-J45,"") -> 33.42 | L45: =+IFERROR(K45/J45,"") | N45: 33.42 | O45: 0 | P45: =+IFERROR(N45-O45,"") -> 33.42 | Q45: =+IFERROR(P45/O45,"")
B46: Other Insurance | D46: 0 | E46: 0 | F46: =+IFERROR(D46-E46,"") -> 0 | G46: =+IFERROR(F46/E46,"") | I46: 0 | J46: 0 | K46: =+IFERROR(I46-J46,"") -> 0 | L46: =+IFERROR(K46/J46,"") | N46: 0 | O46: 0 | P46: =+IFERROR(N46-O46,"") -> 0 | Q46: =+IFERROR(P46/O46,"")
B47: Property Tax | D47: 0 | E47: 0 | F47: =+IFERROR(D47-E47,"") -> 0 | G47: =+IFERROR(F47/E47,"") | I47: 0 | J47: 0 | K47: =+IFERROR(I47-J47,"") -> 0 | L47: =+IFERROR(K47/J47,"") | N47: 0 | O47: 0 | P47: =+IFERROR(N47-O47,"") -> 0 | Q47: =+IFERROR(P47/O47,"")
B48: Other Taxes | D48: 8.95 | E48: 0 | F48: =+IFERROR(D48-E48,"") -> 8.95 | G48: =+IFERROR(F48/E48,"") | I48: 8.95 | J48: 0 | K48: =+IFERROR(I48-J48,"") -> 8.95 | L48: =+IFERROR(K48/J48,"") | N48: 8.95 | O48: 0 | P48: =+IFERROR(N48-O48,"") -> 8.95 | Q48: =+IFERROR(P48/O48,"")
B49: Interest Expense | D49: 0 | E49: 0 | F49: =+IFERROR(D49-E49,"") -> 0 | G49: =+IFERROR(F49/E49,"") | I49: 0 | J49: 0 | K49: =+IFERROR(I49-J49,"") -> 0 | L49: =+IFERROR(K49/J49,"") | N49: 0 | O49: 0 | P49: =+IFERROR(N49-O49,"") -> 0 | Q49: =+IFERROR(P49/O49,"")
B50: Association Fees | D50: 0 | E50: 0 | F50: =+IFERROR(D50-E50,"") -> 0 | G50: =+IFERROR(F50/E50,"") | I50: 0 | J50: 0 | K50: =+IFERROR(I50-J50,"") -> 0 | L50: =+IFERROR(K50/J50,"") | N50: 0 | O50: 0 | P50: =+IFERROR(N50-O50,"") -> 0 | Q50: =+IFERROR(P50/O50,"")
B51: Professional Fees | D51: 0 | E51: 0 | F51: =+IFERROR(D51-E51,"") -> 0 | G51: =+IFERROR(F51/E51,"") | I51: 0 | J51: 0 | K51: =+IFERROR(I51-J51,"") -> 0 | L51: =+IFERROR(K51/J51,"") | N51: 0 | O51: 0 | P51: =+IFERROR(N51-O51,"") -> 0 | Q51: =+IFERROR(P51/O51,"")
B52: Total Other items | D52: =+SUM(D44:D51) -> 42.37 | E52: =+SUM(E44:E51) -> 0 | F52: =+IFERROR(D52-E52,"") -> 42.37 | G52: =+IFERROR(F52/E52,"") | I52: =+SUM(I44:I51) -> 42.37 | J52: =+SUM(J44:J51) -> 0 | K52: =+IFERROR(I52-J52,"") -> 42.37 | L52: =+IFERROR(K52/J52,"") | N52: =+SUM(N44:N51) -> 42.37 | O52: =+SUM(O44:O51) -> 0 | P52: =+IFERROR(N52-O52,"") -> 42.37 | Q52: =+IFERROR(P52/O52,"")
B54: Net Income | D54: =+D41-D52 -> 73108.77 | E54: =+E41-E52 -> 66129.705 | F54: =+IFERROR(D54-E54,"") -> 6979.0649 | G54: =+IFERROR(F54/E54,"") -> 0.105536 | I54: =+I41-I52 -> 73108.77 | J54: =+J41-J52 -> 66129.705 | K54: =+IFERROR(I54-J54,"") -> 6979.0649 | L54: =+IFERROR(K54/J54,"") -> 0.105536 | N54: =+N41-N52 -> 73108.77 | O54: =+O41-O52 -> 66129.705 | P54: =+IFERROR(N54-O54,"") -> 6979.0649 | Q54: =+IFERROR(P54/O54,"") -> 0.105536

Sheet IS.BS.Detail
A2: IS/BS Detail
A3: 77712 - Wentworth (Vacaville, CA)
A4: 1/31/2026
B6: Feb-2025 | C6: Mar-2025 | D6: Apr-2025 | E6: May-2025 | F6: Jun-2025 | G6: Jul-2025 | H6: Aug-2025 | I6: Sep-2025 | J6: Oct-2025 | K6: Nov-2025 | L6: Dec-2025 | M6: Jan-2026
A8: Cash | B8: 138285.76 | C8: 171724.82 | D8: 97506.84 | E8: 109356.15 | F8: 101771.71 | G8: 107949.61 | H8: 120725.16 | I8: 113578.72 | J8: 123543.35 | K8: 116720.29 | L8: 136202.39 | M8: 238209.52
A9: 100110 - Cash - Operations-Cash | B9: 138285.76 | C9: 171724.82 | D9: 97506.84 | E9: 109356.15 | F9: 101771.71 | G9: 107949.61 | H9: 120725.16 | I9: 113578.72 | J9: 123543.35 | K9: 116720.29 | L9: 136202.39 | M9: 238209.52
A10: Account Receivable | B10: -1607.84 | C10: 523.92 | D10: 1263.1 | E10: -331.14 | F10: 1234.87 | G10: 2227.33 | H10: -1557.08 | I10: 2771.19 | J10: 2082.06 | K10: 4105.97 | L10: 3074.62 | M10: 2775.77
A11: 191000 - A/R - DlnqntStrgeRnt-Account Receivable | B11: 1531 | C11: 1570.37 | D11: 1436.67 | E11: 1929.67 | F11: 1021.91 | G11: 2309.23 | H11: 1700.32 | I11: 2549.83 | J11: 2258.95 | K11: 4781.5 | L11: 3804.04 | M11: 3757.06
A12: 192900 - AR/AP IntrprptyClctn-Account Receivable | B12: -3138.84 | C12: -1046.45 | D12: -173.57 | E12: -2260.81 | F12: 212.96 | G12: -81.9 | H12: -3257.4 | I12: 221.36 | J12: -176.89 | K12: -675.53 | L12: -729.42 | M12: -981.29
A13: Inventory | B13: 3446.02 | C13: 3233.43 | D13: 3310.81 | E13: 2958.99 | F13: 3087.17 | G13: 2905.1 | H13: 4109.81 | I13: 3914.71 | J13: 3694.97 | K13: 3908.8 | L13: 3592.53 | M13: 3343.2
A14: 193000 - Inventory - Lock-Inventory | B14: 1427.48 | C14: 1270 | D14: 1457.96 | E14: 1173.48 | F14: 1325.88 | G14: 1163.32 | H14: 2402.84 | I14: 2270.76 | J14: 2103.12 | K14: 1925.32 | L14: 1676.4 | M14: 1457.96
A15: 193010 - Inventory - Box-Inventory | B15: 582.02 | C15: 543.22 | D15: 480.66 | E15: 442.44 | F15: 418.22 | G15: 421.43 | H15: 409.59 | I15: 392.84 | J15: 370.34 | K15: 619.39 | L15: 605.39 | M15: 597.8
A16: 193020 - Inventory - Other-Inventory | B16: 1436.52 | C16: 1420.21 | D16: 1372.19 | E16: 1343.07 | F16: 1343.07 | G16: 1320.35 | H16: 1297.38 | I16: 1251.11 | J16: 1221.51 | K16: 1364.09 | L16: 1310.74 | M16: 1287.44
A17: Prepaid and Other | B17: 0 | C17: 0 | D17: 0 | E17: 0 | F17: 0 | G17: 0 | H17: 0 | I17: 0 | J17: 0 | K17: 0 | L17: 0 | M17: 0
A18: Intercompany | B18: 0 | C18: 0 | D18: 0 | E18: 0 | F18: 0 | G18: 0 | H18: 0 | I18: 0 | J18: 0 | K18: 0 | L18: 0 | M18: 0
A19: Other Assets | B19: 0 | C19: 0 | D19: 0 | E19: 0 | F19: 0 | G19: 0 | H19: 0 | I19: 0 | J19: 0 | K19: 0 | L19: 0 | M19: 0
... A203: Professional Fees | B203: 0 | C203: 0 | D203: 0 | E203: 0 | F203: 0 | G203: 0 | H203: 0 | I203: 0 | J203: 0 | K203: 0 | L203: 0 | M203: 0

Sheet Monthly Activity
A1: Roll-up | B1: Profit Center | C1: G/L Account Number | D1: G/L Account Desc | E1: 45716 | F1: 45747 | G1: 45777 | H1: 45808 | I1: 45838 | J1: 45869 | K1: 45900 | L1: 45930 | M1: 45961 | N1: 45991 | O1: 46022 | P1: 46053
A2: capex | B2: 77712 | C2: 129010 | D2: Bldng&Eqpmnt-NonPS | J2: 2058.61 | K2: 1755 | N2: 2005.69 | P2: 3000
A3: capex | B3: 77712 | C3: 129030 | D3: Rebranding - Non PS | F3: 0
B4: 77712 | C4: 210050 | D4: AP Sales Tax Collctn | G4: 4.86 | H4: 1.62 | K4: 1.62 | M4: 1.62
B5: 77712 | C5: 269020 | D5: Distributn 2 Parent | G5: 116177.51 | H5: 43203.11 | I5: 47592.93 | J5: 48752.3 | K5: 42954.49 | L5: 52604.69 | M5: 53246.95 | N5: 71323.59 | O5: 63089.35 | P5: 70987.01
A6: rent | B6: 77712 | C6: 400060 | D6: Rent Refunds | H6: 36.4 | K6: 1 | P6: 37.74
A7: retail | B7: 77712 | C7: 426000 | D7: Merchndse Sales-Lock | G7: 59.97 | H7: 19.99 | K7: 19.99 | M7: 19.99
A8: PR | B8: 77712 | C8: 500220 | D8: Prprty Mgr -Resident | E8: 2150.51 | F8: 2787.97 | G8: 3063.37 | H8: 3072.56 | I8: 3127.92 | J8: 2887.71 | K8: 2547.72 | L8: 2950.87 | M8: 3280.29 | N8: 3397.21 | O8: 3017.85 | P8: 2575.01
A9: PR | B9: 77712 | C9: 500230 | D9: Prprty Mgr -NonRsdnt | E9: 4061.52 | F9: 1433.72 | G9: 1895.35 | H9: 3127.21 | I9: 2793.04 | J9: 2278.45 | K9: 3709.82 | L9: 2344.74 | M9: 755.62 | N9: 408.02 | O9: 1274.4 | P9: 1552.76
A10: PR | B10: 77712 | C10: 500250 | D10: Accrued Payroll | F10: -129.28 | I10: -35.26 | L10: -38.87 | O10: 180.03
A11: PR | B11: 77712 | C11: 500300 | D11: Overtime Pay | E11: 39.14 | F11: 16.33 | G11: 45.35 | H11: 54.54 | I11: 23.28 | J11: 27.31 | K11: 20.19 | L11: 273.14 | M11: 74.76 | N11: 501.58 | O11: 234.5 | P11: 10.13
A12: PR | B12: 77712 | C12: 500310 | D12: MileageReimb-PrpMgrs | F12: 121.29 | G12: 68.81 | H12: 66.5 | I12: 64.78 | J12: 60.86 | K12: 76.3 | L12: 78.08 | M12: 51.47 | N12: 73.15 | O12: 67.72 | P12: 68.15
A13: PR | B13: 77712 | C13: 500320 | D13: Uniform | F13: 42.04 | G13: 38.53 | H13: 40.12 | I13: 38.8 | J13: 37.57 | K13: 40.69 | L13: 41.15 | M13: 36.32 | N13: 35.47 | O13: 33.59 | P13: 36.23
A14: PR | B14: 77712 | C14: 500330 | D14: Vacation/PTO | F14: 67.9 | G14: 116.99 | H14: 74.26 | I14: 177.96 | J14: 213.79 | K14: 94.51 | L14: 155.89 | M14: 123.53 | N14: 105.1 | O14: 131.29 | P14: 168.1
A15: PR | B15: 77712 | C15: 500350 | D15: Sick Pay | F15: 51.05 | G15: 39.67 | H15: 143.47 | I15: 42.81 | J15: 56.8 | K15: 86.56 | L15: 74.88 | M15: 80.94 | N15: 67.48 | O15: 25.91 | P15: 63.27
A16: PR | B16: 77712 | C16: 500360 | D16: Payout Upon Termintn | L16: 37.91 | P16: 6.5
A17: PR | B17: 77712 | C17: 500390 | D17: Holiday Bonus | O17: 183.22
A18: PR | B18: 77712 | C18: 500400 | D18: Anniversary Pay | G18: 48.91 | N18: 4.85 | P18: 171.28
A19: PR | B19: 77712 | C19: 500410 | D19: Payroll Burden | E19: 159.97 | F19: -29.56 | G19: -11.56 | H19: 10.61 | I19: -15.37 | J19: -4.44 | K19: 4.58 | L19: -14.65 | M19: 0.66 | N19: -1.59 | O19: 72.02 | P19: -4.15
A20: PR | B20: 77712 | C20: 500420 | D20: ER Social Security | E20: 316.06 | F20: 240.43 | G20: 289.17 | H20: 366.87 | I20: 347.8 | J20: 312.83 | K20: 375.73 | L20: 331.88 | M20: 234.57 | N20: 246.53 | O20: 274.52 | P20: 247.32
A21: PR | B21: 77712 | C21: 500430 | D21: ER Medicare | E21: 73.93 | F21: 56.23 | G21: 67.64 | H21: 85.79 | I21: 81.35 | J21: 73.17 | K21: 87.88 | L21: 77.62 | M21: 54.86 | N21: 57.67 | O21: 64.21 | P21: 57.85
A22: PR | B22: 77712 | C22: 500440 | D22: ER SUI | E22: 141.06 | F22: 15.53 | G22: 0.39 | H22: 0.27 | O22: 24.09 | P22: 122.89
A23: PR | B23: 77712 | C23: 500450 | D23: ER OtherStateP/R Tax | E23: 4.88 | F23: 0.48 | O23: 0.84 | P23: 3.41
A24: PR | B24: 77712 | C24: 500470 | D24: Workers Compensation | E24: 268.35 | F24: 254.98 | G24: 285.41 | H24: 364.41 | I24: 331.29 | J24: 311.45 | K24: 350.65 | L24: 322.64 | M24: 243.42 | N24: 244.1 | O24: 258.55 | P24: 255.13
A25: PR | B25: 77712 | C25: 500480 | D25: ER Futa | E25: 29.19 | F25: 3.21 | G25: 0.08 | H25: 0.06 | O25: 111.94 | P25: 23.78
A26: PR | B26: 77712 | C26: 500490 | D26: ER Med Full PremPlan | E26: 133.77 | F26: 994.79 | G26: 1097.26 | H26: 1104.72 | I26: 1111.61 | J26: 1045.03 | K26: 809.17 | L26: 1043.91 | M26: 1106.03 | N26: 1061.66 | O26: 902.88 | P26: 931.66
A27: PR | B27: 77712 | C27: 500500 | D27: ER Med Self-InsrdPln | F27: 0.56 | G27: 3.55
A28: PR | B28: 77712 | C28: 500520 | D28: ER Life | E28: 2.4 | F28: 2.52 | G28: 2.9 | H28: 3.28 | I28: 3.16 | J28: 2.96 | K28: 2.76 | L28: 2.83 | M28: 2.74 | N28: 2.39 | O28: 2.28 | P28: 2.56
A29: PR | B29: 77712 | C29: 500530 | D29: ER 401K Plan | E29: 3.62 | F29: 3.21 | G29: 3.19 | H29: 3.39 | I29: 2.72 | J29: 2.03 | K29: 1.73 | L29: 1.84 | M29: 1.33 | N29: 1.48 | O29: 4.22 | P29: 99.73
A30: PR | B30: 77712 | C30: 500540 | D30: ER AD & D | E30: 0.37 | F30: 0.37 | G30: 0.43 | H30: 0.49 | I30: 0.47 | J30: 0.44 | K30: 0.42 | L30: 0.44 | M30: 0.42 | N30: 0.36 | O30: 0.35 | P30: 0.38
A31: R&M | B31: 77712 | C31: 500720 | D31: Ops-R&M-Apartment | L31: 372.23
A32: R&M | B32: 77712 | C32: 500730 | D32: Ops-R&M-LdscpMtlyRcr | G32: 450 | H32: 450 | I32: 450 | J32: 450 | K32: 450 | L32: 900 | N32: 450 | O32: 450 | P32: 918
A33: R&M | B33: 77712 | C33: 500740 | D33: Ops-R&M-LdscpNonRcrg | I33: 1900 | K33: 3375
A34: R&M | B34: 77712 | C34: 500840 | D34: Ops-R&M-PstCtrl-Rcrg | E34: 67.18 | F34: 67.18 | G34: 67.18 | H34: 67.18 | I34: 67.18 | J34: 67.18 | K34: 67.18 | M34: 71.88 | P34: 71.88
A35: R&M | B35: 77712 | C35: 500900 | D35: Ops-R&M-ScurtyEqpRpr | I35: 445
A36: R&M | B36: 77712 | C36: 500930 | D36: Ops-R&M-Office R&M | F36: 430 | J36: 370
A37: R&M | B37: 77712 | C37: 500960 | D37: Ops-R&M-Door Repairs | G37: 300
A38: R&M | B38: 77712 | C38: 500970 | D38: Ops-R&M-DrRprs BrkIn | I38: 165.42
A39: R&M | B39: 77712 | C39: 501020 | D39: Ops-R&M-GnratorReprs | J39: 1445.06 | L39: 600
A40: R&M | B40: 77712 | C40: 501070 | D40: Ops-R&M-Elctrcl&Lght | F40: 320 | I40: 160 | M40: 320
A41: R&M | B41: 77712 | C41: 501110 | D41: Ops-R&M-GolfCartsRpr | M41: 200
A42: R&M | B42: 77712 | C42: 501130 | D42: Ops-R&M-TrashCollctn | E42: 533.59 | F42: 578.08 | G42: -59.08 | H42: 528.9 | I42: 54.49 | J42: 553.49 | K42: 10 | L42: 1015.56 | N42: 1907.95 | O42: 2540.44 | P42: 644.56
A43: R&M | B43: 77712 | C43: 501160 | D43: Ops-R&M-AbnGdTrRmvl | H43: 540
A44: R&M | B44: 77712 | C44: 501180 | D44: Ops-R&M-Plmbng&Swer | H44: 841.25
A45: R&M | B45: 77712 | C45: 501190 | D45: Ops-R&M-MntSplEqpFul | E45: 268.48 | F45: 18 | G45: 129.31 | H45: 77.37 | I45: 347.98 | J45: 123.41 | K45: 89.07 | L45: 52.01 | M45: 151.48 | O45: 23.77
A46: R&M | B46: 77712 | C46: 501200 | D46: Ops-R&M-BulkSgnsMtrl | G46: 2.25 | I46: 1.75
A47: R&M | B47: 77712 | C47: 501400 | D47: Ops-R&M-SpecialPrjct | E47: 53.66 | O47: 48.42
A48: R&M | B48: 77712 | C48: 501580 | D48: Fac-R&M-ElvCttnPnlty | N48: 225
A49: R&M | B49: 77712 | C49: 501590 | D49: Fac-R&M-AccssCtrlRpr | O49: 80
A50: R&M | B50: 77712 | C50: 501610 | D50: Fac-R&M-Gate | E50: 300 | I50: 319.65
A51: R&M | B51: 77712 | C51: 501630 | D51: Fac-R&M-Roof Repairs | H51: 1005.62
A52: R&M | B52: 77712 | C52: 501700 | D52: Fac-R&M-FreAlrmMntrg | I52: 200 | K52: 150 | N52: 150
A53: R&M | B53: 77712 | C53: 501710 | D53: Fac-R&M-FrePrmtInspc | E53: 450 | F53: 950 | G53: 150 | H53: 435 | J53: 490 | K53: 979.5 | L53: 490 | N53: 245 | O53: 490
A54: R&M | B54: 77712 | C54: 501720 | D54: Fac-R&M-FireExtngshr | P54: 162.38
A55: R&M | B55: 77712 | C55: 501850 | D55: Fac-R&M-GntrMtlyMntn | L55: 1800 | M55: 600 | O55: 600 | P55: 600
A56: R&M | B56: 77712 | C56: 501910 | D56: Fac-R&M-HVAC | K56: 337.23
A57: util | B57: 77712 | C57: 505010 | D57: Electric Utility | J57: 9037.35 | K57: 3049.82 | L57: 3227.07 | M57: 2918.39 | N57: 2867.12 | O57: 3213.76 | P57: 2943.78
A58: util | B58: 77712 | C58: 505040 | D58: Water Utility | E58: 835
A59: util | B59: 77712 | C59: 505100 | D59: UtilitiesProcssngFee | K59: 7.7 | L59: 4.39 | M59: 4.39 | N59: 4.39 | O59: 4.39 | P59: 4.39
A60: util | B60: 77712 | C60: 505110 | D60: EnrgyAudt/BnchmrkFee | M60: 0.6 | N60: 0.3
A61: intadv | B61: 77712 | C61: 505500 | D61: Internet Mktg-Google | E61: 2171.01 | F61: 3638.1 | G61: 3286.03 | H61: 3902.77 | I61: 3207.41 | J61: 2355.29 | K61: 3326.23 | L61: 3370.15 | M61: 1750.46 | N61: 1666.52 | O61: 1645.44 | P61: 2234.45
A62: intadv | B62: 77712 | C62: 505510 | D62: Internet Mktg -Other | E62: 293.24 | F62: 128.23 | G62: 166.19 | H62: 277.91 | I62: 299.64 | J62: 368.31 | K62: 93.68 | L62: 110.76 | N62: 126.08 | O62: 107.48 | P62: 1
A63: intadv | B63: 77712 | C63: 505530 | D63: Intrnt Mktg-Facebook | E63: 226.32 | H63: 104.72
A64: intadv | B64: 77712 | C64: 505570 | D64: VidAds-TVMedia&Suprt | L64: 0
A65: office | B65: 77712 | C65: 506010 | D65: Office Supplies | E65: 36.77 | G65: 88.89 | H65: 154.66 | I65: 52.56 | J65: 48.77 | K65: 413.87 | L65: 45.65 | M65: 53.52 | O65: 42.66
A66: office | B66: 77712 | C66: 506020 | D66: Project Padlocks | E66: 424.41
A67: comp | B67: 77712 | C67: 506040 | D67: ComptrHardwr/Softwr | F67: 0 | H67: 0.55 | I67: 1.86 | L67: 1.83 | O67: 1.81
A68: office | B68: 77712 | C68: 506050 | D68: Software Purchases | G68: 0.62 | H68: 0.62 | I68: 0.62
A69: tel | B69: 77712 | C69: 506060 | D69: Telephone | E69: 6.21 | F69: 3303.39 | G69: 6.19 | H69: 6.16 | I69: 6.17 | J69: 3271.3 | K69: 6.04 | L69: 841.6 | M69: 977.89 | N69: 827.65 | O69: 15.49 | P69: 1645.42
A70: pstg | B70: 77712 | C70: 506080 | D70: CentralzdTnantMailng | E70: 16.04 | F70: 17.87 | G70: 18.61 | H70: 23.91 | I70: 17.03 | J70: 35.27 | K70: 38.71 | L70: 42.98 | M70: 26.43 | N70: 33.21 | O70: 31.24 | P70: 16.72
A71: office | B71: 77712 | C71: 506110 | D71: OfficeBulkSgns/Matrl | E71: 3.21 | F71: 3.77 | I71: 2.26 | J71: 30.96 | K71: 18.05 | L71: 8.49 | M71: 14.06 | N71: 2.26 | O71: 0.36 | P71: 7.86
A72: office | B72: 77712 | C72: 506120 | D72: UniformPurchaseExp | G72: 73.18 | K72: 45.47 | P72: 86.37
A73: lgl | B73: 77712 | C73: 506140 | D73: Eviction Costs | E73: 101.4 | F73: 264.15 | G73: 204.86 | H73: 152.38 | I73: 284.61 | J73: 42.5 | K73: 158 | L73: 50.69 | M73: 263.18 | N73: 213.33 | O73: 42.5 | P73: 163.16
A74: ntwrk | B74: 77712 | C74: 506150 | D74: Network Charges | E74: 260.69 | F74: 260.69 | G74: 260.69 | H74: 260.69 | I74: 260.69 | J74: 260.69 | K74: 260.77 | L74: 260.77 | M74: 260.77 | N74: 260.77 | O74: 260.77 | P74: 273.09
A75: bc | B75: 77712 | C75: 506180 | D75: Bank Charges | E75: 284.04 | F75: 264.89 | G75: 295.5 | H75: 295.24 | I75: 316.84 | J75: 281.08 | K75: 311.19 | L75: 327.42 | M75: 306.72 | N75: 319.68 | O75: 281.58 | P75: 256.38
A76: ccdisc | B76: 77712 | C76: 506190 | D76: Credit Card Discount | E76: 688.79 | F76: 745.47 | G76: 868.93 | H76: 1018.65 | I76: 1018.08 | J76: 1078.19 | K76: 1173.52 | L76: 1145.32 | M76: 1288.68 | N76: 1225.78 | O76: 1449.96 | P76: 1469.89
A77: bc | B77: 77712 | C77: 506200 | D77: FraudProtectionSrvcs | E77: 35.12 | F77: 34.9 | G77: 35.38 | H77: 35.46 | I77: 35.79 | J77: 35.5 | K77: 33.05 | L77: 32.86 | M77: 32.48 | N77: 32.89 | O77: 61.86 | P77: 31.18
A78: lic | B78: 77712 | C78: 506210 | D78: Business License | M78: 410.25
A79: R&M | B79: 77712 | C79: 506260 | D79: Processing Fees | E79: 115 | F79: 115 | G79: 115 | H79: 115 | I79: 115 | J79: 115 | K79: 115 | L79: 115 | M79: 115 | N79: 115 | O79: 115 | P79: 115
A80: PR | B80: 77712 | C80: 506275 | D80: Employee Awards | E80: 10.8
A81: PropIns | B81: 77712 | C81: 506280 | D81: Other Expenses | F81: 117.39 | J81: 14.03 | P81: 33.42
A82: PRDM | B82: 77712 | C82: 510050 | D82: PR/Exp - DistrictMgr | E82: 1303.22 | F82: 1522.62 | G82: 723.29 | H82: 1056.62 | I82: 864.46 | J82: 892.53 | K82: 914.95 | L82: 883.54 | M82: 779.34 | N82: 838.3 | O82: 980.38 | P82: 871.77
A83: PR | B83: 77712 | C83: 510070 | D83: PR/Exp - DTM Manager | H83: 191.28 | I83: 192.08 | J83: 185.79 | K83: 177.51 | L83: 161.22 | M83: 177.49 | N83: 187.82 | O83: 189.22 | P83: 202.16
A84: PR | B84: 77712 | C84: 510510 | D84: PR/Exp - Facilities | I84: 256.51 | J84: 264.65 | K84: 235.33 | L84: 257.96 | M84: 266.64 | N84: 282.7 | O84: 353.1 | P84: 277.35
A85: PRDM | B85: 77712 | C85: 510840 | D85: Field Meals&Entrtnmn | G85: 3.26 | H85: 6.53 | J85: 6.52 | L85: 276.12 | O85: 6.4
A86: mgmt | B86: 77712 | C86: 556000 | D86: Management Fees | E86: 1754.77 | F86: 2058.87 | G86: 2286.18 | H86: 2694.28 | I86: 2709.73 | J86: 2950.41 | K86: 3144.77 | L86: 3149.43 | M86: 3536.17 | N86: 3345.34 | O86: 3636.85 | P86: 3727.71
A87: cctr | B87: 77712 | C87: 556650 | D87: TPM-TelephnRsrvtnCtr | E87: 549 | F87: 549 | G87: 549 | H87: 549 | I87: 549 | J87: 549 | K87: 549 | L87: 549 | M87: 549 | N87: 549 | O87: 549 | P87: 549
A88: comp | B88: 77712 | C88: 556670 | D88: TPM-CntractSftwrFees | E88: 299 | F88: 299 | G88: 299 | H88: 299 | I88: 299 | J88: 299 | K88: 299 | L88: 299 | M88: 299 | N88: 299 | O88: 299 | P88: 299
B89: 77712 | C89: 100110 | D89: Cash - Operations | E89: 28861.34 | F89: 33439.06 | G89: -74217.98 | H89: 11849.31 | I89: -7584.44 | J89: 6177.9 | K89: 12775.55 | L89: -7146.44 | M89: 9964.63 | N89: -6823.06 | O89: 19482.1 | P89: 102007.13
B90: 77712 | C90: 191000 | D90: A/R - DlnqntStrgeRnt | E90: 1138 | F90: 39.37 | G90: -133.7 | H90: 493 | I90: -907.76 | J90: 1287.32 | K90: -608.91 | L90: 849.51 | M90: -290.88 | N90: 2522.55 | O90: -977.46 | P90: -46.98
B91: 77712 | C91: 192900 | D91: AR/AP IntrprptyClctn | E91: -1292.02 | F91: 2092.39 | G91: 872.88 | H91: -2087.24 | I91: 2473.77 | J91: -294.86 | K91: -3175.5 | L91: 3478.76 | M91: -398.25 | N91: -498.64 | O91: -53.89 | P91: -251.87
B92: 77712 | C92: 200000 | D92: AP - Trade | G92: -64.83 | H92: 64.83 | K92: 0 | M92: -21.61 | N92: 21.61 | P92: 0
B93: 77712 | C93: 200010 | D93: AP-Trade-RAMPsupplrs | E93: -450 | F93: -1250 | G93: 1700 | H93: -975 | I93: 975 | J93: -3503.67 | K93: -1911.21 | L93: 4814.88 | M93: 600 | N93: -225 | O93: 0 | P93: -843
B94: 77712 | C94: 200100 | D94: A/P - PS Clearing | E94: -2572.22 | F94: -4481.56 | G94: -4650.39 | H94: -8361.21 | I94: 1812.18 | J94: -11985.49 | K94: -1894.75 | L94: -3175.13 | M94: 4087.15 | N94: -4022.69 | O94: -15753.37 | P94: -105079.05
B95: 77712 | C95: 210050 | D95: AP Sales Tax Collctn | E95: 749 | F95: 73
B96: 77712 | C96: 215060 | D96: DfrrdRvnu-StrgeTnnts | E96: -1041.12 | F96: 303.14 | G96: 441.91 | H96: -3443.52 | I96: 1726.97 | J96: 16.81 | K96: 959.02 | L96: 838.94 | M96: -2921.44 | N96: 1319.66 | O96: -1416.04 | P96: -398.69
B97: 77712 | C97: 295000 | D97: Doc Split Clrng - Ac | E97: -108.05 | F97: -21.61 | G97: -64.83 | H97: -48.72 | I97: -81.04 | J97: -43.22 | K97: -19.44 | L97: -43.22 | N97: -43.22 | P97: -47.56
A98: rent | B98: 77712 | C98: 400000 | D98: Rental Income-Storge | E98: -41228.66 | F98: -48676.5 | G98: -53913.69 | H98: -64068.12 | I98: -64854.37 | J98: -71547.31 | K98: -75135.39 | L98: -76212.46 | M98: -84801.72 | N98: -80393.91 | O98: -86720.43 | P98: -88957.23
A99: other | B99: 77712 | C99: 400020 | D99: NSF Fees-ACH&ChkRtrn | E99: -25 | F99: -50 | G99: -150 | H99: -275 | I99: -100 | J99: -125 | K99: -50 | L99: -50 | M99: -125 | O99: -50 | P99: -25
A100: other | B100: 77712 | C100: 400030 | D100: Collections | O100: -108.8 | P100: -99
...

Sheet Trial Balance
A1: Roll-up | B1: Profit Center | C1: G/L Account Number | D1: G/L Account Desc | E1: 46053
A2: capex | B2: 77712 | C2: 129010 | D2: Building and Equipment - Non PS | E2: 9903.67
A3: capex | B3: 77712 | C3: 129020 | D3: Computer & other equipment - Non PS | E3: 3115.49
A4: capex | B4: 77712 | C4: 129030 | D4: Rebranding - Non PS | E4: 0
A5: AP | B5: 77712 | C5: 210050 | D5: AP Sales Tax Collections | E5: 14.58
A6: Eqty | B6: 77712 | C6: 269020 | D6: Distribution to Parent | E6: 609931.93
A7: PL | B7: 77712 | C7: 400060 | D7: Rent Refunds | E7: 37.74
A8: PL | B8: 77712 | C8: 426000 | D8: Merchandise Sales - Lock
A9: PL | B9: 77712 | C9: 500220 | D9: Property Manager - Resident | E9: 2575.01
A10: PL | B10: 77712 | C10: 500230 | D10: Property Manager - Non-Resident | E10: 1552.76
A11: PL | B11: 77712 | C11: 500250 | D11: Accrued Payroll
A12: PL | B12: 77712 | C12: 500300 | D12: Overtime Pay | E12: 10.13
A13: PL | B13: 77712 | C13: 500310 | D13: Mileage Reimb - Property Mgrs | E13: 68.15
A14: PL | B14: 77712 | C14: 500320 | D14: Uniform | E14: 36.23
A15: PL | B15: 77712 | C15: 500330 | D15: Vacation/PTO | E15: 168.1
A16: PL | B16: 77712 | C16: 500350 | D16: Sick Pay | E16: 63.27
A17: PL | B17: 77712 | C17: 500360 | D17: Payout Upon Termination | E17: 6.5
A18: PL | B18: 77712 | C18: 500390 | D18: Holiday Bonus
A19: PL | B19: 77712 | C19: 500400 | D19: Anniversary Pay | E19: 171.28
A20: PL | B20: 77712 | C20: 500410 | D20: Payroll Burden | E20: -4.15
A21: PL | B21: 77712 | C21: 500420 | D21: ER Social Security | E21: 247.32
A22: PL | B22: 77712 | C22: 500430 | D22: ER Medicare | E22: 57.85
A23: PL | B23: 77712 | C23: 500440 | D23: ER SUI | E23: 122.89
A24: PL | B24: 77712 | C24: 500450 | D24: ER Other State P/R Taxes | E24: 3.41
A25: PL | B25: 77712 | C25: 500470 | D25: Workers Compensation | E25: 255.13
A26: PL | B26: 77712 | C26: 500480 | D26: ER Futa | E26: 23.78
A27: PL | B27: 77712 | C27: 500490 | D27: ER Medical Full Premium Plans | E27: 931.66
A28: PL | B28: 77712 | C28: 500500 | D28: ER Medical Self-Insured Plans
A29: PL | B29: 77712 | C29: 500520 | D29: ER Life | E29: 2.56
A30: PL | B30: 77712 | C30: 500530 | D30: ER 401K Plan | E30: 99.73
A31: PL | B31: 77712 | C31: 500540 | D31: ER AD & D | E31: 0.38
A32: PL | B32: 77712 | C32: 500720 | D32: Ops-R&M-Apartment
A33: PL | B33: 77712 | C33: 500730 | D33: Ops-R&M-Landscaping-Monthly Recurring | E33: 918
A34: PL | B34: 77712 | C34: 500740 | D34: Ops-R&M-Landscaping-Non-Recurring
A35: PL | B35: 77712 | C35: 500840 | D35: Ops-R&M-Pest Control-Recurring | E35: 71.88
A36: PL | B36: 77712 | C36: 500900 | D36: Ops-R&M-Security Equipment Repairs
A37: PL | B37: 77712 | C37: 500930 | D37: Ops-R&M-Office R&M
A38: PL | B38: 77712 | C38: 500960 | D38: Ops-R&M-Door Repairs
A39: PL | B39: 77712 | C39: 500970 | D39: Ops-R&M-Door Repairs-Break Ins
A40: PL | B40: 77712 | C40: 501020 | D40: Ops-R&M-Generator Repairs | E40: 0
A41: PL | B41: 77712 | C41: 501070 | D41: Ops-R&M-Electrical & Lighting
A42: PL | B42: 77712 | C42: 501110 | D42: Ops-R&M-Golf Carts Repair
A43: PL | B43: 77712 | C43: 501130 | D43: Ops-R&M-Trash Collection | E43: 644.56
A44: PL | B44: 77712 | C44: 501160 | D44: Ops-R&M-Abandoned Goods Trash Removal
A45: PL | B45: 77712 | C45: 501180 | D45: Ops-R&M-Plumbing & Sewer
A46: PL | B46: 77712 | C46: 501190 | D46: Ops-R&M-Maint Supplies/Equipment/Fuel
A47: PL | B47: 77712 | C47: 501200 | D47: Ops-R&M-Bulk Signs/Materials
A48: PL | B48: 77712 | C48: 501400 | D48: Ops-R&M-SpecialPrjct
A49: PL | B49: 77712 | C49: 501580 | D49: Fac-R&M-Elevator Citations/Penalties
A50: PL | B50: 77712 | C50: 501590 | D50: Fac-R&M-Access Control Repairs
A51: PL | B51: 77712 | C51: 501610 | D51: Fac-R&M-Gate
A52: PL | B52: 77712 | C52: 501630 | D52: Fac-R&M-Roof Repairs
A53: PL | B53: 77712 | C53: 501700 | D53: Fac-R&M-Fire Alarm Monitoring
A54: PL | B54: 77712 | C54: 501710 | D54: Fac-R&M-Fire Permits/Inspections
A55: PL | B55: 77712 | C55: 501720 | D55: Fac-R&M-Fire Extinguishers | E55: 162.38
A56: PL | B56: 77712 | C56: 501850 | D56: Fac-R&M-Generator Monthly Maintenance | E56: 600
A57: PL | B57: 77712 | C57: 501910 | D57: Fac-R&M-HVAC
A58: PL | B58: 77712 | C58: 505010 | D58: Electric Utility | E58: 2943.78
A59: PL | B59: 77712 | C59: 505040 | D59: Water Utility
A60: PL | B60: 77712 | C60: 505100 | D60: Utilities Processing Fees | E60: 4.39
A61: PL | B61: 77712 | C61: 505110 | D61: Energy Audit/Benchmarking Fees
A62: PL | B62: 77712 | C62: 505500 | D62: Internet Mktg - Google | E62: 2234.45
A63: PL | B63: 77712 | C63: 505510 | D63: Internet Mktg - Other | E63: 1
A64: PL | B64: 77712 | C64: 505530 | D64: Internet Mktg - Facebook
A65: PL | B65: 77712 | C65: 505570 | D65: Video Ads-TV Media & Support
A66: PL | B66: 77712 | C66: 506010 | D66: Office Supplies
A67: PL | B67: 77712 | C67: 506020 | D67: Project Padlocks
A68: PL | B68: 77712 | C68: 506040 | D68: Computer Hardware/Software
A69: PL | B69: 77712 | C69: 506050 | D69: Software Purchases / Maintenance
A70: PL | B70: 77712 | C70: 506060 | D70: Telephone | E70: 1645.42
A71: PL | B71: 77712 | C71: 506080 | D71: Centralized Tenant Mailing | E71: 16.72
A72: PL | B72: 77712 | C72: 506110 | D72: Office Bulk Signs/Materials | E72: 7.86
A73: PL | B73: 77712 | C73: 506120 | D73: Uniform Purchase Expense | E73: 86.37
A74: PL | B74: 77712 | C74: 506140 | D74: Eviction Costs | E74: 163.16
A75: PL | B75: 77712 | C75: 506150 | D75: Network Charges | E75: 273.09
A76: PL | B76: 77712 | C76: 506180 | D76: Bank Charges | E76: 256.38
A77: PL | B77: 77712 | C77: 506190 | D77: Credit Card Discounts | E77: 1469.89
A78: PL | B78: 77712 | C78: 506200 | D78: Fraud Protection Services | E78: 31.18
A79: PL | B79: 77712 | C79: 506210 | D79: Business License
A80: PL | B80: 77712 | C80: 506260 | D80: Processing Fees | E80: 115
A81: PL | B81: 77712 | C81: 506275 | D81: Employee Awards
A82: PL | B82: 77712 | C82: 506280 | D82: Other Expenses | E82: 33.42
A83: PL | B83: 77712 | C83: 510050 | D83: PR/Exp - District Manager | E83: 871.77
A84: PL | B84: 77712 | C84: 510070 | D84: PR/Exp - DTM Manager | E84: 202.16
A85: PL | B85: 77712 | C85: 510510 | D85: PR/Exp - Facilities | E85: 277.35
A86: PL | B86: 77712 | C86: 510840 | D86: Field Meals and Entertaiment
A87: PL | B87: 77712 | C87: 556000 | D87: Management Fees | E87: 3727.71
A88: PL | B88: 77712 | C88: 556650 | D88: TPM-Telephone Reservation Center | E88: 549
A89: PL | B89: 77712 | C89: 556670 | D89: TPM-Contractual Software Fees | E89: 299
A90: cash | B90: 77712 | C90: 100110 | D90: Cash - Operations | E90: 238209.52
A91: AR | B91: 77712 | C91: 191000 | D91: A/R - Delinquent Storage Rent | E91: 3757.06
A92: AR | B92: 77712 | C92: 192900 | D92: AR (AP) - Interproperty Collections | E92: -981.29
A93: AP | B93: 77712 | C93: 200000 | D93: AP - Trade | E93: 0
A94: AP | B94: 77712 | C94: 200010 | D94: AP - Trade - RAMP Suppliers | E94: -1068
A95: AP | B95: 77712 | C95: 200100 | D95: A/P - PS Clearing | E95: -175318.56
A96: AP | B96: 77712 | C96: 210050 | D96: AP Sales Tax Collections | E96: 1214
A97: DefRev | B97: 77712 | C97: 215060 | D97: Deferred Revenue - Storage Tenants | E97: -8077.89
A98: Eqty | B98: 77712 | C98: 269000 | D98: Contributions from Parent | E98: -44278.97
... A107: PL | B107: 77712 | C107: 400090 | D107: DTM Non-Taxable Sales Proceeds | E107: -180
A108: PL | B108: 77712 | C108: 400160 | D108: NSF Checks
...

Sheet GL
A1: Posting Date | B1: Doc. Date | C1: Journal Entry | D1: Journal Entry Type | E1: Journal Entry Item Text | F1: Journal Entry Text | G1: Profit Center | H1: G/L Account Number | I1: G/L Account Desc | J1: Vendor | K1: Vendor Name | L1: Offsetting Acc | M1: Offsetting Acc Name | N1: $
A2: 01/01/2026 | B2: 11/11/2025 | C2: 830019081 | D2: YG | E2: 8310012834696 | F2: Engie/E78 | G2: 77712 | H2: 506060 | I2: Telephone | J2: # | K2: # | L2: R24015609 | M2: AT&T - UNIVERSAL BILLER | N2: 817.82
A3: 01/01/2026 | B3: 11/11/2025 | C3: 830019081 | D3: YG | E3: 8310012834696 | F3: Engie/E78 | G3: 77712 | H3: 200010 | I3: AP-Trade-RAMPsupplrs | J3: R24015609 | K3: AT&T - UNIVERSAL BILLER/60197-5019 CAROL STREAM | L3: 506060 | M3: Telephone | N3: -817.82
A4: 01/01/2026 | B4: 11/11/2025 | C4: 830019081 | D4: YG | E4: 8310012834696 | F4: Engie/E78 | G4: 77712 | H4: 200010 | I4: AP-Trade-RAMPsupplrs | J4: R24015609 | K4: AT&T - UNIVERSAL BILLER/60197-5019 CAROL STREAM | L4: R24015609 | M4: AT&T - UNIVERSAL BILLER | N4: 817.82
A5: 01/01/2026 | B5: 11/11/2025 | C5: 830019081 | D5: YG | E5: 8310012834696 | F5: Engie/E78 | G5: 77712 | H5: 200010 | I5: AP-Trade-RAMPsupplrs | J5: R24022899 | K5: ELEMENT 78, LLC/60673-5472 CHICAGO | L5: 506060 | M5: Telephone | N5: -817.82
A6: 01/01/2026 | B6: 01/01/2026 | C6: 850198770 | D6: CW | E6: ACH Cash | F6: WebChamp Revenue | G6: 77712 | H6: 100110 | I6: Cash - Operations | J6: # | K6: # | L6: 400220 | M6: Accrual RevnueAdjmnt | N6: 146
A7: 01/01/2026 | B7: 01/01/2026 | C7: 850198770 | D7: CW | E7: Conv Fees - Mini | F7: WebChamp Revenue | G7: 77712 | H7: 400210 | I7: IVR Convenience Fees | J7: # | K7: # | L7: 191000 | M7: A/R - DlnqntStrgeRnt | N7: -20
A8: 01/01/2026 | B8: 01/01/2026 | C8: 850198770 | D8: CW | E8: Current Rent - Mini | F8: WebChamp Revenue | G8: 77712 | H8: 400000 | I8: Rental Income-Storge | J8: # | K8: # | L8: 191000 | M8: A/R - DlnqntStrgeRnt | N8: -1371.1
A9: 01/01/2026 | B9: 01/01/2026 | C9: 850198770 | D9: CW | E9: Late Fees - Mini | F9: WebChamp Revenue | G9: 77712 | H9: 402020 | I9: Late Charges | J9: # | K9: # | L9: 191000 | M9: A/R - DlnqntStrgeRnt | N9: -32.55
A10: 01/01/2026 | B10: 01/01/2026 | C10: 850198770 | D10: CW | E10: Lien Fees | F10: WebChamp Revenue | G10: 77712 | H10: 402000 | I10: Lien Fees | J10: # | K10: # | L10: 191000 | M10: A/R - DlnqntStrgeRnt | N10: -55.5
A11: 01/01/2026 | B11: 01/01/2026 | C11: 850198770 | D11: CW | E11: Master Card | F11: WebChamp Revenue | G11: 77712 | H11: 100110 | I11: Cash - Operations | J11: # | K11: # | L11: 400220 | M11: Accrual RevnueAdjmnt | N11: 531.15
A12: 01/01/2026 | B12: 01/01/2026 | C12: 850198770 | D12: CW | E12: Net Change in A/R | F12: WebChamp Revenue | G12: 77712 | H12: 191000 | I12: A/R - DlnqntStrgeRnt | J12: # | K12: # | L12: 400220 | M12: Accrual RevnueAdjmnt | N12: 81893.14
A13: 01/01/2026 | B13: 01/01/2026 | C13: 850198770 | D13: CW | E13: Net Change in A/R | F13: WebChamp Revenue | G13: 77712 | H13: 400220 | I13: Accrual RevnueAdjmnt | J13: # | K13: # | L13: 191000 | M13: A/R - DlnqntStrgeRnt | N13: -81893.14
... A784: 01/31/2026 | B784: 02/04/2026 | C784: 960000738 | D784: TP | E784: # | F784: Third Party Entries | G784: 77712A | H784: 200100 | I784: A/P - PS Clearing | J784: # | K784: # | L784: 480800 | M784: RMAS FeeRvnu-Externl | N784: 3258

Sheet Rent Roll
C2: Rent Roll Report (AR, PPD and SD)
O3: Webchamp2 Conversion Date: | V3: 2024-05-16
C4: Property: | F4: 77712 | I4: Report Date: | J4: 01/31/2026
B7: Unit # | E7: Account # | H7: Name | M7: Move In Date | P7: Rent | R7: Paid Through | T7: Rent Bal | X7: PPD Bal | Z7: SD Bal | AC7: Fee Bal
B8: A1010 | E8: 15356226 | H8: Bragg, Mandingo | M8: 01/09/2026 | P8: 322 | R8: 01/31/2026 | T8: 0 | X8: -187.62 | Z8: 0 | AC8: 0
B9: H1007 | E9: 19756559 | H9: McCarthy, Sean | M9: 05/23/2025 | P9: 224 | R9: 01/31/2026 | T9: 0 | X9: 0 | Z9: 0 | AC9: 0
B10: J1047 | E10: 50084404 | H10: young, gladys | M10: 02/14/2025 | P10: 209 | R10: 01/31/2026 | T10: 0 | X10: 0 | Z10: 0 | AC10: 0
B11: J1044 | E11: 53611246 | H11: Sumner, Meghan | M11: 08/21/2024 | P11: 137 | R11: 01/31/2026 | T11: 0 | X11: 0 | Z11: 0 | AC11: 0
B12: G1021 | E12: 55799042 | H12: Rosell, Jason | M12: 02/08/2025 | P12: 178 | R12: 01/31/2026 | T12: 0 | X12: 0 | Z12: 0 | AC12: 0
B13: A1005 | E13: 56761349 | H13: Mason, Donald | M13: 10/04/2024 | P13: 216 | R13: 01/31/2026 | T13: 0 | X13: 0 | Z13: 0 | AC13: 0
B14: C1018 | E14: 60139631 | H14: Santa, Melanie Della | M14: 08/30/2024 | P14: 137 | R14: 01/31/2026 | T14: 0 | X14: 0 | Z14: 0 | AC14: 0
B15: A1011 | E15: 61452495 | H15: Heber, Larissa | M15: 10/20/2024 | P15: 194 | R15: 01/31/2026 | T15: 0 | X15: 0 | Z15: 0 | AC15: 0
B16: A1003 | E16: 61462003 | H16: prevedelli, Benjamin | M16: 06/01/2024 | P16: 417 | R16: 01/31/2026 | T16: 0 | X16: 0 | Z16: 0 | AC16: 0
B17: B2005 | E17: 61480099 | H17: Kiser, Robert | M17: 06/04/2024 | P17: 271 | R17: 01/31/2026 | T17: 0 | X17: 0 | Z17: 0 | AC17: 0
B18: B1016 | E18: 61490489 | H18: Valenti, Colleen | M18: 06/07/2024 | P18: 96 | R18: 01/31/2026 | T18: 0 | X18: 0 | Z18: 0 | AC18: 0
B19: B1020 | E19: 61500959 | H19: Mizel, Antoine | M19: 12/31/2025 | P19: 98 | R19: 01/31/2026 | T19: 0 | X19: 0 | Z19: 0 | AC19: 0
... B561: G1039 | E561: 65123516 | H561: Pirozzi, Dario | M561: 01/30/2026 | P561: 240 | R561: 02/28/2026 | T561: 0 | X561: -1 | Z561: 0 | AC561: 0
T562: 3757.06 | X562: -8077.89 | Z562: 250 | AC562: 125
