Workbook
Name accountList: #REF!
Name beta_observed: #REF!
Name beta_unlev_comps: #REF!
Name check: #REF!
Name conversionfactor: '[10]E&P'!$D$6
Name convfactor: #REF!
Name costdebtfirm: #REF!
Name costequity: #REF!
Name days_per_year: #REF!
Name debt: #REF!
Name debt_weight: #REF!
Name market_equity: #REF!
Name relevered_beta: #REF!
Name risk_free_rate: #REF!
Name risk_premium: #REF!
Name stubyear: #REF!
Name totalcap: #REF!
Name wacc: #REF!

Sheet Proforma
E4: Projected Rate | H4: =Model2.0!I10 -> 1.0865743 | I4: =Model2.0!J10 -> 1.0938182 | J4: =Model2.0!K10 -> 1.1011103 | K4: =Model2.0!L10 -> 1.108451 | L4: =Model2.0!M10 -> 1.1158407 | M4: =Model2.0!N10 -> 1.1232796 | N4: =Model2.0!O10 -> 1.1307682 | O4: =Model2.0!P10 -> 1.1383066 | ... S4: =Model2.0!T10 -> 1.1689664
E5: General Vacancy | H5: =Model2.0!I11 -> 0.082781457 | I5: =Model2.0!J11 -> 0.082781457 | J5: =Model2.0!K11 -> 0.082781457 | K5: =Model2.0!L11 -> 0.082781457 | L5: =Model2.0!M11 -> 0.082781457 | M5: =Model2.0!N11 -> 0.082781457 | N5: =Model2.0!O11 -> 0.082781457 | O5: =Model2.0!P11 -> 0.082781457 | ... S5: =Model2.0!T11 -> 0.082781457
E8: Income | F8: T-12 Avg | G8: T-12 | H8: =Model2.0!I7 -> 46142 | I8: =Model2.0!J7 -> 46173 | J8: =Model2.0!K7 -> 46203 | K8: =Model2.0!L7 -> 46234 | L8: =Model2.0!M7 -> 46265 | M8: =Model2.0!N7 -> 46295 | N8: =Model2.0!O7 -> 46326 | O8: =Model2.0!P7 -> 46356 | ... S8: =Model2.0!T7 -> 46477 | U8: Current Mgmt | V8: IMPACT TO N.O.I
E9: Rental Income | F9: =G9/12 -> 69400.819 | G9: =Model2.0!F19 -> 832809.83 | H9: =Model2.0!I19 -> 89048.545 | I9: =Model2.0!J19 -> 89642.202 | J9: =Model2.0!K19 -> 90239.817 | K9: =Model2.0!L19 -> 90841.416 | L9: =Model2.0!M19 -> 91447.025 | M9: =Model2.0!N19 -> 92056.672 | N9: =Model2.0!O19 -> 92670.383 | O9: =Model2.0!P19 -> 93288.186 | ... S9: =Model2.0!T19 -> 95800.858 | T9: =Model2.0!BR19 -> 1108647.8 | U9: =Model2.0!BS19 -> 1133367.2 | V9: =Model2.0!BT19 -> -24719.431 | X9: =SUM(H9:S9) -> 1108647.8 | Y9: =X9-U9 -> -24719.431 | Z9: =IF(Y9=V9,"OK","Check") -> OK
E10: STORE Rate Mgmt. Rev | F10: =G10/12 -> 0 | G10: =Model2.0!F20 -> 0 | H10: =Model2.0!I20 -> 0 | I10: =Model2.0!J20 -> 0 | J10: =Model2.0!K20 -> 0 | K10: =Model2.0!L20 -> 4542.0708 | L10: =Model2.0!M20 -> 9114.4221 | M10: =Model2.0!N20 -> 13717.256 | N10: =Model2.0!O20 -> 15570.663 | O10: =Model2.0!P20 -> 17436.427 | ... S10: =Model2.0!T20 -> 25024.698 | T10: =Model2.0!BR20 -> 149034.2 | U10: =Model2.0!BS20 -> 0 | V10: =Model2.0!BT20 -> 149034.2 | X10: =SUM(H10:S10) -> 149034.2 | Y10: =X10-U10 -> 149034.2 | Z10: =IF(Y10=V10,"OK","Check") -> OK
E11: Discounts | F11: =G11/12 -> 0 | G11: =Model2.0!F21 -> 0 | H11: =Model2.0!I21 -> -3214.7489 | I11: =Model2.0!J21 -> -3236.1806 | J11: =Model2.0!K21 -> -3257.7551 | K11: =Model2.0!L21 -> -3279.4735 | L11: =Model2.0!M21 -> -3301.3367 | M11: =Model2.0!N21 -> -3323.3456 | N11: =Model2.0!O21 -> -3345.5012 | O11: =Model2.0!P21 -> -3367.8045 | ... S11: =Model2.0!T21 -> -3458.5147 | T11: =Model2.0!BR21 -> -40023.386 | U11: =Model2.0!BS21 -> -40023.386 | V11: =Model2.0!BT21 -> 0 | X11: =SUM(H11:S11) -> -40023.386 | Y11: =X11-U11 -> 0 | Z11: =IF(Y11=V11,"OK","Check") -> OK
E12: Net Rental Income | F12: =G12/12 -> 69400.819 | G12: =Model2.0!F22 -> 832809.83 | H12: =Model2.0!I22 -> 85833.797 | I12: =Model2.0!J22 -> 86406.022 | J12: =Model2.0!K22 -> 86982.062 | K12: =Model2.0!L22 -> 92104.013 | L12: =Model2.0!M22 -> 97260.111 | M12: =Model2.0!N22 -> 102450.58 | N12: =Model2.0!O22 -> 104895.55 | O12: =Model2.0!P22 -> 107356.81 | ... S12: =Model2.0!T22 -> 117367.04 | T12: =Model2.0!BR22 -> 1217658.6 | U12: =Model2.0!BS22 -> 1093343.8 | V12: =Model2.0!BT22 -> 124314.77 | X12: =SUM(H12:S12) -> 1217658.6 | Y12: =SUM(Y9:Y11) -> 124314.77 | Z12: =IF(ABS(Y12-V12)<1,"OK","Check") -> OK
C14: * | E14: Admin Fee Income | F14: =G14/12 -> 1847.0938 | G14: =Model2.0!F27 -> 22165.125 | H14: =Model2.0!I27 -> 580 | I14: =Model2.0!J27 -> 580 | J14: =Model2.0!K27 -> 580 | K14: =Model2.0!L27 -> 580 | L14: =Model2.0!M27 -> 580 | M14: =Model2.0!N27 -> 580 | N14: =Model2.0!O27 -> 580 | O14: =Model2.0!P27 -> 580 | ... S14: =Model2.0!T27 -> 580 | T14: =Model2.0!BR27 -> 6960 | U14: =Model2.0!BS27 -> 6960 | V14: =Model2.0!BT27 -> 0 | X14: =SUM(H14:S14) -> 6960 | Y14: =X14-U14 -> 0 | Z14: =IF(Y14=V14,"OK","Check") -> OK
C15: * | E15: Late Fee Income | F15: =G15/12 -> 1847.0938 | G15: =Model2.0!F28 -> 22165.125 | H15: =Model2.0!I28 -> 2392.1446 | I15: =Model2.0!J28 -> 2344.3017 | J15: =Model2.0!K28 -> 2297.4157 | K15: =Model2.0!L28 -> 2251.4674 | L15: =Model2.0!M28 -> 2206.438 | M15: =Model2.0!N28 -> 2162.3092 | N15: =Model2.0!O28 -> 2119.0631 | O15: =Model2.0!P28 -> 2076.6818 | ... S15: =Model2.0!T28 -> 1915.4652 | T15: =Model2.0!BR28 -> 25749.436 | U15: =Model2.0!BS28 -> 25749.436 | V15: =Model2.0!BT28 -> 0 | X15: =SUM(H15:S15) -> 25749.436 | Y15: =X15-U15 -> 0 | Z15: =IF(Y15=V15,"OK","Check") -> OK
E16: Current Tenant Protection Split | F16: =G16/12 -> 2983 | G16: =Model2.0!F29 -> 35796 | H16: =Model2.0!I29 -> 2988.966 | I16: =Model2.0!J29 -> 2994.9439 | J16: =Model2.0!K29 -> 3000.9338 | K16: =Model2.0!L29 -> 3006.9357 | L16: =Model2.0!M29 -> 3012.9496 | M16: =Model2.0!N29 -> 3018.9755 | N16: =Model2.0!O29 -> 3025.0134 | O16: =Model2.0!P29 -> 3031.0634 | ... S16: =Model2.0!T29 -> 3055.3848 | T16: =Model2.0!BR29 -> 0 | U16: =Model2.0!BS29 -> 36264.778 | V16: =Model2.0!BT29 -> 0 | X16: =SUM(H16:S16) -> 36264.778 | Y16: =X16-U16 -> 0 | Z16: =IF(Y16=V16,"OK","Check") -> OK | AG16: =T47 -> 1001731.7 | AH16: 634336.54 | AI16: 802467.17
E17: STORE Tenant Protection Split | F17: =G17/12 -> 0 | G17: =Model2.0!F30 -> 0 | H17: =Model2.0!I30 -> 2747.84 | I17: =Model2.0!J30 -> 2836.48 | J17: =Model2.0!K30 -> 2925.12 | K17: =Model2.0!L30 -> 3013.76 | L17: =Model2.0!M30 -> 3102.4 | M17: =Model2.0!N30 -> 3191.04 | N17: =Model2.0!O30 -> 3279.68 | O17: =Model2.0!P30 -> 3368.32 | ... S17: =Model2.0!T30 -> 3545.6 | T17: =Model2.0!BR30 -> 38558.4 | U17: =Model2.0!BS30 -> 0 | V17: =Model2.0!BT30 -> 2293.6223 | X17: =SUM(H17:S17) -> 38558.4 | Y17: =X17-U17 -> 38558.4 | Z17: =IF(Y17=V17,"OK","Check") -> Check | AF17: 0.05 | AG17: =$AG$16/$AF17 -> 20034633 | AH17: =AH$16/$AF17 -> 12686731 | AI17: =AI$16/$AF17 -> 16049343 | AK17: =AG17-AI17 -> 3985289.9
E18: Other Tenant Income | F18: =G18/12 -> 0 | G18: =Model2.0!F31 -> 0 | H18: =Model2.0!I31 -> 0 | I18: =Model2.0!J31 -> 0 | J18: =Model2.0!K31 -> 0 | K18: =Model2.0!L31 -> 0 | L18: =Model2.0!M31 -> 0 | M18: =Model2.0!N31 -> 0 | N18: =Model2.0!O31 -> 0 | O18: =Model2.0!P31 -> 0 | ... S18: =Model2.0!T31 -> 0 | T18: =Model2.0!BR31 -> 0 | U18: =Model2.0!BS31 -> 0 | V18: =Model2.0!BT31 -> 0 | X18: =SUM(H18:S18) -> 0 | Y18: =X18-U18 -> 0 | Z18: =IF(Y18=V18,"OK","Check") -> OK | AF18: 0.055 | AG18: =$AG$16/$AF18 -> 18213303 | AH18: =AH$16/$AF18 -> 11533392 | AI18: =AI$16/$AF18 -> 14590312 | AK18: =AG18-AI18 -> 3622990.8
E19: Retail Sales Income | F19: =G19/12 -> 852.66083 | G19: =Model2.0!F32 -> 10231.93 | H19: =Model2.0!I32 -> 849.04136 | I19: =Model2.0!J32 -> 850.73944 | J19: =Model2.0!K32 -> 852.44092 | K19: =Model2.0!L32 -> 854.1458 | L19: =Model2.0!M32 -> 855.8541 | M19: =Model2.0!N32 -> 857.5658 | N19: =Model2.0!O32 -> 859.28093 | O19: =Model2.0!P32 -> 860.9995 | ... S19: =Model2.0!T32 -> 867.90818 | T19: =Model2.0!BR32 -> 10301.32 | U19: =Model2.0!BS32 -> 10301.32 | V19: =Model2.0!BT32 -> 0 | X19: =SUM(H19:S19) -> 10301.32 | Y19: =X19-U19 -> 0 | Z19: =IF(Y19=V19,"OK","Check") -> OK | AF19: 0.06 | AG19: =$AG$16/$AF19 -> 16695528 | AH19: =AH$16/$AF19 -> 10572276 | AI19: =AI$16/$AF19 -> 13374453 | AK19: =AG19-AI19 -> 3321074.9
AF20: 0.065 | AG20: =$AG$16/$AF20 -> 15411256 | AH20: =AH$16/$AF20 -> 9759023.7 | AI20: =AI$16/$AF20 -> 12345649 | AK20: =AG20-AI20 -> 3065607.6
E21: Total Operating Income | F21: =G21/12 -> 76930.667 | G21: =Model2.0!F34 -> 923168.01 | H21: =Model2.0!I34 -> 92402.822 | I21: =Model2.0!J34 -> 93017.543 | J21: =Model2.0!K34 -> 93637.039 | K21: =Model2.0!L34 -> 98803.386 | L21: =Model2.0!M34 -> 104004.8 | M21: =Model2.0!N34 -> 109241.5 | N21: =Model2.0!O34 -> 111733.57 | O21: =Model2.0!P34 -> 114242.81 | ... S21: =Model2.0!T34 -> 124276.02 | T21: =Model2.0!BR34 -> 1299227.8 | U21: =Model2.0!BS34 -> 1172619.4 | V21: =Model2.0!BT34 -> 126608.39 | X21: =SUM(H21:S21) -> 1299227.8 | Y21: =SUM(Y12:Y19) -> 162873.17 | Z21: =IF(Y21=V21,"OK","Check") -> Check
E23: Expenses
E24: Advertising & Marketing | F24: =G24/12 -> 2904.785 | G24: =Model2.0!F37 -> 34857.42 | H24: =Model2.0!I37 -> 3000 | I24: =Model2.0!J37 -> 3000 | J24: =Model2.0!K37 -> 3000 | K24: =Model2.0!L37 -> 3000 | L24: =Model2.0!M37 -> 3000 | M24: =Model2.0!N37 -> 3000 | N24: =Model2.0!O37 -> 3000 | O24: =Model2.0!P37 -> 3000 | ... S24: =Model2.0!T37 -> 3000 | T24: =Model2.0!BR37 -> 36000 | U24: =Model2.0!BS37 -> 36000 | V24: =Model2.0!BT37 -> 0 | X24: =SUM(H24:S24) -> 36000 | Y24: =U24-X24 -> 0 | Z24: =IF(Y24=V24,"OK","Check") -> OK
E25: Current Payment Processing Fees | F25: =G25/12 -> 1111.145 | G25: =Model2.0!F38 -> 13333.74 | H25: =Model2.0!I38 -> 1333.3464 | I25: =Model2.0!J38 -> 1342.2167 | J25: =Model2.0!K38 -> 1351.1558 | K25: =Model2.0!L38 -> 1425.7048 | L25: =Model2.0!M38 -> 1500.7597 | M25: =Model2.0!N38 -> 1576.3237 | N25: =Model2.0!O38 -> 1612.2836 | O25: =Model2.0!P38 -> 1648.4912 | ... S25: =Model2.0!T38 -> 1793.2675 | T25: =Model2.0!BR38 -> 0 | U25: =Model2.0!BS38 -> 18747.487 | V25: =Model2.0!BT38 -> 0 | X25: =SUM(H25:S25) -> 18747.487 | Y25: =U25-X25 -> 0 | Z25: =IF(Y25=V25,"OK","Check") -> OK
E26: STORE Payment Processing Fees | F26: =G26/12 -> 0 | G26: =Model2.0!F39 -> 0 | H26: =Model2.0!I39 -> 0 | I26: =Model2.0!J39 -> 0 | J26: =Model2.0!K39 -> 0 | K26: =Model2.0!L39 -> 0 | L26: =Model2.0!M39 -> 0 | M26: =Model2.0!N39 -> 0 | N26: =Model2.0!O39 -> 0 | O26: =Model2.0!P39 -> 0 | ... S26: =Model2.0!T39 -> 0 | T26: =Model2.0!BR39 -> 0 | U26: =Model2.0!BS39 -> 0 | V26: =Model2.0!BT39 -> 18747.487 | X26: =SUM(H26:S26) -> 0 | Y26: =X25-X26 -> 18747.487 | Z26: =IF(Y26=V26,"OK","Check") -> OK
E27: Fire Prevention | F27: =G27/12 -> 0 | G27: =Model2.0!F40 -> 0 | H27: =Model2.0!I40 -> 632.95194 | I27: =Model2.0!J40 -> 632.95194 | J27: =Model2.0!K40 -> 632.95194 | K27: =Model2.0!L40 -> 632.95194 | L27: =Model2.0!M40 -> 632.95194 | M27: =Model2.0!N40 -> 632.95194 | N27: =Model2.0!O40 -> 632.95194 | O27: =Model2.0!P40 -> 632.95194 | ... S27: =Model2.0!T40 -> 632.95194 | T27: =Model2.0!BR40 -> 7595.4233 | U27: =Model2.0!BS40 -> 7595.4233 | V27: =Model2.0!BT40 -> 0 | X27: =SUM(H27:S27) -> 7595.4233 | Y27: =U27-X27 -> 0 | Z27: =IF(Y27=V27,"OK","Check") -> OK
E28: Licenses & Permits | F28: =G28/12 -> 34.1875 | G28: =Model2.0!F41 -> 410.25 | H28: =Model2.0!I41 -> 34.1875 | I28: =Model2.0!J41 -> 34.1875 | J28: =Model2.0!K41 -> 34.1875 | K28: =Model2.0!L41 -> 34.1875 | L28: =Model2.0!M41 -> 34.1875 | M28: =Model2.0!N41 -> 34.1875 | N28: =Model2.0!O41 -> 34.1875 | O28: =Model2.0!P41 -> 34.1875 | ... S28: =Model2.0!T41 -> 34.1875 | T28: =Model2.0!BR41 -> 410.25 | U28: =Model2.0!BS41 -> 410.25 | V28: =Model2.0!BT41 -> 0 | X28: =SUM(H28:S28) -> 410.25 | Y28: =U28-X28 -> 0 | Z28: =IF(Y28=V28,"OK","Check") -> OK
E29: Current Mgmt. Fee | F29: =G29/12 -> 3910.3633 | G29: =Model2.0!F42 -> 46924.36 | H29: =Model2.0!I42 -> 5150.0278 | I29: =Model2.0!J42 -> 5184.3613 | J29: =Model2.0!K42 -> 5218.9237 | K29: =Model2.0!L42 -> 5526.2408 | L29: =Model2.0!M42 -> 5835.6066 | M29: =Model2.0!N42 -> 6147.0349 | N29: =Model2.0!O42 -> 6293.7327 | O29: =Model2.0!P42 -> 6441.4085 | ... S29: =Model2.0!T42 -> 7042.0225 | T29: =Model2.0!BR42 -> 0 | U29: =Model2.0!BS42 -> 73059.517 | V29: =Model2.0!BT42 -> 0 | X29: =SUM(H29:S29) -> 73059.517 | Y29: =U29-X29 -> 0 | Z29: =IF(Y29=V29,"OK","Check") -> OK
E30: STORE Mgmt. Fee | F30: =G30/12 -> 0 | G30: =Model2.0!F43 -> 0 | H30: =Model2.0!I43 -> 3433.3519 | I30: =Model2.0!J43 -> 3456.2409 | J30: =Model2.0!K43 -> 3479.2825 | K30: =Model2.0!L43 -> 3684.1605 | L30: =Model2.0!M43 -> 3890.4044 | M30: =Model2.0!N43 -> 4098.0233 | N30: =Model2.0!O43 -> 4195.8218 | O30: =Model2.0!P43 -> 4294.2723 | ... S30: =Model2.0!T43 -> 4694.6817 | T30: =Model2.0!BR43 -> 48706.345 | U30: =Model2.0!BS43 -> 0 | V30: =Model2.0!BT43 -> 24353.172 | X30: =SUM(H30:S30) -> 48706.345 | Y30: =X29-X30 -> 24353.172 | Z30: =IF(Y30=V30,"OK","Check") -> OK
E31: Payroll | F31: =G31/12 -> 7490.3592 | G31: =Model2.0!F44 -> 89884.31 | H31: =Model2.0!I44 -> 7918.572 | I31: =Model2.0!J44 -> 7918.572 | J31: =Model2.0!K44 -> 7918.572 | K31: =Model2.0!L44 -> 7918.572 | L31: =Model2.0!M44 -> 7918.572 | M31: =Model2.0!N44 -> 7918.572 | N31: =Model2.0!O44 -> 7918.572 | O31: =Model2.0!P44 -> 7918.572 | ... S31: =Model2.0!T44 -> 7918.572 | T31: =Model2.0!BR44 -> 95022.864 | U31: =Model2.0!BS44 -> 91681.996 | V31: =Model2.0!BT44 -> -3340.8674 | X31: =SUM(H31:S31) -> 95022.864 | Y31: =U31-X31 -> -3340.8674 | Z31: =IF(Y31=V31,"OK","Check") -> OK
E32: Office Supplies | F32: =G32/12 -> 138.32667 | G32: =Model2.0!F45 -> 1659.92 | H32: =Model2.0!I45 -> 138.32667 | I32: =Model2.0!J45 -> 138.32667 | J32: =Model2.0!K45 -> 138.32667 | K32: =Model2.0!L45 -> 138.32667 | L32: =Model2.0!M45 -> 138.32667 | M32: =Model2.0!N45 -> 138.32667 | N32: =Model2.0!O45 -> 138.32667 | O32: =Model2.0!P45 -> 138.32667 | ... S32: =Model2.0!T45 -> 138.32667 | T32: =Model2.0!BR45 -> 1659.92 | U32: =Model2.0!BS45 -> 1659.92 | V32: =Model2.0!BT45 -> 0 | X32: =SUM(H32:S32) -> 1659.92 | Y32: =U32-X32 -> 0 | Z32: =IF(Y32=V32,"OK","Check") -> OK
E33: Repairs & Maintenance | F33: =G33/12 -> 3315.6358 | G33: =Model2.0!F46 -> 39787.63 | H33: =Model2.0!I46 -> 3315.6358 | I33: =Model2.0!J46 -> 3315.6358 | J33: =Model2.0!K46 -> 3315.6358 | K33: =Model2.0!L46 -> 3315.6358 | L33: =Model2.0!M46 -> 3315.6358 | M33: =Model2.0!N46 -> 3315.6358 | N33: =Model2.0!O46 -> 3315.6358 | O33: =Model2.0!P46 -> 3315.6358 | ... S33: =Model2.0!T46 -> 3315.6358 | T33: =Model2.0!BR46 -> 39787.63 | U33: =Model2.0!BS46 -> 39787.63 | V33: =Model2.0!BT46 -> 0 | X33: =SUM(H33:S33) -> 39787.63 | Y33: =U33-X33 -> 0 | Z33: =IF(Y33=V33,"OK","Check") -> OK
E34: Security | F34: =G34/12 -> 0 | G34: =Model2.0!F47 -> 0 | H34: =Model2.0!I47 -> 120 | I34: =Model2.0!J47 -> 120 | J34: =Model2.0!K47 -> 120 | K34: =Model2.0!L47 -> 120 | L34: =Model2.0!M47 -> 120 | M34: =Model2.0!N47 -> 120 | N34: =Model2.0!O47 -> 120 | O34: =Model2.0!P47 -> 120 | ... S34: =Model2.0!T47 -> 120 | T34: =Model2.0!BR47 -> 1440 | U34: =Model2.0!BS47 -> 0 | V34: =Model2.0!BT47 -> -1440 | X34: =SUM(H34:S34) -> 1440 | Y34: =U34-X34 -> -1440 | Z34: =IF(Y34=V34,"OK","Check") -> OK
E35: Retail Products | F35: =G35/12 -> 308.0475 | G35: =Model2.0!F48 -> 3696.57 | H35: =Model2.0!I48 -> 308.0475 | I35: =Model2.0!J48 -> 308.0475 | J35: =Model2.0!K48 -> 308.0475 | K35: =Model2.0!L48 -> 308.0475 | L35: =Model2.0!M48 -> 308.0475 | M35: =Model2.0!N48 -> 308.0475 | N35: =Model2.0!O48 -> 308.0475 | O35: =Model2.0!P48 -> 308.0475 | ... S35: =Model2.0!T48 -> 308.0475 | T35: =Model2.0!BR48 -> 3696.57 | U35: =Model2.0!BS48 -> 3696.57 | V35: =Model2.0!BT48 -> 0 | X35: =SUM(H35:S35) -> 3696.57 | Y35: =U35-X35 -> 0 | Z35: =IF(Y35=V35,"OK","Check") -> OK
E36: Telephone & Internet | F36: =G36/12 -> 909.45917 | G36: =Model2.0!F49 -> 10913.51 | H36: =Model2.0!I49 -> 909.45917 | I36: =Model2.0!J49 -> 909.45917 | J36: =Model2.0!K49 -> 909.45917 | K36: =Model2.0!L49 -> 909.45917 | L36: =Model2.0!M49 -> 909.45917 | M36: =Model2.0!N49 -> 909.45917 | N36: =Model2.0!O49 -> 909.45917 | O36: =Model2.0!P49 -> 909.45917 | ... S36: =Model2.0!T49 -> 909.45917 | T36: =Model2.0!BR49 -> 10913.51 | U36: =Model2.0!BS49 -> 10913.51 | V36: =Model2.0!BT49 -> 0 | X36: =SUM(H36:S36) -> 10913.51 | Y36: =U36-X36 -> 0 | Z36: =IF(Y36=V36,"OK","Check") -> OK
E37: Software | F37: =G37/12 -> 1441.68 | G37: =Model2.0!F50 -> 17300.16 | H37: =Model2.0!I50 -> 1850 | I37: =Model2.0!J50 -> 1850 | J37: =Model2.0!K50 -> 1850 | K37: =Model2.0!L50 -> 1850 | L37: =Model2.0!M50 -> 1850 | M37: =Model2.0!N50 -> 1850 | N37: =Model2.0!O50 -> 1850 | O37: =Model2.0!P50 -> 1850 | ... S37: =Model2.0!T50 -> 1850 | T37: =Model2.0!BR50 -> 22200 | U37: =Model2.0!BS50 -> 17296.04 | V37: =Model2.0!BT50 -> -4903.96 | X37: =SUM(H37:S37) -> 22200 | Y37: =U37-X37 -> -4903.96 | Z37: =IF(Y37=V37,"OK","Check") -> OK
E38: Bank Charges | F38: =G38/12 -> 0 | G38: =Model2.0!F51 -> 0 | H38: =Model2.0!I51 -> 0 | I38: =Model2.0!J51 -> 0 | J38: =Model2.0!K51 -> 0 | K38: =Model2.0!L51 -> 0 | L38: =Model2.0!M51 -> 0 | M38: =Model2.0!N51 -> 0 | N38: =Model2.0!O51 -> 0 | O38: =Model2.0!P51 -> 0 | ... S38: =Model2.0!T51 -> 0 | T38: =Model2.0!BR51 -> 0 | U38: =Model2.0!BS51 -> 0 | V38: =Model2.0!BT51 -> 0
E39: Prof Fees - Legal/Acctg | F39: =G39/12 -> 161.73 | G39: =Model2.0!F52 -> 1940.76 | H39: =Model2.0!I52 -> 161.73 | I39: =Model2.0!J52 -> 161.73 | J39: =Model2.0!K52 -> 161.73 | K39: =Model2.0!L52 -> 161.73 | L39: =Model2.0!M52 -> 161.73 | M39: =Model2.0!N52 -> 161.73 | N39: =Model2.0!O52 -> 161.73 | O39: =Model2.0!P52 -> 161.73 | ... S39: =Model2.0!T52 -> 161.73 | T39: =Model2.0!BR52 -> 1940.76 | U39: =Model2.0!BS52 -> 1940.76 | V39: =Model2.0!BT52 -> 0 | X39: =SUM(H39:S39) -> 1940.76 | Y39: =U39-X39 -> 0 | Z39: =IF(Y39=V39,"OK","Check") -> OK
E40: Utilities | F40: =G40/12 -> 2343.57 | G40: =Model2.0!F53 -> 28122.84 | H40: =Model2.0!I53 -> 2343.57 | I40: =Model2.0!J53 -> 2343.57 | J40: =Model2.0!K53 -> 2343.57 | K40: =Model2.0!L53 -> 2343.57 | L40: =Model2.0!M53 -> 2343.57 | M40: =Model2.0!N53 -> 2343.57 | N40: =Model2.0!O53 -> 2343.57 | O40: =Model2.0!P53 -> 2343.57 | ... S40: =Model2.0!T53 -> 2343.57 | T40: =Model2.0!BR53 -> 28122.84 | U40: =Model2.0!BS53 -> 28122.84 | V40: =Model2.0!BT53 -> 0 | X40: =SUM(H40:S40) -> 28122.84 | Y40: =U40-X40 -> 0 | Z40: =IF(Y40=V40,"OK","Check") -> OK
E41: Insurance | F41: =G41/12 -> 0 | G41: =Model2.0!F54 -> 0 | H41: =Model2.0!I54 -> 0 | I41: =Model2.0!J54 -> 0 | J41: =Model2.0!K54 -> 0 | K41: =Model2.0!L54 -> 0 | L41: =Model2.0!M54 -> 0 | M41: =Model2.0!N54 -> 0 | N41: =Model2.0!O54 -> 0 | O41: =Model2.0!P54 -> 0 | ... S41: =Model2.0!T54 -> 0 | T41: =Model2.0!BR54 -> 0 | U41: =Model2.0!BS54 -> 0 | V41: =Model2.0!BT54 -> 0 | X41: =SUM(H41:S41) -> 0 | Y41: =U41-X41 -> 0 | Z41: =IF(Y41=V41,"OK","Check") -> OK
E42: Property Taxes | F42: =G42/12 -> 0 | G42: =Model2.0!F55 -> 0 | H42: =Model2.0!I55 -> 0 | I42: =Model2.0!J55 -> 0 | J42: =Model2.0!K55 -> 0 | K42: =Model2.0!L55 -> 0 | L42: =Model2.0!M55 -> 0 | M42: =Model2.0!N55 -> 0 | N42: =Model2.0!O55 -> 0 | O42: =Model2.0!P55 -> 0 | ... S42: =Model2.0!T55 -> 0 | T42: =Model2.0!BR55 -> 0 | U42: =Model2.0!BS55 -> 0 | V42: =Model2.0!BT55 -> 0 | X42: =SUM(H42:S42) -> 0 | Y42: =U42-X42 -> 0 | Z42: =IF(Y42=V42,"OK","Check") -> OK
E43: Other Expense | F43: =G43/12 -> 0 | G43: =Model2.0!F56 -> 0 | H43: =Model2.0!I56 -> 0 | I43: =Model2.0!J56 -> 0 | J43: =Model2.0!K56 -> 0 | K43: =Model2.0!L56 -> 0 | L43: =Model2.0!M56 -> 0 | M43: =Model2.0!N56 -> 0 | N43: =Model2.0!O56 -> 0 | O43: =Model2.0!P56 -> 0 | ... S43: =Model2.0!T56 -> 0 | T43: =Model2.0!BR56 -> 0 | U43: =Model2.0!BS56 -> 0 | V43: =Model2.0!BT56 -> 0
E45: Total Operating Expense | F45: =G45/12 -> 24069.289 | G45: =Model2.0!F58 -> 288831.47 | H45: =Model2.0!I58 -> 24165.832 | I45: =Model2.0!J58 -> 24188.721 | J45: =Model2.0!K58 -> 24211.763 | K45: =Model2.0!L58 -> 24416.641 | L45: =Model2.0!M58 -> 24622.885 | M45: =Model2.0!N58 -> 24830.504 | N45: =Model2.0!O58 -> 24928.302 | O45: =Model2.0!P58 -> 25026.753 | ... S45: =Model2.0!T58 -> 25427.162 | T45: =Model2.0!BR58 -> 297496.11 | U45: =Model2.0!BS58 -> 330911.94 | V45: =Model2.0!BT58 -> 33415.832 | W45: =V45/U45 -> 0.10098104 | X45: =SUM(H45:S45) -> 297496.11 | Y45: =SUM(Y24:Y42) -> 33415.832 | Z45: =IF(Y45=V45,"OK","Check") -> OK
E47: Net Operating Income | F47: =G47/12 -> 52861.378 | G47: =Model2.0!F60 -> 634336.54 | H47: =Model2.0!I60 -> 68236.99 | I47: =Model2.0!J60 -> 68828.822 | J47: =Model2.0!K60 -> 69425.276 | K47: =Model2.0!L60 -> 74386.745 | L47: =Model2.0!M60 -> 79381.918 | M47: =Model2.0!N60 -> 84410.993 | N47: =Model2.0!O60 -> 86805.267 | O47: =Model2.0!P60 -> 89216.057 | ... S47: =Model2.0!T60 -> 98848.853 | T47: =Model2.0!BR60 -> 1001731.7 | U47: =Model2.0!BS60 -> 841707.44 | V47: =Model2.0!BT60 -> 160024.22 | W47: =V47/U47 -> 0.19011858
H49: =H21-H45 -> 68236.99 | I49: =I21-I45 -> 68828.822 | J49: =J21-J45 -> 69425.276 | K49: =K21-K45 -> 74386.745 | L49: =L21-L45 -> 79381.918 | M49: =M21-M45 -> 84410.993 | N49: =N21-N45 -> 86805.267 | O49: =O21-O45 -> 89216.057 | ... S49: =S21-S45 -> 98848.853
H50: =IF(H49=H47,"OK","Check") -> OK | I50: =IF(I49=I47,"OK","Check") -> OK | J50: =IF(J49=J47,"OK","Check") -> OK | K50: =IF(K49=K47,"OK","Check") -> OK | L50: =IF(L49=L47,"OK","Check") -> OK | M50: =IF(M49=M47,"OK","Check") -> OK | N50: =IF(N49=N47,"OK","Check") -> OK | O50: =IF(O49=O47,"OK","Check") -> OK | ... S50: =IF(S49=S47,"OK","Check") -> OK

Sheet 5 Year Proforma
D2: Wentworth - Vacaville, CA
D3: 5-Year Proforma
G6: 1 | L6: 2 | Q6: 3 | V6: 4 | AA6: 5
G7: 2027 | H7: Assumptions | L7: 2028 | M7: Assumptions | Q7: 2029 | R7: Assumptions | V7: 2030 | W7: Assumptions | AA7: 2031 | AB7: Assumptions
D8: Income
D9: Rental Income | G9: =Model2.0!BW19 -> 1108647.8 | L9: =Model2.0!BX19 -> 1174825.5 | M9: =(L9-G9)/G9 -> 0.059692273 | Q9: =Model2.0!BY19 -> 1222689.7 | R9: =(Q9-L9)/L9 -> 0.040741543 | V9: =Model2.0!BZ19 -> 1272504 | W9: =(V9-Q9)/Q9 -> 0.040741543 | AA9: =Model2.0!CA19 -> 1324347.8 | AB9: =(AA9-V9)/V9 -> 0.040741543
D10: STORE Rate Mgmt. Rev. | G10: =Model2.0!BW20 -> 149034.2 | H10: =IF(G10>0,G10/G9,"") -> 0.13442881 | L10: =Model2.0!BX20 -> 122035.47 | M10: =IF(L10>0,L10/L9,"") -> 0.1038754 | Q10: =Model2.0!BY20 -> 127007.39 | R10: =IF(Q10>0,Q10/Q9,"") -> 0.1038754 | V10: =Model2.0!BZ20 -> 132181.86 | W10: =IF(V10>0,V10/V9,"") -> 0.1038754 | AA10: =Model2.0!CA20 -> 137567.16 | AB10: =IF(AA10>0,AA10/AA9,"") -> 0.1038754
D11: Discounts | G11: =Model2.0!BW21 -> -40023.386 | L11: =Model2.0!BX21 -> -42412.473 | Q11: =Model2.0!BY21 -> -44140.423 | R11: =(Q11-L11)/L11 -> 0.040741543 | V11: =Model2.0!BZ21 -> -45938.772 | W11: =(V11-Q11)/Q11 -> 0.040741543 | AA11: =Model2.0!CA21 -> -47810.388 | AB11: =(AA11-V11)/V11 -> 0.040741543 | AK11: we looked at your original proforma and it does look like there's a significant delay in revenue
D12: Net Rental Income | G12: =Model2.0!BW22 -> 1217658.6 | L12: =Model2.0!BX22 -> 1254448.5 | Q12: =Model2.0!BY22 -> 1305556.7 | V12: =Model2.0!BZ22 -> 1358747.1 | AA12: =Model2.0!CA22 -> 1414104.5
D14: Admin Fee Income | G14: =Model2.0!BW27 -> 6960 | L14: =Model2.0!BX27 -> 6960 | Q14: =Model2.0!BY27 -> 6960 | V14: =Model2.0!BZ27 -> 6960 | AA14: =Model2.0!CA27 -> 6960
D15: Late Fee Income | G15: =Model2.0!BW28 -> 25749.436 | L15: =Model2.0!BX28 -> 20206.013 | Q15: =Model2.0!BY28 -> 15855.997 | V15: =Model2.0!BZ28 -> 12442.466 | W15: 4% Ann. Growth | AA15: =Model2.0!CA28 -> 9763.8109 | AB15: 4% Ann. Growth
D16: Current Tenant Protection Split | G16: =Model2.0!BW29 -> 36264.778 | L16: =Model2.0!BX29 -> 37144.77 | Q16: =Model2.0!BY29 -> 38046.117 | V16: =Model2.0!BZ29 -> 38969.335 | AA16: =Model2.0!CA29 -> 39914.956
D17: STORE Tenant Protection Split | G17: =Model2.0!BW30 -> 38558.4 | L17: =Model2.0!BX30 -> 43185.408 | Q17: =Model2.0!BY30 -> 43833.189 | V17: =Model2.0!BZ30 -> 44490.687 | AA17: =Model2.0!CA30 -> 45158.047 | AG17: x | AH17: increase
D18: Other Tenant Income | G18: =Model2.0!BW31 -> 0 | L18: =Model2.0!BX31 -> 0 | Q18: =Model2.0!BY31 -> 0 | V18: =Model2.0!BZ31 -> 0 | AA18: =Model2.0!CA31 -> 0
D19: Retail Sales Income | G19: =Model2.0!BW32 -> 10301.32 | L19: =Model2.0!BX32 -> 10551.29 | Q19: =Model2.0!BY32 -> 10807.325 | V19: =Model2.0!BZ32 -> 11069.573 | AA19: =Model2.0!CA32 -> 11338.185
D21: Total Operating Income | G21: =SUM(G12:G15,G17:G19) -> 1299227.8 | L21: =SUM(L12:L15,L17:L19) -> 1335351.2 | Q21: =SUM(Q12:Q15,Q17:Q19) -> 1383013.2 | V21: =SUM(V12:V15,V17:V19) -> 1433709.8 | AA21: =SUM(AA12:AA15,AA17:AA19) -> 1487324.6
D23: Expenses
D24: Advertising & Marketing | G24: =Model2.0!BW37 -> 36000 | L24: =Model2.0!BX37 -> 36720 | Q24: =Model2.0!BY37 -> 37454.4 | V24: =Model2.0!BZ37 -> 38203.488 | AA24: =Model2.0!CA37 -> 38967.558
D25: Current Payment Processing Fees | G25: =Model2.0!BW38 -> 18747.487 | L25: =Model2.0!BX38 -> 19268.738 | Q25: =Model2.0!BY38 -> 19956.487 | V25: =Model2.0!BZ38 -> 20688.024 | AA25: =Model2.0!CA38 -> 21461.67 | AG25: x | AH25: increase
D26: STORE Payment Processing Fees | G26: =Model2.0!BW39 -> 0 | L26: =Model2.0!BX39 -> 0 | Q26: =Model2.0!BY39 -> 0 | V26: =Model2.0!BZ39 -> 0 | AA26: =Model2.0!CA39 -> 0
D27: Fire Prevention | G27: =Model2.0!BW40 -> 7595.4233 | L27: =Model2.0!BX40 -> 7747.3318 | Q27: =Model2.0!BY40 -> 7902.2784 | V27: =Model2.0!BZ40 -> 8060.324 | AA27: =Model2.0!CA40 -> 8221.5305
D28: Licenses & Permits | G28: =Model2.0!BW41 -> 410.25 | L28: =Model2.0!BX41 -> 418.455 | Q28: =Model2.0!BY41 -> 426.8241 | V28: =Model2.0!BZ41 -> 435.36058 | AA28: =Model2.0!CA41 -> 444.06779
D29: Current Mgmt. Fee | G29: =Model2.0!BW42 -> 73059.517 | L29: =Model2.0!BX42 -> 75266.911 | Q29: =Model2.0!BY42 -> 78333.401 | V29: =Model2.0!BZ42 -> 81524.824 | AA29: =Model2.0!CA42 -> 84846.271
D30: STORE Mgmt. Fee | G30: =Model2.0!BW43 -> 48706.345 | L30: =Model2.0!BX43 -> 56450.183 | Q30: =Model2.0!BY43 -> 65277.834 | V30: =Model2.0!BZ43 -> 67937.354 | AA30: =Model2.0!CA43 -> 70705.226 | AG30: Increase Mgmt
D31: Payroll | G31: =Model2.0!BW44 -> 95022.864 | H31: ='Inputs & Drivers'!$E$54 -> 62Hrs/Wk @ $26 + Burden Rate | L31: =Model2.0!BX44 -> 96923.321 | M31: ='Inputs & Drivers'!$E$54 -> 62Hrs/Wk @ $26 + Burden Rate | Q31: =Model2.0!BY44 -> 98861.787 | R31: ='Inputs & Drivers'!$E$54 -> 62Hrs/Wk @ $26 + Burden Rate | V31: =Model2.0!BZ44 -> 100839.02 | W31: ='Inputs & Drivers'!$E$54 -> 62Hrs/Wk @ $26 + Burden Rate | AA31: =Model2.0!CA44 -> 102855.8 | AB31: ='Inputs & Drivers'!$E$54 -> 62Hrs/Wk @ $26 + Burden Rate
D32: Office Supplies | G32: =Model2.0!BW45 -> 1659.92 | L32: =Model2.0!BX45 -> 1693.1184 | Q32: =Model2.0!BY45 -> 1726.9808 | V32: =Model2.0!BZ45 -> 1761.5204 | AA32: =Model2.0!CA45 -> 1796.7508
D33: Repairs & Maintenance | G33: =Model2.0!BW46 -> 39787.63 | H33: Includes... & Preventive Maint. | L33: =Model2.0!BX46 -> 40583.383 | Q33: =Model2.0!BY46 -> 41395.05 | V33: =Model2.0!BZ46 -> 42222.951 | AA33: =Model2.0!CA46 -> 43067.41
D34: Security | G34: =Model2.0!BW47 -> 1440 | H34: Includes Gate Access & 24-Hour Monitoring | L34: =Model2.0!BX47 -> 1468.8 | Q34: =Model2.0!BY47 -> 1498.176 | V34: =Model2.0!BZ47 -> 1528.1395 | AA34: =Model2.0!CA47 -> 1558.7023
D35: Retail Products | G35: =Model2.0!BW48 -> 3696.57 | L35: =Model2.0!BX48 -> 3770.5014 | Q35: =Model2.0!BY48 -> 3845.9114 | V35: =Model2.0!BZ48 -> 3922.8297 | AA35: =Model2.0!CA48 -> 4001.2862
D36: Telephone & Internet | G36: =Model2.0!BW49 -> 10913.51 | L36: =Model2.0!BX49 -> 11131.78 | Q36: =Model2.0!BY49 -> 11354.416 | V36: =Model2.0!BZ49 -> 11581.504 | AA36: =Model2.0!CA49 -> 11813.134
D37: Software | G37: =Model2.0!BW50 -> 22200 | L37: =Model2.0!BX50 -> 22533 | Q37: =Model2.0!BY50 -> 22870.995 | V37: =Model2.0!BZ50 -> 23214.06 | AA37: =Model2.0!CA50 -> 23562.271 | AG37: x | AH37: increase
D38: Bank Charges | G38: =Model2.0!BW51 -> 0 | L38: =Model2.0!BX51 -> 0 | Q38: =Model2.0!BY51 -> 0 | V38: =Model2.0!BZ51 -> 0 | AA38: =Model2.0!CA51 -> 0
D39: Prof Fees - Legal/Acctg | G39: =Model2.0!BW52 -> 1940.76 | L39: =Model2.0!BX52 -> 1979.5752 | Q39: =Model2.0!BY52 -> 2019.1667 | V39: =Model2.0!BZ52 -> 2059.55 | AA39: =Model2.0!CA52 -> 2100.741
D40: Utilities | G40: =Model2.0!BW53 -> 28122.84 | L40: =Model2.0!BX53 -> 28685.297 | Q40: =Model2.0!BY53 -> 29259.003 | V40: =Model2.0!BZ53 -> 29844.183 | AA40: =Model2.0!CA53 -> 30441.066
D41: Insurance | G41: =Model2.0!BW54 -> 0 | L41: =Model2.0!BX54 -> 0 | Q41: =Model2.0!BY54 -> 0 | V41: =Model2.0!BZ54 -> 0 | AA41: =Model2.0!CA54 -> 0
D42: Property Taxes | G42: =Model2.0!BW55 -> 0 | L42: =Model2.0!BX55 -> 0 | M42: ="Assumed "&TEXT('Inputs & Drivers'!$J$62,"0%")&" Growth Rate" -> Assumed 1% Growth Rate | Q42: =Model2.0!BY55 -> 0 | R42: ="Assumed "&TEXT('Inputs & Drivers'!$J$63,"0%")&" Growth Rate" -> Assumed 1% Growth Rate | V42: =Model2.0!BZ55 -> 0 | W42: ="Assumed "&TEXT('Inputs & Drivers'!$J$64,"0%")&" Growth Rate" -> Assumed 1% Growth Rate | AA42: =Model2.0!CA55 -> 0 | AB42: ="Assumed "&TEXT('Inputs & Drivers'!$J$65,"0%")&" Growth Rate" -> Assumed 1% Growth Rate
D43: Other Expense | G43: =Model2.0!BW56 -> 0 | L43: =Model2.0!BX56 -> 0 | M43: ="Assumed "&TEXT('Inputs & Drivers'!$J$62,"0%")&" Growth Rate" -> Assumed 1% Growth Rate | Q43: =Model2.0!BY56 -> 0 | R43: ="Assumed "&TEXT('Inputs & Drivers'!$J$63,"0%")&" Growth Rate" -> Assumed 1% Growth Rate | V43: =Model2.0!BZ56 -> 0 | W43: ="Assumed "&TEXT('Inputs & Drivers'!$J$64,"0%")&" Growth Rate" -> Assumed 1% Growth Rate | AA43: =Model2.0!CA56 -> 0
D45: Total Operating Expense | G45: =SUM(G30:G43,G27:G28,G26,G24) -> 297496.11 | L45: =SUM(L30:L43,L27:L28,L26,L24) -> 310104.75 | Q45: =SUM(Q30:Q43,Q27:Q28,Q26,Q24) -> 323892.82 | V45: =SUM(V30:V43,V27:V28,V26,V24) -> 331610.29 | AA45: =SUM(AA30:AA43,AA27:AA28,AA26,AA24) -> 339535.55
D47: Net Operating Income | G47: =G21-G45 -> 1001731.7 | L47: =L21-L45 -> 1025246.5 | Q47: =Q21-Q45 -> 1059120.4 | V47: =V21-V45 -> 1102099.5 | AA47: =AA21-AA45 -> 1147789
L51: =L47-G47 -> 23514.814 | Q51: =Q47-L47 -> 33873.89 | V51: =V47-Q47 -> 42979.144 | AA51: =AA47-V47 -> 45689.508
L52: =L51/G47 -> 0.023474165 | Q52: =Q51/L47 -> 0.033039753 | V52: =V51/Q47 -> 0.040580037 | AA52: =AA51/V47 -> 0.04145679

Sheet Inputs & Drivers
B2: Inputs
B4: Property Overview
B5: Name | E5: Vacaville Property
B6: Type | E6: Storage
B7: Location | E7: 5920 Cherry Glen Rd, Vacaville, CA 95688
B8: Units Available | E8: 604
B9: Units Occupied | E9: 554
B10: NRSF | E10: 89350
B11: Acquisition Assumptions | G11: Sales Assumptions
B12: Acquisition Date | E12: 46082 | G12: Financing
B13: Hold Period | E13: 5 | G13: Loan-to-Value (LTV) | I13: 0.65
B14: Purchase Price | E14: 14000000 | G14: SOFR Rate | I14: 0.043 | J14: As of Mar 2026 (~4.30%)
B15: Acquisition Closing Costs | E15: 0.01 | G15: Spread (bps) | I15: 0.02 | J15: 240 bps
G16: All-In Rate | I16: =I14+I15 -> 0.063
G17: Amortization (Years) | I17: 25
G18: Loan Term (Years) | I18: 5
G19: Loan Amount | I19: =E14*I13 -> 9100000
G21: Capital Expenditures
G22: Upfront CapEx (Day 1) | I22: 25000
G23: Year 1 CapEx (Mo. 6-12) | I23: 0
G24: Total CapEx | I24: =I22+I23 -> 25000
G25: Annual CapEx Reserve (Yr 2-5) | I25: 0 | J25: Adjust if needed
G27: Exit Assumptions
G28: Exit Cap Rate | I28: 0.0625
G29: Disposition Costs | I29: 0.02
G30: Going-In Cap Rate | I30: =Model2.0!F60/E14 -> 0.045309753 | J30: T-12 NOI / Purchase Price
G31: Asset Management Fee | I31: 75000 | J31: Annual
B32: Drivers
B34: In-place Income (T-3) | G34: In-place Expenses
D35: Assumption | E35: Total | H35: % | I35: Per Rentable SqFt | J35: Total
B36: Occupancy | E36: =Model2.0!E24 -> 0.91721854 | G36: Advertising & Marketing | I36: 0.39012222 | J36: =I36*$E$10 -> 34857.42 | L36: 34857.42 | M36: =L36/$E$10 -> 0.39012222 | N36: Advertising & Marketing
B37: Effective Rate / SqFt | E37: =Model2.0!E23 -> 1.0390211 | G37: Current Credit Card Security Fees | H37: 0.014429716 | I37: 0 | J37: =H37*E42 -> 14744.524 | L37: 13333.74 | M37: 0 | N37: Current Credit Card Security Fees
G38: STORE Credit Card Security Fees | H38: 0 | I38: 0 | M38: =L38/$E$10 -> 0 | N38: STORE Credit Card Security Fees
B39: Rental Income | E39: =E37*(E10*E36)*12 -> 1021816.7 | G39: Fire Prevention | I39: 0.085007536 | J39: =I39*$E$10 -> 7595.4233 | L39: 0 | M39: =L39/$E$10 -> 0 | N39: Fire Prevention
B40: Discounts | D40: =-E40/$E$39 -> 0 | E40: =Model2.0!E21 -> 0 | G40: Licenses & Permits | I40: 0.0045914941 | J40: =I40*$E$10 -> 410.25 | L40: 410.25 | M40: =L40/$E$10 -> 0.0045914941 | N40: Licenses & Permits
B41: Bad Debt/Rental Refunds | D41: =-E41/$E$39 -> 0 | E41: 0 | G41: Current Mgmt. Fee | H41: 0.06 | I41: 0 | J41: =H41*E42 -> 61309.001 | L41: 46924.36 | M41: 0 | N41: Current Mgmt. Fee
B42: Total Rental Income | E42: =SUM(E39:E41) -> 1021816.7 | G42: STORE Mgmt. Fee | H42: 0.04 | I42: 0 | J42: =H42*E42 -> 40872.667 | L42: 0 | M42: =L42/$E$10 -> 0 | N42: STORE Mgmt. Fee
B43: Admin Fee Income | D43: 29 | E43: =Model2.0!E27 -> 29888.72 | G43: Payroll | I43: 1.00598 | J43: =(((52*($D$53*$D$55)+(D54*(($D$53*$D$55))))/12)+((D44*$E$9)*12))*12 -> 95022.864 | L43: 89884.31 | M43: =L43/$E$10 -> 1.00598 | N43: Payroll
B44: Late Fee Income | D44: ='P-Builder'!F82 -> 0.13431688 | E44: =Model2.0!E28 -> 29888.72 | G44: Office Supplies | I44: 0.018577728 | J44: =I44*$E$10 -> 1659.92 | L44: 1659.92 | M44: =L44/$E$10 -> 0.018577728 | N44: Office Supplies
B45: Current Tenant Protection Split | E45: =Model2.0!E29 -> 38040 | G45: Repairs & Maintenance | I45: 0.44530084 | J45: =I45*$E$10 -> 39787.63 | L45: 39787.63 | M45: =L45/$E$10 -> 0.44530084 | N45: Repairs & Maintenance
B46: STORE Tenant Insurance Income | E46: =Model2.0!E30 -> 0 | G46: Security | I46: 0 | J46: =I46*$E$10 -> 0 | L46: 0 | M46: =L46/$E$10 -> 0 | N46: Security
B47: Other Income | E47: =Model2.0!E31 -> 0 | G47: Retail Products | I47: 0.041371796 | J47: =I47*$E$10 -> 3696.57 | L47: 3696.57 | M47: =L47/$E$10 -> 0.041371796 | N47: Retail Products
B48: Retail Sales Income | E48: =Model2.0!E32 -> 10168.16 | G48: Telephone & Internet | I48: 0.12214337 | J48: =I48*$E$10 -> 10913.51 | L48: 10913.51 | M48: =L48/$E$10 -> 0.12214337 | N48: Telephone & Internet
B49: Total Income | E49: =SUM(E42:E48) -> 1129802.3 | G49: Software | I49: 0.1491117 | J49: =I49*$E$10 -> 13323.13 | L49: 13323.13 | M49: =L49/$E$10 -> 0.1491117 | N49: Software
G50: Bank Charges | I50: 0.044510688 | J50: =I50*$E$10 -> 3977.03 | L50: 3977.03 | M50: =L50/$E$10 -> 0.044510688 | N50: Bank Charges
B51: Payroll | G51: Prof Fees - Legal/Acctg | I51: 0.021720873 | J51: =I51*$E$10 -> 1940.76 | L51: 1940.76 | M51: =L51/$E$10 -> 0.021720873 | N51: Prof Fees - Legal/Acctg
D52: Assumption | G52: Utilities | I52: 0.31474919 | J52: =I52*$E$10 -> 28122.84 | L52: 28122.84 | M52: =L52/$E$10 -> 0.31474919 | N52: Utilities
B53: Pay Rate (Hourly) | D53: 26 | G53: Insurance | I53: 0 | J53: =I53*$E$10 -> 0 | L53: 0 | M53: =L53/$E$10 -> 0 | N53: Insurance
B54: Burden Rate | D54: 0.3 | E54: =D55&"Hrs/Wk @ "&"$"&D53&" + Burden Rate" -> 62Hrs/Wk @ $26 + Burden Rate | G54: Property Taxes | I54: 0 | J54: =I54*$E$10 -> 0 | L54: 0 | M54: =L54/$E$10 -> 0 | N54: Property Taxes
B55: Payroll Hours | D55: 62 | G55: Other Expense | I55: 0 | J55: =I55*$E$10 -> 0 | L55: 0 | M55: =L55/$E$10 -> 0 | N55: Other Expense
B56: Delinquency Rate | D56: ='P-Builder'!F82 -> 0.13431688 | G56: Total | I56: =SUM(I36:I55) -> 2.6431874 | J56: =SUM(J36:J55) -> 358233.54
B58: Revenue & Expense Assumptions
E59: Rent | G59: Management | I59: Expense | J59: RET | L59: Tenant Protection | N59: Management
B60: Year | D60: Occupancy | E60: Growth | G60: Fee | I60: Growth | J60: Growth | N60: 0.04
B61: 1 | D61: 0.95 | E61: 0.08 | G61: 0.04 | I61: 0.01 | J61: 0 | N61: 0.045
B62: =++B61+1 -> 2 | D62: 0.95 | E62: 0.04 | G62: 0.045 | I62: 0.02 | J62: 0.01 | N62: 0.05
B63: =++B62+1 -> 3 | D63: 0.95 | E63: 0.04 | G63: 0.05 | I63: 0.02 | J63: 0.01 | N63: 0.05
B64: =++B63+1 -> 4 | D64: 0.95 | E64: 0.04 | G64: 0.05 | I64: 0.02 | J64: 0.01 | N64: 0.05
B65: =++B64+1 -> 5 | D65: =D64 -> 0.95 | E65: 0.04 | G65: 0.05 | I65: =I64 -> 0.02 | J65: 0.01 | N65: 0.05
D68: Tenant | L68: Tenant Prot. | N68: Software
B69: Year | D69: Protection Assumptions | L69: Ann. Growth | N69: Ann. Growth
B70: 1 | C70: Amount | D70: 16 | L70: 0.015 | N70: 0.015
B71: =++B70+1 -> 2 | C71: Split | D71: 0.5 | G71: =6695.18/20 -> 334.759
B72: =++B71+1 -> 3
B73: =++B72+1 -> 4
B74: =++B73+1 -> 5
B77: Partnership / JV Structure | G77: Acquisition Cost Breakdown
H78: % | I78: $
B79: GP Equity % | D79: 0.1 | G79: Title & Escrow | H79: 0.005 | I79: =H79*'Inputs & Drivers'!E14 -> 70000
B80: LP Equity % | D80: =1-E79 -> 1 | G80: Legal | I80: 0
B81: Preferred Return | D81: 0.08 | G81: Phase 1 Environmental | I81: 3500
B82: Pref Compounded? | D82: No | G82: Other Due Diligence | I82: 0 | J82: ALTA, inspections, etc.
B83: GP Promote (above pref) | D83: 0.25 | G83: Broker Fee | H83: 0 | I83: =H83*'Inputs & Drivers'!E14 -> 0
G84: Acquisition Fee | H84: 0 | I84: =H84*'Inputs & Drivers'!E14 -> 0
B85: Hold Period Scenarios | G85: Subtotal Closing Costs | H85: =I85/E14 -> 0.00525 | I85: =SUM(I79:I84) -> 73500
B86: Primary Hold (years) | D86: =E13 -> 5 | E86: (from above)
B87: Alt Hold #1 (years) | D87: 3 | G87: Loan Origination Fee | H87: 0.01 | I87: =H87*'Inputs & Drivers'!I19 -> 91000
B88: Alt Hold #2 (years) | D88: 7 | G88: Loan Exit Fee | H88: 0
G90: Total Acq. & Financing Costs | H90: =I90/E14 -> 0.01175 | I90: =I85+I87 -> 164500
G92: Effective Purchase Price | I92: =E14+I90 -> 14164500

Sheet Model2.0
B2: Model | BV2: x
U3: x | AG3: x | AS3: x | BE3: x
B4: NRSF | C4: ='Inputs & Drivers'!E10 -> 89350 | E4: 0.25 | F4: =E4/12 -> 0.020833333 | H4: Monthly | BR4: Comparison
B5: Start Date | C5: ='Inputs & Drivers'!E12 -> 46082 | H5: 0 | I5: 1 | J5: 1 | K5: 1 | L5: 1 | M5: 1 | N5: 1 | O5: 1 | P5: 1 | Q5: 1 | R5: 1 | S5: 1 | T5: =1+H5 -> 1 | U5: =1+I5 -> 2 | V5: =1+J5 -> 2 | W5: =1+K5 -> 2 | X5: =1+L5 -> 2 | Y5: =1+M5 -> 2 | Z5: =1+N5 -> 2 | AA5: =1+O5 -> 2 | ... BP5: =1+BD5 -> 5 | BR5: 1
B6: Units Available | C6: ='Inputs & Drivers'!E8 -> 604 | H6: 0 | I6: =++H6+1 -> 1 | J6: =++I6+1 -> 2 | K6: =++J6+1 -> 3 | L6: =++K6+1 -> 4 | M6: =++L6+1 -> 5 | N6: =++M6+1 -> 6 | O6: =++N6+1 -> 7 | P6: =++O6+1 -> 8 | ... BP6: =++BO6+1 -> 60
B7: Units Occupied | C7: ='Inputs & Drivers'!E9 -> 554 | E7: T-3 | F7: T-12 | H7: =C5 -> 46082 | I7: =EOMONTH(H7,1) -> 46142 | J7: =EOMONTH(I7,1) -> 46173 | K7: =EOMONTH(J7,1) -> 46203 | L7: =EOMONTH(K7,1) -> 46234 | M7: =EOMONTH(L7,1) -> 46265 | N7: =EOMONTH(M7,1) -> 46295 | O7: =EOMONTH(N7,1) -> 46326 | P7: =EOMONTH(O7,1) -> 46356 | ... BP7: =EOMONTH(BO7,1) -> 47938 | BR7: STORE | BS7: Current Mgmt | BT7: Additional Revenue
B9: Net Rentable SqFt | E9: =C4 -> 89350 | F9: =C4 -> 89350 | I9: =$C$4 -> 89350 | J9: =$C$4 -> 89350 | K9: =$C$4 -> 89350 | L9: =$C$4 -> 89350 | M9: =$C$4 -> 89350 | N9: =$C$4 -> 89350 | O9: =$C$4 -> 89350 | P9: =$C$4 -> 89350 | ... BP9: =$C$4 -> 89350
B10: Projected Rate ($/sqft) | E10: =E19/($C$4*E24)/12 -> 1.0390211 | F10: =H19/($C$4*F24) -> 1.0793785 | H10: =H19/($C$4*E24) -> 1.0793785 | I10: =(1+(INDEX('Inputs & Drivers'!$E$61:$E$65,MATCH(Model2.0!I$5,'Inputs & Drivers'!$B$61:$B$65,0))/12))*H10 -> 1.0865743 | J10: =(1+(INDEX('Inputs & Drivers'!$E$61:$E$65,MATCH(Model2.0!J$5,'Inputs & Drivers'!$B$61:$B$65,0))/12))*I10 -> 1.0938182 | K10: =(1+(INDEX('Inputs & Drivers'!$E$61:$E$65,MATCH(Model2.0!K$5,'Inputs & Drivers'!$B$61:$B$65,0))/12))*J10 -> 1.1011103 | L10: =(1+(INDEX('Inputs & Drivers'!$E$61:$E$65,MATCH(Model2.0!L$5,'Inputs & Drivers'!$B$61:$B$65,0))/12))*K10 -> 1.108451 | M10: =(1+(INDEX('Inputs & Drivers'!$E$61:$E$65,MATCH(Model2.0!M$5,'Inputs & Drivers'!$B$61:$B$65,0))/12))*L10 -> 1.1158407 | N10: =(1+(INDEX('Inputs & Drivers'!$E$61:$E$65,MATCH(Model2.0!N$5,'Inputs & Drivers'!$B$61:$B$65,0))/12))*M10 -> 1.1232796 | O10: =(1+(INDEX('Inputs & Drivers'!$E$61:$E$65,MATCH(Model2.0!O$5,'Inputs & Drivers'!$B$61:$B$65,0))/12))*N10 -> 1.1307682 | P10: =(1+(INDEX('Inputs & Drivers'!$E$61:$E$65,MATCH(Model2.0!P$5,'Inputs & Drivers'!$B$61:$B$65,0))/12))*O10 -> 1.1383066 | ... BP10: =(1+(INDEX('Inputs & Drivers'!$E$61:$E$65,MATCH(Model2.0!BP$5,'Inputs & Drivers'!$B$61:$B$65,0))/12))*BO10 -> 1.3714298
B11: General Vacancy | E11: =1-E24 -> 0.082781457 | F11: =1-F24 -> 0.082781457 | I11: =($C$6-I15)/$C$6 -> 0.082781457 | J11: =($C$6-J15)/$C$6 -> 0.082781457 | K11: =($C$6-K15)/$C$6 -> 0.082781457 | L11: =($C$6-L15)/$C$6 -> 0.082781457 | M11: =($C$6-M15)/$C$6 -> 0.082781457 | N11: =($C$6-N15)/$C$6 -> 0.082781457 | O11: =($C$6-O15)/$C$6 -> 0.082781457 | P11: =($C$6-P15)/$C$6 -> 0.082781457 | ... BP11: =($C$6-BP15)/$C$6 -> 0.082781457
B12: ECRI | F12: ECRI | I12: 0 | J12: 0 | K12: 0 | L12: 0.05 | M12: 0.05 | N12: 0.05 | O12: 0.02 | P12: 0.02 | Q12: 0.02 | R12: 0.02 | S12: 0.02 | T12: 0.02 | U12: 0.05 | V12: 0.01 | W12: 0.01 | X12: 0.01 | Y12: 0.01 | Z12: 0.01 | AA12: 0.01 | AB12: 0.01 | AC12: 0.01 | AD12: 0.01 | AE12: 0.01 | AF12: 0.01 | AG12: 0.05 | AH12: 0.01 | AI12: 0.01 | AJ12: 0.01 | AK12: 0.01 | AL12: 0.01 | AM12: 0.01 | AN12: 0.01 | AO12: 0.01 | AP12: 0.01 | AQ12: 0.01 | AR12: 0.01 | AS12: 0.05 | AT12: 0.01 | AU12: 0.01 | AV12: 0.01 | AW12: 0.01 | AX12: 0.01 | AY12: 0.01 | AZ12: 0.01 | BA12: 0.01 | BB12: 0.01 | BC12: 0.01 | BD12: 0.01 | BE12: 0.05 | BF12: 0.01 | BG12: 0.01 | BH12: 0.01 | BI12: 0.01 | BJ12: 0.01 | BK12: 0.01 | BL12: 0.01 | BM12: 0.01 | BN12: 0.01 | BO12: 0.01 | BP12: 0.01
B13: Move-ins | H13: 20 | I13: 20 | J13: 20 | K13: 20 | L13: 20 | M13: 20 | N13: 20 | O13: 20 | P13: 20 | Q13: 20 | R13: 20 | S13: 20 | T13: 20 | U13: 20 | V13: 20 | W13: 20 | X13: 20 | Y13: 20 | Z13: 20 | AA13: 20 | AB13: 20 | AC13: 20 | AD13: 20 | AE13: 20 | AF13: 20 | AG13: 20 | AH13: 20 | AI13: 20 | AJ13: 20 | AK13: 20 | AL13: 20 | AM13: 20 | AN13: 20 | AO13: 20 | AP13: 20 | AQ13: 20 | AR13: 20 | AS13: 20 | AT13: 20 | AU13: 20 | AV13: 20 | AW13: 20 | AX13: 20 | AY13: 20 | AZ13: 20 | BA13: 20 | BB13: 20 | BC13: 20 | BD13: 20 | BE13: 20 | BF13: 20 | BG13: 20 | BH13: 20 | BI13: 20 | BJ13: 20 | BK13: 20 | BL13: 20 | BM13: 20 | BN13: 20 | BO13: 20 | BP13: 20
B14: Move-Outs | H14: 20 | I14: 20 | J14: 20 | K14: 20 | L14: 20 | M14: 20 | N14: 20 | O14: 20 | P14: 20 | Q14: 20 | R14: 20 | S14: 20 | T14: 20 | U14: 20 | V14: 20 | W14: 20 | X14: 20 | Y14: 20 | Z14: 20 | AA14: 20 | AB14: 20 | AC14: 20 | AD14: 20 | AE14: 20 | AF14: 20 | AG14: 20 | AH14: 20 | AI14: 20 | AJ14: 20 | AK14: 20 | AL14: 20 | AM14: 20 | AN14: 20 | AO14: 20 | AP14: 20 | AQ14: 20 | AR14: 20 | AS14: 20 | AT14: 20 | AU14: 20 | AV14: 20 | AW14: 20 | AX14: 20 | AY14: 20 | AZ14: 20 | BA14: 20 | BB14: 20 | BC14: 20 | BD14: 20 | BE14: 20 | BF14: 20 | BG14: 20 | BH14: 20 | BI14: 20 | BJ14: 20 | BK14: 20 | BL14: 20 | BM14: 20 | BN14: 20 | BO14: 20 | BP14: 20
B15: Occupied Units | E15: =C7 -> 554 | F15: =C7 -> 554 | H15: =E15+(H13-H14) -> 554 | I15: =F15+(I13-I14) -> 554 | J15: =I15+(J13-J14) -> 554 | K15: =J15+(K13-K14) -> 554 | L15: =K15+(L13-L14) -> 554 | M15: =L15+(M13-M14) -> 554 | N15: =M15+(N13-N14) -> 554 | O15: =N15+(O13-O14) -> 554 | P15: =O15+(P13-P14) -> 554 | Q15: =P15+(Q13-Q14) -> 554 | ... BP15: =BO15+(BP13-BP14) -> 554
B16: Tenant Protection Capture | H16: 0.6 | I16: =H16+0.02 -> 0.62 | J16: =I16+0.02 -> 0.64 | K16: =J16+0.02 -> 0.66 | L16: =K16+0.02 -> 0.68 | M16: =L16+0.02 -> 0.7 | N16: =M16+0.02 -> 0.72 | O16: =N16+0.02 -> 0.74 | P16: =O16+0.02 -> 0.76 | ... R16: =Q16+0.02 -> 0.8 | S16: =R16 -> 0.8 | T16: =S16 -> 0.8 | U16: =T16 -> 0.8 | V16: =U16 -> 0.8 | W16: =V16 -> 0.8 | X16: =W16 -> 0.8 | Y16: =X16 -> 0.8 | Z16: =Y16 -> 0.8 | ... BP16: =BO16 -> 0.8 | BW16: Yearly
E17: =1-E11 -> 0.91721854 | F17: =1-F11 -> 0.91721854 | I17: =1-I11 -> 0.91721854 | J17: =1-J11 -> 0.91721854 | K17: =1-K11 -> 0.91721854 | L17: =1-L11 -> 0.91721854 | M17: =1-M11 -> 0.91721854 | N17: =1-N11 -> 0.91721854 | O17: =1-O11 -> 0.91721854 | P17: =1-P11 -> 0.91721854 | ... BP17: =1-BP11 -> 0.91721854
B18: Income | BV18: Income | BW18: 1 | BX18: 2 | BY18: 3 | BZ18: 4 | CA18: 5
B19: Rental Income | E19: =SUM('P-Builder'!O5:Q5)*4 -> 1021816.7 | F19: =SUM('P-Builder'!F5:Q5) -> 832809.83 | H19: ='P-Builder'!Q5 -> 88458.82 | I19: =I10*(I9*(1-I11)) -> 89048.545 | J19: =J10*(J9*(1-J11)) -> 89642.202 | K19: =K10*(K9*(1-K11)) -> 90239.817 | L19: =L10*(L9*(1-L11)) -> 90841.416 | M19: =M10*(M9*(1-M11)) -> 91447.025 | N19: =N10*(N9*(1-N11)) -> 92056.672 | O19: =O10*(O9*(1-O11)) -> 92670.383 | P19: =P10*(P9*(1-P11)) -> 93288.186 | ... BP19: =BP10*(BP9*(1-BP11)) -> 112393.44 | BR19: =SUM(I19:T19) -> 1108647.8 | BS19: =(E19*1.07)+ABS(BR21) -> 1133367.2 | BT19: =BR19-BS19 -> -24719.431 | BV19: Rental Income | BW19: =SUMIF($I$5:$BP$5,BW$18,$I19:$BP19) -> 1108647.8 | BX19: =SUMIF($I$5:$BP$5,BX$18,$I19:$BP19) -> 1174825.5 | BY19: =SUMIF($I$5:$BP$5,BY$18,$I19:$BP19) -> 1222689.7 | BZ19: =SUMIF($I$5:$BP$5,BZ$18,$I19:$BP19) -> 1272504 | CA19: =SUMIF($I$5:$BP$5,CA$18,$I19:$BP19) -> 1324347.8 | CC19: =SUM($I19:$T19) -> 1108647.8 | CD19: =SUM($U19:$AF19) -> 1174825.5 | CE19: =SUM($AG19:$AR19) -> 1222689.7 | CF19: =SUM($AS19:$BD19) -> 1272504 | CG19: =SUM($BE19:$BP19) -> 1324347.8 | CI19: =IF(CC19=BW19,"OK","Check") -> OK | CJ19: =IF(CD19=BX19,"OK","Check") -> OK | CK19: =IF(CE19=BY19,"OK","Check") -> OK | CL19: =IF(CF19=BZ19,"OK","Check") -> OK | CM19: =IF(CG19=CA19,"OK","Check") -> OK
B20: STORE Rate Mgmt. Rev | E20: 0 | F20: 0 | H20: =H19*H12 -> 0 | I20: =IF(I5=H5,H20+(I19*I12),I19*I12) -> 0 | J20: =IF(J5=I5,I20+(J19*J12),J19*J12) -> 0 | K20: =IF(K5=J5,J20+(K19*K12),K19*K12) -> 0 | L20: =IF(L5=K5,K20+(L19*L12),L19*L12) -> 4542.0708 | M20: =IF(M5=L5,L20+(M19*M12),M19*M12) -> 9114.4221 | N20: =IF(N5=M5,M20+(N19*N12),N19*N12) -> 13717.256 | O20: =IF(O5=N5,N20+(O19*O12),O19*O12) -> 15570.663 | P20: =IF(P5=O5,O20+(P19*P12),P19*P12) -> 17436.427 | ... BP20: =IF(BP5=BO5,BO20+(BP19*BP12),BP19*BP12) -> 17577.621 | BR20: =SUM(I20:T20) -> 149034.2 | BS20: =E20 -> 0 | BT20: =BR20-BS20 -> 149034.2 | BV20: STORE Rate Mgmt. Rev | BW20: =SUMIF($I$5:$BP$5,BW$18,$I20:$BP20) -> 149034.2 | BX20: =SUMIF($I$5:$BP$5,BX$18,$I20:$BP20) -> 122035.47 | BY20: =SUMIF($I$5:$BP$5,BY$18,$I20:$BP20) -> 127007.39 | BZ20: =SUMIF($I$5:$BP$5,BZ$18,$I20:$BP20) -> 132181.86 | CA20: =SUMIF($I$5:$BP$5,CA$18,$I20:$BP20) -> 137567.16 | CC20: =SUM($I20:$T20) -> 149034.2 | CD20: =SUM($U20:$AF20) -> 122035.47 | CE20: =SUM($AG20:$AR20) -> 127007.39 | CF20: =SUM($AS20:$BD20) -> 132181.86 | CG20: =SUM($BE20:$BP20) -> 137567.16 | CI20: =IF(CC20=BW20,"OK","Check") -> OK | CJ20: =IF(CD20=BX20,"OK","Check") -> OK | CK20: =IF(CE20=BY20,"OK","Check") -> OK | CL20: =IF(CF20=BZ20,"OK","Check") -> OK | CM20: =IF(CG20=CA20,"OK","Check") -> OK
B21: Discounts | E21: =SUM('P-Builder'!O6:Q6)*4 -> 0 | F21: =SUM('P-Builder'!F6:Q6) -> 0 | H21: ='P-Builder'!Q7 -> 0 | I21: =((I10*I13)*($C$4/$C$6))*(-1) -> -3214.7489 | J21: =((J10*J13)*($C$4/$C$6))*(-1) -> -3236.1806 | K21: =((K10*K13)*($C$4/$C$6))*(-1) -> -3257.7551 | L21: =((L10*L13)*($C$4/$C$6))*(-1) -> -3279.4735 | M21: =((M10*M13)*($C$4/$C$6))*(-1) -> -3301.3367 | N21: =((N10*N13)*($C$4/$C$6))*(-1) -> -3323.3456 | O21: =((O10*O13)*($C$4/$C$6))*(-1) -> -3345.5012 | P21: =((P10*P13)*($C$4/$C$6))*(-1) -> -3367.8045 | ... BP21: =((BP10*BP13)*($C$4/$C$6))*(-1) -> -4057.5249 | BR21: =SUM(I21:T21) -> -40023.386 | BS21: =BR21 -> -40023.386 | BT21: =BR21-BS21 -> 0 | BV21: Discounts | BW21: =SUMIF($I$5:$BP$5,BW$18,$I21:$BP21) -> -40023.386 | BX21: =SUMIF($I$5:$BP$5,BX$18,$I21:$BP21) -> -42412.473 | BY21: =SUMIF($I$5:$BP$5,BY$18,$I21:$BP21) -> -44140.423 | BZ21: =SUMIF($I$5:$BP$5,BZ$18,$I21:$BP21) -> -45938.772 | CA21: =SUMIF($I$5:$BP$5,CA$18,$I21:$BP21) -> -47810.388 | CC21: =SUM($I21:$T21) -> -40023.386 | CD21: =SUM($U21:$AF21) -> -42412.473 | CE21: =SUM($AG21:$AR21) -> -44140.423 | CF21: =SUM($AS21:$BD21) -> -45938.772 | CG21: =SUM($BE21:$BP21) -> -47810.388 | CI21: =IF(CC21=BW21,"OK","Check") -> OK | CJ21: =IF(CD21=BX21,"OK","Check") -> OK | CK21: =IF(CE21=BY21,"OK","Check") -> OK | CL21: =IF(CF21=BZ21,"OK","Check") -> OK | CM21: =IF(CG21=CA21,"OK","Check") -> OK
B22: Net Rental Income | E22: =SUM(E19:E21) -> 1021816.7 | F22: =SUM(F19:F21) -> 832809.83 | H22: ='P-Builder'!Q8 -> 88458.82 | I22: =SUM(I19:I21) -> 85833.797 | J22: =SUM(J19:J21) -> 86406.022 | K22: =SUM(K19:K21) -> 86982.062 | L22: =SUM(L19:L21) -> 92104.013 | M22: =SUM(M19:M21) -> 97260.111 | N22: =SUM(N19:N21) -> 102450.58 | O22: =SUM(O19:O21) -> 104895.55 | P22: =SUM(P19:P21) -> 107356.81 | ... BP22: =SUM(BP19:BP21) -> 125913.54 | BR22: =SUM(BR19:BR21) -> 1217658.6 | BS22: =SUM(BS19:BS21) -> 1093343.8 | BT22: =BR22-BS22 -> 124314.77 | BV22: Net Rental Income | BW22: =SUMIF($I$5:$BP$5,BW$18,$I22:$BP22) -> 1217658.6 | BX22: =SUMIF($I$5:$BP$5,BX$18,$I22:$BP22) -> 1254448.5 | BY22: =SUMIF($I$5:$BP$5,BY$18,$I22:$BP22) -> 1305556.7 | BZ22: =SUMIF($I$5:$BP$5,BZ$18,$I22:$BP22) -> 1358747.1 | CA22: =SUMIF($I$5:$BP$5,CA$18,$I22:$BP22) -> 1414104.5 | CC22: =SUM($I22:$T22) -> 1217658.6 | CD22: =SUM($U22:$AF22) -> 1254448.5 | CE22: =SUM($AG22:$AR22) -> 1305556.7 | CF22: =SUM($AS22:$BD22) -> 1358747.1 | CG22: =SUM($BE22:$BP22) -> 1414104.5
B23: Effective Rent / Month | E23: =E19/($C$4*E24)/12 -> 1.0390211 | F23: =F19/($C$4*F24)/12 -> 0.84683191 | H23: ='Inputs & Drivers'!E37 -> 1.0390211 | I23: =I19/($C$4*I24) -> 1.0865743 | J23: =J19/($C$4*J24) -> 1.0938182 | K23: =K19/($C$4*K24) -> 1.1011103 | L23: =L19/($C$4*L24) -> 1.108451 | M23: =M19/($C$4*M24) -> 1.1158407 | N23: =N19/($C$4*N24) -> 1.1232796 | O23: =O19/($C$4*O24) -> 1.1307682 | P23: =P19/($C$4*P24) -> 1.1383066 | ... BP23: =BP19/($C$4*BP24) -> 1.3714298 | CC23: =IF(CC22=BW22,"OK","Check") -> OK | CD23: =IF(CD22=BX22,"OK","Check") -> OK | CE23: =IF(CE22=BY22,"OK","Check") -> OK | CF23: =IF(CF22=BZ22,"OK","Check") -> OK | CG23: =IF(CG22=CA22,"OK","Check") -> OK
B24: Physical Occupancy | E24: =C7/C6 -> 0.91721854 | F24: =C7/C6 -> 0.91721854 | H24: =H15/$C$6 -> 0.91721854 | I24: =I15/$C$6 -> 0.91721854 | J24: =J15/$C$6 -> 0.91721854 | K24: =K15/$C$6 -> 0.91721854 | L24: =L15/$C$6 -> 0.91721854 | M24: =M15/$C$6 -> 0.91721854 | N24: =N15/$C$6 -> 0.91721854 | O24: =O15/$C$6 -> 0.91721854 | ... BP24: =BP15/$C$6 -> 0.91721854
B27: Admin Fee Income | E27: =SUM('P-Builder'!O10:Q10)*4 -> 29888.72 | F27: =SUM('P-Builder'!F10:Q10) -> 22165.125 | H27: ='Inputs & Drivers'!D43*H13 -> 580 | I27: =I13*'Inputs & Drivers'!$D$43 -> 580 | J27: =J13*'Inputs & Drivers'!$D$43 -> 580 | K27: =K13*'Inputs & Drivers'!$D$43 -> 580 | L27: =L13*'Inputs & Drivers'!$D$43 -> 580 | M27: =M13*'Inputs & Drivers'!$D$43 -> 580 | N27: =N13*'Inputs & Drivers'!$D$43 -> 580 | O27: =O13*'Inputs & Drivers'!$D$43 -> 580 | P27: =P13*'Inputs & Drivers'!$D$43 -> 580 | ... BP27: =BP13*'Inputs & Drivers'!$D$43 -> 580 | BR27: =SUM(I27:T27) -> 6960 | BS27: =SUM(I27:T27) -> 6960 | BT27: =BR27-BS27 -> 0 | BV27: Admin Fee Income | BW27: =SUMIF($I$5:$BP$5,BW$18,$I27:$BP27) -> 6960 | BX27: =SUMIF($I$5:$BP$5,BX$18,$I27:$BP27) -> 6960 | BY27: =SUMIF($I$5:$BP$5,BY$18,$I27:$BP27) -> 6960 | BZ27: =SUMIF($I$5:$BP$5,BZ$18,$I27:$BP27) -> 6960 | CA27: =SUMIF($I$5:$BP$5,CA$18,$I27:$BP27) -> 6960 | CC27: =SUM($I27:$T27) -> 6960 | CD27: =SUM($U27:$AF27) -> 6960 | CE27: =SUM($AG27:$AR27) -> 6960 | CF27: =SUM($AS27:$BD27) -> 6960 | CG27: =SUM($BE27:$BP27) -> 6960 | CI27: =IF(CC27=BW27,"OK","Check") -> OK | CJ27: =IF(CD27=BX27,"OK","Check") -> OK | CK27: =IF(CE27=BY27,"OK","Check") -> OK | CL27: =IF(CF27=BZ27,"OK","Check") -> OK | CM27: =IF(CG27=CA27,"OK","Check") -> OK
B28: Late Fee Income | E28: =SUM('P-Builder'!O11:Q11)*4 -> 29888.72 | F28: =SUM('P-Builder'!F11:Q11) -> 22165.125 | H28: =(H19*'Inputs & Drivers'!D44)*0.2 -> 2376.3026 | I28: =(I19*'Inputs & Drivers'!D44)*0.2 -> 2392.1446 | J28: =I28*0.98 -> 2344.3017 | K28: =J28*0.98 -> 2297.4157 | L28: =K28*0.98 -> 2251.4674 | M28: =L28*0.98 -> 2206.438 | N28: =M28*0.98 -> 2162.3092 | O28: =N28*0.98 -> 2119.0631 | P28: =O28*0.98 -> 2076.6818 | Q28: =P28*0.98 -> 2035.1482 | ... BP28: =BO28*0.98 -> 726.31647 | BR28: =SUM(I28:T28) -> 25749.436 | BS28: =SUM(I28:T28) -> 25749.436 | BT28: =BR28-BS28 -> 0 | BV28: Late Fee Income | BW28: =SUMIF($I$5:$BP$5,BW$18,$I28:$BP28) -> 25749.436 | BX28: =SUMIF($I$5:$BP$5,BX$18,$I28:$BP28) -> 20206.013 | BY28: =SUMIF($I$5:$BP$5,BY$18,$I28:$BP28) -> 15855.997 | BZ28: =SUMIF($I$5:$BP$5,BZ$18,$I28:$BP28) -> 12442.466 | CA28: =SUMIF($I$5:$BP$5,CA$18,$I28:$BP28) -> 9763.8109 | CC28: =SUM($I28:$T28) -> 25749.436 | CD28: =SUM($U28:$AF28) -> 20206.013 | CE28: =SUM($AG28:$AR28) -> 15855.997 | CF28: =SUM($AS28:$BD28) -> 12442.466 | CG28: =SUM($BE28:$BP28) -> 9763.8109 | CI28: =IF(CC28=BW28,"OK","Check") -> OK | CJ28: =IF(CD28=BX28,"OK","Check") -> OK | CK28: =IF(CE28=BY28,"OK","Check") -> OK | CL28: =IF(CF28=BZ28,"OK","Check") -> OK | CM28: =IF(CG28=CA28,"OK","Check") -> OK
B29: Current Tenant Protection Split | E29: =SUM('P-Builder'!O12:Q12)*4 -> 38040 | F29: =SUM('P-Builder'!F12:Q12) -> 35796 | H29: =F29/12 -> 2983 | I29: =H29*1.002 -> 2988.966 | J29: =I29*1.002 -> 2994.9439 | K29: =J29*1.002 -> 3000.9338 | L29: =K29*1.002 -> 3006.9357 | M29: =L29*1.002 -> 3012.9496 | N29: =M29*1.002 -> 3018.9755 | O29: =N29*1.002 -> 3025.0134 | P29: =O29*1.002 -> 3031.0634 | ... BP29: =BO29*1.002 -> 3362.9201 | BR29: 0 | BS29: =SUM(I29:T29) -> 36264.778 | BV29: Current Tenant Protection Split | BW29: =SUMIF($I$5:$BP$5,BW$18,$I29:$BP29) -> 36264.778 | BX29: =SUMIF($I$5:$BP$5,BX$18,$I29:$BP29) -> 37144.77 | BY29: =SUMIF($I$5:$BP$5,BY$18,$I29:$BP29) -> 38046.117 | BZ29: =SUMIF($I$5:$BP$5,BZ$18,$I29:$BP29) -> 38969.335 | CA29: =SUMIF($I$5:$BP$5,CA$18,$I29:$BP29) -> 39914.956 | CC29: =SUM($I29:$T29) -> 36264.778 | CD29: =SUM($U29:$AF29) -> 37144.77 | CE29: =SUM($AG29:$AR29) -> 38046.117 | CF29: =SUM($AS29:$BD29) -> 38969.335 | CG29: =SUM($BE29:$BP29) -> 39914.956 | CI29: =IF(CC29=BW29,"OK","Check") -> OK | CJ29: =IF(CD29=BX29,"OK","Check") -> OK | CK29: =IF(CE29=BY29,"OK","Check") -> OK | CL29: =IF(CF29=BZ29,"OK","Check") -> OK | CM29: =IF(CG29=CA29,"OK","Check") -> OK
B30: STORE Tenant Protection Split | E30: =SUM('P-Builder'!O13:Q13)*4 -> 0 | F30: =SUM('P-Builder'!F13:Q13) -> 0 | H30: 15 | I30: =((I15*'Inputs & Drivers'!$D$70)*I16)*'Inputs & Drivers'!$D$71*(1+'Inputs & Drivers'!$L$70)^(I5-1) -> 2747.84 | J30: =((J15*'Inputs & Drivers'!$D$70)*J16)*'Inputs & Drivers'!$D$71*(1+'Inputs & Drivers'!$L$70)^(J5-1) -> 2836.48 | K30: =((K15*'Inputs & Drivers'!$D$70)*K16)*'Inputs & Drivers'!$D$71*(1+'Inputs & Drivers'!$L$70)^(K5-1) -> 2925.12 | L30: =((L15*'Inputs & Drivers'!$D$70)*L16)*'Inputs & Drivers'!$D$71*(1+'Inputs & Drivers'!$L$70)^(L5-1) -> 3013.76 | M30: =((M15*'Inputs & Drivers'!$D$70)*M16)*'Inputs & Drivers'!$D$71*(1+'Inputs & Drivers'!$L$70)^(M5-1) -> 3102.4 | N30: =((N15*'Inputs & Drivers'!$D$70)*N16)*'Inputs & Drivers'!$D$71*(1+'Inputs & Drivers'!$L$70)^(N5-1) -> 3191.04 | O30: =((O15*'Inputs & Drivers'!$D$70)*O16)*'Inputs & Drivers'!$D$71*(1+'Inputs & Drivers'!$L$70)^(O5-1) -> 3279.68 | P30: =((P15*'Inputs & Drivers'!$D$70)*P16)*'Inputs & Drivers'!$D$71*(1+'Inputs & Drivers'!$L$70)^(P5-1) -> 3368.32 | ... BP30: =((BP15*'Inputs & Drivers'!$D$70)*BP16)*'Inputs & Drivers'!$D$71*(1+'Inputs & Drivers'!$L$70)^(BP5-1) -> 3763.1706 | BR30: =SUM(I30:T30) -> 38558.4 | BS30: 0 | BT30: =BR30-BS29 -> 2293.6223 | BV30: STORE Tenant Protection Split | BW30: =SUMIF($I$5:$BP$5,BW$18,$I30:$BP30) -> 38558.4 | BX30: =SUMIF($I$5:$BP$5,BX$18,$I30:$BP30) -> 43185.408 | BY30: =SUMIF($I$5:$BP$5,BY$18,$I30:$BP30) -> 43833.189 | BZ30: =SUMIF($I$5:$BP$5,BZ$18,$I30:$BP30) -> 44490.687 | CA30: =SUMIF($I$5:$BP$5,CA$18,$I30:$BP30) -> 45158.047 | CC30: =SUM($I30:$T30) -> 38558.4 | CD30: =SUM($U30:$AF30) -> 43185.408 | CE30: =SUM($AG30:$AR30) -> 43833.189 | CF30: =SUM($AS30:$BD30) -> 44490.687 | CG30: =SUM($BE30:$BP30) -> 45158.047 | CI30: =IF(CC30=BW30,"OK","Check") -> OK | CJ30: =IF(CD30=BX30,"OK","Check") -> OK | CK30: =IF(CE30=BY30,"OK","Check") -> OK | CL30: =IF(CF30=BZ30,"OK","Check") -> OK | CM30: =IF(CG30=CA30,"OK","Check") -> OK
B31: Other Tenant Income | E31: =SUM('P-Builder'!O14:Q14)*4 -> 0 | F31: =SUM('P-Builder'!F14:Q14) -> 0 | H31: =E31/12 -> 0 | I31: =H31*1.002 -> 0 | J31: =I31*1.002 -> 0 | K31: =J31*1.002 -> 0 | L31: =K31*1.002 -> 0 | M31: =L31*1.002 -> 0 | N31: =M31*1.002 -> 0 | O31: =N31*1.002 -> 0 | P31: =O31*1.002 -> 0 | ... BP31: =BO31*1.002 -> 0 | BR31: =SUM(I31:T31) -> 0 | BS31: =SUM(I31:T31) -> 0 | BT31: =BR31-BS31 -> 0 | BV31: Other Tenant Income | BW31: =SUMIF($I$5:$BP$5,BW$18,$I31:$BP31) -> 0 | BX31: =SUMIF($I$5:$BP$5,BX$18,$I31:$BP31) -> 0 | BY31: =SUMIF($I$5:$BP$5,BY$18,$I31:$BP31) -> 0 | BZ31: =SUMIF($I$5:$BP$5,BZ$18,$I31:$BP31) -> 0 | CA31: =SUMIF($I$5:$BP$5,CA$18,$I31:$BP31) -> 0 | CC31: =SUM($I31:$T31) -> 0 | CD31: =SUM($U31:$AF31) -> 0 | CE31: =SUM($AG31:$AR31) -> 0 | CF31: =SUM($AS31:$BD31) -> 0 | CG31: =SUM($BE31:$BP31) -> 0 | CI31: =IF(CC31=BW31,"OK","Check") -> OK | CJ31: =IF(CD31=BX31,"OK","Check") -> OK | CK31: =IF(CE31=BY31,"OK","Check") -> OK | CL31: =IF(CF31=BZ31,"OK","Check") -> OK | CM31: =IF(CG31=CA31,"OK","Check") -> OK
B32: Retail Sales Income | E32: =SUM('P-Builder'!O15:Q15)*4 -> 10168.16 | F32: =SUM('P-Builder'!F15:Q15) -> 10231.93 | H32: =E32/12 -> 847.34667 | I32: =H32*1.002 -> 849.04136 | J32: =I32*1.002 -> 850.73944 | K32: =J32*1.002 -> 852.44092 | L32: =K32*1.002 -> 854.1458 | M32: =L32*1.002 -> 855.8541 | N32: =M32*1.002 -> 857.5658 | O32: =N32*1.002 -> 859.28093 | P32: =O32*1.002 -> 860.9995 | ... BP32: =BO32*1.002 -> 955.26621 | BR32: =SUM(I32:T32) -> 10301.32 | BS32: =SUM(I32:T32) -> 10301.32 | BT32: =BR32-BS32 -> 0 | BV32: Retail Sales Income | BW32: =SUMIF($I$5:$BP$5,BW$18,$I32:$BP32) -> 10301.32 | BX32: =SUMIF($I$5:$BP$5,BX$18,$I32:$BP32) -> 10551.29 | BY32: =SUMIF($I$5:$BP$5,BY$18,$I32:$BP32) -> 10807.325 | BZ32: =SUMIF($I$5:$BP$5,BZ$18,$I32:$BP32) -> 11069.573 | CA32: =SUMIF($I$5:$BP$5,CA$18,$I32:$BP32) -> 11338.185 | CC32: =SUM($I32:$T32) -> 10301.32 | CD32: =SUM($U32:$AF32) -> 10551.29 | CE32: =SUM($AG32:$AR32) -> 10807.325 | CF32: =SUM($AS32:$BD32) -> 11069.573 | CG32: =SUM($BE32:$BP32) -> 11338.185 | CI32: =IF(CC32=BW32,"OK","Check") -> OK | CJ32: =IF(CD32=BX32,"OK","Check") -> OK | CK32: =IF(CE32=BY32,"OK","Check") -> OK | CL32: =IF(CF32=BZ32,"OK","Check") -> OK | CM32: =IF(CG32=CA32,"OK","Check") -> OK
B34: Total Operating Income | E34: =SUM(E27:E32,E22) -> 1129802.3 | F34: =SUM(F22,F27:F32) -> 923168.01 | I34: =SUM(I22,I27:I28,I30:I32) -> 92402.822 | J34: =SUM(J22,J27:J28,J30:J32) -> 93017.543 | K34: =SUM(K22,K27:K28,K30:K32) -> 93637.039 | L34: =SUM(L22,L27:L28,L30:L32) -> 98803.386 | M34: =SUM(M22,M27:M28,M30:M32) -> 104004.8 | N34: =SUM(N22,N27:N28,N30:N32) -> 109241.5 | O34: =SUM(O22,O27:O28,O30:O32) -> 111733.57 | P34: =SUM(P22,P27:P28,P30:P32) -> 114242.81 | ... BP34: =SUM(BP22,BP27:BP28,BP30:BP32) -> 131938.29 | BR34: =SUM(BR22,BR27:BR32) -> 1299227.8 | BS34: =SUM(BS22,BS27:BS32) -> 1172619.4 | BT34: =BR34-BS34 -> 126608.39 | BV34: Total Operating Income | BW34: =SUM(BW30:BW32,BW27:BW28,BW22) -> 1299227.8 | BX34: =SUM(BX30:BX32,BX27:BX28,BX22) -> 1335351.2 | BY34: =SUM(BY30:BY32,BY27:BY28,BY22) -> 1383013.2 | BZ34: =SUM(BZ30:BZ32,BZ27:BZ28,BZ22) -> 1433709.8 | CA34: =SUM(CA30:CA32,CA27:CA28,CA22) -> 1487324.6 | CC34: =SUM($I34:$T34) -> 1299227.8 | CD34: =SUM($U34:$AF34) -> 1335351.2 | CE34: =SUM($AG34:$AR34) -> 1383013.2 | CF34: =SUM($AS34:$BD34) -> 1433709.8 | CG34: =SUM($BE34:$BP34) -> 1487324.6 | CI34: =IF(CC34=BW34,"OK","Check") -> OK | CJ34: =IF(CD34=BX34,"OK","Check") -> OK | CK34: =IF(CE34=BY34,"OK","Check") -> OK | CL34: =IF(CF34=BZ34,"OK","Check") -> OK | CM34: =IF(CG34=CA34,"OK","Check") -> OK
BX35: =(BX34-BW34)/BW34 -> 0.027803784 | BY35: =(BY34-BX34)/BX34 -> 0.035692458 | BZ35: =(BZ34-BY34)/BY34 -> 0.036656634 | CA35: =(CA34-BZ34)/BZ34 -> 0.037395831 | CC35: =IF(CC34=BW34,"OK","Check") -> OK | CD35: =IF(CD34=BX34,"OK","Check") -> OK | CE35: =IF(CE34=BY34,"OK","Check") -> OK | CF35: =IF(CF34=BZ34,"OK","Check") -> OK | CG35: =IF(CG34=CA34,"OK","Check") -> OK
B36: Expenses | H36: LAST MONTH | BV36: Expenses
B37: Advertising & Marketing | E37: =SUM('P-Builder'!O20:Q20)*4 -> 23123.88 | F37: =SUM('P-Builder'!F20:Q20) -> 34857.42 | H37: ='P-Builder'!Q20 -> 2235.45 | I37: 3000 | J37: =(1+INDEX('Inputs & Drivers'!$I$61:$I$65,MATCH(Model2.0!J$5,'Inputs & Drivers'!$B$61:$B$65,0))*(Model2.0!J$5<>Model2.0!I$5))*Model2.0!I37 -> 3000 | K37: =(1+INDEX('Inputs & Drivers'!$I$61:$I$65,MATCH(Model2.0!K$5,'Inputs & Drivers'!$B$61:$B$65,0))*(Model2.0!K$5<>Model2.0!J$5))*Model2.0!J37 -> 3000 | L37: =(1+INDEX('Inputs & Drivers'!$I$61:$I$65,MATCH(Model2.0!L$5,'Inputs & Drivers'!$B$61:$B$65,0))*(Model2.0!L$5<>Model2.0!K$5))*Model2.0!K37 -> 3000 | M37: =(1+INDEX('Inputs & Drivers'!$I$61:$I$65,MATCH(Model2.0!M$5,'Inputs & Drivers'!$B$61:$B$65,0))*(Model2.0!M$5<>Model2.0!L$5))*Model2.0!L37 -> 3000 | N37: =(1+INDEX('Inputs & Drivers'!$I$61:$I$65,MATCH(Model2.0!N$5,'Inputs & Drivers'!$B$61:$B$65,0))*(Model2.0!N$5<>Model2.0!M$5))*Model2.0!M37 -> 3000 | O37: =(1+INDEX('Inputs & Drivers'!$I$61:$I$65,MATCH(Model2.0!O$5,'Inputs & Drivers'!$B$61:$B$65,0))*(Model2.0!O$5<>Model2.0!N$5))*Model2.0!N37 -> 3000 | P37: =(1+INDEX('Inputs & Drivers'!$I$61:$I$65,MATCH(Model2.0!P$5,'Inputs & Drivers'!$B$61:$B$65,0))*(Model2.0!P$5<>Model2.0!O$5))*Model2.0!O37 -> 3000 | Q37: =(1+INDEX('Inputs & Drivers'!$I$61:$I$65,MATCH(Model2.0!Q$5,'Inputs & Drivers'!$B$61:$B$65,0))*(Model2.0!Q$5<>Model2.0!P$5))*Model2.0!P37 -> 3000 | ... BP37: =(1+INDEX('Inputs & Drivers'!$I$61:$I$65,MATCH(Model2.0!BP$5,'Inputs & Drivers'!$B$61:$B$65,0))*(Model2.0!BP$5<>Model2.0!BO$5))*Model2.0!BO37 -> 3247.2965 | BR37: =SUM(I37:T37) -> 36000 | BS37: =SUM(I37:T37) -> 36000 | BT37: =BS37-BR37 -> 0 | BV37: Advertising & Marketing | BW37: =SUMIF($I$5:$BP$5,BW$18,$I37:$BP37) -> 36000 | BX37: =SUMIF($I$5:$BP$5,BX$18,$I37:$BP37) -> 36720 | BY37: =SUMIF($I$5:$BP$5,BY$18,$I37:$BP37) -> 37454.4 | BZ37: =SUMIF($I$5:$BP$5,BZ$18,$I37:$BP37) -> 38203.488 | CA37: =SUMIF($I$5:$BP$5,CA$18,$I37:$BP37) -> 38967.558 | CC37: =SUM($I37:$T37) -> 36000 | CD37: =SUM($U37:$AF37) -> 36720 | CE37: =SUM($AG37:$AR37) -> 37454.4 | CF37: =SUM($AS37:$BD37) -> 38203.488 | CG37: =SUM($BE37:$BP37) -> 38967.558 | CI37: =IF(CC37=BW37,"OK","Check") -> OK | CJ37: =IF(CD37=BX37,"OK","Check") -> OK | CK37: =IF(CE37=BY37,"OK","Check") -> OK | CL37: =IF(CF37=BZ37,"OK","Check") -> OK | CM37: =IF(CG37=CA37,"OK","Check") -> OK
B38: Current Credit Card Security Fees | E38: =SUM('P-Builder'!O21:Q21)*4 -> 16760.4 | F38: =SUM('P-Builder'!F21:Q21) -> 13333.74 | H38: ='P-Builder'!Q21 -> 1484.59 | I38: =I34*'Inputs & Drivers'!$H$37 -> 1333.3464 | J38: =J34*'Inputs & Drivers'!$H$37 -> 1342.2167 | K38: =K34*'Inputs & Drivers'!$H$37 -> 1351.1558 | L38: =L34*'Inputs & Drivers'!$H$37 -> 1425.7048 | M38: =M34*'Inputs & Drivers'!$H$37 -> 1500.7597 | N38: =N34*'Inputs & Drivers'!$H$37 -> 1576.3237 | O38: =O34*'Inputs & Drivers'!$H$37 -> 1612.2836 | P38: =P34*'Inputs & Drivers'!$H$37 -> 1648.4912 | ... BP38: =BP34*'Inputs & Drivers'!$H$37 -> 1903.832 | BR38: 0 | BS38: =SUM(I38:T38) -> 18747.487 | BV38: Current Credit Card Security Fees | BW38: =SUMIF($I$5:$BP$5,BW$18,$I38:$BP38) -> 18747.487 | BX38: =SUMIF($I$5:$BP$5,BX$18,$I38:$BP38) -> 19268.738 | BY38: =SUMIF($I$5:$BP$5,BY$18,$I38:$BP38) -> 19956.487 | BZ38: =SUMIF($I$5:$BP$5,BZ$18,$I38:$BP38) -> 20688.024 | CA38: =SUMIF($I$5:$BP$5,CA$18,$I38:$BP38) -> 21461.67 | CC38: =SUM($I38:$T38) -> 18747.487 | CD38: =SUM($U38:$AF38) -> 19268.738 | CE38: =SUM($AG38:$AR38) -> 19956.487 | CF38: =SUM($AS38:$BD38) -> 20688.024 | CG38: =SUM($BE38:$BP38) -> 21461.67 | CI38: =IF(CC38=BW38,"OK","Check") -> OK | CJ38: =IF(CD38=BX38,"OK","Check") -> OK | CK38: =IF(CE38=BY38,"OK","Check") -> OK | CL38: =IF(CF38=BZ38,"OK","Check") -> OK | CM38: =IF(CG38=CA38,"OK","Check") -> OK
B39: STORE Credit Card Security Fees | H39: ='P-Builder'!Q22 -> 0 | I39: ='Inputs & Drivers'!J38/12 -> 0 | J39: =(1+INDEX('Inputs & Drivers'!$I$61:$I$65,MATCH(Model2.0!J$5,'Inputs & Drivers'!$B$61:$B$65,0))*(Model2.0!J$5<>Model2.0!I$5))*Model2.0!I39 -> 0 | K39: =(1+INDEX('Inputs & Drivers'!$I$61:$I$65,MATCH(Model2.0!K$5,'Inputs & Drivers'!$B$61:$B$65,0))*(Model2.0!K$5<>Model2.0!J$5))*Model2.0!J39 -> 0 | L39: =(1+INDEX('Inputs & Drivers'!$I$61:$I$65,MATCH(Model2.0!L$5,'Inputs & Drivers'!$B$61:$B$65,0))*(Model2.0!L$5<>Model2.0!K$5))*Model2.0!K39 -> 0 | M39: =(1+INDEX('Inputs & Drivers'!$I$61:$I$65,MATCH(Model2.0!M$5,'Inputs & Drivers'!$B$61:$B$65,0))*(Model2.0!M$5<>Model2.0!L$5))*Model2.0!L39 -> 0 | N39: =(1+INDEX('Inputs & Drivers'!$I$61:$I$65,MATCH(Model2.0!N$5,'Inputs & Drivers'!$B$61:$B$65,0))*(Model2.0!N$5<>Model2.0!M$5))*Model2.0!M39 -> 0 | O39: =(1+INDEX('Inputs & Drivers'!$I$61:$I$65,MATCH(Model2.0!O$5,'Inputs & Drivers'!$B$61:$B$65,0))*(Model2.0!O$5<>Model2.0!N$5))*Model2.0!N39 -> 0 | P39: =(1+INDEX('Inputs & Drivers'!$I$61:$I$65,MATCH(Model2.0!P$5,'Inputs & Drivers'!$B$61:$B$65,0))*(Model2.0!P$5<>Model2.0!O$5))*Model2.0!O39 -> 0 | Q39: =(1+INDEX('Inputs & Drivers'!$I$61:$I$65,MATCH(Model2.0!Q$5,'Inputs & Drivers'!$B$61:$B$65,0))*(Model2.0!Q$5<>Model2.0!P$5))*Model2.0!P39 -> 0 | ... BP39: =(1+INDEX('Inputs & Drivers'!$I$61:$I$65,MATCH(Model2.0!BP$5,'Inputs & Drivers'!$B$61:$B$65,0))*(Model2.0!BP$5<>Model2.0!BO$5))*Model2.0!BO39 -> 0 | BR39: =SUM(I39:T39) -> 0 | BS39: 0 | BT39: =BS38-BR39 -> 18747.487 | BV39: STORE Credit Card Security Fees | BW39: =SUMIF($I$5:$BP$5,BW$18,$I39:$BP39) -> 0 | BX39: =SUMIF($I$5:$BP$5,BX$18,$I39:$BP39) -> 0 | BY39: =SUMIF($I$5:$BP$5,BY$18,$I39:$BP39) -> 0 | BZ39: =SUMIF($I$5:$BP$5,BZ$18,$I39:$BP39) -> 0 | CA39: =SUMIF($I$5:$BP$5,CA$18,$I39:$BP39) -> 0 | CC39: =SUM($I39:$T39) -> 0 | CD39: =SUM($U39:$AF39) -> 0 | CE39: =SUM($AG39:$AR39) -> 0 | CF39: =SUM($AS39:$BD39) -> 0 | CG39: =SUM($BE39:$BP39) -> 0 | CI39: =IF(CC39=BW39,"OK","Check") -> OK | CJ39: =IF(CD39=BX39,"OK","Check") -> OK | CK39: =IF(CE39=BY39,"OK","Check") -> OK | CL39: =IF(CF39=BZ39,"OK","Check") -> OK | CM39: =IF(CG39=CA39,"OK","Check") -> OK
B40: Fire Prevention | E40: =SUM('P-Builder'!O23:Q23)*4 -> 0 | F40: =SUM('P-Builder'!F23:Q23) -> 0 | H40: ='P-Builder'!Q23 -> 0 | I40: ='Inputs & Drivers'!J39/12 -> 632.95194 | J40: =(1+INDEX('Inputs & Drivers'!$I$61:$I$65,MATCH(Model2.0!J$5,'Inputs & Drivers'!$B$61:$B$65,0))*(Model2.0!J$5<>Model2.0!I$5))*Model2.0!I40 -> 632.95194 | K40: =(1+INDEX('Inputs & Drivers'!$I$61:$I$65,MATCH(Model2.0!K$5,'Inputs & Drivers'!$B$61:$B$65,0))*(Model2.0!K$5<>Model2.0!J$5))*Model2.0!J40 -> 632.95194 | L40: =(1+INDEX('Inputs & Drivers'!$I$61:$I$65,MATCH(Model2.0!L$5,'Inputs & Drivers'!$B$61:$B$65,0))*(Model2.0!L$5<>Model2.0!K$5))*Model2.0!K40 -> 632.95194 | M40: =(1+INDEX('Inputs & Drivers'!$I$61:$I$65,MATCH(Model2.0!M$5,'Inputs & Drivers'!$B$61:$B$65,0))*(Model2.0!M$5<>Model2.0!L$5))*Model2.0!L40 -> 632.95194 | N40: =(1+INDEX('Inputs & Drivers'!$I$61:$I$65,MATCH(Model2.0!N$5,'Inputs & Drivers'!$B$61:$B$65,0))*(Model2.0!N$5<>Model2.0!M$5))*Model2.0!M40 -> 632.95194 | O40: =(1+INDEX('Inputs & Drivers'!$I$61:$I$65,MATCH(Model2.0!O$5,'Inputs & Drivers'!$B$61:$B$65,0))*(Model2.0!O$5<>Model2.0!N$5))*Model2.0!N40 -> 632.95194 | P40: =(1+INDEX('Inputs & Drivers'!$I$61:$I$65,MATCH(Model2.0!P$5,'Inputs & Drivers'!$B$61:$B$65,0))*(Model2.0!P$5<>Model2.0!O$5))*Model2.0!O40 -> 632.95194 | Q40: =(1+INDEX('Inputs & Drivers'!$I$61:$I$65,MATCH(Model2.0!Q$5,'Inputs & Drivers'!$B$61:$B$65,0))*(Model2.0!Q$5<>Model2.0!P$5))*Model2.0!P40 -> 632.95194 | ... BP40: =(1+INDEX('Inputs & Drivers'!$I$61:$I$65,MATCH(Model2.0!BP$5,'Inputs & Drivers'!$B$61:$B$65,0))*(Model2.0!BP$5<>Model2.0!BO$5))*Model2.0!BO40 -> 685.12754 | BR40: =SUM(I40:T40) -> 7595.4233 | BS40: =SUM(I40:T40) -> 7595.4233 | BT40: =BS40-BR40 -> 0 | BV40: Fire Prevention | BW40: =SUMIF($I$5:$BP$5,BW$18,$I40:$BP40) -> 7595.4233 | BX40: =SUMIF($I$5:$BP$5,BX$18,$I40:$BP40) -> 7747.3318 | BY40: =SUMIF($I$5:$BP$5,BY$18,$I40:$BP40) -> 7902.2784 | BZ40: =SUMIF($I$5:$BP$5,BZ$18,$I40:$BP40) -> 8060.324 | CA40: =SUMIF($I$5:$BP$5,CA$18,$I40:$BP40) -> 8221.5305 | CC40: =SUM($I40:$T40) -> 7595.4233 | CD40: =SUM($U40:$AF40) -> 7747.3318 | CE40: =SUM($AG40:$AR40) -> 7902.2784 | CF40: =SUM($AS40:$BD40) -> 8060.324 | CG40: =SUM($BE40:$BP40) -> 8221.5305 | CI40: =IF(CC40=BW40,"OK","Check") -> OK | CJ40: =IF(CD40=BX40,"OK","Check") -> OK | CK40: =IF(CE40=BY40,"OK","Check") -> OK | CL40: =IF(CF40=BZ40,"OK","Check") -> OK | CM40: =IF(CG40=CA40,"OK","Check") -> OK
B41: Licenses & Permits | E41: =SUM('P-Builder'!O24:Q24)*4 -> 0 | F41: =SUM('P-Builder'!F24:Q24) -> 410.25 | H41: ='P-Builder'!Q24 -> 0 | I41: ='Inputs & Drivers'!J40/12 -> 34.1875 | J41: =(1+INDEX('Inputs & Drivers'!$I$61:$I$65,MATCH(Model2.0!J$5,'Inputs & Drivers'!$B$61:$B$65,0))*(Model2.0!J$5<>Model2.0!I$5))*Model2.0!I41 -> 34.1875 | K41: =(1+INDEX('Inputs & Drivers'!$I$61:$I$65,MATCH(Model2.0!K$5,'Inputs & Drivers'!$B$61:$B$65,0))*(Model2.0!K$5<>Model2.0!J$5))*Model2.0!J41 -> 34.1875 | L41: =(1+INDEX('Inputs & Drivers'!$I$61:$I$65,MATCH(Model2.0!L$5,'Inputs & Drivers'!$B$61:$B$65,0))*(Model2.0!L$5<>Model2.0!K$5))*Model2.0!K41 -> 34.1875 | M41: =(1+INDEX('Inputs & Drivers'!$I$61:$I$65,MATCH(Model2.0!M$5,'Inputs & Drivers'!$B$61:$B$65,0))*(Model2.0!M$5<>Model2.0!L$5))*Model2.0!L41 -> 34.1875 | N41: =(1+INDEX('Inputs & Drivers'!$I$61:$I$65,MATCH(Model2.0!N$5,'Inputs & Drivers'!$B$61:$B$65,0))*(Model2.0!N$5<>Model2.0!M$5))*Model2.0!M41 -> 34.1875 | O41: =(1+INDEX('Inputs & Drivers'!$I$61:$I$65,MATCH(Model2.0!O$5,'Inputs & Drivers'!$B$61:$B$65,0))*(Model2.0!O$5<>Model2.0!N$5))*Model2.0!N41 -> 34.1875 | P41: =(1+INDEX('Inputs & Drivers'!$I$61:$I$65,MATCH(Model2.0!P$5,'Inputs & Drivers'!$B$61:$B$65,0))*(Model2.0!P$5<>Model2.0!O$5))*Model2.0!O41 -> 34.1875 | Q41: =(1+INDEX('Inputs & Drivers'!$I$61:$I$65,MATCH(Model2.0!Q$5,'Inputs & Drivers'!$B$61:$B$65,0))*(Model2.0!Q$5<>Model2.0!P$5))*Model2.0!P41 -> 34.1875 | ... BP41: =(1+INDEX('Inputs & Drivers'!$I$61:$I$65,MATCH(Model2.0!BP$5,'Inputs & Drivers'!$B$61:$B$65,0))*(Model2.0!BP$5<>Model2.0!BO$5))*Model2.0!BO41 -> 37.005649 | BR41: =SUM(I41:T41) -> 410.25 | BS41: =SUM(I41:T41) -> 410.25 | BT41: =BS41-BR41 -> 0 | BV41: Licenses & Permits | BW41: =SUMIF($I$5:$BP$5,BW$18,$I41:$BP41) -> 410.25 | BX41: =SUMIF($I$5:$BP$5,BX$18,$I41:$BP41) -> 418.455 | BY41: =SUMIF($I$5:$BP$5,BY$18,$I41:$BP41) -> 426.8241 | BZ41: =SUMIF($I$5:$BP$5,BZ$18,$I41:$BP41) -> 435.36058 | CA41: =SUMIF($I$5:$BP$5,CA$18,$I41:$BP41) -> 444.06779 | CC41: =SUM($I41:$T41) -> 410.25 | CD41: =SUM($U41:$AF41) -> 418.455 | CE41: =SUM($AG41:$AR41) -> 426.8241 | CF41: =SUM($AS41:$BD41) -> 435.36058 | CG41: =SUM($BE41:$BP41) -> 444.06779 | CI41: =IF(CC41=BW41,"OK","Check") -> OK | CJ41: =IF(CD41=BX41,"OK","Check") -> OK | CK41: =IF(CE41=BY41,"OK","Check") -> OK | CL41: =IF(CF41=BZ41,"OK","Check") -> OK | CM41: =IF(CG41=CA41,"OK","Check") -> OK
B42: Current Mgmt. Fee | E42: =SUM('P-Builder'!O25:Q25)*4 -> 53627 | F42: =SUM('P-Builder'!F25:Q25) -> 46924.36 | H42: ='P-Builder'!Q25 -> 4599.48 | I42: =I22*'Inputs & Drivers'!$H$41 -> 5150.0278 | J42: =J22*'Inputs & Drivers'!$H$41 -> 5184.3613 | K42: =K22*'Inputs & Drivers'!$H$41 -> 5218.9237 | L42: =L22*'Inputs & Drivers'!$H$41 -> 5526.2408 | M42: =M22*'Inputs & Drivers'!$H$41 -> 5835.6066 | N42: =N22*'Inputs & Drivers'!$H$41 -> 6147.0349 | O42: =O22*'Inputs & Drivers'!$H$41 -> 6293.7327 | P42: =P22*'Inputs & Drivers'!$H$41 -> 6441.4085 | ... BP42: =BP22*'Inputs & Drivers'!$H$41 -> 7554.8122 | BR42: 0 | BS42: =SUM(I42:T42) -> 73059.517 | BV42: Current Mgmt. Fee | BW42: =SUMIF($I$5:$BP$5,BW$18,$I42:$BP42) -> 73059.517 | BX42: =SUMIF($I$5:$BP$5,BX$18,$I42:$BP42) -> 75266.911 | BY42: =SUMIF($I$5:$BP$5,BY$18,$I42:$BP42) -> 78333.401 | BZ42: =SUMIF($I$5:$BP$5,BZ$18,$I42:$BP42) -> 81524.824 | CA42: =SUMIF($I$5:$BP$5,CA$18,$I42:$BP42) -> 84846.271 | CC42: =SUM($I42:$T42) -> 73059.517 | CD42: =SUM($U42:$AF42) -> 75266.911 | CE42: =SUM($AG42:$AR42) -> 78333.401 | CF42: =SUM($AS42:$BD42) -> 81524.824 | CG42: =SUM($BE42:$BP42) -> 84846.271 | CI42: =IF(CC42=BW42,"OK","Check") -> OK | CJ42: =IF(CD42=BX42,"OK","Check") -> OK | CK42: =IF(CE42=BY42,"OK","Check") -> OK | CL42: =IF(CF42=BZ42,"OK","Check") -> OK | CM42: =IF(CG42=CA42,"OK","Check") -> OK
B43: STORE Mgmt. Fee | E43: =SUM('P-Builder'!O26:Q26)*4 -> 0 | F43: =SUM('P-Builder'!F26:Q26) -> 0 | H43: ='P-Builder'!Q26 -> 0 | I43: =MAX(2000, I22*(INDEX('Inputs & Drivers'!$G$61:$G$65, MATCH(Model2.0!I5, 'Inputs & Drivers'!$B$61:$B$65, 0)))) -> 3433.3519 | J43: =MAX(2000, J22*(INDEX('Inputs & Drivers'!$G$61:$G$65, MATCH(Model2.0!J5, 'Inputs & Drivers'!$B$61:$B$65, 0)))) -> 3456.2409 | K43: =MAX(2000, K22*(INDEX('Inputs & Drivers'!$G$61:$G$65, MATCH(Model2.0!K5, 'Inputs & Drivers'!$B$61:$B$65, 0)))) -> 3479.2825 | L43: =MAX(2000, L22*(INDEX('Inputs & Drivers'!$G$61:$G$65, MATCH(Model2.0!L5, 'Inputs & Drivers'!$B$61:$B$65, 0)))) -> 3684.1605 | M43: =MAX(2000, M22*(INDEX('Inputs & Drivers'!$G$61:$G$65, MATCH(Model2.0!M5, 'Inputs & Drivers'!$B$61:$B$65, 0)))) -> 3890.4044 | N43: =MAX(2000, N22*(INDEX('Inputs & Drivers'!$G$61:$G$65, MATCH(Model2.0!N5, 'Inputs & Drivers'!$B$61:$B$65, 0)))) -> 4098.0233 | O43: =MAX(2000, O22*(INDEX('Inputs & Drivers'!$G$61:$G$65, MATCH(Model2.0!O5, 'Inputs & Drivers'!$B$61:$B$65, 0)))) -> 4195.8218 | P43: =MAX(2000, P22*(INDEX('Inputs & Drivers'!$G$61:$G$65, MATCH(Model2.0!P5, 'Inputs & Drivers'!$B$61:$B$65, 0)))) -> 4294.2723 | ... BP43: =MAX(2000, BP22*(INDEX('Inputs & Drivers'!$G$61:$G$65, MATCH(Model2.0!BP5, 'Inputs & Drivers'!$B$61:$B$65, 0)))) -> 6295.6768 | BR43: =SUM(I43:T43) -> 48706.345 | BS43: 0 | BT43: =BS42-BR43 -> 24353.172 | BV43: STORE Mgmt. Fee | BW43: =SUMIF($I$5:$BP$5,BW$18,$I43:$BP43) -> 48706.345 | BX43: =SUMIF($I$5:$BP$5,BX$18,$I43:$BP43) -> 56450.183 | BY43: =SUMIF($I$5:$BP$5,BY$18,$I43:$BP43) -> 65277.834 | BZ43: =SUMIF($I$5:$BP$5,BZ$18,$I43:$BP43) -> 67937.354 | CA43: =SUMIF($I$5:$BP$5,CA$18,$I43:$BP43) -> 70705.226 | CC43: =SUM($I43:$T43) -> 48706.345 | CD43: =SUM($U43:$AF43) -> 56450.183 | CE43: =SUM($AG43:$AR43) -> 65277.834 | CF43: =SUM($AS43:$BD43) -> 67937.354 | CG43: =SUM($BE43:$BP43) -> 70705.226 | CI43: =IF(CC43=BW43,"OK","Check") -> OK | CJ43: =IF(CD43=BX43,"OK","Check") -> OK | CK43: =IF(CE43=BY43,"OK","Check") -> OK | CL43: =IF(CF43=BZ43,"OK","Check") -> OK | CM43: =IF(CG43=CA43,"OK","Check") -> OK
B44: Payroll | E44: =SUM('P-Builder'!O27:Q27,'P-Builder'!O22:Q22)*4 -> 84141.52 | F44: =SUM('P-Builder'!F27:Q27,'P-Builder'!F22:Q22) -> 89884.31 | H44: ='P-Builder'!Q27 -> 6888.22 | I44: ='Inputs & Drivers'!J43/12 -> 7918.572 | J44: =(1+INDEX('Inputs & Drivers'!$I$61:$I$65,MATCH(Model2.0!J$5,'Inputs & Drivers'!$B$61:$B$65,0))*(Model2.0!J$5<>Model2.0!I$5))*Model2.0!I44 -> 7918.572 | K44: =(1+INDEX('Inputs & Drivers'!$I$61:$I$65,MATCH(Model2.0!K$5,'Inputs & Drivers'!$B$61:$B$65,0))*(Model2.0!K$5<>Model2.0!J$5))*Model2.0!J44 -> 7918.572 | L44: =(1+INDEX('Inputs & Drivers'!$I$61:$I$65,MATCH(Model2.0!L$5,'Inputs & Drivers'!$B$61:$B$65,0))*(Model2.0!L$5<>Model2.0!K$5))*Model2.0!K44 -> 7918.572 | M44: =(1+INDEX('Inputs & Drivers'!$I$61:$I$65,MATCH(Model2.0!M$5,'Inputs & Drivers'!$B$61:$B$65,0))*(Model2.0!M$5<>Model2.0!L$5))*Model2.0!L44 -> 7918.572 | N44: =(1+INDEX('Inputs & Drivers'!$I$61:$I$65,MATCH(Model2.0!N$5,'Inputs & Drivers'!$B$61:$B$65,0))*(Model2.0!N$5<>Model2.0!M$5))*Model2.0!M44 -> 7918.572 | O44: =(1+INDEX('Inputs & Drivers'!$I$61:$I$65,MATCH(Model2.0!O$5,'Inputs & Drivers'!$B$61:$B$65,0))*(Model2.0!O$5<>Model2.0!N$5))*Model2.0!N44 -> 7918.572 | P44: =(1+INDEX('Inputs & Drivers'!$I$61:$I$65,MATCH(Model2.0!P$5,'Inputs & Drivers'!$B$61:$B$65,0))*(Model2.0!P$5<>Model2.0!O$5))*Model2.0!O44 -> 7918.572 | Q44: =(1+INDEX('Inputs & Drivers'!$I$61:$I$65,MATCH(Model2.0!Q$5,'Inputs & Drivers'!$B$61:$B$65,0))*(Model2.0!Q$5<>Model2.0!P$5))*Model2.0!P44 -> 7918.572 | ... BP44: =(1+INDEX('Inputs & Drivers'!$I$61:$I$65,MATCH(Model2.0!BP$5,'Inputs & Drivers'!$B$61:$B$65,0))*(Model2.0!BP$5<>Model2.0!BO$5))*Model2.0!BO44 -> 8571.317 | BR44: =SUM(I44:T44) -> 95022.864 | BS44: =F44*1.02 -> 91681.996 | BT44: =BS44-BR44 -> -3340.8674 | BV44: Payroll | BW44: =SUMIF($I$5:$BP$5,BW$18,$I44:$BP44) -> 95022.864 | BX44: =SUMIF($I$5:$BP$5,BX$18,$I44:$BP44) -> 96923.321 | BY44: =SUMIF($I$5:$BP$5,BY$18,$I44:$BP44) -> 98861.787 | BZ44: =SUMIF($I$5:$BP$5,BZ$18,$I44:$BP44) -> 100839.02 | CA44: =SUMIF($I$5:$BP$5,CA$18,$I44:$BP44) -> 102855.8 | CC44: =SUM($I44:$T44) -> 95022.864 | CD44: =SUM($U44:$AF44) -> 96923.321 | CE44: =SUM($AG44:$AR44) -> 98861.787 | CF44: =SUM($AS44:$BD44) -> 100839.02 | CG44: =SUM($BE44:$BP44) -> 102855.8 | CI44: =IF(CC44=BW44,"OK","Check") -> OK | CJ44: =IF(CD44=BX44,"OK","Check") -> OK | CK44: =IF(CE44=BY44,"OK","Check") -> OK | CL44: =IF(CF44=BZ44,"OK","Check") -> OK | CM44: =IF(CG44=CA44,"OK","Check") -> OK
B45: Office Supplies | E45: =SUM('P-Builder'!O28:Q28)*4 -> 558.04 | F45: =SUM('P-Builder'!F28:Q28) -> 1659.92 | H45: ='P-Builder'!Q28 -> 94.23 | I45: ='Inputs & Drivers'!J44/12 -> 138.32667 | J45: =(1+INDEX('Inputs & Drivers'!$I$61:$I$65,MATCH(Model2.0!J$5,'Inputs & Drivers'!$B$61:$B$65,0))*(Model2.0!J$5<>Model2.0!I$5))*Model2.0!I45 -> 138.32667 | K45: =(1+INDEX('Inputs & Drivers'!$I$61:$I$65,MATCH(Model2.0!K$5,'Inputs & Drivers'!$B$61:$B$65,0))*(Model2.0!K$5<>Model2.0!J$5))*Model2.0!J45 -> 138.32667 | L45: =(1+INDEX('Inputs & Drivers'!$I$61:$I$65,MATCH(Model2.0!L$5,'Inputs & Drivers'!$B$61:$B$65,0))*(Model2.0!L$5<>Model2.0!K$5))*Model2.0!K45 -> 138.32667 | M45: =(1+INDEX('Inputs & Drivers'!$I$61:$I$65,MATCH(Model2.0!M$5,'Inputs & Drivers'!$B$61:$B$65,0))*(Model2.0!M$5<>Model2.0!L$5))*Model2.0!L45 -> 138.32667 | N45: =(1+INDEX('Inputs & Drivers'!$I$61:$I$65,MATCH(Model2.0!N$5,'Inputs & Drivers'!$B$61:$B$65,0))*(Model2.0!N$5<>Model2.0!M$5))*Model2.0!M45 -> 138.32667 | O45: =(1+INDEX('Inputs & Drivers'!$I$61:$I$65,MATCH(Model2.0!O$5,'Inputs & Drivers'!$B$61:$B$65,0))*(Model2.0!O$5<>Model2.0!N$5))*Model2.0!N45 -> 138.32667 | P45: =(1+INDEX('Inputs & Drivers'!$I$61:$I$65,MATCH(Model2.0!P$5,'Inputs & Drivers'!$B$61:$B$65,0))*(Model2.0!P$5<>Model2.0!O$5))*Model2.0!O45 -> 138.32667 | Q45: =(1+INDEX('Inputs & Drivers'!$I$61:$I$65,MATCH(Model2.0!Q$5,'Inputs & Drivers'!$B$61:$B$65,0))*(Model2.0!Q$5<>Model2.0!P$5))*Model2.0!P45 -> 138.32667 | ... BP45: =(1+INDEX('Inputs & Drivers'!$I$61:$I$65,MATCH(Model2.0!BP$5,'Inputs & Drivers'!$B$61:$B$65,0))*(Model2.0!BP$5<>Model2.0!BO$5))*Model2.0!BO45 -> 149.72923 | BR45: =SUM(I45:T45) -> 1659.92 | BS45: =SUM(I45:T45) -> 1659.92 | BT45: =BS45-BR45 -> 0 | BV45: Office Supplies | BW45: =SUMIF($I$5:$BP$5,BW$18,$I45:$BP45) -> 1659.92 | BX45: =SUMIF($I$5:$BP$5,BX$18,$I45:$BP45) -> 1693.1184 | BY45: =SUMIF($I$5:$BP$5,BY$18,$I45:$BP45) -> 1726.9808 | BZ45: =SUMIF($I$5:$BP$5,BZ$18,$I45:$BP45) -> 1761.5204 | CA45: =SUMIF($I$5:$BP$5,CA$18,$I45:$BP45) -> 1796.7508 | CC45: =SUM($I45:$T45) -> 1659.92 | CD45: =SUM($U45:$AF45) -> 1693.1184 | CE45: =SUM($AG45:$AR45) -> 1726.9808 | CF45: =SUM($AS45:$BD45) -> 1761.5204 | CG45: =SUM($BE45:$BP45) -> 1796.7508 | CI45: =IF(CC45=BW45,"OK","Check") -> OK | CJ45: =IF(CD45=BX45,"OK","Check") -> OK | CK45: =IF(CE45=BY45,"OK","Check") -> OK | CL45: =IF(CF45=BZ45,"OK","Check") -> OK | CM45: =IF(CG45=CA45,"OK","Check") -> OK
B46: Repairs & Maintenance | E46: =SUM('P-Builder'!O29:Q29)*4 -> 39809.6 | F46: =SUM('P-Builder'!F29:Q29) -> 39787.63 | H46: ='P-Builder'!Q29 -> 2511.82 | I46: ='Inputs & Drivers'!J45/12 -> 3315.6358 | J46: =(1+INDEX('Inputs & Drivers'!$I$61:$I$65,MATCH(Model2.0!J$5,'Inputs & Drivers'!$B$61:$B$65,0))*(Model2.0!J$5<>Model2.0!I$5))*Model2.0!I46 -> 3315.6358 | K46: =(1+INDEX('Inputs & Drivers'!$I$61:$I$65,MATCH(Model2.0!K$5,'Inputs & Drivers'!$B$61:$B$65,0))*(Model2.0!K$5<>Model2.0!J$5))*Model2.0!J46 -> 3315.6358 | L46: =(1+INDEX('Inputs & Drivers'!$I$61:$I$65,MATCH(Model2.0!L$5,'Inputs & Drivers'!$B$61:$B$65,0))*(Model2.0!L$5<>Model2.0!K$5))*Model2.0!K46 -> 3315.6358 | M46: =(1+INDEX('Inputs & Drivers'!$I$61:$I$65,MATCH(Model2.0!M$5,'Inputs & Drivers'!$B$61:$B$65,0))*(Model2.0!M$5<>Model2.0!L$5))*Model2.0!L46 -> 3315.6358 | N46: =(1+INDEX('Inputs & Drivers'!$I$61:$I$65,MATCH(Model2.0!N$5,'Inputs & Drivers'!$B$61:$B$65,0))*(Model2.0!N$5<>Model2.0!M$5))*Model2.0!M46 -> 3315.6358 | O46: =(1+INDEX('Inputs & Drivers'!$I$61:$I$65,MATCH(Model2.0!O$5,'Inputs & Drivers'!$B$61:$B$65,0))*(Model2.0!O$5<>Model2.0!N$5))*Model2.0!N46 -> 3315.6358 | P46: =(1+INDEX('Inputs & Drivers'!$I$61:$I$65,MATCH(Model2.0!P$5,'Inputs & Drivers'!$B$61:$B$65,0))*(Model2.0!P$5<>Model2.0!O$5))*Model2.0!O46 -> 3315.6358 | Q46: =(1+INDEX('Inputs & Drivers'!$I$61:$I$65,MATCH(Model2.0!Q$5,'Inputs & Drivers'!$B$61:$B$65,0))*(Model2.0!Q$5<>Model2.0!P$5))*Model2.0!P46 -> 3315.6358 | ... BP46: =(1+INDEX('Inputs & Drivers'!$I$61:$I$65,MATCH(Model2.0!BP$5,'Inputs & Drivers'!$B$61:$B$65,0))*(Model2.0!BP$5<>Model2.0!BO$5))*Model2.0!BO46 -> 3588.9509 | BR46: =SUM(I46:T46) -> 39787.63 | BS46: =SUM(I46:T46) -> 39787.63 | BT46: =BS46-BR46 -> 0 | BV46: Repairs & Maintenance | BW46: =SUMIF($I$5:$BP$5,BW$18,$I46:$BP46) -> 39787.63 | BX46: =SUMIF($I$5:$BP$5,BX$18,$I46:$BP46) -> 40583.383 | BY46: =SUMIF($I$5:$BP$5,BY$18,$I46:$BP46) -> 41395.05 | BZ46: =SUMIF($I$5:$BP$5,BZ$18,$I46:$BP46) -> 42222.951 | CA46: =SUMIF($I$5:$BP$5,CA$18,$I46:$BP46) -> 43067.41 | CC46: =SUM($I46:$T46) -> 39787.63 | CD46: =SUM($U46:$AF46) -> 40583.383 | CE46: =SUM($AG46:$AR46) -> 41395.05 | CF46: =SUM($AS46:$BD46) -> 42222.951 | CG46: =SUM($BE46:$BP46) -> 43067.41 | CI46: =IF(CC46=BW46,"OK","Check") -> OK | CJ46: =IF(CD46=BX46,"OK","Check") -> OK | CK46: =IF(CE46=BY46,"OK","Check") -> OK | CL46: =IF(CF46=BZ46,"OK","Check") -> OK | CM46: =IF(CG46=CA46,"OK","Check") -> OK
B47: Security | E47: =SUM('P-Builder'!O30:Q30)*4 -> 0 | F47: =SUM('P-Builder'!F30:Q30) -> 0 | H47: ='P-Builder'!Q30 -> 0 | I47: 120 | J47: =(1+INDEX('Inputs & Drivers'!$I$61:$I$65,MATCH(Model2.0!J$5,'Inputs & Drivers'!$B$61:$B$65,0))*(Model2.0!J$5<>Model2.0!I$5))*Model2.0!I47 -> 120 | K47: =(1+INDEX('Inputs & Drivers'!$I$61:$I$65,MATCH(Model2.0!K$5,'Inputs & Drivers'!$B$61:$B$65,0))*(Model2.0!K$5<>Model2.0!J$5))*Model2.0!J47 -> 120 | L47: =(1+INDEX('Inputs & Drivers'!$I$61:$I$65,MATCH(Model2.0!L$5,'Inputs & Drivers'!$B$61:$B$65,0))*(Model2.0!L$5<>Model2.0!K$5))*Model2.0!K47 -> 120 | M47: =(1+INDEX('Inputs & Drivers'!$I$61:$I$65,MATCH(Model2.0!M$5,'Inputs & Drivers'!$B$61:$B$65,0))*(Model2.0!M$5<>Model2.0!L$5))*Model2.0!L47 -> 120 | N47: =(1+INDEX('Inputs & Drivers'!$I$61:$I$65,MATCH(Model2.0!N$5,'Inputs & Drivers'!$B$61:$B$65,0))*(Model2.0!N$5<>Model2.0!M$5))*Model2.0!M47 -> 120 | O47: =(1+INDEX('Inputs & Drivers'!$I$61:$I$65,MATCH(Model2.0!O$5,'Inputs & Drivers'!$B$61:$B$65,0))*(Model2.0!O$5<>Model2.0!N$5))*Model2.0!N47 -> 120 | P47: =(1+INDEX('Inputs & Drivers'!$I$61:$I$65,MATCH(Model2.0!P$5,'Inputs & Drivers'!$B$61:$B$65,0))*(Model2.0!P$5<>Model2.0!O$5))*Model2.0!O47 -> 120 | Q47: =(1+INDEX('Inputs & Drivers'!$I$61:$I$65,MATCH(Model2.0!Q$5,'Inputs & Drivers'!$B$61:$B$65,0))*(Model2.0!Q$5<>Model2.0!P$5))*Model2.0!P47 -> 120 | ... BP47: =(1+INDEX('Inputs & Drivers'!$I$61:$I$65,MATCH(Model2.0!BP$5,'Inputs & Drivers'!$B$61:$B$65,0))*(Model2.0!BP$5<>Model2.0!BO$5))*Model2.0!BO47 -> 129.89186 | BR47: =SUM(I47:T47) -> 1440 | BS47: 0 | BT47: =BS47-BR47 -> -1440 | BV47: Security | BW47: =SUMIF($I$5:$BP$5,BW$18,$I47:$BP47) -> 1440 | BX47: =SUMIF($I$5:$BP$5,BX$18,$I47:$BP47) -> 1468.8 | BY47: =SUMIF($I$5:$BP$5,BY$18,$I47:$BP47) -> 1498.176 | BZ47: =SUMIF($I$5:$BP$5,BZ$18,$I47:$BP47) -> 1528.1395 | CA47: =SUMIF($I$5:$BP$5,CA$18,$I47:$BP47) -> 1558.7023 | CC47: =SUM($I47:$T47) -> 1440 | CD47: =SUM($U47:$AF47) -> 1468.8 | CE47: =SUM($AG47:$AR47) -> 1498.176 | CF47: =SUM($AS47:$BD47) -> 1528.1395 | CG47: =SUM($BE47:$BP47) -> 1558.7023 | CI47: =IF(CC47=BW47,"OK","Check") -> OK | CJ47: =IF(CD47=BX47,"OK","Check") -> OK | CK47: =IF(CE47=BY47,"OK","Check") -> OK | CL47: =IF(CF47=BZ47,"OK","Check") -> OK | CM47: =IF(CG47=CA47,"OK","Check") -> OK
B48: Retail Products | E48: =SUM('P-Builder'!O31:Q31)*4 -> 4313.96 | F48: =SUM('P-Builder'!F31:Q31) -> 3696.57 | H48: ='P-Builder'!Q31 -> 359.28 | I48: ='Inputs & Drivers'!J47/12 -> 308.0475 | J48: =(1+INDEX('Inputs & Drivers'!$I$61:$I$65,MATCH(Model2.0!J$5,'Inputs & Drivers'!$B$61:$B$65,0))*(Model2.0!J$5<>Model2.0!I$5))*Model2.0!I48 -> 308.0475 | K48: =(1+INDEX('Inputs & Drivers'!$I$61:$I$65,MATCH(Model2.0!K$5,'Inputs & Drivers'!$B$61:$B$65,0))*(Model2.0!K$5<>Model2.0!J$5))*Model2.0!J48 -> 308.0475 | L48: =(1+INDEX('Inputs & Drivers'!$I$61:$I$65,MATCH(Model2.0!L$5,'Inputs & Drivers'!$B$61:$B$65,0))*(Model2.0!L$5<>Model2.0!K$5))*Model2.0!K48 -> 308.0475 | M48: =(1+INDEX('Inputs & Drivers'!$I$61:$I$65,MATCH(Model2.0!M$5,'Inputs & Drivers'!$B$61:$B$65,0))*(Model2.0!M$5<>Model2.0!L$5))*Model2.0!L48 -> 308.0475 | N48: =(1+INDEX('Inputs & Drivers'!$I$61:$I$65,MATCH(Model2.0!N$5,'Inputs & Drivers'!$B$61:$B$65,0))*(Model2.0!N$5<>Model2.0!M$5))*Model2.0!M48 -> 308.0475 | O48: =(1+INDEX('Inputs & Drivers'!$I$61:$I$65,MATCH(Model2.0!O$5,'Inputs & Drivers'!$B$61:$B$65,0))*(Model2.0!O$5<>Model2.0!N$5))*Model2.0!N48 -> 308.0475 | P48: =(1+INDEX('Inputs & Drivers'!$I$61:$I$65,MATCH(Model2.0!P$5,'Inputs & Drivers'!$B$61:$B$65,0))*(Model2.0!P$5<>Model2.0!O$5))*Model2.0!O48 -> 308.0475 | Q48: =(1+INDEX('Inputs & Drivers'!$I$61:$I$65,MATCH(Model2.0!Q$5,'Inputs & Drivers'!$B$61:$B$65,0))*(Model2.0!Q$5<>Model2.0!P$5))*Model2.0!P48 -> 308.0475 | ... BP48: =(1+INDEX('Inputs & Drivers'!$I$61:$I$65,MATCH(Model2.0!BP$5,'Inputs & Drivers'!$B$61:$B$65,0))*(Model2.0!BP$5<>Model2.0!BO$5))*Model2.0!BO48 -> 333.44052 | BR48: =SUM(I48:T48) -> 3696.57 | BS48: =SUM(I48:T48) -> 3696.57 | BT48: =BS48-BR48 -> 0 | BV48: Retail Products | BW48: =SUMIF($I$5:$BP$5,BW$18,$I48:$BP48) -> 3696.57 | BX48: =SUMIF($I$5:$BP$5,BX$18,$I48:$BP48) -> 3770.5014 | BY48: =SUMIF($I$5:$BP$5,BY$18,$I48:$BP48) -> 3845.9114 | BZ48: =SUMIF($I$5:$BP$5,BZ$18,$I48:$BP48) -> 3922.8297 | CA48: =SUMIF($I$5:$BP$5,CA$18,$I48:$BP48) -> 4001.2862 | CC48: =SUM($I48:$T48) -> 3696.57 | CD48: =SUM($U48:$AF48) -> 3770.5014 | CE48: =SUM($AG48:$AR48) -> 3845.9114 | CF48: =SUM($AS48:$BD48) -> 3922.8297 | CG48: =SUM($BE48:$BP48) -> 4001.2862 | CI48: =IF(CC48=BW48,"OK","Check") -> OK | CJ48: =IF(CD48=BX48,"OK","Check") -> OK | CK48: =IF(CE48=BY48,"OK","Check") -> OK | CL48: =IF(CF48=BZ48,"OK","Check") -> OK | CM48: =IF(CG48=CA48,"OK","Check") -> OK
B49: Telephone & Internet | E49: =SUM('P-Builder'!O32:Q32)*4 -> 9954.24 | F49: =SUM('P-Builder'!F32:Q32) -> 10913.51 | H49: ='P-Builder'!Q32 -> 1645.42 | I49: ='Inputs & Drivers'!J48/12 -> 909.45917 | J49: =(1+INDEX('Inputs & Drivers'!$I$61:$I$65,MATCH(Model2.0!J$5,'Inputs & Drivers'!$B$61:$B$65,0))*(Model2.0!J$5<>Model2.0!I$5))*Model2.0!I49 -> 909.45917 | K49: =(1+INDEX('Inputs & Drivers'!$I$61:$I$65,MATCH(Model2.0!K$5,'Inputs & Drivers'!$B$61:$B$65,0))*(Model2.0!K$5<>Model2.0!J$5))*Model2.0!J49 -> 909.45917 | L49: =(1+INDEX('Inputs & Drivers'!$I$61:$I$65,MATCH(Model2.0!L$5,'Inputs & Drivers'!$B$61:$B$65,0))*(Model2.0!L$5<>Model2.0!K$5))*Model2.0!K49 -> 909.45917 | M49: =(1+INDEX('Inputs & Drivers'!$I$61:$I$65,MATCH(Model2.0!M$5,'Inputs & Drivers'!$B$61:$B$65,0))*(Model2.0!M$5<>Model2.0!L$5))*Model2.0!L49 -> 909.45917 | N49: =(1+INDEX('Inputs & Drivers'!$I$61:$I$65,MATCH(Model2.0!N$5,'Inputs & Drivers'!$B$61:$B$65,0))*(Model2.0!N$5<>Model2.0!M$5))*Model2.0!M49 -> 909.45917 | O49: =(1+INDEX('Inputs & Drivers'!$I$61:$I$65,MATCH(Model2.0!O$5,'Inputs & Drivers'!$B$61:$B$65,0))*(Model2.0!O$5<>Model2.0!N$5))*Model2.0!N49 -> 909.45917 | P49: =(1+INDEX('Inputs & Drivers'!$I$61:$I$65,MATCH(Model2.0!P$5,'Inputs & Drivers'!$B$61:$B$65,0))*(Model2.0!P$5<>Model2.0!O$5))*Model2.0!O49 -> 909.45917 | Q49: =(1+INDEX('Inputs & Drivers'!$I$61:$I$65,MATCH(Model2.0!Q$5,'Inputs & Drivers'!$B$61:$B$65,0))*(Model2.0!Q$5<>Model2.0!P$5))*Model2.0!P49 -> 909.45917 | ... BP49: =(1+INDEX('Inputs & Drivers'!$I$61:$I$65,MATCH(Model2.0!BP$5,'Inputs & Drivers'!$B$61:$B$65,0))*(Model2.0!BP$5<>Model2.0!BO$5))*Model2.0!BO49 -> 984.42785 | BR49: =SUM(I49:T49) -> 10913.51 | BS49: =SUM(I49:T49) -> 10913.51 | BT49: =BS49-BR49 -> 0 | BV49: Telephone & Internet | BW49: =SUMIF($I$5:$BP$5,BW$18,$I49:$BP49) -> 10913.51 | BX49: =SUMIF($I$5:$BP$5,BX$18,$I49:$BP49) -> 11131.78 | BY49: =SUMIF($I$5:$BP$5,BY$18,$I49:$BP49) -> 11354.416 | BZ49: =SUMIF($I$5:$BP$5,BZ$18,$I49:$BP49) -> 11581.504 | CA49: =SUMIF($I$5:$BP$5,CA$18,$I49:$BP49) -> 11813.134 | CC49: =SUM($I49:$T49) -> 10913.51 | CD49: =SUM($U49:$AF49) -> 11131.78 | CE49: =SUM($AG49:$AR49) -> 11354.416 | CF49: =SUM($AS49:$BD49) -> 11581.504 | CG49: =SUM($BE49:$BP49) -> 11813.134 | CI49: =IF(CC49=BW49,"OK","Check") -> OK | CJ49: =IF(CD49=BX49,"OK","Check") -> OK | CK49: =IF(CE49=BY49,"OK","Check") -> OK | CL49: =IF(CF49=BZ49,"OK","Check") -> OK | CM49: =IF(CG49=CA49,"OK","Check") -> OK
B50: Software | E50: =SUM('P-Builder'!O33:Q33)*4 -> 17296.04 | F50: =SUM('P-Builder'!F33:Q33) -> 17300.16 | H50: ='P-Builder'!Q33 -> 1408.65 | I50: =1850*(1+'Inputs & Drivers'!$N$70)^(I5-1) -> 1850 | J50: =1850*(1+'Inputs & Drivers'!$N$70)^(J5-1) -> 1850 | K50: =1850*(1+'Inputs & Drivers'!$N$70)^(K5-1) -> 1850 | L50: =1850*(1+'Inputs & Drivers'!$N$70)^(L5-1) -> 1850 | M50: =1850*(1+'Inputs & Drivers'!$N$70)^(M5-1) -> 1850 | N50: =1850*(1+'Inputs & Drivers'!$N$70)^(N5-1) -> 1850 | O50: =1850*(1+'Inputs & Drivers'!$N$70)^(O5-1) -> 1850 | P50: =1850*(1+'Inputs & Drivers'!$N$70)^(P5-1) -> 1850 | ... BP50: =1850*(1+'Inputs & Drivers'!$N$70)^(BP5-1) -> 1963.5226 | BR50: =SUM(I50:T50) -> 22200 | BS50: =E50 -> 17296.04 | BT50: =BS50-BR50 -> -4903.96 | BV50: Software | BW50: =SUMIF($I$5:$BP$5,BW$18,$I50:$BP50) -> 22200 | BX50: =SUMIF($I$5:$BP$5,BX$18,$I50:$BP50) -> 22533 | BY50: =SUMIF($I$5:$BP$5,BY$18,$I50:$BP50) -> 22870.995 | BZ50: =SUMIF($I$5:$BP$5,BZ$18,$I50:$BP50) -> 23214.06 | CA50: =SUMIF($I$5:$BP$5,CA$18,$I50:$BP50) -> 23562.271 | CC50: =SUM($I50:$T50) -> 22200 | CD50: =SUM($U50:$AF50) -> 22533 | CE50: =SUM($AG50:$AR50) -> 22870.995 | CF50: =SUM($AS50:$BD50) -> 23214.06 | CG50: =SUM($BE50:$BP50) -> 23562.271 | CI50: =IF(CC50=BW50,"OK","Check") -> OK | CJ50: =IF(CD50=BX50,"OK","Check") -> OK | CK50: =IF(CE50=BY50,"OK","Check") -> OK | CL50: =IF(CF50=BZ50,"OK","Check") -> OK | CM50: =IF(CG50=CA50,"OK","Check") -> OK
B51: Bank Charges | E51: =SUM('P-Builder'!O34:Q34)*4 -> 0 | F51: =SUM('P-Builder'!F34:Q34) -> 0 | H51: ='P-Builder'!Q34 -> 0 | I51: 0 | J51: =(1+INDEX('Inputs & Drivers'!$I$61:$I$65,MATCH(Model2.0!J$5,'Inputs & Drivers'!$B$61:$B$65,0))*(Model2.0!J$5<>Model2.0!I$5))*Model2.0!I51 -> 0 | K51: =(1+INDEX('Inputs & Drivers'!$I$61:$I$65,MATCH(Model2.0!K$5,'Inputs & Drivers'!$B$61:$B$65,0))*(Model2.0!K$5<>Model2.0!J$5))*Model2.0!J51 -> 0 | L51: =(1+INDEX('Inputs & Drivers'!$I$61:$I$65,MATCH(Model2.0!L$5,'Inputs & Drivers'!$B$61:$B$65,0))*(Model2.0!L$5<>Model2.0!K$5))*Model2.0!K51 -> 0 | M51: =(1+INDEX('Inputs & Drivers'!$I$61:$I$65,MATCH(Model2.0!M$5,'Inputs & Drivers'!$B$61:$B$65,0))*(Model2.0!M$5<>Model2.0!L$5))*Model2.0!L51 -> 0 | N51: =(1+INDEX('Inputs & Drivers'!$I$61:$I$65,MATCH(Model2.0!N$5,'Inputs & Drivers'!$B$61:$B$65,0))*(Model2.0!N$5<>Model2.0!M$5))*Model2.0!M51 -> 0 | O51: =(1+INDEX('Inputs & Drivers'!$I$61:$I$65,MATCH(Model2.0!O$5,'Inputs & Drivers'!$B$61:$B$65,0))*(Model2.0!O$5<>Model2.0!N$5))*Model2.0!N51 -> 0 | P51: =(1+INDEX('Inputs & Drivers'!$I$61:$I$65,MATCH(Model2.0!P$5,'Inputs & Drivers'!$B$61:$B$65,0))*(Model2.0!P$5<>Model2.0!O$5))*Model2.0!O51 -> 0 | Q51: =(1+INDEX('Inputs & Drivers'!$I$61:$I$65,MATCH(Model2.0!Q$5,'Inputs & Drivers'!$B$61:$B$65,0))*(Model2.0!Q$5<>Model2.0!P$5))*Model2.0!P51 -> 0 | ... BP51: =(1+INDEX('Inputs & Drivers'!$I$61:$I$65,MATCH(Model2.0!BP$5,'Inputs & Drivers'!$B$61:$B$65,0))*(Model2.0!BP$5<>Model2.0!BO$5))*Model2.0!BO51 -> 0 | BR51: =SUM(I51:T51) -> 0 | BS51: =E51 -> 0 | BT51: =BS51-BR51 -> 0 | BV51: Bank Charges | BW51: =SUMIF($I$5:$BP$5,BW$18,$I51:$BP51) -> 0 | BX51: =SUMIF($I$5:$BP$5,BX$18,$I51:$BP51) -> 0 | BY51: =SUMIF($I$5:$BP$5,BY$18,$I51:$BP51) -> 0 | BZ51: =SUMIF($I$5:$BP$5,BZ$18,$I51:$BP51) -> 0 | CA51: =SUMIF($I$5:$BP$5,CA$18,$I51:$BP51) -> 0 | CC51: =SUM($I51:$T51) -> 0 | CD51: =SUM($U51:$AF51) -> 0 | CE51: =SUM($AG51:$AR51) -> 0 | CF51: =SUM($AS51:$BD51) -> 0 | CG51: =SUM($BE51:$BP51) -> 0 | CI51: =IF(CC51=BW51,"OK","Check") -> OK | CJ51: =IF(CD51=BX51,"OK","Check") -> OK | CK51: =IF(CE51=BY51,"OK","Check") -> OK | CL51: =IF(CF51=BZ51,"OK","Check") -> OK | CM51: =IF(CG51=CA51,"OK","Check") -> OK
B52: Prof Fees - Legal/Acctg | E52: =SUM('P-Builder'!O35:Q35)*4 -> 1675.96 | F52: =SUM('P-Builder'!F35:Q35) -> 1940.76 | H52: ='P-Builder'!Q35 -> 163.16 | I52: ='Inputs & Drivers'!J51/12 -> 161.73 | J52: =(1+INDEX('Inputs & Drivers'!$I$61:$I$65,MATCH(Model2.0!J$5,'Inputs & Drivers'!$B$61:$B$65,0))*(Model2.0!J$5<>Model2.0!I$5))*Model2.0!I52 -> 161.73 | K52: =(1+INDEX('Inputs & Drivers'!$I$61:$I$65,MATCH(Model2.0!K$5,'Inputs & Drivers'!$B$61:$B$65,0))*(Model2.0!K$5<>Model2.0!J$5))*Model2.0!J52 -> 161.73 | L52: =(1+INDEX('Inputs & Drivers'!$I$61:$I$65,MATCH(Model2.0!L$5,'Inputs & Drivers'!$B$61:$B$65,0))*(Model2.0!L$5<>Model2.0!K$5))*Model2.0!K52 -> 161.73 | M52: =(1+INDEX('Inputs & Drivers'!$I$61:$I$65,MATCH(Model2.0!M$5,'Inputs & Drivers'!$B$61:$B$65,0))*(Model2.0!M$5<>Model2.0!L$5))*Model2.0!L52 -> 161.73 | N52: =(1+INDEX('Inputs & Drivers'!$I$61:$I$65,MATCH(Model2.0!N$5,'Inputs & Drivers'!$B$61:$B$65,0))*(Model2.0!N$5<>Model2.0!M$5))*Model2.0!M52 -> 161.73 | O52: =(1+INDEX('Inputs & Drivers'!$I$61:$I$65,MATCH(Model2.0!O$5,'Inputs & Drivers'!$B$61:$B$65,0))*(Model2.0!O$5<>Model2.0!N$5))*Model2.0!N52 -> 161.73 | P52: =(1+INDEX('Inputs & Drivers'!$I$61:$I$65,MATCH(Model2.0!P$5,'Inputs & Drivers'!$B$61:$B$65,0))*(Model2.0!P$5<>Model2.0!O$5))*Model2.0!O52 -> 161.73 | Q52: =(1+INDEX('Inputs & Drivers'!$I$61:$I$65,MATCH(Model2.0!Q$5,'Inputs & Drivers'!$B$61:$B$65,0))*(Model2.0!Q$5<>Model2.0!P$5))*Model2.0!P52 -> 161.73 | ... BP52: =(1+INDEX('Inputs & Drivers'!$I$61:$I$65,MATCH(Model2.0!BP$5,'Inputs & Drivers'!$B$61:$B$65,0))*(Model2.0!BP$5<>Model2.0!BO$5))*Model2.0!BO52 -> 175.06175 | BR52: =SUM(I52:T52) -> 1940.76 | BS52: =SUM(I52:T52) -> 1940.76 | BT52: =BS52-BR52 -> 0 | BV52: Prof Fees - Legal/Acctg | BW52: =SUMIF($I$5:$BP$5,BW$18,$I52:$BP52) -> 1940.76 | BX52: =SUMIF($I$5:$BP$5,BX$18,$I52:$BP52) -> 1979.5752 | BY52: =SUMIF($I$5:$BP$5,BY$18,$I52:$BP52) -> 2019.1667 | BZ52: =SUMIF($I$5:$BP$5,BZ$18,$I52:$BP52) -> 2059.55 | CA52: =SUMIF($I$5:$BP$5,CA$18,$I52:$BP52) -> 2100.741 | CC52: =SUM($I52:$T52) -> 1940.76 | CD52: =SUM($U52:$AF52) -> 1979.5752 | CE52: =SUM($AG52:$AR52) -> 2019.1667 | CF52: =SUM($AS52:$BD52) -> 2059.55 | CG52: =SUM($BE52:$BP52) -> 2100.741 | CI52: =IF(CC52=BW52,"OK","Check") -> OK | CJ52: =IF(CD52=BX52,"OK","Check") -> OK | CK52: =IF(CE52=BY52,"OK","Check") -> OK | CL52: =IF(CF52=BZ52,"OK","Check") -> OK | CM52: =IF(CG52=CA52,"OK","Check") -> OK
B53: Utilities | E53: =SUM('P-Builder'!O36:Q36)*4 -> 36152.52 | F53: =SUM('P-Builder'!F36:Q36) -> 28122.84 | H53: ='P-Builder'!Q36 -> 2948.17 | I53: ='Inputs & Drivers'!J52/12 -> 2343.57 | J53: =(1+INDEX('Inputs & Drivers'!$I$61:$I$65,MATCH(Model2.0!J$5,'Inputs & Drivers'!$B$61:$B$65,0))*(Model2.0!J$5<>Model2.0!I$5))*Model2.0!I53 -> 2343.57 | K53: =(1+INDEX('Inputs & Drivers'!$I$61:$I$65,MATCH(Model2.0!K$5,'Inputs & Drivers'!$B$61:$B$65,0))*(Model2.0!K$5<>Model2.0!J$5))*Model2.0!J53 -> 2343.57 | L53: =(1+INDEX('Inputs & Drivers'!$I$61:$I$65,MATCH(Model2.0!L$5,'Inputs & Drivers'!$B$61:$B$65,0))*(Model2.0!L$5<>Model2.0!K$5))*Model2.0!K53 -> 2343.57 | M53: =(1+INDEX('Inputs & Drivers'!$I$61:$I$65,MATCH(Model2.0!M$5,'Inputs & Drivers'!$B$61:$B$65,0))*(Model2.0!M$5<>Model2.0!L$5))*Model2.0!L53 -> 2343.57 | N53: =(1+INDEX('Inputs & Drivers'!$I$61:$I$65,MATCH(Model2.0!N$5,'Inputs & Drivers'!$B$61:$B$65,0))*(Model2.0!N$5<>Model2.0!M$5))*Model2.0!M53 -> 2343.57 | O53: =(1+INDEX('Inputs & Drivers'!$I$61:$I$65,MATCH(Model2.0!O$5,'Inputs & Drivers'!$B$61:$B$65,0))*(Model2.0!O$5<>Model2.0!N$5))*Model2.0!N53 -> 2343.57 | P53: =(1+INDEX('Inputs & Drivers'!$I$61:$I$65,MATCH(Model2.0!P$5,'Inputs & Drivers'!$B$61:$B$65,0))*(Model2.0!P$5<>Model2.0!O$5))*Model2.0!O53 -> 2343.57 | Q53: =(1+INDEX('Inputs & Drivers'!$I$61:$I$65,MATCH(Model2.0!Q$5,'Inputs & Drivers'!$B$61:$B$65,0))*(Model2.0!Q$5<>Model2.0!P$5))*Model2.0!P53 -> 2343.57 | ... BP53: =(1+INDEX('Inputs & Drivers'!$I$61:$I$65,MATCH(Model2.0!BP$5,'Inputs & Drivers'!$B$61:$B$65,0))*(Model2.0!BP$5<>Model2.0!BO$5))*Model2.0!BO53 -> 2536.7555 | BR53: =SUM(I53:T53) -> 28122.84 | BS53: =SUM(I53:T53) -> 28122.84 | BT53: =BS53-BR53 -> 0 | BV53: Utilities | BW53: =SUMIF($I$5:$BP$5,BW$18,$I53:$BP53) -> 28122.84 | BX53: =SUMIF($I$5:$BP$5,BX$18,$I53:$BP53) -> 28685.297 | BY53: =SUMIF($I$5:$BP$5,BY$18,$I53:$BP53) -> 29259.003 | BZ53: =SUMIF($I$5:$BP$5,BZ$18,$I53:$BP53) -> 29844.183 | CA53: =SUMIF($I$5:$BP$5,CA$18,$I53:$BP53) -> 30441.066 | CC53: =SUM($I53:$T53) -> 28122.84 | CD53: =SUM($U53:$AF53) -> 28685.297 | CE53: =SUM($AG53:$AR53) -> 29259.003 | CF53: =SUM($AS53:$BD53) -> 29844.183 | CG53: =SUM($BE53:$BP53) -> 30441.066 | CI53: =IF(CC53=BW53,"OK","Check") -> OK | CJ53: =IF(CD53=BX53,"OK","Check") -> OK | CK53: =IF(CE53=BY53,"OK","Check") -> OK | CL53: =IF(CF53=BZ53,"OK","Check") -> OK | CM53: =IF(CG53=CA53,"OK","Check") -> OK
B54: Insurance | E54: =SUM('P-Builder'!O37:Q37)*4 -> 0 | F54: =SUM('P-Builder'!F37:Q37) -> 0 | H54: ='P-Builder'!Q37 -> 0 | I54: ='Inputs & Drivers'!J53/12 -> 0 | J54: =(1+INDEX('Inputs & Drivers'!$I$61:$I$65,MATCH(Model2.0!J$5,'Inputs & Drivers'!$B$61:$B$65,0))*(Model2.0!J$5<>Model2.0!I$5))*Model2.0!I54 -> 0 | K54: =(1+INDEX('Inputs & Drivers'!$I$61:$I$65,MATCH(Model2.0!K$5,'Inputs & Drivers'!$B$61:$B$65,0))*(Model2.0!K$5<>Model2.0!J$5))*Model2.0!J54 -> 0 | L54: =(1+INDEX('Inputs & Drivers'!$I$61:$I$65,MATCH(Model2.0!L$5,'Inputs & Drivers'!$B$61:$B$65,0))*(Model2.0!L$5<>Model2.0!K$5))*Model2.0!K54 -> 0 | M54: =(1+INDEX('Inputs & Drivers'!$I$61:$I$65,MATCH(Model2.0!M$5,'Inputs & Drivers'!$B$61:$B$65,0))*(Model2.0!M$5<>Model2.0!L$5))*Model2.0!L54 -> 0 | N54: =(1+INDEX('Inputs & Drivers'!$I$61:$I$65,MATCH(Model2.0!N$5,'Inputs & Drivers'!$B$61:$B$65,0))*(Model2.0!N$5<>Model2.0!M$5))*Model2.0!M54 -> 0 | O54: =(1+INDEX('Inputs & Drivers'!$I$61:$I$65,MATCH(Model2.0!O$5,'Inputs & Drivers'!$B$61:$B$65,0))*(Model2.0!O$5<>Model2.0!N$5))*Model2.0!N54 -> 0 | P54: =(1+INDEX('Inputs & Drivers'!$I$61:$I$65,MATCH(Model2.0!P$5,'Inputs & Drivers'!$B$61:$B$65,0))*(Model2.0!P$5<>Model2.0!O$5))*Model2.0!O54 -> 0 | Q54: =(1+INDEX('Inputs & Drivers'!$I$61:$I$65,MATCH(Model2.0!Q$5,'Inputs & Drivers'!$B$61:$B$65,0))*(Model2.0!Q$5<>Model2.0!P$5))*Model2.0!P54 -> 0 | ... BP54: =(1+INDEX('Inputs & Drivers'!$I$61:$I$65,MATCH(Model2.0!BP$5,'Inputs & Drivers'!$B$61:$B$65,0))*(Model2.0!BP$5<>Model2.0!BO$5))*Model2.0!BO54 -> 0 | BR54: =SUM(I54:T54) -> 0 | BS54: =SUM(I54:T54) -> 0 | BT54: =BS54-BR54 -> 0 | BV54: Insurance | BW54: =SUMIF($I$5:$BP$5,BW$18,$I54:$BP54) -> 0 | BX54: =SUMIF($I$5:$BP$5,BX$18,$I54:$BP54) -> 0 | BY54: =SUMIF($I$5:$BP$5,BY$18,$I54:$BP54) -> 0 | BZ54: =SUMIF($I$5:$BP$5,BZ$18,$I54:$BP54) -> 0 | CA54: =SUMIF($I$5:$BP$5,CA$18,$I54:$BP54) -> 0 | CC54: =SUM($I54:$T54) -> 0 | CD54: =SUM($U54:$AF54) -> 0 | CE54: =SUM($AG54:$AR54) -> 0 | CF54: =SUM($AS54:$BD54) -> 0 | CG54: =SUM($BE54:$BP54) -> 0 | CI54: =IF(CC54=BW54,"OK","Check") -> OK | CJ54: =IF(CD54=BX54,"OK","Check") -> OK | CK54: =IF(CE54=BY54,"OK","Check") -> OK | CL54: =IF(CF54=BZ54,"OK","Check") -> OK | CM54: =IF(CG54=CA54,"OK","Check") -> OK
B55: Property Taxes | E55: =SUM('P-Builder'!O38:Q38)*4 -> 0 | F55: =SUM('P-Builder'!F38:Q38) -> 0 | H55: ='P-Builder'!Q38 -> 0 | I55: ='Inputs & Drivers'!J54/12 -> 0 | J55: =(1+INDEX('Inputs & Drivers'!$J$61:$J$65,MATCH(Model2.0!J$5,'Inputs & Drivers'!$B$61:$B$65,0))*(Model2.0!J$5<>Model2.0!I$5))*Model2.0!I55 -> 0 | K55: =(1+INDEX('Inputs & Drivers'!$J$61:$J$65,MATCH(Model2.0!K$5,'Inputs & Drivers'!$B$61:$B$65,0))*(Model2.0!K$5<>Model2.0!J$5))*Model2.0!J55 -> 0 | L55: =(1+INDEX('Inputs & Drivers'!$J$61:$J$65,MATCH(Model2.0!L$5,'Inputs & Drivers'!$B$61:$B$65,0))*(Model2.0!L$5<>Model2.0!K$5))*Model2.0!K55 -> 0 | M55: =(1+INDEX('Inputs & Drivers'!$J$61:$J$65,MATCH(Model2.0!M$5,'Inputs & Drivers'!$B$61:$B$65,0))*(Model2.0!M$5<>Model2.0!L$5))*Model2.0!L55 -> 0 | N55: =(1+INDEX('Inputs & Drivers'!$J$61:$J$65,MATCH(Model2.0!N$5,'Inputs & Drivers'!$B$61:$B$65,0))*(Model2.0!N$5<>Model2.0!M$5))*Model2.0!M55 -> 0 | O55: =(1+INDEX('Inputs & Drivers'!$J$61:$J$65,MATCH(Model2.0!O$5,'Inputs & Drivers'!$B$61:$B$65,0))*(Model2.0!O$5<>Model2.0!N$5))*Model2.0!N55 -> 0 | P55: =(1+INDEX('Inputs & Drivers'!$J$61:$J$65,MATCH(Model2.0!P$5,'Inputs & Drivers'!$B$61:$B$65,0))*(Model2.0!P$5<>Model2.0!O$5))*Model2.0!O55 -> 0 | Q55: =(1+INDEX('Inputs & Drivers'!$J$61:$J$65,MATCH(Model2.0!Q$5,'Inputs & Drivers'!$B$61:$B$65,0))*(Model2.0!Q$5<>Model2.0!P$5))*Model2.0!P55 -> 0 | ... BP55: =(1+INDEX('Inputs & Drivers'!$J$61:$J$65,MATCH(Model2.0!BP$5,'Inputs & Drivers'!$B$61:$B$65,0))*(Model2.0!BP$5<>Model2.0!BO$5))*Model2.0!BO55 -> 0 | BR55: =SUM(I55:T55) -> 0 | BS55: =SUM(I55:T55) -> 0 | BT55: =BS55-BR55 -> 0 | BV55: Property Tax | BW55: =SUMIF($I$5:$BP$5,BW$18,$I55:$BP55) -> 0 | BX55: =SUMIF($I$5:$BP$5,BX$18,$I55:$BP55) -> 0 | BY55: =SUMIF($I$5:$BP$5,BY$18,$I55:$BP55) -> 0 | BZ55: =SUMIF($I$5:$BP$5,BZ$18,$I55:$BP55) -> 0 | CA55: =SUMIF($I$5:$BP$5,CA$18,$I55:$BP55) -> 0 | CC55: =SUM($I55:$T55) -> 0 | CD55: =SUM($U55:$AF55) -> 0 | CE55: =SUM($AG55:$AR55) -> 0 | CF55: =SUM($AS55:$BD55) -> 0 | CG55: =SUM($BE55:$BP55) -> 0 | CI55: =IF(CC55=BW55,"OK","Check") -> OK | CJ55: =IF(CD55=BX55,"OK","Check") -> OK | CK55: =IF(CE55=BY55,"OK","Check") -> OK | CL55: =IF(CF55=BZ55,"OK","Check") -> OK | CM55: =IF(CG55=CA55,"OK","Check") -> OK
B56: Other Expense | E56: =SUM('P-Builder'!O39:Q39)*4 -> 0 | F56: =SUM('P-Builder'!F39:Q39) -> 0 | H56: ='P-Builder'!Q39 -> 0 | I56: ='Inputs & Drivers'!J55/12 -> 0 | J56: =(1+INDEX('Inputs & Drivers'!$I$61:$I$65,MATCH(Model2.0!J$5,'Inputs & Drivers'!$B$61:$B$65,0))*(Model2.0!J$5<>Model2.0!I$5))*Model2.0!I56 -> 0 | K56: =(1+INDEX('Inputs & Drivers'!$I$61:$I$65,MATCH(Model2.0!K$5,'Inputs & Drivers'!$B$61:$B$65,0))*(Model2.0!K$5<>Model2.0!J$5))*Model2.0!J56 -> 0 | L56: =(1+INDEX('Inputs & Drivers'!$I$61:$I$65,MATCH(Model2.0!L$5,'Inputs & Drivers'!$B$61:$B$65,0))*(Model2.0!L$5<>Model2.0!K$5))*Model2.0!K56 -> 0 | M56: =(1+INDEX('Inputs & Drivers'!$I$61:$I$65,MATCH(Model2.0!M$5,'Inputs & Drivers'!$B$61:$B$65,0))*(Model2.0!M$5<>Model2.0!L$5))*Model2.0!L56 -> 0 | N56: =(1+INDEX('Inputs & Drivers'!$I$61:$I$65,MATCH(Model2.0!N$5,'Inputs & Drivers'!$B$61:$B$65,0))*(Model2.0!N$5<>Model2.0!M$5))*Model2.0!M56 -> 0 | O56: =(1+INDEX('Inputs & Drivers'!$I$61:$I$65,MATCH(Model2.0!O$5,'Inputs & Drivers'!$B$61:$B$65,0))*(Model2.0!O$5<>Model2.0!N$5))*Model2.0!N56 -> 0 | P56: =(1+INDEX('Inputs & Drivers'!$I$61:$I$65,MATCH(Model2.0!P$5,'Inputs & Drivers'!$B$61:$B$65,0))*(Model2.0!P$5<>Model2.0!O$5))*Model2.0!O56 -> 0 | Q56: =(1+INDEX('Inputs & Drivers'!$I$61:$I$65,MATCH(Model2.0!Q$5,'Inputs & Drivers'!$B$61:$B$65,0))*(Model2.0!Q$5<>Model2.0!P$5))*Model2.0!P56 -> 0 | ... BP56: =(1+INDEX('Inputs & Drivers'!$I$61:$I$65,MATCH(Model2.0!BP$5,'Inputs & Drivers'!$B$61:$B$65,0))*(Model2.0!BP$5<>Model2.0!BO$5))*Model2.0!BO56 -> 0 | BR56: =SUM(I56:T56) -> 0 | BS56: =SUM(I56:T56) -> 0 | BT56: =BS56-BR56 -> 0 | BV56: Other Expense | BW56: =SUMIF($I$5:$BP$5,BW$18,$I56:$BP56) -> 0 | BX56: =SUMIF($I$5:$BP$5,BX$18,$I56:$BP56) -> 0 | BY56: =SUMIF($I$5:$BP$5,BY$18,$I56:$BP56) -> 0 | BZ56: =SUMIF($I$5:$BP$5,BZ$18,$I56:$BP56) -> 0 | CA56: =SUMIF($I$5:$BP$5,CA$18,$I56:$BP56) -> 0 | CC56: =SUM($I56:$T56) -> 0 | CD56: =SUM($U56:$AF56) -> 0 | CE56: =SUM($AG56:$AR56) -> 0 | CF56: =SUM($AS56:$BD56) -> 0 | CG56: =SUM($BE56:$BP56) -> 0 | CI56: =IF(CC56=BW56,"OK","Check") -> OK | CJ56: =IF(CD56=BX56,"OK","Check") -> OK | CK56: =IF(CE56=BY56,"OK","Check") -> OK | CL56: =IF(CF56=BZ56,"OK","Check") -> OK | CM56: =IF(CG56=CA56,"OK","Check") -> OK
B58: Total Operating Expense | E58: =SUM(E37:E55) -> 287413.16 | F58: =SUM(F37:F55) -> 288831.47 | H58: ='P-Builder'!Q41 -> 24338.47 | I58: =SUM(I37,I39:I41,I43:I56) -> 24165.832 | J58: =SUM(J37,J39:J41,J43:J56) -> 24188.721 | K58: =SUM(K37,K39:K41,K43:K56) -> 24211.763 | L58: =SUM(L37,L39:L41,L43:L56) -> 24416.641 | M58: =SUM(M37,M39:M41,M43:M56) -> 24622.885 | N58: =SUM(N37,N39:N41,N43:N56) -> 24830.504 | O58: =SUM(O37,O39:O41,O43:O56) -> 24928.302 | P58: =SUM(P37,P39:P41,P43:P56) -> 25026.753 | ... BP58: =SUM(BP37,BP39:BP41,BP43:BP56) -> 28698.204 | BR58: =SUM(BR37:BR56) -> 297496.11 | BS58: =SUM(BS37:BS56) -> 330911.94 | BT58: =SUM(BT37:BT56) -> 33415.832 | BV58: Total Operating Expense | BW58: =SUM(BW43:BW56,BW39:BW41,BW37) -> 297496.11 | BX58: =SUM(BX43:BX56,BX39:BX41,BX37) -> 310104.75 | BY58: =SUM(BY43:BY56,BY39:BY41,BY37) -> 323892.82 | BZ58: =SUM(BZ43:BZ56,BZ39:BZ41,BZ37) -> 331610.29 | CA58: =SUM(CA43:CA56,CA39:CA41,CA37) -> 339535.55 | CC58: =SUM($I58:$T58) -> 297496.11 | CD58: =SUM($U58:$AF58) -> 310104.75 | CE58: =SUM($AG58:$AR58) -> 323892.82 | CF58: =SUM($AS58:$BD58) -> 331610.29 | CG58: =SUM($BE58:$BP58) -> 339535.55
H59: ='P-Builder'!Q42 -> 0 | CC59: =IF(CC58=BW58,"OK","Check") -> OK | CD59: =IF(CD58=BX58,"OK","Check") -> OK | CE59: =IF(CE58=BY58,"OK","Check") -> OK | CF59: =IF(CF58=BZ58,"OK","Check") -> OK | CG59: =IF(CG58=CA58,"OK","Check") -> OK
B60: Net Operating Income | E60: =E34-E58 -> 842389.12 | F60: =F34-F58 -> 634336.54 | H60: ='P-Builder'!Q43 -> 73151.14 | I60: =I34-I58 -> 68236.99 | J60: =J34-J58 -> 68828.822 | K60: =K34-K58 -> 69425.276 | L60: =L34-L58 -> 74386.745 | M60: =M34-M58 -> 79381.918 | N60: =N34-N58 -> 84410.993 | O60: =O34-O58 -> 86805.267 | P60: =P34-P58 -> 89216.057 | ... BP60: =BP34-BP58 -> 103240.09 | BR60: =BR34-BR58 -> 1001731.7 | BS60: =BS34-BS58 -> 841707.44 | BT60: =BR60-BS60 -> 160024.22 | BV60: Net Operating Income | BW60: =BW34-BW58 -> 1001731.7 | BX60: =BX34-BX58 -> 1025246.5 | BY60: =BY34-BY58 -> 1059120.4 | BZ60: =BZ34-BZ58 -> 1102099.5 | CA60: =CA34-CA58 -> 1147789 | CC60: =SUM($I60:$T60) -> 1001731.7 | CD60: =SUM($U60:$AF60) -> 1025246.5 | CE60: =SUM($AG60:$AR60) -> 1059120.4 | CF60: =SUM($AS60:$BD60) -> 1102099.5 | CG60: =SUM($BE60:$BP60) -> 1147789
CC61: =IF(CC60=BW60,"OK","Check") -> OK | CD61: =IF(CD60=BX60,"OK","Check") -> OK | CE61: =IF(CE60=BY60,"OK","Check") -> OK | CF61: =IF(CF60=BZ60,"OK","Check") -> OK | CG61: =IF(CG60=CA60,"OK","Check") -> OK
BT63: =BS58-BR58 -> 33415.832
BS66: =BR58/BS58 -> 0.89901896

Sheet P-Builder
B1: TRANSLATED TO STANDARD ACCOUNTS
B2: Month | D2: 45689 | F2: =SUM(F5:F43) -> 201534.53 | G2: =SUM(G5:G43) -> 236283.89 | H2: =SUM(H5:H43) -> 255075.86 | I2: =SUM(I5:I43) -> 290199.68 | J2: =SUM(J5:J43) -> 306114.01 | K2: =SUM(K5:K43) -> 343684.95 | L2: =SUM(L5:L43) -> 353865.87 | M2: =SUM(M5:M43) -> 357758.05 | ... Q2: =SUM(Q5:Q43) -> 405266.12 | X2: Growth Rate | AF2: Forecast | AH2: Forecast
D3: Public | F3: =EDATE(D2,0) -> 45689 | G3: =EDATE(F3,1) -> 45717 | H3: =EDATE(G3,1) -> 45748 | I3: =EDATE(H3,1) -> 45778 | J3: =EDATE(I3,1) -> 45809 | K3: =EDATE(J3,1) -> 45839 | L3: =EDATE(K3,1) -> 45870 | M3: =EDATE(L3,1) -> 45901 | N3: =EDATE(M3,1) -> 45931 | ... Q3: =EDATE(P3,1) -> 46023 | T3: Sum | V3: Average | X3: Average | Z3: Last Quarter Avg | AB3: Last Period | AD3: YoY | AF3: T-3 | AH3: T-12
E4: Income | AJ4: 1279529.1 | AL4: Income
E5: Rental Income | F5: =SUMIFS('Data Drop'!$G:$G,'Data Drop'!$H:$H,$E5, 'Data Drop'!$D:$D,MONTH(F$3),'Data Drop'!$E:$E,YEAR(F$3)) -> 41324.65 | G5: =SUMIFS('Data Drop'!$G:$G,'Data Drop'!$H:$H,$E5, 'Data Drop'!$D:$D,MONTH(G$3),'Data Drop'!$E:$E,YEAR(G$3)) -> 48906.56 | H5: =SUMIFS('Data Drop'!$G:$G,'Data Drop'!$H:$H,$E5, 'Data Drop'!$D:$D,MONTH(H$3),'Data Drop'!$E:$E,YEAR(H$3)) -> 54138.43 | I5: =SUMIFS('Data Drop'!$G:$G,'Data Drop'!$H:$H,$E5, 'Data Drop'!$D:$D,MONTH(I$3),'Data Drop'!$E:$E,YEAR(I$3)) -> 60857.87 | J5: =SUMIFS('Data Drop'!$G:$G,'Data Drop'!$H:$H,$E5, 'Data Drop'!$D:$D,MONTH(J$3),'Data Drop'!$E:$E,YEAR(J$3)) -> 65220.38 | K5: =SUMIFS('Data Drop'!$G:$G,'Data Drop'!$H:$H,$E5, 'Data Drop'!$D:$D,MONTH(K$3),'Data Drop'!$E:$E,YEAR(K$3)) -> 72813.54 | L5: =SUMIFS('Data Drop'!$G:$G,'Data Drop'!$H:$H,$E5, 'Data Drop'!$D:$D,MONTH(L$3),'Data Drop'!$E:$E,YEAR(L$3)) -> 75484.5 | M5: =SUMIFS('Data Drop'!$G:$G,'Data Drop'!$H:$H,$E5, 'Data Drop'!$D:$D,MONTH(M$3),'Data Drop'!$E:$E,YEAR(M$3)) -> 77101.22 | ... Q5: =SUMIFS('Data Drop'!$G:$G,'Data Drop'!$H:$H,$E5, 'Data Drop'!$D:$D,MONTH(Q$3),'Data Drop'!$E:$E,YEAR(Q$3)) -> 88458.82 | T5: =SUM(F5:Q5) -> 832809.83 | V5: =IFERROR(AVERAGEIF($F$2:$Q$2,">0",F5:Q5),"") -> 69400.819 | X5: {=IFERROR(AVERAGE(IF($F$2:$P$2>0,$G5:$Q5/$F5:$P5-1)),"")} -> 0.072962803 | Z5: {=IFERROR(AVERAGE($O5:$Q5/$N5:$P5-1),"")} -> 0.028219015 | AB5: =IFERROR(AVERAGE($Q5/$P5-1),"") -> 0.067717049 | AD5: =IFERROR(AVERAGE($Q5/$F5-1),"") -> 1.1405824 | AF5: =SUM(O5:Q5)*4 -> 1021816.7 | AJ5: 592 | AL5: Rental Income
E6: Discounts | F6: =SUMIFS('Data Drop'!$G:$G,'Data Drop'!$H:$H,$E6, 'Data Drop'!$D:$D,MONTH(F$3),'Data Drop'!$E:$E,YEAR(F$3)) -> 0 | G6: =SUMIFS('Data Drop'!$G:$G,'Data Drop'!$H:$H,$E6, 'Data Drop'!$D:$D,MONTH(G$3),'Data Drop'!$E:$E,YEAR(G$3)) -> 0 | H6: =SUMIFS('Data Drop'!$G:$G,'Data Drop'!$H:$H,$E6, 'Data Drop'!$D:$D,MONTH(H$3),'Data Drop'!$E:$E,YEAR(H$3)) -> 0 | I6: =SUMIFS('Data Drop'!$G:$G,'Data Drop'!$H:$H,$E6, 'Data Drop'!$D:$D,MONTH(I$3),'Data Drop'!$E:$E,YEAR(I$3)) -> 0 | J6: =SUMIFS('Data Drop'!$G:$G,'Data Drop'!$H:$H,$E6, 'Data Drop'!$D:$D,MONTH(J$3),'Data Drop'!$E:$E,YEAR(J$3)) -> 0 | K6: =SUMIFS('Data Drop'!$G:$G,'Data Drop'!$H:$H,$E6, 'Data Drop'!$D:$D,MONTH(K$3),'Data Drop'!$E:$E,YEAR(K$3)) -> 0 | L6: =SUMIFS('Data Drop'!$G:$G,'Data Drop'!$H:$H,$E6, 'Data Drop'!$D:$D,MONTH(L$3),'Data Drop'!$E:$E,YEAR(L$3)) -> 0 | M6: =SUMIFS('Data Drop'!$G:$G,'Data Drop'!$H:$H,$E6, 'Data Drop'!$D:$D,MONTH(M$3),'Data Drop'!$E:$E,YEAR(M$3)) -> 0 | ... Q6: =SUMIFS('Data Drop'!$G:$G,'Data Drop'!$H:$H,$E6, 'Data Drop'!$D:$D,MONTH(Q$3),'Data Drop'!$E:$E,YEAR(Q$3)) -> 0 | T6: =SUM(F6:Q6) -> 0 | V6: =IFERROR(AVERAGEIF($F$2:$Q$2,">0",F6:Q6),"") -> 0 | X6: {=IFERROR(AVERAGE(IF($F$2:$P$2>0,$G6:$Q6/$F6:$P6-1)),"")} | Z6: {=IFERROR(AVERAGE($O6:$Q6/$N6:$P6-1),"")} | AB6: =IFERROR(AVERAGE($Q6/$P6-1),"") | AD6: =IFERROR(AVERAGE($Q6/$F6-1),"") | AF6: =SUM(O6:Q6)*4 -> 0 | AJ6: =AJ4/AJ5/12 -> 180.1139 | AL6: Discounts
E7: Bad Debt/Rental Refunds | F7: =SUMIFS('Data Drop'!$G:$G,'Data Drop'!$H:$H,$E7, 'Data Drop'!$D:$D,MONTH(F$3),'Data Drop'!$E:$E,YEAR(F$3)) -> 0 | G7: =SUMIFS('Data Drop'!$G:$G,'Data Drop'!$H:$H,$E7, 'Data Drop'!$D:$D,MONTH(G$3),'Data Drop'!$E:$E,YEAR(G$3)) -> 0 | H7: =SUMIFS('Data Drop'!$G:$G,'Data Drop'!$H:$H,$E7, 'Data Drop'!$D:$D,MONTH(H$3),'Data Drop'!$E:$E,YEAR(H$3)) -> 0 | I7: =SUMIFS('Data Drop'!$G:$G,'Data Drop'!$H:$H,$E7, 'Data Drop'!$D:$D,MONTH(I$3),'Data Drop'!$E:$E,YEAR(I$3)) -> 0 | J7: =SUMIFS('Data Drop'!$G:$G,'Data Drop'!$H:$H,$E7, 'Data Drop'!$D:$D,MONTH(J$3),'Data Drop'!$E:$E,YEAR(J$3)) -> 0 | K7: =SUMIFS('Data Drop'!$G:$G,'Data Drop'!$H:$H,$E7, 'Data Drop'!$D:$D,MONTH(K$3),'Data Drop'!$E:$E,YEAR(K$3)) -> 0 | L7: =SUMIFS('Data Drop'!$G:$G,'Data Drop'!$H:$H,$E7, 'Data Drop'!$D:$D,MONTH(L$3),'Data Drop'!$E:$E,YEAR(L$3)) -> 0 | M7: =SUMIFS('Data Drop'!$G:$G,'Data Drop'!$H:$H,$E7, 'Data Drop'!$D:$D,MONTH(M$3),'Data Drop'!$E:$E,YEAR(M$3)) -> 0 | ... Q7: =SUMIFS('Data Drop'!$G:$G,'Data Drop'!$H:$H,$E7, 'Data Drop'!$D:$D,MONTH(Q$3),'Data Drop'!$E:$E,YEAR(Q$3)) -> 0 | T7: =SUM(F7:Q7) -> 0 | V7: =IFERROR(AVERAGEIF($F$2:$Q$2,">0",F7:Q7),"") -> 0 | X7: {=IFERROR(AVERAGE(IF($F$2:$P$2>0,$G7:$Q7/$F7:$P7-1)),"")} | Z7: {=IFERROR(AVERAGE($O7:$Q7/$N7:$P7-1),"")} | AB7: =IFERROR(AVERAGE($Q7/$P7-1),"") | AD7: =IFERROR(AVERAGE($Q7/$F7-1),"") | AF7: =SUM(O7:Q7)*4 -> 0 | AL7: Bad Debt/Rental Refunds
B8: Check: Net Rental Income | E8: Net Rental Income | F8: =SUM(F5:F7) -> 41324.65 | G8: =SUM(G5:G7) -> 48906.56 | H8: =SUM(H5:H7) -> 54138.43 | I8: =SUM(I5:I7) -> 60857.87 | J8: =SUM(J5:J7) -> 65220.38 | K8: =SUM(K5:K7) -> 72813.54 | L8: =SUM(L5:L7) -> 75484.5 | M8: =SUM(M5:M7) -> 77101.22 | ... Q8: =SUM(Q5:Q7) -> 88458.82 | T8: =SUM(F8:Q8) -> 832809.83 | V8: =IFERROR(AVERAGEIF($F$2:$Q$2,">0",F8:Q8),"") -> 69400.819 | X8: {=IFERROR(AVERAGE(IF($F$2:$P$2>0,$G8:$Q8/$F8:$P8-1)),"")} -> 0.072962803 | Z8: {=IFERROR(AVERAGE($O8:$Q8/$N8:$P8-1),"")} -> 0.028219015 | AB8: =IFERROR(AVERAGE($Q8/$P8-1),"") -> 0.067717049 | AD8: =IFERROR(AVERAGE($Q8/$F8-1),"") -> 1.1405824 | AF8: =SUM(O8:Q8)*4 -> 1021816.7 | AL8: Net Rental Income
V9: =IFERROR(AVERAGEIF($F$2:$Q$2,">0",F9:Q9),"") | X9: {=IFERROR(AVERAGE(IF($F$2:$P$2>0,$G9:$Q9/$F9:$P9-1)),"")} | AF9: =SUM(O9:Q9)*4 -> 0
E10: Admin Fee Income | F10: =SUMIFS('Data Drop'!$G:$G,'Data Drop'!$H:$H,$E10, 'Data Drop'!$D:$D,MONTH(F$3),'Data Drop'!$E:$E,YEAR(F$3))/2 -> 1216 | G10: =SUMIFS('Data Drop'!$G:$G,'Data Drop'!$H:$H,$E10, 'Data Drop'!$D:$D,MONTH(G$3),'Data Drop'!$E:$E,YEAR(G$3))/2 -> 1453.8 | H10: =SUMIFS('Data Drop'!$G:$G,'Data Drop'!$H:$H,$E10, 'Data Drop'!$D:$D,MONTH(H$3),'Data Drop'!$E:$E,YEAR(H$3))/2 -> 1681.435 | I10: =SUMIFS('Data Drop'!$G:$G,'Data Drop'!$H:$H,$E10, 'Data Drop'!$D:$D,MONTH(I$3),'Data Drop'!$E:$E,YEAR(I$3))/2 -> 1733.8 | J10: =SUMIFS('Data Drop'!$G:$G,'Data Drop'!$H:$H,$E10, 'Data Drop'!$D:$D,MONTH(J$3),'Data Drop'!$E:$E,YEAR(J$3))/2 -> 1742.2 | K10: =SUMIFS('Data Drop'!$G:$G,'Data Drop'!$H:$H,$E10, 'Data Drop'!$D:$D,MONTH(K$3),'Data Drop'!$E:$E,YEAR(K$3))/2 -> 1289.7 | L10: =SUMIFS('Data Drop'!$G:$G,'Data Drop'!$H:$H,$E10, 'Data Drop'!$D:$D,MONTH(L$3),'Data Drop'!$E:$E,YEAR(L$3))/2 -> 1791.295 | M10: =SUMIFS('Data Drop'!$G:$G,'Data Drop'!$H:$H,$E10, 'Data Drop'!$D:$D,MONTH(M$3),'Data Drop'!$E:$E,YEAR(M$3))/2 -> 1641.28 | ... Q10: =SUMIFS('Data Drop'!$G:$G,'Data Drop'!$H:$H,$E10, 'Data Drop'!$D:$D,MONTH(Q$3),'Data Drop'!$E:$E,YEAR(Q$3))/2 -> 2492.49 | T10: =SUM(F10:Q10) -> 22165.125 | V10: =IFERROR(AVERAGEIF($F$2:$Q$2,">0",F10:Q10),"") -> 1847.0938 | X10: {=IFERROR(AVERAGE(IF($F$2:$P$2>0,$G10:$Q10/$F10:$P10-1)),"")} -> 0.093792658 | Z10: {=IFERROR(AVERAGE($O10:$Q10/$N10:$P10-1),"")} -> 0.097397173 | AB10: =IFERROR(AVERAGE($Q10/$P10-1),"") -> -0.18014243 | AD10: =IFERROR(AVERAGE($Q10/$F10-1),"") -> 1.0497451 | AF10: =SUM(O10:Q10)*4 -> 29888.72 | AL10: Admin Fee Income
E11: Late Fee Income | F11: =SUMIFS('Data Drop'!$G:$G,'Data Drop'!$H:$H,$E10, 'Data Drop'!$D:$D,MONTH(F$3),'Data Drop'!$E:$E,YEAR(F$3))/2 -> 1216 | G11: =SUMIFS('Data Drop'!$G:$G,'Data Drop'!$H:$H,$E10, 'Data Drop'!$D:$D,MONTH(G$3),'Data Drop'!$E:$E,YEAR(G$3))/2 -> 1453.8 | H11: =SUMIFS('Data Drop'!$G:$G,'Data Drop'!$H:$H,$E10, 'Data Drop'!$D:$D,MONTH(H$3),'Data Drop'!$E:$E,YEAR(H$3))/2 -> 1681.435 | I11: =SUMIFS('Data Drop'!$G:$G,'Data Drop'!$H:$H,$E10, 'Data Drop'!$D:$D,MONTH(I$3),'Data Drop'!$E:$E,YEAR(I$3))/2 -> 1733.8 | J11: =SUMIFS('Data Drop'!$G:$G,'Data Drop'!$H:$H,$E10, 'Data Drop'!$D:$D,MONTH(J$3),'Data Drop'!$E:$E,YEAR(J$3))/2 -> 1742.2 | K11: =SUMIFS('Data Drop'!$G:$G,'Data Drop'!$H:$H,$E10, 'Data Drop'!$D:$D,MONTH(K$3),'Data Drop'!$E:$E,YEAR(K$3))/2 -> 1289.7 | L11: =SUMIFS('Data Drop'!$G:$G,'Data Drop'!$H:$H,$E10, 'Data Drop'!$D:$D,MONTH(L$3),'Data Drop'!$E:$E,YEAR(L$3))/2 -> 1791.295 | M11: =SUMIFS('Data Drop'!$G:$G,'Data Drop'!$H:$H,$E10, 'Data Drop'!$D:$D,MONTH(M$3),'Data Drop'!$E:$E,YEAR(M$3))/2 -> 1641.28 | ... Q11: =SUMIFS('Data Drop'!$G:$G,'Data Drop'!$H:$H,$E10, 'Data Drop'!$D:$D,MONTH(Q$3),'Data Drop'!$E:$E,YEAR(Q$3))/2 -> 2492.49 | T11: =SUM(F11:Q11) -> 22165.125 | V11: =IFERROR(AVERAGEIF($F$2:$Q$2,">0",F11:Q11),"") -> 1847.0938 | X11: {=IFERROR(AVERAGE(IF($F$2:$P$2>0,$G11:$Q11/$F11:$P11-1)),"")} -> 0.093792658 | Z11: {=IFERROR(AVERAGE($O11:$Q11/$N11:$P11-1),"")} -> 0.097397173 | AB11: =IFERROR(AVERAGE($Q11/$P11-1),"") -> -0.18014243 | AD11: =IFERROR(AVERAGE($Q11/$F11-1),"") -> 1.0497451 | AF11: =SUM(O11:Q11)*4 -> 29888.72 | AL11: Late Fee Income
E12: Current Tenant Protection Split | F12: =SUMIFS('Data Drop'!$G:$G,'Data Drop'!$H:$H,$E12, 'Data Drop'!$D:$D,MONTH(F$3),'Data Drop'!$E:$E,YEAR(F$3)) -> 2454 | G12: =SUMIFS('Data Drop'!$G:$G,'Data Drop'!$H:$H,$E12, 'Data Drop'!$D:$D,MONTH(G$3),'Data Drop'!$E:$E,YEAR(G$3)) -> 2646 | H12: =SUMIFS('Data Drop'!$G:$G,'Data Drop'!$H:$H,$E12, 'Data Drop'!$D:$D,MONTH(H$3),'Data Drop'!$E:$E,YEAR(H$3)) -> 2742 | I12: =SUMIFS('Data Drop'!$G:$G,'Data Drop'!$H:$H,$E12, 'Data Drop'!$D:$D,MONTH(I$3),'Data Drop'!$E:$E,YEAR(I$3)) -> 2964 | J12: =SUMIFS('Data Drop'!$G:$G,'Data Drop'!$H:$H,$E12, 'Data Drop'!$D:$D,MONTH(J$3),'Data Drop'!$E:$E,YEAR(J$3)) -> 3054 | K12: =SUMIFS('Data Drop'!$G:$G,'Data Drop'!$H:$H,$E12, 'Data Drop'!$D:$D,MONTH(K$3),'Data Drop'!$E:$E,YEAR(K$3)) -> 3102 | L12: =SUMIFS('Data Drop'!$G:$G,'Data Drop'!$H:$H,$E12, 'Data Drop'!$D:$D,MONTH(L$3),'Data Drop'!$E:$E,YEAR(L$3)) -> 3144 | M12: =SUMIFS('Data Drop'!$G:$G,'Data Drop'!$H:$H,$E12, 'Data Drop'!$D:$D,MONTH(M$3),'Data Drop'!$E:$E,YEAR(M$3)) -> 3096 | ... Q12: =SUMIFS('Data Drop'!$G:$G,'Data Drop'!$H:$H,$E12, 'Data Drop'!$D:$D,MONTH(Q$3),'Data Drop'!$E:$E,YEAR(Q$3)) -> 3258 | T12: =SUM(F12:Q12) -> 35796 | V12: =IFERROR(AVERAGEIF($F$2:$Q$2,">0",F12:Q12),"") -> 2983 | X12: {=IFERROR(AVERAGE(IF($F$2:$P$2>0,$G12:$Q12/$F12:$P12-1)),"")} -> 0.026515468 | Z12: {=IFERROR(AVERAGE($O12:$Q12/$N12:$P12-1),"")} -> 0.018569529 | AB12: =IFERROR(AVERAGE($Q12/$P12-1),"") -> 0.026465028 | AD12: =IFERROR(AVERAGE($Q12/$F12-1),"") -> 0.32762836 | AF12: =SUM(O12:Q12)*4 -> 38040 | AL12: Current Tenant Protection Split
E13: STORE Tenant Insurance Income | T13: =SUM(F13:Q13) -> 0 | V13: =IFERROR(AVERAGEIF($F$2:$Q$2,">0",F13:Q13),"") | X13: {=IFERROR(AVERAGE(IF($F$2:$P$2>0,$G13:$Q13/$F13:$P13-1)),"")} | Z13: {=IFERROR(AVERAGE($O13:$Q13/$N13:$P13-1),"")} | AB13: =IFERROR(AVERAGE($Q13/$P13-1),"") | AD13: =IFERROR(AVERAGE($Q13/$F13-1),"") | AF13: =SUM(O13:Q13)*4 -> 0 | AL13: STORE Tenant Insurance Income
E14: Other Tenant Income | F14: =SUMIFS('Data Drop'!$G:$G,'Data Drop'!$H:$H,$E14, 'Data Drop'!$D:$D,MONTH(F$3),'Data Drop'!$E:$E,YEAR(F$3)) -> 0 | G14: =SUMIFS('Data Drop'!$G:$G,'Data Drop'!$H:$H,$E14, 'Data Drop'!$D:$D,MONTH(G$3),'Data Drop'!$E:$E,YEAR(G$3)) -> 0 | H14: =SUMIFS('Data Drop'!$G:$G,'Data Drop'!$H:$H,$E14, 'Data Drop'!$D:$D,MONTH(H$3),'Data Drop'!$E:$E,YEAR(H$3)) -> 0 | I14: =SUMIFS('Data Drop'!$G:$G,'Data Drop'!$H:$H,$E14, 'Data Drop'!$D:$D,MONTH(I$3),'Data Drop'!$E:$E,YEAR(I$3)) -> 0 | J14: =SUMIFS('Data Drop'!$G:$G,'Data Drop'!$H:$H,$E14, 'Data Drop'!$D:$D,MONTH(J$3),'Data Drop'!$E:$E,YEAR(J$3)) -> 0 | K14: =SUMIFS('Data Drop'!$G:$G,'Data Drop'!$H:$H,$E14, 'Data Drop'!$D:$D,MONTH(K$3),'Data Drop'!$E:$E,YEAR(K$3)) -> 0 | L14: =SUMIFS('Data Drop'!$G:$G,'Data Drop'!$H:$H,$E14, 'Data Drop'!$D:$D,MONTH(L$3),'Data Drop'!$E:$E,YEAR(L$3)) -> 0 | M14: =SUMIFS('Data Drop'!$G:$G,'Data Drop'!$H:$H,$E14, 'Data Drop'!$D:$D,MONTH(M$3),'Data Drop'!$E:$E,YEAR(M$3)) -> 0 | ... Q14: =SUMIFS('Data Drop'!$G:$G,'Data Drop'!$H:$H,$E14, 'Data Drop'!$D:$D,MONTH(Q$3),'Data Drop'!$E:$E,YEAR(Q$3)) -> 0 | T14: =SUM(F14:Q14) -> 0 | V14: =IFERROR(AVERAGEIF($F$2:$Q$2,">0",F14:Q14),"") -> 0 | X14: {=IFERROR(AVERAGE(IF($F$2:$P$2>0,$G14:$Q14/$F14:$P14-1)),"")} | Z14: {=IFERROR(AVERAGE($O14:$Q14/$N14:$P14-1),"")} | AB14: =IFERROR(AVERAGE($Q14/$P14-1),"") | AD14: =IFERROR(AVERAGE($Q14/$F14-1),"") | AF14: =SUM(O14:Q14)*4 -> 0 | AL14: Other Tenant Income
E15: Retail Sales Income | F15: =SUMIFS('Data Drop'!$G:$G,'Data Drop'!$H:$H,$E15, 'Data Drop'!$D:$D,MONTH(F$3),'Data Drop'!$E:$E,YEAR(F$3)) -> 912.96 | G15: =SUMIFS('Data Drop'!$G:$G,'Data Drop'!$H:$H,$E15, 'Data Drop'!$D:$D,MONTH(G$3),'Data Drop'!$E:$E,YEAR(G$3)) -> 756.69 | H15: =SUMIFS('Data Drop'!$G:$G,'Data Drop'!$H:$H,$E15, 'Data Drop'!$D:$D,MONTH(H$3),'Data Drop'!$E:$E,YEAR(H$3)) -> 843.42 | I15: =SUMIFS('Data Drop'!$G:$G,'Data Drop'!$H:$H,$E15, 'Data Drop'!$D:$D,MONTH(I$3),'Data Drop'!$E:$E,YEAR(I$3)) -> 1118.63 | J15: =SUMIFS('Data Drop'!$G:$G,'Data Drop'!$H:$H,$E15, 'Data Drop'!$D:$D,MONTH(J$3),'Data Drop'!$E:$E,YEAR(J$3)) -> 889.55 | K15: =SUMIFS('Data Drop'!$G:$G,'Data Drop'!$H:$H,$E15, 'Data Drop'!$D:$D,MONTH(K$3),'Data Drop'!$E:$E,YEAR(K$3)) -> 760.21 | L15: =SUMIFS('Data Drop'!$G:$G,'Data Drop'!$H:$H,$E15, 'Data Drop'!$D:$D,MONTH(L$3),'Data Drop'!$E:$E,YEAR(L$3)) -> 1091.8 | M15: =SUMIFS('Data Drop'!$G:$G,'Data Drop'!$H:$H,$E15, 'Data Drop'!$D:$D,MONTH(M$3),'Data Drop'!$E:$E,YEAR(M$3)) -> 619.78 | ... Q15: =SUMIFS('Data Drop'!$G:$G,'Data Drop'!$H:$H,$E15, 'Data Drop'!$D:$D,MONTH(Q$3),'Data Drop'!$E:$E,YEAR(Q$3)) -> 787.81 | T15: =SUM(F15:Q15) -> 10231.93 | V15: =IFERROR(AVERAGEIF($F$2:$Q$2,">0",F15:Q15),"") -> 852.66083 | X15: {=IFERROR(AVERAGE(IF($F$2:$P$2>0,$G15:$Q15/$F15:$P15-1)),"")} -> 0.029534627 | Z15: {=IFERROR(AVERAGE($O15:$Q15/$N15:$P15-1),"")} -> 0.092371391 | AB15: =IFERROR(AVERAGE($Q15/$P15-1),"") -> -0.26164502 | AD15: =IFERROR(AVERAGE($Q15/$F15-1),"") -> -0.13708158 | AF15: =SUM(O15:Q15)*4 -> 10168.16 | AL15: Retail Sales Income
V16: =IFERROR(AVERAGEIF($F$2:$Q$2,">0",F16:Q16),"") | X16: {=IFERROR(AVERAGE(IF($F$2:$P$2>0,$G16:$Q16/$F16:$P16-1)),"")} | AF16: =SUM(O16:Q16)*4 -> 0
B17: Check: Total Operating Income | E17: Total Operating Income | F17: =SUM(F15,F8:F14) -> 47123.61 | G17: =SUM(G15,G8:G14) -> 55216.85 | H17: =SUM(H15,H8:H14) -> 61086.72 | I17: =SUM(I15,I8:I14) -> 68408.1 | J17: =SUM(J15,J8:J14) -> 72648.33 | K17: =SUM(K15,K8:K14) -> 79255.15 | L17: =SUM(L15,L8:L14) -> 83302.89 | M17: =SUM(M15,M8:M14) -> 84099.56 | ... Q17: =SUM(Q15,Q8:Q14) -> 97489.61 | T17: =SUM(F17:Q17) -> 923168.01 | V17: =IFERROR(AVERAGEIF($F$2:$Q$2,">0",F17:Q17),"") -> 76930.667 | X17: {=IFERROR(AVERAGE(IF($F$2:$P$2>0,$G17:$Q17/$F17:$P17-1)),"")} -> 0.069336161 | Z17: {=IFERROR(AVERAGE($O17:$Q17/$N17:$P17-1),"")} -> 0.028703657 | AB17: =IFERROR(AVERAGE($Q17/$P17-1),"") -> 0.046364467 | AD17: =IFERROR(AVERAGE($Q17/$F17-1),"") -> 1.0688061 | AF17: =SUM(O17:Q17)*4 -> 1129802.3 | AL17: Total Operating Income
T18: =SUM(F18:Q18) -> 0 | V18: =IFERROR(AVERAGEIF($F$2:$Q$2,">0",F18:Q18),"") | X18: {=IFERROR(AVERAGE(IF($F$2:$P$2>0,$G18:$Q18/$F18:$P18-1)),"")} | Z18: {=IFERROR(AVERAGE($O18:$Q18/$N18:$P18-1),"")} | AB18: =IFERROR(AVERAGE($Q18/$P18-1),"") | AD18: =IFERROR(AVERAGE($Q18/$F18-1),"") | AF18: =SUM(O18:Q18)*4 -> 0
E19: Expenses | T19: =SUM(F19:Q19) -> 0 | V19: =IFERROR(AVERAGEIF($F$2:$Q$2,">0",F19:Q19),"") | X19: {=IFERROR(AVERAGE(IF($F$2:$P$2>0,$G19:$Q19/$F19:$P19-1)),"")} | Z19: {=IFERROR(AVERAGE($O19:$Q19/$N19:$P19-1),"")} | AB19: =IFERROR(AVERAGE($Q19/$P19-1),"") | AD19: =IFERROR(AVERAGE($Q19/$F19-1),"") | AF19: =SUM(O19:Q19)*4 -> 0 | AL19: Expenses
E20: Advertising & Marketing | F20: =SUMIFS('Data Drop'!$G:$G,'Data Drop'!$H:$H,$E20, 'Data Drop'!$D:$D,MONTH(F$3),'Data Drop'!$E:$E,YEAR(F$3)) -> 2690.57 | G20: =SUMIFS('Data Drop'!$G:$G,'Data Drop'!$H:$H,$E20, 'Data Drop'!$D:$D,MONTH(G$3),'Data Drop'!$E:$E,YEAR(G$3)) -> 3766.33 | H20: =SUMIFS('Data Drop'!$G:$G,'Data Drop'!$H:$H,$E20, 'Data Drop'!$D:$D,MONTH(H$3),'Data Drop'!$E:$E,YEAR(H$3)) -> 3452.22 | I20: =SUMIFS('Data Drop'!$G:$G,'Data Drop'!$H:$H,$E20, 'Data Drop'!$D:$D,MONTH(I$3),'Data Drop'!$E:$E,YEAR(I$3)) -> 4285.4 | J20: =SUMIFS('Data Drop'!$G:$G,'Data Drop'!$H:$H,$E20, 'Data Drop'!$D:$D,MONTH(J$3),'Data Drop'!$E:$E,YEAR(J$3)) -> 3507.05 | K20: =SUMIFS('Data Drop'!$G:$G,'Data Drop'!$H:$H,$E20, 'Data Drop'!$D:$D,MONTH(K$3),'Data Drop'!$E:$E,YEAR(K$3)) -> 2723.6 | L20: =SUMIFS('Data Drop'!$G:$G,'Data Drop'!$H:$H,$E20, 'Data Drop'!$D:$D,MONTH(L$3),'Data Drop'!$E:$E,YEAR(L$3)) -> 3419.91 | M20: =SUMIFS('Data Drop'!$G:$G,'Data Drop'!$H:$H,$E20, 'Data Drop'!$D:$D,MONTH(M$3),'Data Drop'!$E:$E,YEAR(M$3)) -> 3480.91 | ... Q20: =SUMIFS('Data Drop'!$G:$G,'Data Drop'!$H:$H,$E20, 'Data Drop'!$D:$D,MONTH(Q$3),'Data Drop'!$E:$E,YEAR(Q$3)) -> 2235.45 | T20: =SUM(F20:Q20) -> 34857.42 | V20: =IFERROR(AVERAGEIF($F$2:$Q$2,">0",F20:Q20),"") -> 2904.785 | X20: {=IFERROR(AVERAGE(IF($F$2:$P$2>0,$G20:$Q20/$F20:$P20-1)),"")} -> 0.018757345 | Z20: {=IFERROR(AVERAGE($O20:$Q20/$N20:$P20-1),"")} -> 0.092403448 | AB20: =IFERROR(AVERAGE($Q20/$P20-1),"") -> 0.27527212 | AD20: =IFERROR(AVERAGE($Q20/$F20-1),"") -> -0.16915375 | AF20: =SUM(O20:Q20)*4 -> 23123.88 | AL20: Advertising & Marketing
E21: Current Credit Card Security Fees | F21: =SUMIFS('Data Drop'!$G:$G,'Data Drop'!$H:$H,$E21, 'Data Drop'!$D:$D,MONTH(F$3),'Data Drop'!$E:$E,YEAR(F$3)) -> 703.49 | G21: =SUMIFS('Data Drop'!$G:$G,'Data Drop'!$H:$H,$E21, 'Data Drop'!$D:$D,MONTH(G$3),'Data Drop'!$E:$E,YEAR(G$3)) -> 756.68 | H21: =SUMIFS('Data Drop'!$G:$G,'Data Drop'!$H:$H,$E21, 'Data Drop'!$D:$D,MONTH(H$3),'Data Drop'!$E:$E,YEAR(H$3)) -> 881.92 | I21: =SUMIFS('Data Drop'!$G:$G,'Data Drop'!$H:$H,$E21, 'Data Drop'!$D:$D,MONTH(I$3),'Data Drop'!$E:$E,YEAR(I$3)) -> 1037.71 | J21: =SUMIFS('Data Drop'!$G:$G,'Data Drop'!$H:$H,$E21, 'Data Drop'!$D:$D,MONTH(J$3),'Data Drop'!$E:$E,YEAR(J$3)) -> 1031.97 | K21: =SUMIFS('Data Drop'!$G:$G,'Data Drop'!$H:$H,$E21, 'Data Drop'!$D:$D,MONTH(K$3),'Data Drop'!$E:$E,YEAR(K$3)) -> 1088.87 | L21: =SUMIFS('Data Drop'!$G:$G,'Data Drop'!$H:$H,$E21, 'Data Drop'!$D:$D,MONTH(L$3),'Data Drop'!$E:$E,YEAR(L$3)) -> 1189.62 | M21: =SUMIFS('Data Drop'!$G:$G,'Data Drop'!$H:$H,$E21, 'Data Drop'!$D:$D,MONTH(M$3),'Data Drop'!$E:$E,YEAR(M$3)) -> 1153.06 | ... Q21: =SUMIFS('Data Drop'!$G:$G,'Data Drop'!$H:$H,$E21, 'Data Drop'!$D:$D,MONTH(Q$3),'Data Drop'!$E:$E,YEAR(Q$3)) -> 1484.59 | T21: =SUM(F21:Q21) -> 13333.74 | V21: =IFERROR(AVERAGEIF($F$2:$Q$2,">0",F21:Q21),"") -> 1111.145 | X21: {=IFERROR(AVERAGE(IF($F$2:$P$2>0,$G21:$Q21/$F21:$P21-1)),"")} -> 0.073288223 | Z21: {=IFERROR(AVERAGE($O21:$Q21/$N21:$P21-1),"")} -> 0.04976257 | AB21: =IFERROR(AVERAGE($Q21/$P21-1),"") -> 0.011218429 | AD21: =IFERROR(AVERAGE($Q21/$F21-1),"") -> 1.1103214 | AF21: =SUM(O21:Q21)*4 -> 16760.4 | AL21: Credit Card Merchant Fees
E22: STORE Credit Card Security Fees | F22: =SUMIFS('Data Drop'!$G:$G,'Data Drop'!$H:$H,$E22, 'Data Drop'!$D:$D,MONTH(F$3),'Data Drop'!$E:$E,YEAR(F$3)) -> 0 | G22: =SUMIFS('Data Drop'!$G:$G,'Data Drop'!$H:$H,$E22, 'Data Drop'!$D:$D,MONTH(G$3),'Data Drop'!$E:$E,YEAR(G$3)) -> 0 | H22: =SUMIFS('Data Drop'!$G:$G,'Data Drop'!$H:$H,$E22, 'Data Drop'!$D:$D,MONTH(H$3),'Data Drop'!$E:$E,YEAR(H$3)) -> 0 | I22: =SUMIFS('Data Drop'!$G:$G,'Data Drop'!$H:$H,$E22, 'Data Drop'!$D:$D,MONTH(I$3),'Data Drop'!$E:$E,YEAR(I$3)) -> 0 | J22: =SUMIFS('Data Drop'!$G:$G,'Data Drop'!$H:$H,$E22, 'Data Drop'!$D:$D,MONTH(J$3),'Data Drop'!$E:$E,YEAR(J$3)) -> 0 | K22: =SUMIFS('Data Drop'!$G:$G,'Data Drop'!$H:$H,$E22, 'Data Drop'!$D:$D,MONTH(K$3),'Data Drop'!$E:$E,YEAR(K$3)) -> 0 | L22: =SUMIFS('Data Drop'!$G:$G,'Data Drop'!$H:$H,$E22, 'Data Drop'!$D:$D,MONTH(L$3),'Data Drop'!$E:$E,YEAR(L$3)) -> 0 | M22: =SUMIFS('Data Drop'!$G:$G,'Data Drop'!$H:$H,$E22, 'Data Drop'!$D:$D,MONTH(M$3),'Data Drop'!$E:$E,YEAR(M$3)) -> 0 | ... Q22: =SUMIFS('Data Drop'!$G:$G,'Data Drop'!$H:$H,$E22, 'Data Drop'!$D:$D,MONTH(Q$3),'Data Drop'!$E:$E,YEAR(Q$3)) -> 0 | T22: =SUM(F22:Q22) -> 0 | V22: =IFERROR(AVERAGEIF($F$2:$Q$2,">0",F22:Q22),"") -> 0 | X22: {=IFERROR(AVERAGE(IF($F$2:$P$2>0,$G22:$Q22/$F22:$P22-1)),"")} | Z22: {=IFERROR(AVERAGE($O22:$Q22/$N22:$P22-1),"")} | AB22: =IFERROR(AVERAGE($Q22/$P22-1),"") | AD22: =IFERROR(AVERAGE($Q22/$F22-1),"") | AF22: =SUM(O22:Q22)*4 -> 0 | AL22: Auction
E23: Fire Prevention | F23: =SUMIFS('Data Drop'!$G:$G,'Data Drop'!$H:$H,$E23, 'Data Drop'!$D:$D,MONTH(F$3),'Data Drop'!$E:$E,YEAR(F$3)) -> 0 | G23: =SUMIFS('Data Drop'!$G:$G,'Data Drop'!$H:$H,$E23, 'Data Drop'!$D:$D,MONTH(G$3),'Data Drop'!$E:$E,YEAR(G$3)) -> 0 | H23: =SUMIFS('Data Drop'!$G:$G,'Data Drop'!$H:$H,$E23, 'Data Drop'!$D:$D,MONTH(H$3),'Data Drop'!$E:$E,YEAR(H$3)) -> 0 | I23: =SUMIFS('Data Drop'!$G:$G,'Data Drop'!$H:$H,$E23, 'Data Drop'!$D:$D,MONTH(I$3),'Data Drop'!$E:$E,YEAR(I$3)) -> 0 | J23: =SUMIFS('Data Drop'!$G:$G,'Data Drop'!$H:$H,$E23, 'Data Drop'!$D:$D,MONTH(J$3),'Data Drop'!$E:$E,YEAR(J$3)) -> 0 | K23: =SUMIFS('Data Drop'!$G:$G,'Data Drop'!$H:$H,$E23, 'Data Drop'!$D:$D,MONTH(K$3),'Data Drop'!$E:$E,YEAR(K$3)) -> 0 | L23: =SUMIFS('Data Drop'!$G:$G,'Data Drop'!$H:$H,$E23, 'Data Drop'!$D:$D,MONTH(L$3),'Data Drop'!$E:$E,YEAR(L$3)) -> 0 | M23: =SUMIFS('Data Drop'!$G:$G,'Data Drop'!$H:$H,$E23, 'Data Drop'!$D:$D,MONTH(M$3),'Data Drop'!$E:$E,YEAR(M$3)) -> 0 | ... Q23: =SUMIFS('Data Drop'!$G:$G,'Data Drop'!$H:$H,$E23, 'Data Drop'!$D:$D,MONTH(Q$3),'Data Drop'!$E:$E,YEAR(Q$3)) -> 0 | T23: =SUM(F23:Q23) -> 0 | V23: =IFERROR(AVERAGEIF($F$2:$Q$2,">0",F23:Q23),"") -> 0 | X23: {=IFERROR(AVERAGE(IF($F$2:$P$2>0,$G23:$Q23/$F23:$P23-1)),"")} | Z23: {=IFERROR(AVERAGE($O23:$Q23/$N23:$P23-1),"")} | AB23: =IFERROR(AVERAGE($Q23/$P23-1),"") | AD23: =IFERROR(AVERAGE($Q23/$F23-1),"") | AF23: =SUM(O23:Q23)*4 -> 0 | AL23: Fire Prevention
E24: Licenses & Permits | F24: =SUMIFS('Data Drop'!$G:$G,'Data Drop'!$H:$H,$E24, 'Data Drop'!$D:$D,MONTH(F$3),'Data Drop'!$E:$E,YEAR(F$3)) -> 0 | G24: =SUMIFS('Data Drop'!$G:$G,'Data Drop'!$H:$H,$E24, 'Data Drop'!$D:$D,MONTH(G$3),'Data Drop'!$E:$E,YEAR(G$3)) -> 0 | H24: =SUMIFS('Data Drop'!$G:$G,'Data Drop'!$H:$H,$E24, 'Data Drop'!$D:$D,MONTH(H$3),'Data Drop'!$E:$E,YEAR(H$3)) -> 0 | I24: =SUMIFS('Data Drop'!$G:$G,'Data Drop'!$H:$H,$E24, 'Data Drop'!$D:$D,MONTH(I$3),'Data Drop'!$E:$E,YEAR(I$3)) -> 0 | J24: =SUMIFS('Data Drop'!$G:$G,'Data Drop'!$H:$H,$E24, 'Data Drop'!$D:$D,MONTH(J$3),'Data Drop'!$E:$E,YEAR(J$3)) -> 0 | K24: =SUMIFS('Data Drop'!$G:$G,'Data Drop'!$H:$H,$E24, 'Data Drop'!$D:$D,MONTH(K$3),'Data Drop'!$E:$E,YEAR(K$3)) -> 0 | L24: =SUMIFS('Data Drop'!$G:$G,'Data Drop'!$H:$H,$E24, 'Data Drop'!$D:$D,MONTH(L$3),'Data Drop'!$E:$E,YEAR(L$3)) -> 0 | M24: =SUMIFS('Data Drop'!$G:$G,'Data Drop'!$H:$H,$E24, 'Data Drop'!$D:$D,MONTH(M$3),'Data Drop'!$E:$E,YEAR(M$3)) -> 0 | ... Q24: =SUMIFS('Data Drop'!$G:$G,'Data Drop'!$H:$H,$E24, 'Data Drop'!$D:$D,MONTH(Q$3),'Data Drop'!$E:$E,YEAR(Q$3)) -> 0 | T24: =SUM(F24:Q24) -> 410.25 | V24: =IFERROR(AVERAGEIF($F$2:$Q$2,">0",F24:Q24),"") -> 34.1875 | X24: {=IFERROR(AVERAGE(IF($F$2:$P$2>0,$G24:$Q24/$F24:$P24-1)),"")} | Z24: {=IFERROR(AVERAGE($O24:$Q24/$N24:$P24-1),"")} | AB24: =IFERROR(AVERAGE($Q24/$P24-1),"") | AD24: =IFERROR(AVERAGE($Q24/$F24-1),"") | AF24: =SUM(O24:Q24)*4 -> 0 | AL24: Licenses & Permits
E25: Current Mgmt. Fee | F25: =SUMIFS('Data Drop'!$G:$G,'Data Drop'!$H:$H,$E25, 'Data Drop'!$D:$D,MONTH(F$3),'Data Drop'!$E:$E,YEAR(F$3)) -> 3057.99 | G25: =SUMIFS('Data Drop'!$G:$G,'Data Drop'!$H:$H,$E25, 'Data Drop'!$D:$D,MONTH(G$3),'Data Drop'!$E:$E,YEAR(G$3)) -> 3581.49 | H25: =SUMIFS('Data Drop'!$G:$G,'Data Drop'!$H:$H,$E25, 'Data Drop'!$D:$D,MONTH(H$3),'Data Drop'!$E:$E,YEAR(H$3)) -> 3012.73 | I25: =SUMIFS('Data Drop'!$G:$G,'Data Drop'!$H:$H,$E25, 'Data Drop'!$D:$D,MONTH(I$3),'Data Drop'!$E:$E,YEAR(I$3)) -> 3757.43 | J25: =SUMIFS('Data Drop'!$G:$G,'Data Drop'!$H:$H,$E25, 'Data Drop'!$D:$D,MONTH(J$3),'Data Drop'!$E:$E,YEAR(J$3)) -> 3574.19 | K25: =SUMIFS('Data Drop'!$G:$G,'Data Drop'!$H:$H,$E25, 'Data Drop'!$D:$D,MONTH(K$3),'Data Drop'!$E:$E,YEAR(K$3)) -> 3849.46 | L25: =SUMIFS('Data Drop'!$G:$G,'Data Drop'!$H:$H,$E25, 'Data Drop'!$D:$D,MONTH(L$3),'Data Drop'!$E:$E,YEAR(L$3)) -> 4059.72 | M25: =SUMIFS('Data Drop'!$G:$G,'Data Drop'!$H:$H,$E25, 'Data Drop'!$D:$D,MONTH(M$3),'Data Drop'!$E:$E,YEAR(M$3)) -> 4309.09 | ... Q25: =SUMIFS('Data Drop'!$G:$G,'Data Drop'!$H:$H,$E25, 'Data Drop'!$D:$D,MONTH(Q$3),'Data Drop'!$E:$E,YEAR(Q$3)) -> 4599.48 | T25: =SUM(F25:Q25) -> 46924.36 | V25: =IFERROR(AVERAGEIF($F$2:$Q$2,">0",F25:Q25),"") -> 3910.3633 | X25: {=IFERROR(AVERAGE(IF($F$2:$P$2>0,$G25:$Q25/$F25:$P25-1)),"")} -> 0.043158484 | Z25: {=IFERROR(AVERAGE($O25:$Q25/$N25:$P25-1),"")} -> 0.023129597 | AB25: =IFERROR(AVERAGE($Q25/$P25-1),"") -> -0.0052231688 | AD25: =IFERROR(AVERAGE($Q25/$F25-1),"") -> 0.50408602 | AF25: =SUM(O25:Q25)*4 -> 53627 | AL25: Currenl Mgmt. Fee
E26: STORE Mgmt. Fee | T26: =SUM(F26:Q26) -> 0 | V26: =IFERROR(AVERAGEIF($F$2:$Q$2,">0",F26:Q26),"") | X26: {=IFERROR(AVERAGE(IF($F$2:$P$2>0,$G26:$Q26/$F26:$P26-1)),"")} | Z26: {=IFERROR(AVERAGE($O26:$Q26/$N26:$P26-1),"")} | AB26: =IFERROR(AVERAGE($Q26/$P26-1),"") | AD26: =IFERROR(AVERAGE($Q26/$F26-1),"") | AF26: =SUM(O26:Q26)*4 -> 0 | AL26: STORE Management Fees
E27: Payroll | F27: =SUMIFS('Data Drop'!$G:$G,'Data Drop'!$H:$H,$E27, 'Data Drop'!$D:$D,MONTH(F$3),'Data Drop'!$E:$E,YEAR(F$3)) -> 7411.61 | G27: =SUMIFS('Data Drop'!$G:$G,'Data Drop'!$H:$H,$E27, 'Data Drop'!$D:$D,MONTH(G$3),'Data Drop'!$E:$E,YEAR(G$3)) -> 5951.64 | H27: =SUMIFS('Data Drop'!$G:$G,'Data Drop'!$H:$H,$E27, 'Data Drop'!$D:$D,MONTH(H$3),'Data Drop'!$E:$E,YEAR(H$3)) -> 7074.05 | I27: =SUMIFS('Data Drop'!$G:$G,'Data Drop'!$H:$H,$E27, 'Data Drop'!$D:$D,MONTH(I$3),'Data Drop'!$E:$E,YEAR(I$3)) -> 8733.74 | J27: =SUMIFS('Data Drop'!$G:$G,'Data Drop'!$H:$H,$E27, 'Data Drop'!$D:$D,MONTH(J$3),'Data Drop'!$E:$E,YEAR(J$3)) -> 8561.98 | K27: =SUMIFS('Data Drop'!$G:$G,'Data Drop'!$H:$H,$E27, 'Data Drop'!$D:$D,MONTH(K$3),'Data Drop'!$E:$E,YEAR(K$3)) -> 7791.67 | L27: =SUMIFS('Data Drop'!$G:$G,'Data Drop'!$H:$H,$E27, 'Data Drop'!$D:$D,MONTH(L$3),'Data Drop'!$E:$E,YEAR(L$3)) -> 8660.26 | M27: =SUMIFS('Data Drop'!$G:$G,'Data Drop'!$H:$H,$E27, 'Data Drop'!$D:$D,MONTH(M$3),'Data Drop'!$E:$E,YEAR(M$3)) -> 8146.46 | ... Q27: =SUMIFS('Data Drop'!$G:$G,'Data Drop'!$H:$H,$E27, 'Data Drop'!$D:$D,MONTH(Q$3),'Data Drop'!$E:$E,YEAR(Q$3)) -> 6888.22 | T27: =SUM(F27:Q27) -> 89884.31 | V27: =IFERROR(AVERAGEIF($F$2:$Q$2,">0",F27:Q27),"") -> 7490.3592 | X27: {=IFERROR(AVERAGE(IF($F$2:$P$2>0,$G27:$Q27/$F27:$P27-1)),"")} -> 0.0029907856 | Z27: {=IFERROR(AVERAGE($O27:$Q27/$N27:$P27-1),"")} -> 0.021373757 | AB27: =IFERROR(AVERAGE($Q27/$P27-1),"") -> -0.073911296 | AD27: =IFERROR(AVERAGE($Q27/$F27-1),"") -> -0.070617585 | AF27: =SUM(O27:Q27)*4 -> 84141.52 | AL27: Payroll
E28: Office Supplies | F28: =SUMIFS('Data Drop'!$G:$G,'Data Drop'!$H:$H,$E28, 'Data Drop'!$D:$D,MONTH(F$3),'Data Drop'!$E:$E,YEAR(F$3)) -> 464.39 | G28: =SUMIFS('Data Drop'!$G:$G,'Data Drop'!$H:$H,$E28, 'Data Drop'!$D:$D,MONTH(G$3),'Data Drop'!$E:$E,YEAR(G$3)) -> 3.77 | H28: =SUMIFS('Data Drop'!$G:$G,'Data Drop'!$H:$H,$E28, 'Data Drop'!$D:$D,MONTH(H$3),'Data Drop'!$E:$E,YEAR(H$3)) -> 162.69 | I28: =SUMIFS('Data Drop'!$G:$G,'Data Drop'!$H:$H,$E28, 'Data Drop'!$D:$D,MONTH(I$3),'Data Drop'!$E:$E,YEAR(I$3)) -> 155.28 | J28: =SUMIFS('Data Drop'!$G:$G,'Data Drop'!$H:$H,$E28, 'Data Drop'!$D:$D,MONTH(J$3),'Data Drop'!$E:$E,YEAR(J$3)) -> 55.44 | K28: =SUMIFS('Data Drop'!$G:$G,'Data Drop'!$H:$H,$E28, 'Data Drop'!$D:$D,MONTH(K$3),'Data Drop'!$E:$E,YEAR(K$3)) -> 79.73 | L28: =SUMIFS('Data Drop'!$G:$G,'Data Drop'!$H:$H,$E28, 'Data Drop'!$D:$D,MONTH(L$3),'Data Drop'!$E:$E,YEAR(L$3)) -> 477.39 | M28: =SUMIFS('Data Drop'!$G:$G,'Data Drop'!$H:$H,$E28, 'Data Drop'!$D:$D,MONTH(M$3),'Data Drop'!$E:$E,YEAR(M$3)) -> 54.14 | ... Q28: =SUMIFS('Data Drop'!$G:$G,'Data Drop'!$H:$H,$E28, 'Data Drop'!$D:$D,MONTH(Q$3),'Data Drop'!$E:$E,YEAR(Q$3)) -> 94.23 | T28: =SUM(F28:Q28) -> 1659.92 | V28: =IFERROR(AVERAGEIF($F$2:$Q$2,">0",F28:Q28),"") -> 138.32667 | X28: {=IFERROR(AVERAGE(IF($F$2:$P$2>0,$G28:$Q28/$F28:$P28-1)),"")} -> 5.7745486 | Z28: {=IFERROR(AVERAGE($O28:$Q28/$N28:$P28-1),"")} -> 6.0864055 | AB28: =IFERROR(AVERAGE($Q28/$P28-1),"") -> 1.1903766 | AD28: =IFERROR(AVERAGE($Q28/$F28-1),"") -> -0.79708865 | AF28: =SUM(O28:Q28)*4 -> 558.04 | AL28: Office Supplies
E29: Repairs & Maintenance | F29: =SUMIFS('Data Drop'!$G:$G,'Data Drop'!$H:$H,$E29, 'Data Drop'!$D:$D,MONTH(F$3),'Data Drop'!$E:$E,YEAR(F$3)) -> 1787.91 | G29: =SUMIFS('Data Drop'!$G:$G,'Data Drop'!$H:$H,$E29, 'Data Drop'!$D:$D,MONTH(G$3),'Data Drop'!$E:$E,YEAR(G$3)) -> 2478.26 | H29: =SUMIFS('Data Drop'!$G:$G,'Data Drop'!$H:$H,$E29, 'Data Drop'!$D:$D,MONTH(H$3),'Data Drop'!$E:$E,YEAR(H$3)) -> 1154.66 | I29: =SUMIFS('Data Drop'!$G:$G,'Data Drop'!$H:$H,$E29, 'Data Drop'!$D:$D,MONTH(I$3),'Data Drop'!$E:$E,YEAR(I$3)) -> 4197.65 | J29: =SUMIFS('Data Drop'!$G:$G,'Data Drop'!$H:$H,$E29, 'Data Drop'!$D:$D,MONTH(J$3),'Data Drop'!$E:$E,YEAR(J$3)) -> 4226.47 | K29: =SUMIFS('Data Drop'!$G:$G,'Data Drop'!$H:$H,$E29, 'Data Drop'!$D:$D,MONTH(K$3),'Data Drop'!$E:$E,YEAR(K$3)) -> 3614.14 | L29: =SUMIFS('Data Drop'!$G:$G,'Data Drop'!$H:$H,$E29, 'Data Drop'!$D:$D,MONTH(L$3),'Data Drop'!$E:$E,YEAR(L$3)) -> 5572.98 | M29: =SUMIFS('Data Drop'!$G:$G,'Data Drop'!$H:$H,$E29, 'Data Drop'!$D:$D,MONTH(M$3),'Data Drop'!$E:$E,YEAR(M$3)) -> 5344.8 | ... Q29: =SUMIFS('Data Drop'!$G:$G,'Data Drop'!$H:$H,$E29, 'Data Drop'!$D:$D,MONTH(Q$3),'Data Drop'!$E:$E,YEAR(Q$3)) -> 2511.82 | T29: =SUM(F29:Q29) -> 39787.63 | V29: =IFERROR(AVERAGEIF($F$2:$Q$2,">0",F29:Q29),"") -> 3315.6358 | X29: {=IFERROR(AVERAGE(IF($F$2:$P$2>0,$G29:$Q29/$F29:$P29-1)),"")} -> 0.29341556 | Z29: {=IFERROR(AVERAGE($O29:$Q29/$N29:$P29-1),"")} -> 0.3680813 | AB29: =IFERROR(AVERAGE($Q29/$P29-1),"") -> -0.42225534 | AD29: =IFERROR(AVERAGE($Q29/$F29-1),"") -> 0.40489175 | AF29: =SUM(O29:Q29)*4 -> 39809.6 | AL29: Repairs & Maintenance
E30: Security | F30: =SUMIFS('Data Drop'!$G:$G,'Data Drop'!$H:$H,$E30, 'Data Drop'!$D:$D,MONTH(F$3),'Data Drop'!$E:$E,YEAR(F$3)) -> 0 | G30: =SUMIFS('Data Drop'!$G:$G,'Data Drop'!$H:$H,$E30, 'Data Drop'!$D:$D,MONTH(G$3),'Data Drop'!$E:$E,YEAR(G$3)) -> 0 | H30: =SUMIFS('Data Drop'!$G:$G,'Data Drop'!$H:$H,$E30, 'Data Drop'!$D:$D,MONTH(H$3),'Data Drop'!$E:$E,YEAR(H$3)) -> 0 | I30: =SUMIFS('Data Drop'!$G:$G,'Data Drop'!$H:$H,$E30, 'Data Drop'!$D:$D,MONTH(I$3),'Data Drop'!$E:$E,YEAR(I$3)) -> 0 | J30: =SUMIFS('Data Drop'!$G:$G,'Data Drop'!$H:$H,$E30, 'Data Drop'!$D:$D,MONTH(J$3),'Data Drop'!$E:$E,YEAR(J$3)) -> 0 | K30: =SUMIFS('Data Drop'!$G:$G,'Data Drop'!$H:$H,$E30, 'Data Drop'!$D:$D,MONTH(K$3),'Data Drop'!$E:$E,YEAR(K$3)) -> 0 | L30: =SUMIFS('Data Drop'!$G:$G,'Data Drop'!$H:$H,$E30, 'Data Drop'!$D:$D,MONTH(L$3),'Data Drop'!$E:$E,YEAR(L$3)) -> 0 | M30: =SUMIFS('Data Drop'!$G:$G,'Data Drop'!$H:$H,$E30, 'Data Drop'!$D:$D,MONTH(M$3),'Data Drop'!$E:$E,YEAR(M$3)) -> 0 | ... Q30: =SUMIFS('Data Drop'!$G:$G,'Data Drop'!$H:$H,$E30, 'Data Drop'!$D:$D,MONTH(Q$3),'Data Drop'!$E:$E,YEAR(Q$3)) -> 0 | T30: =SUM(F30:Q30) -> 0 | V30: =IFERROR(AVERAGEIF($F$2:$Q$2,">0",F30:Q30),"") -> 0 | X30: {=IFERROR(AVERAGE(IF($F$2:$P$2>0,$G30:$Q30/$F30:$P30-1)),"")} | Z30: {=IFERROR(AVERAGE($O30:$Q30/$N30:$P30-1),"")} | AB30: =IFERROR(AVERAGE($Q30/$P30-1),"") | AD30: =IFERROR(AVERAGE($Q30/$F30-1),"") | AF30: =SUM(O30:Q30)*4 -> 0 | AL30: Security
E31: Retail Products | F31: =SUMIFS('Data Drop'!$G:$G,'Data Drop'!$H:$H,$E31, 'Data Drop'!$D:$D,MONTH(F$3),'Data Drop'!$E:$E,YEAR(F$3)) -> 352.63 | G31: =SUMIFS('Data Drop'!$G:$G,'Data Drop'!$H:$H,$E31, 'Data Drop'!$D:$D,MONTH(G$3),'Data Drop'!$E:$E,YEAR(G$3)) -> 212.59 | H31: =SUMIFS('Data Drop'!$G:$G,'Data Drop'!$H:$H,$E31, 'Data Drop'!$D:$D,MONTH(H$3),'Data Drop'!$E:$E,YEAR(H$3)) -> 288.38 | I31: =SUMIFS('Data Drop'!$G:$G,'Data Drop'!$H:$H,$E31, 'Data Drop'!$D:$D,MONTH(I$3),'Data Drop'!$E:$E,YEAR(I$3)) -> 351.82 | J31: =SUMIFS('Data Drop'!$G:$G,'Data Drop'!$H:$H,$E31, 'Data Drop'!$D:$D,MONTH(J$3),'Data Drop'!$E:$E,YEAR(J$3)) -> 237.58 | K31: =SUMIFS('Data Drop'!$G:$G,'Data Drop'!$H:$H,$E31, 'Data Drop'!$D:$D,MONTH(K$3),'Data Drop'!$E:$E,YEAR(K$3)) -> 182.07 | L31: =SUMIFS('Data Drop'!$G:$G,'Data Drop'!$H:$H,$E31, 'Data Drop'!$D:$D,MONTH(L$3),'Data Drop'!$E:$E,YEAR(L$3)) -> 418.25 | M31: =SUMIFS('Data Drop'!$G:$G,'Data Drop'!$H:$H,$E31, 'Data Drop'!$D:$D,MONTH(M$3),'Data Drop'!$E:$E,YEAR(M$3)) -> 275.06 | ... Q31: =SUMIFS('Data Drop'!$G:$G,'Data Drop'!$H:$H,$E31, 'Data Drop'!$D:$D,MONTH(Q$3),'Data Drop'!$E:$E,YEAR(Q$3)) -> 359.28 | T31: =SUM(F31:Q31) -> 3696.57 | V31: =IFERROR(AVERAGEIF($F$2:$Q$2,">0",F31:Q31),"") -> 308.0475 | X31: {=IFERROR(AVERAGE(IF($F$2:$P$2>0,$G31:$Q31/$F31:$P31-1)),"")} -> 0.10820541 | Z31: {=IFERROR(AVERAGE($O31:$Q31/$N31:$P31-1),"")} -> 0.17494489 | AB31: =IFERROR(AVERAGE($Q31/$P31-1),"") -> -0.24551125 | AD31: =IFERROR(AVERAGE($Q31/$F31-1),"") -> 0.018858293 | AF31: =SUM(O31:Q31)*4 -> 4313.96 | AL31: Retail Products
E32: Telephone & Internet | F32: =SUMIFS('Data Drop'!$G:$G,'Data Drop'!$H:$H,$E32, 'Data Drop'!$D:$D,MONTH(F$3),'Data Drop'!$E:$E,YEAR(F$3)) -> 6.21 | G32: =SUMIFS('Data Drop'!$G:$G,'Data Drop'!$H:$H,$E32, 'Data Drop'!$D:$D,MONTH(G$3),'Data Drop'!$E:$E,YEAR(G$3)) -> 3303.39 | H32: =SUMIFS('Data Drop'!$G:$G,'Data Drop'!$H:$H,$E32, 'Data Drop'!$D:$D,MONTH(H$3),'Data Drop'!$E:$E,YEAR(H$3)) -> 6.19 | I32: =SUMIFS('Data Drop'!$G:$G,'Data Drop'!$H:$H,$E32, 'Data Drop'!$D:$D,MONTH(I$3),'Data Drop'!$E:$E,YEAR(I$3)) -> 6.16 | J32: =SUMIFS('Data Drop'!$G:$G,'Data Drop'!$H:$H,$E32, 'Data Drop'!$D:$D,MONTH(J$3),'Data Drop'!$E:$E,YEAR(J$3)) -> 6.17 | K32: =SUMIFS('Data Drop'!$G:$G,'Data Drop'!$H:$H,$E32, 'Data Drop'!$D:$D,MONTH(K$3),'Data Drop'!$E:$E,YEAR(K$3)) -> 3271.3 | L32: =SUMIFS('Data Drop'!$G:$G,'Data Drop'!$H:$H,$E32, 'Data Drop'!$D:$D,MONTH(L$3),'Data Drop'!$E:$E,YEAR(L$3)) -> 6.04 | M32: =SUMIFS('Data Drop'!$G:$G,'Data Drop'!$H:$H,$E32, 'Data Drop'!$D:$D,MONTH(M$3),'Data Drop'!$E:$E,YEAR(M$3)) -> 841.6 | ... Q32: =SUMIFS('Data Drop'!$G:$G,'Data Drop'!$H:$H,$E32, 'Data Drop'!$D:$D,MONTH(Q$3),'Data Drop'!$E:$E,YEAR(Q$3)) -> 1645.42 | T32: =SUM(F32:Q32) -> 10913.51 | V32: =IFERROR(AVERAGEIF($F$2:$Q$2,">0",F32:Q32),"") -> 909.45917 | X32: {=IFERROR(AVERAGE(IF($F$2:$P$2>0,$G32:$Q32/$F32:$P32-1)),"")} -> 118.2483 | Z32: {=IFERROR(AVERAGE($O32:$Q32/$N32:$P32-1),"")} -> 34.69658 | AB32: =IFERROR(AVERAGE($Q32/$P32-1),"") -> 105.22466 | AD32: =IFERROR(AVERAGE($Q32/$F32-1),"") -> 263.96296 | AF32: =SUM(O32:Q32)*4 -> 9954.24 | AL32: Telephone & Internet
E33: Software | F33: =SUMIFS('Data Drop'!$G:$G,'Data Drop'!$H:$H,$E33, 'Data Drop'!$D:$D,MONTH(F$3),'Data Drop'!$E:$E,YEAR(F$3)) -> 1427.85 | G33: =SUMIFS('Data Drop'!$G:$G,'Data Drop'!$H:$H,$E33, 'Data Drop'!$D:$D,MONTH(G$3),'Data Drop'!$E:$E,YEAR(G$3)) -> 1408.48 | H33: =SUMIFS('Data Drop'!$G:$G,'Data Drop'!$H:$H,$E33, 'Data Drop'!$D:$D,MONTH(H$3),'Data Drop'!$E:$E,YEAR(H$3)) -> 1439.57 | I33: =SUMIFS('Data Drop'!$G:$G,'Data Drop'!$H:$H,$E33, 'Data Drop'!$D:$D,MONTH(I$3),'Data Drop'!$E:$E,YEAR(I$3)) -> 1439.94 | J33: =SUMIFS('Data Drop'!$G:$G,'Data Drop'!$H:$H,$E33, 'Data Drop'!$D:$D,MONTH(J$3),'Data Drop'!$E:$E,YEAR(J$3)) -> 1463.18 | K33: =SUMIFS('Data Drop'!$G:$G,'Data Drop'!$H:$H,$E33, 'Data Drop'!$D:$D,MONTH(K$3),'Data Drop'!$E:$E,YEAR(K$3)) -> 1425.27 | L33: =SUMIFS('Data Drop'!$G:$G,'Data Drop'!$H:$H,$E33, 'Data Drop'!$D:$D,MONTH(L$3),'Data Drop'!$E:$E,YEAR(L$3)) -> 1453.01 | M33: =SUMIFS('Data Drop'!$G:$G,'Data Drop'!$H:$H,$E33, 'Data Drop'!$D:$D,MONTH(M$3),'Data Drop'!$E:$E,YEAR(M$3)) -> 1470.88 | ... Q33: =SUMIFS('Data Drop'!$G:$G,'Data Drop'!$H:$H,$E33, 'Data Drop'!$D:$D,MONTH(Q$3),'Data Drop'!$E:$E,YEAR(Q$3)) -> 1408.65 | T33: =SUM(F33:Q33) -> 17300.16 | V33: =IFERROR(AVERAGEIF($F$2:$Q$2,">0",F33:Q33),"") -> 1441.68 | X33: {=IFERROR(AVERAGE(IF($F$2:$P$2>0,$G33:$Q33/$F33:$P33-1)),"")} -> -0.0010725366 | Z33: {=IFERROR(AVERAGE($O33:$Q33/$N33:$P33-1),"")} -> -0.0089928772 | AB33: =IFERROR(AVERAGE($Q33/$P33-1),"") -> -0.031203147 | AD33: =IFERROR(AVERAGE($Q33/$F33-1),"") -> -0.013446791 | AF33: =SUM(O33:Q33)*4 -> 17296.04 | AL33: Software
E34: Bank Charges | F34: =SUMIFS('Data Drop'!$G:$G,'Data Drop'!$H:$H,$E34, 'Data Drop'!$D:$D,MONTH(F$3),'Data Drop'!$E:$E,YEAR(F$3)) -> 0 | G34: =SUMIFS('Data Drop'!$G:$G,'Data Drop'!$H:$H,$E34, 'Data Drop'!$D:$D,MONTH(G$3),'Data Drop'!$E:$E,YEAR(G$3)) -> 0 | H34: =SUMIFS('Data Drop'!$G:$G,'Data Drop'!$H:$H,$E34, 'Data Drop'!$D:$D,MONTH(H$3),'Data Drop'!$E:$E,YEAR(H$3)) -> 0 | I34: =SUMIFS('Data Drop'!$G:$G,'Data Drop'!$H:$H,$E34, 'Data Drop'!$D:$D,MONTH(I$3),'Data Drop'!$E:$E,YEAR(I$3)) -> 0 | J34: =SUMIFS('Data Drop'!$G:$G,'Data Drop'!$H:$H,$E34, 'Data Drop'!$D:$D,MONTH(J$3),'Data Drop'!$E:$E,YEAR(J$3)) -> 0 | K34: =SUMIFS('Data Drop'!$G:$G,'Data Drop'!$H:$H,$E34, 'Data Drop'!$D:$D,MONTH(K$3),'Data Drop'!$E:$E,YEAR(K$3)) -> 0 | L34: =SUMIFS('Data Drop'!$G:$G,'Data Drop'!$H:$H,$E34, 'Data Drop'!$D:$D,MONTH(L$3),'Data Drop'!$E:$E,YEAR(L$3)) -> 0 | M34: =SUMIFS('Data Drop'!$G:$G,'Data Drop'!$H:$H,$E34, 'Data Drop'!$D:$D,MONTH(M$3),'Data Drop'!$E:$E,YEAR(M$3)) -> 0 | ... Q34: =SUMIFS('Data Drop'!$G:$G,'Data Drop'!$H:$H,$E34, 'Data Drop'!$D:$D,MONTH(Q$3),'Data Drop'!$E:$E,YEAR(Q$3)) -> 0 | T34: =SUM(F34:Q34) -> 0 | V34: =IFERROR(AVERAGEIF($F$2:$Q$2,">0",F34:Q34),"") -> 0 | X34: {=IFERROR(AVERAGE(IF($F$2:$P$2>0,$G34:$Q34/$F34:$P34-1)),"")} | Z34: {=IFERROR(AVERAGE($O34:$Q34/$N34:$P34-1),"")} | AB34: =IFERROR(AVERAGE($Q34/$P34-1),"") | AD34: =IFERROR(AVERAGE($Q34/$F34-1),"") | AF34: =SUM(O34:Q34)*4 -> 0 | AL34: Bank Charges
E35: Prof Fees - Legal/Acctg | F35: =SUMIFS('Data Drop'!$G:$G,'Data Drop'!$H:$H,$E35, 'Data Drop'!$D:$D,MONTH(F$3),'Data Drop'!$E:$E,YEAR(F$3)) -> 101.4 | G35: =SUMIFS('Data Drop'!$G:$G,'Data Drop'!$H:$H,$E35, 'Data Drop'!$D:$D,MONTH(G$3),'Data Drop'!$E:$E,YEAR(G$3)) -> 264.15 | H35: =SUMIFS('Data Drop'!$G:$G,'Data Drop'!$H:$H,$E35, 'Data Drop'!$D:$D,MONTH(H$3),'Data Drop'!$E:$E,YEAR(H$3)) -> 204.86 | I35: =SUMIFS('Data Drop'!$G:$G,'Data Drop'!$H:$H,$E35, 'Data Drop'!$D:$D,MONTH(I$3),'Data Drop'!$E:$E,YEAR(I$3)) -> 152.38 | J35: =SUMIFS('Data Drop'!$G:$G,'Data Drop'!$H:$H,$E35, 'Data Drop'!$D:$D,MONTH(J$3),'Data Drop'!$E:$E,YEAR(J$3)) -> 284.61 | K35: =SUMIFS('Data Drop'!$G:$G,'Data Drop'!$H:$H,$E35, 'Data Drop'!$D:$D,MONTH(K$3),'Data Drop'!$E:$E,YEAR(K$3)) -> 42.5 | L35: =SUMIFS('Data Drop'!$G:$G,'Data Drop'!$H:$H,$E35, 'Data Drop'!$D:$D,MONTH(L$3),'Data Drop'!$E:$E,YEAR(L$3)) -> 158 | M35: =SUMIFS('Data Drop'!$G:$G,'Data Drop'!$H:$H,$E35, 'Data Drop'!$D:$D,MONTH(M$3),'Data Drop'!$E:$E,YEAR(M$3)) -> 50.69 | ... Q35: =SUMIFS('Data Drop'!$G:$G,'Data Drop'!$H:$H,$E35, 'Data Drop'!$D:$D,MONTH(Q$3),'Data Drop'!$E:$E,YEAR(Q$3)) -> 163.16 | T35: =SUM(F35:Q35) -> 1940.76 | V35: =IFERROR(AVERAGEIF($F$2:$Q$2,">0",F35:Q35),"") -> 161.73 | X35: {=IFERROR(AVERAGE(IF($F$2:$P$2>0,$G35:$Q35/$F35:$P35-1)),"")} -> 0.83825257 | Z35: {=IFERROR(AVERAGE($O35:$Q35/$N35:$P35-1),"")} -> 0.61628887 | AB35: =IFERROR(AVERAGE($Q35/$P35-1),"") -> 2.8390588 | AD35: =IFERROR(AVERAGE($Q35/$F35-1),"") -> 0.60907298 | AF35: =SUM(O35:Q35)*4 -> 1675.96 | AL35: Prof Fees - Legal/Acctg
E36: Utilities | F36: =SUMIFS('Data Drop'!$G:$G,'Data Drop'!$H:$H,$E36, 'Data Drop'!$D:$D,MONTH(F$3),'Data Drop'!$E:$E,YEAR(F$3)) -> 835 | G36: =SUMIFS('Data Drop'!$G:$G,'Data Drop'!$H:$H,$E36, 'Data Drop'!$D:$D,MONTH(G$3),'Data Drop'!$E:$E,YEAR(G$3)) -> 0 | H36: =SUMIFS('Data Drop'!$G:$G,'Data Drop'!$H:$H,$E36, 'Data Drop'!$D:$D,MONTH(H$3),'Data Drop'!$E:$E,YEAR(H$3)) -> 0 | I36: =SUMIFS('Data Drop'!$G:$G,'Data Drop'!$H:$H,$E36, 'Data Drop'!$D:$D,MONTH(I$3),'Data Drop'!$E:$E,YEAR(I$3)) -> 0 | J36: =SUMIFS('Data Drop'!$G:$G,'Data Drop'!$H:$H,$E36, 'Data Drop'!$D:$D,MONTH(J$3),'Data Drop'!$E:$E,YEAR(J$3)) -> 0 | K36: =SUMIFS('Data Drop'!$G:$G,'Data Drop'!$H:$H,$E36, 'Data Drop'!$D:$D,MONTH(K$3),'Data Drop'!$E:$E,YEAR(K$3)) -> 9037.35 | L36: =SUMIFS('Data Drop'!$G:$G,'Data Drop'!$H:$H,$E36, 'Data Drop'!$D:$D,MONTH(L$3),'Data Drop'!$E:$E,YEAR(L$3)) -> 3057.52 | M36: =SUMIFS('Data Drop'!$G:$G,'Data Drop'!$H:$H,$E36, 'Data Drop'!$D:$D,MONTH(M$3),'Data Drop'!$E:$E,YEAR(M$3)) -> 3231.46 | ... Q36: =SUMIFS('Data Drop'!$G:$G,'Data Drop'!$H:$H,$E36, 'Data Drop'!$D:$D,MONTH(Q$3),'Data Drop'!$E:$E,YEAR(Q$3)) -> 2948.17 | T36: =SUM(F36:Q36) -> 28122.84 | V36: =IFERROR(AVERAGEIF($F$2:$Q$2,">0",F36:Q36),"") -> 2343.57 | X36: {=IFERROR(AVERAGE(IF($F$2:$P$2>0,$G36:$Q36/$F36:$P36-1)),"")} | Z36: {=IFERROR(AVERAGE($O36:$Q36/$N36:$P36-1),"")} -> 0.0063554804 | AB36: =IFERROR(AVERAGE($Q36/$P36-1),"") -> -0.08389292 | AD36: =IFERROR(AVERAGE($Q36/$F36-1),"") -> 2.5307425 | AF36: =SUM(O36:Q36)*4 -> 36152.52 | AL36: Utilities
E37: Insurance | F37: =SUMIFS('Data Drop'!$G:$G,'Data Drop'!$H:$H,$E37, 'Data Drop'!$D:$D,MONTH(F$3),'Data Drop'!$E:$E,YEAR(F$3)) -> 0 | G37: =SUMIFS('Data Drop'!$G:$G,'Data Drop'!$H:$H,$E37, 'Data Drop'!$D:$D,MONTH(G$3),'Data Drop'!$E:$E,YEAR(G$3)) -> 0 | H37: =SUMIFS('Data Drop'!$G:$G,'Data Drop'!$H:$H,$E37, 'Data Drop'!$D:$D,MONTH(H$3),'Data Drop'!$E:$E,YEAR(H$3)) -> 0 | I37: =SUMIFS('Data Drop'!$G:$G,'Data Drop'!$H:$H,$E37, 'Data Drop'!$D:$D,MONTH(I$3),'Data Drop'!$E:$E,YEAR(I$3)) -> 0 | J37: =SUMIFS('Data Drop'!$G:$G,'Data Drop'!$H:$H,$E37, 'Data Drop'!$D:$D,MONTH(J$3),'Data Drop'!$E:$E,YEAR(J$3)) -> 0 | K37: =SUMIFS('Data Drop'!$G:$G,'Data Drop'!$H:$H,$E37, 'Data Drop'!$D:$D,MONTH(K$3),'Data Drop'!$E:$E,YEAR(K$3)) -> 0 | L37: =SUMIFS('Data Drop'!$G:$G,'Data Drop'!$H:$H,$E37, 'Data Drop'!$D:$D,MONTH(L$3),'Data Drop'!$E:$E,YEAR(L$3)) -> 0 | M37: =SUMIFS('Data Drop'!$G:$G,'Data Drop'!$H:$H,$E37, 'Data Drop'!$D:$D,MONTH(M$3),'Data Drop'!$E:$E,YEAR(M$3)) -> 0 | ... Q37: =SUMIFS('Data Drop'!$G:$G,'Data Drop'!$H:$H,$E37, 'Data Drop'!$D:$D,MONTH(Q$3),'Data Drop'!$E:$E,YEAR(Q$3)) -> 0 | T37: =SUM(F37:Q37) -> 0 | V37: =IFERROR(AVERAGEIF($F$2:$Q$2,">0",F37:Q37),"") -> 0 | X37: {=IFERROR(AVERAGE(IF($F$2:$P$2>0,$G37:$Q37/$F37:$P37-1)),"")} | Z37: {=IFERROR(AVERAGE($O37:$Q37/$N37:$P37-1),"")} | AB37: =IFERROR(AVERAGE($Q37/$P37-1),"") | AD37: =IFERROR(AVERAGE($Q37/$F37-1),"") | AF37: =SUM(O37:Q37)*4 -> 0 | AL37: Insurance
E38: Property Taxes | F38: =SUMIFS('Data Drop'!$G:$G,'Data Drop'!$H:$H,$E38, 'Data Drop'!$D:$D,MONTH(F$3),'Data Drop'!$E:$E,YEAR(F$3)) -> 0 | G38: =SUMIFS('Data Drop'!$G:$G,'Data Drop'!$H:$H,$E38, 'Data Drop'!$D:$D,MONTH(G$3),'Data Drop'!$E:$E,YEAR(G$3)) -> 0 | H38: =SUMIFS('Data Drop'!$G:$G,'Data Drop'!$H:$H,$E38, 'Data Drop'!$D:$D,MONTH(H$3),'Data Drop'!$E:$E,YEAR(H$3)) -> 0 | I38: =SUMIFS('Data Drop'!$G:$G,'Data Drop'!$H:$H,$E38, 'Data Drop'!$D:$D,MONTH(I$3),'Data Drop'!$E:$E,YEAR(I$3)) -> 0 | J38: =SUMIFS('Data Drop'!$G:$G,'Data Drop'!$H:$H,$E38, 'Data Drop'!$D:$D,MONTH(J$3),'Data Drop'!$E:$E,YEAR(J$3)) -> 0 | K38: =SUMIFS('Data Drop'!$G:$G,'Data Drop'!$H:$H,$E38, 'Data Drop'!$D:$D,MONTH(K$3),'Data Drop'!$E:$E,YEAR(K$3)) -> 0 | L38: =SUMIFS('Data Drop'!$G:$G,'Data Drop'!$H:$H,$E38, 'Data Drop'!$D:$D,MONTH(L$3),'Data Drop'!$E:$E,YEAR(L$3)) -> 0 | M38: =SUMIFS('Data Drop'!$G:$G,'Data Drop'!$H:$H,$E38, 'Data Drop'!$D:$D,MONTH(M$3),'Data Drop'!$E:$E,YEAR(M$3)) -> 0 | ... Q38: =SUMIFS('Data Drop'!$G:$G,'Data Drop'!$H:$H,$E38, 'Data Drop'!$D:$D,MONTH(Q$3),'Data Drop'!$E:$E,YEAR(Q$3)) -> 0 | T38: =SUM(F38:Q38) -> 0 | V38: =IFERROR(AVERAGEIF($F$2:$Q$2,">0",F38:Q38),"") -> 0 | X38: {=IFERROR(AVERAGE(IF($F$2:$P$2>0,$G38:$Q38/$F38:$P38-1)),"")} | Z38: {=IFERROR(AVERAGE($O38:$Q38/$N38:$P38-1),"")} | AB38: =IFERROR(AVERAGE($Q38/$P38-1),"") | AD38: =IFERROR(AVERAGE($Q38/$F38-1),"") | AF38: =SUM(O38:Q38)*4 -> 0
E39: Other Expense | F39: =SUMIFS('Data Drop'!$G:$G,'Data Drop'!$H:$H,$E39, 'Data Drop'!$D:$D,MONTH(F$3),'Data Drop'!$E:$E,YEAR(F$3)) -> 0 | G39: =SUMIFS('Data Drop'!$G:$G,'Data Drop'!$H:$H,$E39, 'Data Drop'!$D:$D,MONTH(G$3),'Data Drop'!$E:$E,YEAR(G$3)) -> 0 | H39: =SUMIFS('Data Drop'!$G:$G,'Data Drop'!$H:$H,$E39, 'Data Drop'!$D:$D,MONTH(H$3),'Data Drop'!$E:$E,YEAR(H$3)) -> 0 | I39: =SUMIFS('Data Drop'!$G:$G,'Data Drop'!$H:$H,$E39, 'Data Drop'!$D:$D,MONTH(I$3),'Data Drop'!$E:$E,YEAR(I$3)) -> 0 | J39: =SUMIFS('Data Drop'!$G:$G,'Data Drop'!$H:$H,$E39, 'Data Drop'!$D:$D,MONTH(J$3),'Data Drop'!$E:$E,YEAR(J$3)) -> 0 | K39: =SUMIFS('Data Drop'!$G:$G,'Data Drop'!$H:$H,$E39, 'Data Drop'!$D:$D,MONTH(K$3),'Data Drop'!$E:$E,YEAR(K$3)) -> 0 | L39: =SUMIFS('Data Drop'!$G:$G,'Data Drop'!$H:$H,$E39, 'Data Drop'!$D:$D,MONTH(L$3),'Data Drop'!$E:$E,YEAR(L$3)) -> 0 | M39: =SUMIFS('Data Drop'!$G:$G,'Data Drop'!$H:$H,$E39, 'Data Drop'!$D:$D,MONTH(M$3),'Data Drop'!$E:$E,YEAR(M$3)) -> 0 | ... Q39: =SUMIFS('Data Drop'!$G:$G,'Data Drop'!$H:$H,$E39, 'Data Drop'!$D:$D,MONTH(Q$3),'Data Drop'!$E:$E,YEAR(Q$3)) -> 0 | T39: =SUM(F39:Q39) -> 0 | V39: =IFERROR(AVERAGEIF($F$2:$Q$2,">0",F39:Q39),"") -> 0 | X39: {=IFERROR(AVERAGE(IF($F$2:$P$2>0,$G39:$Q39/$F39:$P39-1)),"")} | Z39: {=IFERROR(AVERAGE($O39:$Q39/$N39:$P39-1),"")} | AB39: =IFERROR(AVERAGE($Q39/$P39-1),"") | AD39: =IFERROR(AVERAGE($Q39/$F39-1),"") | AF39: =SUM(O39:Q39)*4 -> 0 | AL39: Other Expense
T40: =SUM(F40:Q40) -> 0 | V40: =IFERROR(AVERAGEIF($F$2:$Q$2,">0",F40:Q40),"") | X40: {=IFERROR(AVERAGE(IF($F$2:$P$2>0,$G40:$Q40/$F40:$P40-1)),"")} | Z40: {=IFERROR(AVERAGE($O40:$Q40/$N40:$P40-1),"")} | AB40: =IFERROR(AVERAGE($Q40/$P40-1),"") | AD40: =IFERROR(AVERAGE($Q40/$F40-1),"") | AF40: =SUM(O40:Q40)*4 -> 0
B41: Check: Total Operating Expense | E41: Total Operating Expense | F41: =SUM(F20:F39) -> 18839.05 | G41: =SUM(G20:G39) -> 21726.78 | H41: =SUM(H20:H39) -> 17677.27 | I41: =SUM(I20:I39) -> 24117.51 | J41: =SUM(J20:J39) -> 22948.64 | K41: =SUM(K20:K39) -> 33105.96 | L41: =SUM(L20:L39) -> 28472.7 | M41: =SUM(M20:M39) -> 28358.15 | ... Q41: =SUM(Q20:Q39) -> 24338.47 | T41: =SUM(F41:Q41) -> 288831.47 | V41: =IFERROR(AVERAGEIF($F$2:$Q$2,">0",F41:Q41),"") -> 24069.289 | X41: {=IFERROR(AVERAGE(IF($F$2:$P$2>0,$G41:$Q41/$F41:$P41-1)),"")} -> 0.042427214 | Z41: {=IFERROR(AVERAGE($O41:$Q41/$N41:$P41-1),"")} -> 0.039653559 | AB41: =IFERROR(AVERAGE($Q41/$P41-1),"") -> -0.021751521 | AD41: =IFERROR(AVERAGE($Q41/$F41-1),"") -> 0.29191599 | AF41: =SUM(O41:Q41)*4 -> 287413.16 | AL41: Total Operating Expense
T42: =SUM(F42:Q42) -> 0 | V42: =IFERROR(AVERAGEIF($F$2:$Q$2,">0",F42:Q42),"") | X42: {=IFERROR(AVERAGE(IF($F$2:$P$2>0,$G42:$Q42/$F42:$P42-1)),"")} | Z42: {=IFERROR(AVERAGE($O42:$Q42/$N42:$P42-1),"")} | AB42: =IFERROR(AVERAGE($Q42/$P42-1),"") | AD42: =IFERROR(AVERAGE($Q42/$F42-1),"") | AF42: =SUM(O42:Q42)*4 -> 0
B43: Check: Net Operating Income | E43: Net Operating Income | F43: =F17-F41 -> 28284.56 | G43: =G17-G41 -> 33490.07 | H43: =H17-H41 -> 43409.45 | I43: =I17-I41 -> 44290.59 | J43: =J17-J41 -> 49699.69 | K43: =K17-K41 -> 46149.19 | L43: =L17-L41 -> 54830.19 | M43: =M17-M41 -> 55741.41 | ... Q43: =Q17-Q41 -> 73151.14 | T43: =SUM(F43:Q43) -> 634336.54 | V43: =IFERROR(AVERAGEIF($F$2:$Q$2,">0",F43:Q43),"") -> 52861.378 | X43: {=IFERROR(AVERAGE(IF($F$2:$P$2>0,$G43:$Q43/$F43:$P43-1)),"")} -> 0.095551145 | Z43: {=IFERROR(AVERAGE($O43:$Q43/$N43:$P43-1),"")} -> 0.025999306 | AB43: =IFERROR(AVERAGE($Q43/$P43-1),"") -> 0.071180638 | AD43: =IFERROR(AVERAGE($Q43/$F43-1),"") -> 1.586257 | AF43: =SUM(O43:Q43)*4 -> 842389.12 | AL43: Net Operating Income
F48: =F36*1.02 -> 851.7 | G48: =G36*1.02 -> 0 | H48: =H36*1.02 -> 0 | I48: =I36*1.02 -> 0 | J48: =J36*1.02 -> 0 | K48: =K36*1.02 -> 9218.097 | L48: =L36*1.02 -> 3118.6704 | M48: =M36*1.02 -> 3296.0892 | ... Q48: =Q36*1.02 -> 3007.1334
E49: N/A
E50: Total
E53: Management Fee rate | F53: =F25/F17 -> 0.064892949 | G53: =G25/G17 -> 0.064862266 | H53: =H25/H17 -> 0.049318903 | I53: =I25/I17 -> 0.054926683 | J53: =J25/J17 -> 0.049198516 | K53: =K25/K17 -> 0.048570471 | L53: =L25/L17 -> 0.048734444 | M53: =M25/M17 -> 0.051237961 | ... Q53: =Q25/Q17 -> 0.047179181
E54: Average | F54: =AVERAGE(G53:Q53) -> 0.050673548
E55: CC Fee | F55: =F21/F17 -> 0.01492861 | G55: =G21/G17 -> 0.013703788 | H55: =H21/H17 -> 0.01443718 | I55: =I21/I17 -> 0.015169402 | J55: =J21/J17 -> 0.014205007 | K55: =K21/K17 -> 0.013738792 | L55: =L21/L17 -> 0.014280657 | M55: =M21/M17 -> 0.013710654 | ... Q55: =Q21/Q17 -> 0.015228187
E56: Average | F56: =AVERAGE(F55:Q55) -> 0.014429716
B58: Balance Check
B60: Net Operating Income | F60: =SUMIFS('Data Drop'!$G:$G,'Data Drop'!$I:$I,$B60, 'Data Drop'!$D:$D,MONTH(F$3),'Data Drop'!$E:$E,YEAR(F$3)) -> 28284.56 | G60: =SUMIFS('Data Drop'!$G:$G,'Data Drop'!$I:$I,$B60, 'Data Drop'!$D:$D,MONTH(G$3),'Data Drop'!$E:$E,YEAR(G$3)) -> 33490.07 | H60: =SUMIFS('Data Drop'!$G:$G,'Data Drop'!$I:$I,$B60, 'Data Drop'!$D:$D,MONTH(H$3),'Data Drop'!$E:$E,YEAR(H$3)) -> 43409.45 | I60: =SUMIFS('Data Drop'!$G:$G,'Data Drop'!$I:$I,$B60, 'Data Drop'!$D:$D,MONTH(I$3),'Data Drop'!$E:$E,YEAR(I$3)) -> 44290.59 | J60: =SUMIFS('Data Drop'!$G:$G,'Data Drop'!$I:$I,$B60, 'Data Drop'!$D:$D,MONTH(J$3),'Data Drop'!$E:$E,YEAR(J$3)) -> 49699.69 | K60: =SUMIFS('Data Drop'!$G:$G,'Data Drop'!$I:$I,$B60, 'Data Drop'!$D:$D,MONTH(K$3),'Data Drop'!$E:$E,YEAR(K$3)) -> 46149.19 | L60: =SUMIFS('Data Drop'!$G:$G,'Data Drop'!$I:$I,$B60, 'Data Drop'!$D:$D,MONTH(L$3),'Data Drop'!$E:$E,YEAR(L$3)) -> 54830.19 | M60: =SUMIFS('Data Drop'!$G:$G,'Data Drop'!$I:$I,$B60, 'Data Drop'!$D:$D,MONTH(M$3),'Data Drop'!$E:$E,YEAR(M$3)) -> 55741.41 | ... Q60: =SUMIFS('Data Drop'!$G:$G,'Data Drop'!$I:$I,$B60, 'Data Drop'!$D:$D,MONTH(Q$3),'Data Drop'!$E:$E,YEAR(Q$3)) -> 73151.14
B61: Net Operating Income (P-Builder) | F61: =F43 -> 28284.56 | G61: =G43 -> 33490.07 | H61: =H43 -> 43409.45 | I61: =I43 -> 44290.59 | J61: =J43 -> 49699.69 | K61: =K43 -> 46149.19 | L61: =L43 -> 54830.19 | M61: =M43 -> 55741.41 | ... Q61: =Q43 -> 73151.14
E62: Current Tenant Protection Split | F62: =F60-F61 -> 0 | G62: =G60-G61 -> 0 | H62: =H60-H61 -> 0 | I62: =I60-I61 -> 0 | J62: =J60-J61 -> 0 | K62: =K60-K61 -> 0 | L62: =L60-L61 -> 0 | M62: =M60-M61 -> 0 | ... Q62: =Q60-Q61 -> 0
B65: Net Rental Income | F65: =SUMIFS('Data Drop'!$G:$G,'Data Drop'!$I:$I,$B65, 'Data Drop'!$D:$D,MONTH(F$3),'Data Drop'!$E:$E,YEAR(F$3)) -> 41324.65 | G65: =SUMIFS('Data Drop'!$G:$G,'Data Drop'!$I:$I,$B65, 'Data Drop'!$D:$D,MONTH(G$3),'Data Drop'!$E:$E,YEAR(G$3)) -> 48906.56 | H65: =SUMIFS('Data Drop'!$G:$G,'Data Drop'!$I:$I,$B65, 'Data Drop'!$D:$D,MONTH(H$3),'Data Drop'!$E:$E,YEAR(H$3)) -> 54138.43 | I65: =SUMIFS('Data Drop'!$G:$G,'Data Drop'!$I:$I,$B65, 'Data Drop'!$D:$D,MONTH(I$3),'Data Drop'!$E:$E,YEAR(I$3)) -> 60857.87 | J65: =SUMIFS('Data Drop'!$G:$G,'Data Drop'!$I:$I,$B65, 'Data Drop'!$D:$D,MONTH(J$3),'Data Drop'!$E:$E,YEAR(J$3)) -> 65220.38 | K65: =SUMIFS('Data Drop'!$G:$G,'Data Drop'!$I:$I,$B65, 'Data Drop'!$D:$D,MONTH(K$3),'Data Drop'!$E:$E,YEAR(K$3)) -> 72813.54 | L65: =SUMIFS('Data Drop'!$G:$G,'Data Drop'!$I:$I,$B65, 'Data Drop'!$D:$D,MONTH(L$3),'Data Drop'!$E:$E,YEAR(L$3)) -> 75484.5 | M65: =SUMIFS('Data Drop'!$G:$G,'Data Drop'!$I:$I,$B65, 'Data Drop'!$D:$D,MONTH(M$3),'Data Drop'!$E:$E,YEAR(M$3)) -> 77101.22 | ... Q65: =SUMIFS('Data Drop'!$G:$G,'Data Drop'!$I:$I,$B65, 'Data Drop'!$D:$D,MONTH(Q$3),'Data Drop'!$E:$E,YEAR(Q$3)) -> 88458.82
F66: =F65-F8 -> 0 | G66: =G65-G8 -> 0 | H66: =H65-H8 -> 0 | I66: =I65-I8 -> 0 | J66: =J65-J8 -> 0 | K66: =K65-K8 -> 0 | L66: =L65-L8 -> 0 | M66: =M65-M8 -> 0 | ... Q66: =Q65-Q8 -> 0
B69: Total Operating Expense | F69: =SUMIFS('Data Drop'!$G:$G,'Data Drop'!$I:$I,$B69, 'Data Drop'!$D:$D,MONTH(F$3),'Data Drop'!$E:$E,YEAR(F$3)) -> 18839.05 | G69: =SUMIFS('Data Drop'!$G:$G,'Data Drop'!$I:$I,$B69, 'Data Drop'!$D:$D,MONTH(G$3),'Data Drop'!$E:$E,YEAR(G$3)) -> 21726.78 | H69: =SUMIFS('Data Drop'!$G:$G,'Data Drop'!$I:$I,$B69, 'Data Drop'!$D:$D,MONTH(H$3),'Data Drop'!$E:$E,YEAR(H$3)) -> 17677.27 | I69: =SUMIFS('Data Drop'!$G:$G,'Data Drop'!$I:$I,$B69, 'Data Drop'!$D:$D,MONTH(I$3),'Data Drop'!$E:$E,YEAR(I$3)) -> 24117.51 | J69: =SUMIFS('Data Drop'!$G:$G,'Data Drop'!$I:$I,$B69, 'Data Drop'!$D:$D,MONTH(J$3),'Data Drop'!$E:$E,YEAR(J$3)) -> 22948.64 | K69: =SUMIFS('Data Drop'!$G:$G,'Data Drop'!$I:$I,$B69, 'Data Drop'!$D:$D,MONTH(K$3),'Data Drop'!$E:$E,YEAR(K$3)) -> 33105.96 | L69: =SUMIFS('Data Drop'!$G:$G,'Data Drop'!$I:$I,$B69, 'Data Drop'!$D:$D,MONTH(L$3),'Data Drop'!$E:$E,YEAR(L$3)) -> 28472.7 | M69: =SUMIFS('Data Drop'!$G:$G,'Data Drop'!$I:$I,$B69, 'Data Drop'!$D:$D,MONTH(M$3),'Data Drop'!$E:$E,YEAR(M$3)) -> 28358.15 | ... Q69: =SUMIFS('Data Drop'!$G:$G,'Data Drop'!$I:$I,$B69, 'Data Drop'!$D:$D,MONTH(Q$3),'Data Drop'!$E:$E,YEAR(Q$3)) -> 24338.47
B70: Total Operating Expense (P-Builder) | F70: =F41 -> 18839.05 | G70: =G41 -> 21726.78 | H70: =H41 -> 17677.27 | I70: =I41 -> 24117.51 | J70: =J41 -> 22948.64 | K70: =K41 -> 33105.96 | L70: =L41 -> 28472.7 | M70: =M41 -> 28358.15 | ... Q70: =Q41 -> 24338.47
F71: =F69-F70 -> 0 | G71: =G69-G70 -> 0 | H71: =H69-H70 -> 0 | I71: =I69-I70 -> 0 | J71: =J69-J70 -> 0 | K71: =K69-K70 -> 0 | L71: =L69-L70 -> 0 | M71: =M69-M70 -> 0 | ... Q71: =Q69-Q70 -> 0
E76: Delinquency Rate Calculator
E77: Rental Income | F77: =F8 -> 41324.65 | G77: =G8 -> 48906.56 | H77: =H8 -> 54138.43 | I77: =I8 -> 60857.87 | J77: =J8 -> 65220.38 | K77: =K8 -> 72813.54 | L77: =L8 -> 75484.5 | M77: =M8 -> 77101.22 | ... Q77: =Q8 -> 88458.82
E78: Late Fees | F78: =F11 -> 1216 | G78: =G11 -> 1453.8 | H78: =H11 -> 1681.435 | I78: =I11 -> 1733.8 | J78: =J11 -> 1742.2 | K78: =K11 -> 1289.7 | L78: =L11 -> 1791.295 | M78: =M11 -> 1641.28 | ... Q78: =Q11 -> 2492.49
E80: Late Fee / 20% | F80: =F78/0.2 -> 6080 | G80: =G78/0.2 -> 7269 | H80: =H78/0.2 -> 8407.175 | I80: =I78/0.2 -> 8669 | J80: =J78/0.2 -> 8711 | K80: =K78/0.2 -> 6448.5 | L80: =L78/0.2 -> 8956.475 | M80: =M78/0.2 -> 8206.4 | ... Q80: =Q78/0.2 -> 12462.45
E81: Delinquency Rate | F81: =F80/F77 -> 0.14712768 | G81: =G80/G77 -> 0.14863037 | H81: =H80/H77 -> 0.15529034 | I81: =I80/I77 -> 0.14244665 | J81: =J80/J77 -> 0.13356255 | K81: =K80/K77 -> 0.088561825 | L81: =L80/L77 -> 0.11865317 | M81: =M80/M77 -> 0.10643671 | ... Q81: =Q80/Q77 -> 0.1408842
E82: Average Delinquency Rate | F82: =IFERROR(AVERAGEIF($F$80:$Q$80,">0",F81:Q81),"") -> 0.13431688
E86: Admin Fee | F86: =F10 -> 1216 | G86: =G10 -> 1453.8 | H86: =H10 -> 1681.435 | I86: =I10 -> 1733.8 | J86: =J10 -> 1742.2 | K86: =K10 -> 1289.7 | L86: =L10 -> 1791.295 | M86: =M10 -> 1641.28 | ... Q86: =Q10 -> 2492.49
E87: Move-Ins | F87: =F86/29 -> 41.931034 | G87: =G86/29 -> 50.131034 | H87: =H86/29 -> 57.980517 | I87: =I86/29 -> 59.786207 | J87: =J86/29 -> 60.075862 | K87: =K86/29 -> 44.472414 | L87: =L86/29 -> 61.768793 | M87: =M86/29 -> 56.595862 | ... Q87: =Q86/29 -> 85.947931
E88: Average | F88: =AVERAGE(F87:Q87) -> 63.692888
E91: Rental Income | F91: =F5 -> 41324.65 | G91: =G5 -> 48906.56 | H91: =H5 -> 54138.43 | I91: =I5 -> 60857.87 | J91: =J5 -> 65220.38 | K91: =K5 -> 72813.54 | L91: =L5 -> 75484.5 | M91: =M5 -> 77101.22 | ... Q91: =Q5 -> 88458.82
E92: Discounts | F92: =F6 -> 0 | G92: =G6 -> 0 | H92: =H6 -> 0 | I92: =I6 -> 0 | J92: =J6 -> 0 | K92: =K6 -> 0 | L92: =L6 -> 0 | M92: =M6 -> 0 | ... Q92: =Q6 -> 0
E94: Discount Rate | F94: =F92/F91 -> 0 | G94: =G92/G91 -> 0 | H94: =H92/H91 -> 0 | I94: =I92/I91 -> 0 | J94: =J92/J91 -> 0 | K94: =K92/K91 -> 0 | L94: =L92/L91 -> 0 | M94: =M92/M91 -> 0 | ... Q94: =Q92/Q91 -> 0
E95: Average | F95: =AVERAGE(F94:Q94) -> 0
E96: Median | F96: =MEDIAN(F94:Q94) -> 0
E97: Max | F97: =MAX(F94:Q94) -> 0
E98: Min | F98: =MIN(F94:Q94) -> 0

Sheet Data Drop
A1: Actual/Budget | B1: Entity | C1: Account | D1: Month | E1: Year | F1: Period | G1: Amount ($) | H1: COA | I1: COA 2 | J1: Type | O1: Account
A2: Actual | B2: Vacaville | C2: Rental Income | D2: 11 | E2: 2024 | F2: 45597 | G2: 24759.42 | H2: =_xlfn.XLOOKUP(C2,'COA Translation'!A:A,'COA Translation'!B:B) -> Rental Income | I2: =_xlfn.XLOOKUP(C2,'COA Translation'!A:A,'COA Translation'!C:C) -> Net Rental Income | J2: =_xlfn.XLOOKUP(C2,'COA Translation'!A:A,'COA Translation'!E:E) -> Income | N2: Rental Income | O2: Rental Income | P2: =_xlfn.XLOOKUP(O2,'COA Translation'!A:A,'COA Translation'!B:B) -> Rental Income | Q2: =_xlfn.XLOOKUP(O2,'COA Translation'!A:A,'COA Translation'!C:C) -> Net Rental Income
A3: Actual | B3: Vacaville | C3: Tenant Insurance RMASA Fee | D3: 11 | E3: 2024 | F3: 45597 | G3: 1944 | H3: =_xlfn.XLOOKUP(C3,'COA Translation'!A:A,'COA Translation'!B:B) -> Current Tenant Protection Split | I3: =_xlfn.XLOOKUP(C3,'COA Translation'!A:A,'COA Translation'!C:C) -> 0 | J3: =_xlfn.XLOOKUP(C3,'COA Translation'!A:A,'COA Translation'!E:E) -> Income | N3: Tenant Insurance RMASA Fee | O3: Tenant Insurance RMASA Fee | P3: =_xlfn.XLOOKUP(O3,'COA Translation'!A:A,'COA Translation'!B:B) -> Current Tenant Protection Split | Q3: =_xlfn.XLOOKUP(O3,'COA Translation'!A:A,'COA Translation'!C:C) -> 0
A4: Actual | B4: Vacaville | C4: Merchandise Sales | D4: 11 | E4: 2024 | F4: 45597 | G4: 1433.1 | H4: =_xlfn.XLOOKUP(C4,'COA Translation'!A:A,'COA Translation'!B:B) -> Retail Sales Income | I4: =_xlfn.XLOOKUP(C4,'COA Translation'!A:A,'COA Translation'!C:C) -> 0 | J4: =_xlfn.XLOOKUP(C4,'COA Translation'!A:A,'COA Translation'!E:E) -> Income | N4: Merchandise Sales | O4: Merchandise Sales | P4: =_xlfn.XLOOKUP(O4,'COA Translation'!A:A,'COA Translation'!B:B) -> Retail Sales Income | Q4: =_xlfn.XLOOKUP(O4,'COA Translation'!A:A,'COA Translation'!C:C) -> 0
A5: Actual | B5: Vacaville | C5: Admin Fees, Late Fees, and Other Fees | D5: 11 | E5: 2024 | F5: 45597 | G5: 2752.45 | H5: =_xlfn.XLOOKUP(C5,'COA Translation'!A:A,'COA Translation'!B:B) -> Admin Fee Income | I5: =_xlfn.XLOOKUP(C5,'COA Translation'!A:A,'COA Translation'!C:C) -> 0 | J5: =_xlfn.XLOOKUP(C5,'COA Translation'!A:A,'COA Translation'!E:E) -> Income | N5: Admin Fees, Late Fees, and Other Fees | O5: Admin Fees, Late Fees, and Other Fees | P5: =_xlfn.XLOOKUP(O5,'COA Translation'!A:A,'COA Translation'!B:B) -> Admin Fee Income | Q5: =_xlfn.XLOOKUP(O5,'COA Translation'!A:A,'COA Translation'!C:C) -> 0
A6: Actual | B6: Vacaville | C6: Total Revenue | D6: 11 | E6: 2024 | F6: 45597 | G6: 30888.97 | H6: =_xlfn.XLOOKUP(C6,'COA Translation'!A:A,'COA Translation'!B:B) -> 0 | I6: =_xlfn.XLOOKUP(C6,'COA Translation'!A:A,'COA Translation'!C:C) -> Total Revenue | J6: =_xlfn.XLOOKUP(C6,'COA Translation'!A:A,'COA Translation'!E:E) -> TOTAL | N6: Total Revenue | O6: Total Revenue | P6: =_xlfn.XLOOKUP(O6,'COA Translation'!A:A,'COA Translation'!B:B) -> 0 | Q6: =_xlfn.XLOOKUP(O6,'COA Translation'!A:A,'COA Translation'!C:C) -> Total Revenue
A7: Actual | B7: Vacaville | C7: Property Management Software | D7: 11 | E7: 2024 | F7: 45597 | G7: 299 | H7: =_xlfn.XLOOKUP(C7,'COA Translation'!A:A,'COA Translation'!B:B) -> Software | I7: =_xlfn.XLOOKUP(C7,'COA Translation'!A:A,'COA Translation'!C:C) -> 0 | J7: =_xlfn.XLOOKUP(C7,'COA Translation'!A:A,'COA Translation'!E:E) -> Expense | N7: Property Management Software | O7: Property Management Software | P7: =_xlfn.XLOOKUP(O7,'COA Translation'!A:A,'COA Translation'!B:B) -> Software | Q7: =_xlfn.XLOOKUP(O7,'COA Translation'!A:A,'COA Translation'!C:C) -> 0
A8: Actual | B8: Vacaville | C8: Customer Care Center | D8: 11 | E8: 2024 | F8: 45597 | G8: 549 | H8: =_xlfn.XLOOKUP(C8,'COA Translation'!A:A,'COA Translation'!B:B) -> Software | I8: =_xlfn.XLOOKUP(C8,'COA Translation'!A:A,'COA Translation'!C:C) -> 0 | J8: =_xlfn.XLOOKUP(C8,'COA Translation'!A:A,'COA Translation'!E:E) -> Expense | N8: Customer Care Center | O8: Customer Care Center | P8: =_xlfn.XLOOKUP(O8,'COA Translation'!A:A,'COA Translation'!B:B) -> Software | Q8: =_xlfn.XLOOKUP(O8,'COA Translation'!A:A,'COA Translation'!C:C) -> 0
A9: Actual | B9: Vacaville | C9: Management Fees | D9: 11 | E9: 2024 | F9: 45597 | G9: 1153.86 | H9: =_xlfn.XLOOKUP(C9,'COA Translation'!A:A,'COA Translation'!B:B) -> Current Mgmt. Fee | I9: =_xlfn.XLOOKUP(C9,'COA Translation'!A:A,'COA Translation'!C:C) -> 0 | J9: =_xlfn.XLOOKUP(C9,'COA Translation'!A:A,'COA Translation'!E:E) -> Expense | N9: Management Fees | O9: Management Fees | P9: =_xlfn.XLOOKUP(O9,'COA Translation'!A:A,'COA Translation'!B:B) -> Current Mgmt. Fee | Q9: =_xlfn.XLOOKUP(O9,'COA Translation'!A:A,'COA Translation'!C:C) -> 0
A10: Actual | B10: Vacaville | C10: Total Contractually set fees | D10: 11 | E10: 2024 | F10: 45597 | G10: 2001.86 | H10: =_xlfn.XLOOKUP(C10,'COA Translation'!A:A,'COA Translation'!B:B) -> 0 | I10: =_xlfn.XLOOKUP(C10,'COA Translation'!A:A,'COA Translation'!C:C) -> 0 | J10: =_xlfn.XLOOKUP(C10,'COA Translation'!A:A,'COA Translation'!E:E) -> TOTAL | N10: Total Contractually set fees | O10: Total Contractually set fees | P10: =_xlfn.XLOOKUP(O10,'COA Translation'!A:A,'COA Translation'!B:B) -> 0 | Q10: =_xlfn.XLOOKUP(O10,'COA Translation'!A:A,'COA Translation'!C:C) -> 0
A11: Actual | B11: Vacaville | C11: Cost of Goods Sold | D11: 11 | E11: 2024 | F11: 45597 | G11: 334.55 | H11: =_xlfn.XLOOKUP(C11,'COA Translation'!A:A,'COA Translation'!B:B) -> Retail Products | I11: =_xlfn.XLOOKUP(C11,'COA Translation'!A:A,'COA Translation'!C:C) -> 0 | J11: =_xlfn.XLOOKUP(C11,'COA Translation'!A:A,'COA Translation'!E:E) -> Expense | N11: Cost of Goods Sold | O11: Cost of Goods Sold | P11: =_xlfn.XLOOKUP(O11,'COA Translation'!A:A,'COA Translation'!B:B) -> Retail Products | Q11: =_xlfn.XLOOKUP(O11,'COA Translation'!A:A,'COA Translation'!C:C) -> 0
A12: Actual | B12: Vacaville | C12: Payroll - Property Manager | D12: 11 | E12: 2024 | F12: 45597 | G12: 4668.95 | H12: =_xlfn.XLOOKUP(C12,'COA Translation'!A:A,'COA Translation'!B:B) -> Payroll | I12: =_xlfn.XLOOKUP(C12,'COA Translation'!A:A,'COA Translation'!C:C) -> 0 | J12: =_xlfn.XLOOKUP(C12,'COA Translation'!A:A,'COA Translation'!E:E) -> Expense | N12: Payroll - Property Manager | O12: Payroll - Property Manager | P12: =_xlfn.XLOOKUP(O12,'COA Translation'!A:A,'COA Translation'!B:B) -> Payroll | Q12: =_xlfn.XLOOKUP(O12,'COA Translation'!A:A,'COA Translation'!C:C) -> 0
A13: Actual | B13: Vacaville | C13: Payroll - District Manager | D13: 11 | E13: 2024 | F13: 45597 | G13: 701.32 | H13: =_xlfn.XLOOKUP(C13,'COA Translation'!A:A,'COA Translation'!B:B) -> Current Mgmt. Fee | I13: =_xlfn.XLOOKUP(C13,'COA Translation'!A:A,'COA Translation'!C:C) -> 0 | J13: =_xlfn.XLOOKUP(C13,'COA Translation'!A:A,'COA Translation'!E:E) -> Expense | N13: Payroll - District Manager | O13: Payroll - District Manager | P13: =_xlfn.XLOOKUP(O13,'COA Translation'!A:A,'COA Translation'!B:B) -> Current Mgmt. Fee | Q13: =_xlfn.XLOOKUP(O13,'COA Translation'!A:A,'COA Translation'!C:C) -> 0
... A20: Actual | B20: Vacaville | C20: Telephone | D20: 11 | E20: 2024 | F20: 45597 | G20: 0.01 | H20: =_xlfn.XLOOKUP(C20,'COA Translation'!A:A,'COA Translation'!B:B) -> Telephone & Internet | I20: =_xlfn.XLOOKUP(C20,'COA Translation'!A:A,'COA Translation'!C:C) -> 0 | J20: =_xlfn.XLOOKUP(C20,'COA Translation'!A:A,'COA Translation'!E:E) -> Expense | N20: Telephone | O20: Telephone | P20: =_xlfn.XLOOKUP(O20,'COA Translation'!A:A,'COA Translation'!B:B) -> Telephone & Internet | Q20: =_xlfn.XLOOKUP(O20,'COA Translation'!A:A,'COA Translation'!C:C) -> 0
A21: Actual | B21: Vacaville | C21: Tenant Mailings | D21: 11 | E21: 2024 | F21: 45597 | G21: 11.35 | H21: =_xlfn.XLOOKUP(C21,'COA Translation'!A:A,'COA Translation'!B:B) -> Payroll | I21: =_xlfn.XLOOKUP(C21,'COA Translation'!A:A,'COA Translation'!C:C) -> 0 | J21: =_xlfn.XLOOKUP(C21,'COA Translation'!A:A,'COA Translation'!E:E) -> Expense | N21: Tenant Mailings | O21: Tenant Mailings | P21: =_xlfn.XLOOKUP(O21,'COA Translation'!A:A,'COA Translation'!B:B) -> Payroll | Q21: =_xlfn.XLOOKUP(O21,'COA Translation'!A:A,'COA Translation'!C:C) -> 0 | R21: AUCTIONS?
A22: Actual | B22: Vacaville | C22: Office Expense | D22: 11 | E22: 2024 | F22: 45597 | G22: 139.66 | H22: =_xlfn.XLOOKUP(C22,'COA Translation'!A:A,'COA Translation'!B:B) -> Office Supplies | I22: =_xlfn.XLOOKUP(C22,'COA Translation'!A:A,'COA Translation'!C:C) -> 0 | J22: =_xlfn.XLOOKUP(C22,'COA Translation'!A:A,'COA Translation'!E:E) -> Expense | N22: Office Expense | O22: Office Expense | P22: =_xlfn.XLOOKUP(O22,'COA Translation'!A:A,'COA Translation'!B:B) -> Office Supplies | Q22: =_xlfn.XLOOKUP(O22,'COA Translation'!A:A,'COA Translation'!C:C) -> 0
A23: Actual | B23: Vacaville | C23: Business Licenses and Permits | D23: 11 | E23: 2024 | F23: 45597 | G23: 0 | H23: =_xlfn.XLOOKUP(C23,'COA Translation'!A:A,'COA Translation'!B:B) -> Licenses & Permits | I23: =_xlfn.XLOOKUP(C23,'COA Translation'!A:A,'COA Translation'!C:C) -> 0 | J23: =_xlfn.XLOOKUP(C23,'COA Translation'!A:A,'COA Translation'!E:E) -> Expense | N23: Business Licenses and Permits | O23: Business Licenses and Permits | P23: =_xlfn.XLOOKUP(O23,'COA Translation'!A:A,'COA Translation'!B:B) -> Licenses & Permits | Q23: =_xlfn.XLOOKUP(O23,'COA Translation'!A:A,'COA Translation'!C:C) -> 0
A24: Actual | B24: Vacaville | C24: Legal and Evictions | D24: 11 | E24: 2024 | F24: 45597 | G24: 42.5 | H24: =_xlfn.XLOOKUP(C24,'COA Translation'!A:A,'COA Translation'!B:B) -> Prof Fees - Legal/Acctg | I24: =_xlfn.XLOOKUP(C24,'COA Translation'!A:A,'COA Translation'!C:C) -> 0 | J24: =_xlfn.XLOOKUP(C24,'COA Translation'!A:A,'COA Translation'!E:E) -> Expense | N24: Legal and Evictions | O24: Legal and Evictions | P24: =_xlfn.XLOOKUP(O24,'COA Translation'!A:A,'COA Translation'!B:B) -> Prof Fees - Legal/Acctg | Q24: =_xlfn.XLOOKUP(O24,'COA Translation'!A:A,'COA Translation'!C:C) -> 0
A25: Actual | B25: Vacaville | C25: Total Other Expenses | D25: 11 | E25: 2024 | F25: 45597 | G25: 12546.56 | H25: =_xlfn.XLOOKUP(C25,'COA Translation'!A:A,'COA Translation'!B:B) -> 0 | I25: =_xlfn.XLOOKUP(C25,'COA Translation'!A:A,'COA Translation'!C:C) -> 0 | J25: =_xlfn.XLOOKUP(C25,'COA Translation'!A:A,'COA Translation'!E:E) -> TOTAL | N25: Total Other Expenses | O25: Total Other Expenses | P25: =_xlfn.XLOOKUP(O25,'COA Translation'!A:A,'COA Translation'!B:B) -> 0 | Q25: =_xlfn.XLOOKUP(O25,'COA Translation'!A:A,'COA Translation'!C:C) -> 0
A26: Actual | B26: Vacaville | C26: Total Operating Expenses | D26: 11 | E26: 2024 | F26: 45597 | G26: 14548.42 | H26: =_xlfn.XLOOKUP(C26,'COA Translation'!A:A,'COA Translation'!B:B) -> 0 | I26: =_xlfn.XLOOKUP(C26,'COA Translation'!A:A,'COA Translation'!C:C) -> Total Operating Expense | J26: =_xlfn.XLOOKUP(C26,'COA Translation'!A:A,'COA Translation'!E:E) -> TOTAL | N26: Total Operating Expenses | O26: Total Operating Expenses | P26: =_xlfn.XLOOKUP(O26,'COA Translation'!A:A,'COA Translation'!B:B) -> 0 | Q26: =_xlfn.XLOOKUP(O26,'COA Translation'!A:A,'COA Translation'!C:C) -> Total Operating Expense
A27: Actual | B27: Vacaville | C27: Net Operating Income | D27: 11 | E27: 2024 | F27: 45597 | G27: 16340.55 | H27: =_xlfn.XLOOKUP(C27,'COA Translation'!A:A,'COA Translation'!B:B) -> 0 | I27: =_xlfn.XLOOKUP(C27,'COA Translation'!A:A,'COA Translation'!C:C) -> Net Operating Income | J27: =_xlfn.XLOOKUP(C27,'COA Translation'!A:A,'COA Translation'!E:E) -> TOTAL | N27: Net Operating Income | O27: Net Operating Income | P27: =_xlfn.XLOOKUP(O27,'COA Translation'!A:A,'COA Translation'!B:B) -> 0 | Q27: =_xlfn.XLOOKUP(O27,'COA Translation'!A:A,'COA Translation'!C:C) -> Net Operating Income
A28: Actual | B28: Vacaville | C28: Rental Income | D28: 12 | E28: 2024 | F28: 45627 | G28: 30443.36 | H28: =_xlfn.XLOOKUP(C28,'COA Translation'!A:A,'COA Translation'!B:B) -> Rental Income | I28: =_xlfn.XLOOKUP(C28,'COA Translation'!A:A,'COA Translation'!C:C) -> Net Rental Income | J28: =_xlfn.XLOOKUP(C28,'COA Translation'!A:A,'COA Translation'!E:E) -> Income
A29: Actual | B29: Vacaville | C29: Tenant Insurance RMASA Fee | D29: 12 | E29: 2024 | F29: 45627 | G29: 2100 | H29: =_xlfn.XLOOKUP(C29,'COA Translation'!A:A,'COA Translation'!B:B) -> Current Tenant Protection Split | I29: =_xlfn.XLOOKUP(C29,'COA Translation'!A:A,'COA Translation'!C:C) -> 0 | J29: =_xlfn.XLOOKUP(C29,'COA Translation'!A:A,'COA Translation'!E:E) -> Income
A30: Actual | B30: Vacaville | C30: Merchandise Sales | D30: 12 | E30: 2024 | F30: 45627 | G30: 1005.03 | H30: =_xlfn.XLOOKUP(C30,'COA Translation'!A:A,'COA Translation'!B:B) -> Retail Sales Income | I30: =_xlfn.XLOOKUP(C30,'COA Translation'!A:A,'COA Translation'!C:C) -> 0 | J30: =_xlfn.XLOOKUP(C30,'COA Translation'!A:A,'COA Translation'!E:E) -> Income
A31: Actual | B31: Vacaville | C31: Admin Fees, Late Fees, and Other Fees | D31: 12 | E31: 2024 | F31: 45627 | G31: 2929.6 | H31: =_xlfn.XLOOKUP(C31,'COA Translation'!A:A,'COA Translation'!B:B) -> Admin Fee Income | I31: =_xlfn.XLOOKUP(C31,'COA Translation'!A:A,'COA Translation'!C:C) -> 0 | J31: =_xlfn.XLOOKUP(C31,'COA Translation'!A:A,'COA Translation'!E:E) -> Income
A32: Actual | B32: Vacaville | C32: Total Revenue | D32: 12 | E32: 2024 | F32: 45627 | G32: 36477.99 | H32: =_xlfn.XLOOKUP(C32,'COA Translation'!A:A,'COA Translation'!B:B) -> 0 | I32: =_xlfn.XLOOKUP(C32,'COA Translation'!A:A,'COA Translation'!C:C) -> Total Revenue | J32: =_xlfn.XLOOKUP(C32,'COA Translation'!A:A,'COA Translation'!E:E) -> TOTAL
A33: Actual | B33: Vacaville | C33: Property Management Software | D33: 12 | E33: 2024 | F33: 45627 | G33: 300.87 | H33: =_xlfn.XLOOKUP(C33,'COA Translation'!A:A,'COA Translation'!B:B) -> Software | I33: =_xlfn.XLOOKUP(C33,'COA Translation'!A:A,'COA Translation'!C:C) -> 0 | J33: =_xlfn.XLOOKUP(C33,'COA Translation'!A:A,'COA Translation'!E:E) -> Expense
A34: Actual | B34: Vacaville | C34: Customer Care Center | D34: 12 | E34: 2024 | F34: 45627 | G34: 549 | H34: =_xlfn.XLOOKUP(C34,'COA Translation'!A:A,'COA Translation'!B:B) -> Software | I34: =_xlfn.XLOOKUP(C34,'COA Translation'!A:A,'COA Translation'!C:C) -> 0 | J34: =_xlfn.XLOOKUP(C34,'COA Translation'!A:A,'COA Translation'!E:E) -> Expense
A35: Actual | B35: Vacaville | C35: Management Fees | D35: 12 | E35: 2024 | F35: 45627 | G35: 1334.95 | H35: =_xlfn.XLOOKUP(C35,'COA Translation'!A:A,'COA Translation'!B:B) -> Current Mgmt. Fee | I35: =_xlfn.XLOOKUP(C35,'COA Translation'!A:A,'COA Translation'!C:C) -> 0 | J35: =_xlfn.XLOOKUP(C35,'COA Translation'!A:A,'COA Translation'!E:E) -> Expense
A36: Actual | B36: Vacaville | C36: Total Contractually set fees | D36: 12 | E36: 2024 | F36: 45627 | G36: 2184.82 | H36: =_xlfn.XLOOKUP(C36,'COA Translation'!A:A,'COA Translation'!B:B) -> 0 | I36: =_xlfn.XLOOKUP(C36,'COA Translation'!A:A,'COA Translation'!C:C) -> 0 | J36: =_xlfn.XLOOKUP(C36,'COA Translation'!A:A,'COA Translation'!E:E) -> TOTAL
A37: Actual | B37: Vacaville | C37: Cost of Goods Sold | D37: 12 | E37: 2024 | F37: 45627 | G37: 39.58 | H37: =_xlfn.XLOOKUP(C37,'COA Translation'!A:A,'COA Translation'!B:B) -> Retail Products | I37: =_xlfn.XLOOKUP(C37,'COA Translation'!A:A,'COA Translation'!C:C) -> 0 | J37: =_xlfn.XLOOKUP(C37,'COA Translation'!A:A,'COA Translation'!E:E) -> Expense
A38: Actual | B38: Vacaville | C38: Payroll - Property Manager | D38: 12 | E38: 2024 | F38: 45627 | G38: 4666.49 | H38: =_xlfn.XLOOKUP(C38,'COA Translation'!A:A,'COA Translation'!B:B) -> Payroll | I38: =_xlfn.XLOOKUP(C38,'COA Translation'!A:A,'COA Translation'!C:C) -> 0 | J38: =_xlfn.XLOOKUP(C38,'COA Translation'!A:A,'COA Translation'!E:E) -> Expense
A39: Actual | B39: Vacaville | C39: Payroll - District Manager | D39: 12 | E39: 2024 | F39: 45627 | G39: 1743.77 | H39: =_xlfn.XLOOKUP(C39,'COA Translation'!A:A,'COA Translation'!B:B) -> Current Mgmt. Fee | I39: =_xlfn.XLOOKUP(C39,'COA Translation'!A:A,'COA Translation'!C:C) -> 0 | J39: =_xlfn.XLOOKUP(C39,'COA Translation'!A:A,'COA Translation'!E:E) -> Expense
... A391: Actual | B391: Vacaville | C391: Net Operating Income | D391: 1 | E391: 2026 | F391: 46023 | G391: 73151.14 | H391: =_xlfn.XLOOKUP(C391,'COA Translation'!A:A,'COA Translation'!B:B) -> 0 | I391: =_xlfn.XLOOKUP(C391,'COA Translation'!A:A,'COA Translation'!C:C) -> Net Operating Income | J391: =_xlfn.XLOOKUP(C391,'COA Translation'!A:A,'COA Translation'!E:E) -> TOTAL

Sheet COA Translation
A1: Account | B1: COA | C1: Top Tier | D1: Header | E1: Type
A2: Rental Income | B2: Rental Income | C2: Net Rental Income | E2: Income
A3: Tenant Insurance RMASA Fee | B3: Current Tenant Protection Split | E3: Income
A4: Merchandise Sales | B4: Retail Sales Income | E4: Income
A5: Admin Fees, Late Fees, and Other Fees | B5: Admin Fee Income | E5: Income
A6: Total Revenue | C6: Total Revenue | E6: TOTAL
A7: Property Management Software | B7: Software | E7: Expense
A8: Customer Care Center | B8: Software | E8: Expense
A9: Management Fees | B9: Current Mgmt. Fee | E9: Expense
A10: Total Contractually set fees | E10: TOTAL
A11: Cost of Goods Sold | B11: Retail Products | E11: Expense
A12: Payroll - Property Manager | B12: Payroll | E12: Expense
A13: Payroll - District Manager | B13: Current Mgmt. Fee | E13: Expense
A14: Utilities | B14: Utilities | E14: Expense
A15: Repairs and Maintenance | B15: Repairs & Maintenance | E15: Expense
A16: Credit Card Charges | B16: Current Credit Card Security Fees | E16: Expense
A17: Internet Advertising | B17: Advertising & Marketing | E17: Expense
A18: Network Charges | B18: Software | E18: Expense
A19: Bank Charges | B19: Software | E19: Expense
A20: Telephone | B20: Telephone & Internet | E20: Expense
A21: Tenant Mailings | B21: Payroll | E21: Expense
A22: Office Expense | B22: Office Supplies | E22: Expense
... A24: Legal and Evictions | B24: Prof Fees - Legal/Acctg | E24: Expense
A25: Total Other Expenses | E25: TOTAL
A26: Total Operating Expenses | C26: Total Operating Expense | E26: TOTAL
A27: Net Operating Income | C27: Net Operating Income | E27: TOTAL

Sheet Valuation Sheet
B2: Charleston Ashley Phosphate — Acquisition & Returns Analysis
B4: Sources & Uses | G4: Key Metrics
B5: Sources | D5: Uses | G5: Purchase Price | H5: ='Inputs & Drivers'!E14 -> 14000000
B6: Senior Debt | C6: ='Inputs & Drivers'!I19 -> 9100000 | D6: Purchase Price | E6: ='Inputs & Drivers'!E14 -> 14000000 | G6: Going-In Cap Rate | H6: ='Inputs & Drivers'!I30 -> 0.045309753
B7: Equity | C7: =E13-C6 -> 5065000 | D7: Closing Costs | E7: ='Inputs & Drivers'!E15*'Inputs & Drivers'!E14 -> 140000 | G7: ="All-In Interest Rate (SOFR+"&TEXT('Inputs & Drivers'!I15*10000,"0")&"bps)" -> All-In Interest Rate (SOFR+200bps) | H7: ='Inputs & Drivers'!I16 -> 0.063
G8: LTV | H8: ='Inputs & Drivers'!I13 -> 0.65
D9: Upfront CapEx | E9: ='Inputs & Drivers'!I22 -> 25000 | G9: Loan Amount | H9: ='Inputs & Drivers'!I19 -> 9100000
G10: Equity Required | H10: =C7 -> 5065000
G11: Total CapEx | H11: ='Inputs & Drivers'!I24 -> 25000
G12: NRSF | H12: ='Inputs & Drivers'!E10 -> 89350
B13: Total Sources | C13: =C6+C7 -> 14165000 | D13: Total Uses | E13: =E6+E7+E9 -> 14165000 | G13: Price / SqFt | H13: =H5/H12 -> 156.68719
G14: Asset Mgmt Fee | H14: ='Inputs & Drivers'!I31 -> 75000
B15: Debt Service Schedule | V15: =850000/16600000 -> 0.051204819
C16: Year 1 | D16: Year 2 | E16: Year 3 | F16: Year 4 | G16: Year 5
B17: Beginning Balance | C17: ='Inputs & Drivers'!I19 -> 9100000 | D17: =C22 -> 8945141.5 | E17: =D22 -> 8780240.2 | F17: =E22 -> 8604644.9 | G17: =F22 -> 8417661.9
B18: Annual Debt Service | C18: =-PMT('Inputs & Drivers'!I16/12, 'Inputs & Drivers'!I17*12, 'Inputs & Drivers'!I19)*12 -> 723737.69 | D18: =C18 -> 723737.69 | E18: =C18 -> 723737.69 | F18: =C18 -> 723737.69 | G18: =C18 -> 723737.69
B19: Interest Portion | C19: =-CUMIPMT('Inputs & Drivers'!I16/12, 'Inputs & Drivers'!I17*12, 'Inputs & Drivers'!I19, 1, 12, 0) -> 568879.19 | D19: =-CUMIPMT('Inputs & Drivers'!I16/12, 'Inputs & Drivers'!I17*12, 'Inputs & Drivers'!I19, 13, 24, 0) -> 558836.41 | E19: =-CUMIPMT('Inputs & Drivers'!I16/12, 'Inputs & Drivers'!I17*12, 'Inputs & Drivers'!I19, 25, 36, 0) -> 548142.34 | F19: =-CUMIPMT('Inputs & Drivers'!I16/12, 'Inputs & Drivers'!I17*12, 'Inputs & Drivers'!I19, 37, 48, 0) -> 536754.74 | G19: =-CUMIPMT('Inputs & Drivers'!I16/12, 'Inputs & Drivers'!I17*12, 'Inputs & Drivers'!I19, 49, 60, 0) -> 524628.65
B20: Principal Portion | C20: =C18-C19 -> 154858.5 | D20: =D18-D19 -> 164901.28 | E20: =E18-E19 -> 175595.35 | F20: =F18-F19 -> 186982.95 | G20: =G18-G19 -> 199109.04
B21: DSCR | C21: =C26/C18 -> 1.3841087 | D21: =D26/D18 -> 1.4165995 | E21: =E26/E18 -> 1.4634036 | F21: =F26/F18 -> 1.5227886 | G21: =G26/G18 -> 1.5859185
B22: Ending Balance | C22: =C17-C20 -> 8945141.5 | D22: =D17-D20 -> 8780240.2 | E22: =E17-E20 -> 8604644.9 | F22: =F17-F20 -> 8417661.9 | G22: =G17-G20 -> 8218552.9
B24: Levered Cash Flow
C25: Year 1 | D25: Year 2 | E25: Year 3 | F25: Year 4 | G25: Year 5
B26: Net Operating Income | C26: ='5 Year Proforma'!G47 -> 1001731.7 | D26: ='5 Year Proforma'!L47 -> 1025246.5 | E26: ='5 Year Proforma'!Q47 -> 1059120.4 | F26: ='5 Year Proforma'!V47 -> 1102099.5 | G26: ='5 Year Proforma'!AA47 -> 1147789
B27: Less: CapEx | C27: =-'Inputs & Drivers'!I23 -> 0 | D27: =-'Inputs & Drivers'!I25 -> 0 | E27: =-'Inputs & Drivers'!I25 -> 0 | F27: =-'Inputs & Drivers'!I25 -> 0 | G27: =-'Inputs & Drivers'!I25 -> 0
B28: Less: Debt Service | C28: =-C18 -> -723737.69 | D28: =-D18 -> -723737.69 | E28: =-E18 -> -723737.69 | F28: =-F18 -> -723737.69 | G28: =-G18 -> -723737.69
B29: Less: Asset Mgmt Fee | C29: =-'Inputs & Drivers'!I31 -> -75000 | D29: =-'Inputs & Drivers'!I31 -> -75000 | E29: =-'Inputs & Drivers'!I31 -> -75000 | F29: =-'Inputs & Drivers'!I31 -> -75000 | G29: =-'Inputs & Drivers'!I31 -> -75000
B30: Levered Cash Flow | C30: =SUM(C26:C29) -> 202993.97 | D30: =SUM(D26:D29) -> 226508.79 | E30: =SUM(E26:E29) -> 260382.68 | F30: =SUM(F26:F29) -> 303361.82 | G30: =SUM(G26:G29) -> 349051.33
B32: Cash-on-Cash Return | C32: =C30/C7 -> 0.040077783 | D32: =D30/C7 -> 0.044720392 | E32: =E30/C7 -> 0.051408228 | F32: =F30/C7 -> 0.059893745 | G32: =G30/C7 -> 0.068914379
B33: Yield on Cost | C33: =C26/E13 -> 0.07071879 | D33: =D26/E13 -> 0.072378855 | E33: =E26/E13 -> 0.074770234 | F33: =F26/E13 -> 0.077804413 | G33: =G26/E13 -> 0.081029934
B35: Hold Period Comparison
C37: 3-Year Hold | D37: 5-Year Hold | E37: 7-Year Hold | J37: 3yr Proj
B38: Exit Assumptions | J38: =-C7 -> -5065000 | K38: =C30 -> 202993.97 | L38: =D30 -> 226508.79 | M38: =E30+C45 -> 8927025.5
B39: Exit Year NOI | C39: =E26 -> 1059120.4 | D39: =G26 -> 1147789 | E39: =G26*(1+'Inputs & Drivers'!E65)^2 -> 1241448.6 | J39: 3yr GP
B40: Forward NOI (exit + 1 yr) | C40: =C39*(1+'Inputs & Drivers'!E63) -> 1101485.2 | D40: =D39*(1+'Inputs & Drivers'!E65) -> 1193700.6 | E40: =E39*(1+'Inputs & Drivers'!E65) -> 1291106.5 | J40: =-D98 -> -506500 | K40: =C120 -> 20299.397 | L40: =D120 -> 22650.879 | M40: =E120+C45*C98+MAX(E30+C45-548480-D100,0)*(C103+(1-C103)*C98)-MAX(E30+C45-548480-D100,0)*(C103+(1-C103)*C98)+C45*0 -> 892702.55
B41: Gross Sale Price | C41: =C40/'Inputs & Drivers'!I28 -> 17623763 | D41: =D40/'Inputs & Drivers'!I28 -> 19099209 | E41: =E40/'Inputs & Drivers'!I28 -> 20657705
B42: Disposition Costs | C42: =-C41*'Inputs & Drivers'!I29 -> -352475.26 | D42: =-D41*'Inputs & Drivers'!I29 -> -381984.19 | E42: =-E41*'Inputs & Drivers'!I29 -> -413154.1 | J42: 3yr TotCF
B43: Net Sale Price | C43: =C41+C42 -> 17271288 | D43: =D41+D42 -> 18717225 | E43: =E41+E42 -> 20244551 | J43: =C30+D30+E30+C45 -> 9356528.2
B44: Loan Balance at Exit | C44: =E22 -> 8604644.9 | D44: =G22 -> 8218552.9 | E44: ='Inputs & Drivers'!I19+CUMPRINC('Inputs & Drivers'!I16/12,'Inputs & Drivers'!I17*12,'Inputs & Drivers'!I19,1,84,0) -> 7780759.9 | J44: =3*D100*C102 -> 1215600
B45: Net Equity Proceeds | C45: =C43-C44 -> 8666642.8 | D45: =D43-D44 -> 10498672 | E45: =E43-E44 -> 12463791 | J45: =MIN(J44, MAX(J43,0)) -> 1215600
J46: =MIN(MAX(J43-J45,0), D100) -> 5065000
B47: Project-Level Returns | J47: =MAX(J43-J45-J46,0) -> 3075928.2
B48: Levered IRR | C48: =J151 -> 0.23391534 | D48: =C67 -> 0.19581797 | E48: =J175 -> 0.17950314 | J48: =J45*C98 + J46*C98 + J47*(C103 + (1-C103)*C98) -> 1627736.7
B49: Equity Multiple | C49: =(SUM(K38:M38))/-J38 -> 1.8472909 | D49: =C68 -> 2.3378027 | E49: =(SUM(K158:Q158))/-J158 -> 2.9207824 | J49: =J43-J48 -> 7728791.5
B51: Exit / Disposition Analysis (5-year Hold)
B53: Exit Cap Rate | G53: ='Inputs & Drivers'!I28 -> 0.0625
B54: Year 6 Forward NOI (est.) | G54: =G26*(1+'Inputs & Drivers'!E65) -> 1193700.6 | H54: Yr 5 NOI × (1 + rent growth)
B55: Gross Sale Price | G55: =G54/G53 -> 19099209
B56: Less: Disposition Costs | G56: =-G55*'Inputs & Drivers'!I29 -> -381984.19
B57: Net Sale Price | G57: =G55+G56 -> 18717225
B58: Less: Loan Payoff | G58: =-G22 -> -8218552.9
B59: Net Equity Proceeds at Sale | G59: =G57+G58 -> 10498672
B62: Returns Summary
B64: IRR Calculation | C64: Year 0 | D64: Year 1 | E64: Year 2 | F64: Year 3 | G64: Year 4 | H64: Year 5
B65: Cash Flows | C65: =-C7 -> -5065000 | D65: =C30 -> 202993.97 | E65: =D30 -> 226508.79 | F65: =E30 -> 260382.68 | G65: =F30 -> 303361.82 | H65: =G30+G59 -> 10847724
B67: Levered IRR | C67: =IRR(C65:H65) -> 0.19581797
B68: Equity Multiple | C68: =(SUM(D65:H65))/-C65 -> 2.3378027
B69: Avg Cash-on-Cash | C69: =AVERAGE(C32:G32) -> 0.053002905
B72: Sensitivity Analysis
B74: Cap Rate Sensitivity — Implied Value at Exit (Year 5 NOI)
B75: Exit Cap Rate | C75: Gross Sale | D75: Net Proceeds | E75: Equity Proceeds | F75: Equity Multiple | G75: Levered IRR | J75: Helper CFs
B76: 0.055 | C76: =$G$54/B76 -> 21703647 | D76: =C76*(1-'Inputs & Drivers'!$I$29) -> 21269574 | E76: =D76-$G$22 -> 13051021 | F76: =(SUM($C$30:$G$30)+E76)/$C$7 -> 2.8417216 | G76: =IRR(J76:O76) -> 0.24422561 | J76: =$C$65 -> -5065000 | K76: =$D$65 -> 202993.97 | L76: =$E$65 -> 226508.79 | M76: =$F$65 -> 260382.68 | N76: =$G$65 -> 303361.82 | O76: =$G$30+E76 -> 13400072
B77: 0.0575 | C77: =$G$54/B77 -> 20760010 | D77: =C77*(1-'Inputs & Drivers'!$I$29) -> 20344810 | E77: =D77-$G$22 -> 12126257 | F77: =(SUM($C$30:$G$30)+E77)/$C$7 -> 2.6591423 | G77: =IRR(J77:O77) -> 0.22758548 | J77: =$C$65 -> -5065000 | K77: =$D$65 -> 202993.97 | L77: =$E$65 -> 226508.79 | M77: =$F$65 -> 260382.68 | N77: =$G$65 -> 303361.82 | O77: =$G$30+E77 -> 12475308
B78: 0.06 | C78: =$G$54/B78 -> 19895010 | D78: =C78*(1-'Inputs & Drivers'!$I$29) -> 19497109 | E78: =D78-$G$22 -> 11278557 | F78: =(SUM($C$30:$G$30)+E78)/$C$7 -> 2.4917779 | G78: =IRR(J78:O78) -> 0.21146935 | J78: =$C$65 -> -5065000 | K78: =$D$65 -> 202993.97 | L78: =$E$65 -> 226508.79 | M78: =$F$65 -> 260382.68 | N78: =$G$65 -> 303361.82 | O78: =$G$30+E78 -> 11627608
B79: 0.065 | C79: =$G$54/B79 -> 18364624 | D79: =C79*(1-'Inputs & Drivers'!$I$29) -> 17997332 | E79: =D79-$G$22 -> 9778778.9 | F79: =(SUM($C$30:$G$30)+E79)/$C$7 -> 2.1956718 | G79: =IRR(J79:O79) -> 0.18057853 | J79: =$C$65 -> -5065000 | K79: =$D$65 -> 202993.97 | L79: =$E$65 -> 226508.79 | M79: =$F$65 -> 260382.68 | N79: =$G$65 -> 303361.82 | O79: =$G$30+E79 -> 10127830
B80: 0.07 | C80: =$G$54/B80 -> 17052865 | D80: =C80*(1-'Inputs & Drivers'!$I$29) -> 16711808 | E80: =D80-$G$22 -> 8493255.2 | F80: =(SUM($C$30:$G$30)+E80)/$C$7 -> 1.9418665 | G80: =IRR(J80:O80) -> 0.15114973 | J80: =$C$65 -> -5065000 | K80: =$D$65 -> 202993.97 | L80: =$E$65 -> 226508.79 | M80: =$F$65 -> 260382.68 | N80: =$G$65 -> 303361.82 | O80: =$G$30+E80 -> 8842306.6
B81: 0.075 | C81: =$G$54/B81 -> 15916008 | D81: =C81*(1-'Inputs & Drivers'!$I$29) -> 15597688 | E81: =D81-$G$22 -> 7379134.7 | F81: =(SUM($C$30:$G$30)+E81)/$C$7 -> 1.7219019 | G81: =IRR(J81:O81) -> 0.12285097 | J81: =$C$65 -> -5065000 | K81: =$D$65 -> 202993.97 | L81: =$E$65 -> 226508.79 | M81: =$F$65 -> 260382.68 | N81: =$G$65 -> 303361.82 | O81: =$G$30+E81 -> 7728186
B82: 0.08 | C82: =$G$54/B82 -> 14921257 | D82: =C82*(1-'Inputs & Drivers'!$I$29) -> 14622832 | E82: =D82-$G$22 -> 6404279.2 | F82: =(SUM($C$30:$G$30)+E82)/$C$7 -> 1.5294329 | G82: =IRR(J82:O82) -> 0.095398609 | J82: =$C$65 -> -5065000 | K82: =$D$65 -> 202993.97 | L82: =$E$65 -> 226508.79 | M82: =$F$65 -> 260382.68 | N82: =$G$65 -> 303361.82 | O82: =$G$30+E82 -> 6753330.6
B83: 0.085 | C83: =$G$54/B83 -> 14043536 | D83: =C83*(1-'Inputs & Drivers'!$I$29) -> 13762666 | E83: =D83-$G$22 -> 5544112.6 | F83: =(SUM($C$30:$G$30)+E83)/$C$7 -> 1.3596073 | G83: =IRR(J83:O83) -> 0.068540324 | J83: =$C$65 -> -5065000 | K83: =$D$65 -> 202993.97 | L83: =$E$65 -> 226508.79 | M83: =$F$65 -> 260382.68 | N83: =$G$65 -> 303361.82 | O83: =$G$30+E83 -> 5893164
B85: Interest Rate Sensitivity — Levered IRR (Exit Cap × All-In Rate) | J85: Helpers — Interest Rate Sensitivity
J86: Rate → | K86: =C87 -> 0.053 | L86: =D87 -> 0.058 | M86: =E87 -> 0.063 | N86: =F87 -> 0.068 | O86: =G87 -> 0.073
B87: Exit Cap \ All-In Rate | C87: 0.053 | D87: 0.058 | E87: 0.063 | F87: 0.068 | G87: 0.073 | J87: Ann. DS | K87: =-PMT(K86/12,'Inputs & Drivers'!$I$17*12,'Inputs & Drivers'!$I$19)*12 -> 657603.71 | L87: =-PMT(L86/12,'Inputs & Drivers'!$I$17*12,'Inputs & Drivers'!$I$19)*12 -> 690287.5 | M87: =-PMT(M86/12,'Inputs & Drivers'!$I$17*12,'Inputs & Drivers'!$I$19)*12 -> 723737.69 | N87: =-PMT(N86/12,'Inputs & Drivers'!$I$17*12,'Inputs & Drivers'!$I$19)*12 -> 757926.73 | O87: =-PMT(O86/12,'Inputs & Drivers'!$I$17*12,'Inputs & Drivers'!$I$19)*12 -> 792826.18
B88: 0.055 | C88: =IRR(CHOOSE({1,2,3,4,5,6},K$88,K$89,K$90,K$91,K$92,K96)) -> 0.25570746 | D88: =IRR(CHOOSE({1,2,3,4,5,6},L$88,L$89,L$90,L$91,L$92,L96)) -> 0.24999878 | E88: =IRR(CHOOSE({1,2,3,4,5,6},M$88,M$89,M$90,M$91,M$92,M96)) -> 0.24422561 | F88: =IRR(CHOOSE({1,2,3,4,5,6},N$88,N$89,N$90,N$91,N$92,N96)) -> 0.23839302 | G88: =IRR(CHOOSE({1,2,3,4,5,6},O$88,O$89,O$90,O$91,O$92,O96)) -> 0.23250603 | J88: Yr0 | K88: =-$C$7 -> -5065000 | L88: =-$C$7 -> -5065000 | M88: =-$C$7 -> -5065000 | N88: =-$C$7 -> -5065000 | O88: =-$C$7 -> -5065000
B89: 0.06 | C89: =IRR(CHOOSE({1,2,3,4,5,6},K$88,K$89,K$90,K$91,K$92,K97)) -> 0.22362664 | D89: =IRR(CHOOSE({1,2,3,4,5,6},L$88,L$89,L$90,L$91,L$92,L97)) -> 0.21758235 | E89: =IRR(CHOOSE({1,2,3,4,5,6},M$88,M$89,M$90,M$91,M$92,M97)) -> 0.21146935 | F89: =IRR(CHOOSE({1,2,3,4,5,6},N$88,N$89,N$90,N$91,N$92,N97)) -> 0.20529293 | G89: =IRR(CHOOSE({1,2,3,4,5,6},O$88,O$89,O$90,O$91,O$92,O97)) -> 0.19905838 | J89: Yr1 | K89: =$C$26-K$87-'Inputs & Drivers'!$I$31 -> 269127.96 | L89: =$C$26-L$87-'Inputs & Drivers'!$I$31 -> 236444.16 | M89: =$C$26-M$87-'Inputs & Drivers'!$I$31 -> 202993.97 | N89: =$C$26-N$87-'Inputs & Drivers'!$I$31 -> 168804.93 | O89: =$C$26-O$87-'Inputs & Drivers'!$I$31 -> 133905.48
B90: 0.065 | C90: =IRR(CHOOSE({1,2,3,4,5,6},K$88,K$89,K$90,K$91,K$92,K98)) -> 0.19344993 | D90: =IRR(CHOOSE({1,2,3,4,5,6},L$88,L$89,L$90,L$91,L$92,L98)) -> 0.18705119 | E90: =IRR(CHOOSE({1,2,3,4,5,6},M$88,M$89,M$90,M$91,M$92,M98)) -> 0.18057853 | F90: =IRR(CHOOSE({1,2,3,4,5,6},N$88,N$89,N$90,N$91,N$92,N98)) -> 0.17403749 | G90: =IRR(CHOOSE({1,2,3,4,5,6},O$88,O$89,O$90,O$91,O$92,O98)) -> 0.16743356 | J90: Yr2 | K90: =$D$26-K$87-'Inputs & Drivers'!$I$31 -> 292642.77 | L90: =$D$26-L$87-'Inputs & Drivers'!$I$31 -> 259958.97 | M90: =$D$26-M$87-'Inputs & Drivers'!$I$31 -> 226508.79 | N90: =$D$26-N$87-'Inputs & Drivers'!$I$31 -> 192319.74 | O90: =$D$26-O$87-'Inputs & Drivers'!$I$31 -> 157420.29
B91: 0.07 | C91: =IRR(CHOOSE({1,2,3,4,5,6},K$88,K$89,K$90,K$91,K$92,K99)) -> 0.16478198 | D91: =IRR(CHOOSE({1,2,3,4,5,6},L$88,L$89,L$90,L$91,L$92,L99)) -> 0.15800604 | E91: =IRR(CHOOSE({1,2,3,4,5,6},M$88,M$89,M$90,M$91,M$92,M99)) -> 0.15114973 | F91: =IRR(CHOOSE({1,2,3,4,5,6},N$88,N$89,N$90,N$91,N$92,N99)) -> 0.1442188 | G91: =IRR(CHOOSE({1,2,3,4,5,6},O$88,O$89,O$90,O$91,O$92,O99)) -> 0.13721896 | J91: Yr3 | K91: =$E$26-K$87-'Inputs & Drivers'!$I$31 -> 326516.66 | L91: =$E$26-L$87-'Inputs & Drivers'!$I$31 -> 293832.86 | M91: =$E$26-M$87-'Inputs & Drivers'!$I$31 -> 260382.68 | N91: =$E$26-N$87-'Inputs & Drivers'!$I$31 -> 226193.63 | O91: =$E$26-O$87-'Inputs & Drivers'!$I$31 -> 191294.18
B92: 0.075 | C92: =IRR(CHOOSE({1,2,3,4,5,6},K$88,K$89,K$90,K$91,K$92,K100)) -> 0.13730036 | D92: =IRR(CHOOSE({1,2,3,4,5,6},L$88,L$89,L$90,L$91,L$92,L100)) -> 0.13011987 | E92: =IRR(CHOOSE({1,2,3,4,5,6},M$88,M$89,M$90,M$91,M$92,M100)) -> 0.12285097 | F92: =IRR(CHOOSE({1,2,3,4,5,6},N$88,N$89,N$90,N$91,N$92,N100)) -> 0.11549958 | G92: =IRR(CHOOSE({1,2,3,4,5,6},O$88,O$89,O$90,O$91,O$92,O100)) -> 0.10807161 | J92: Yr4 | K92: =$F$26-K$87-'Inputs & Drivers'!$I$31 -> 369495.8 | L92: =$F$26-L$87-'Inputs & Drivers'!$I$31 -> 336812.01 | M92: =$F$26-M$87-'Inputs & Drivers'!$I$31 -> 303361.82 | N92: =$F$26-N$87-'Inputs & Drivers'!$I$31 -> 269172.78 | O92: =$F$26-O$87-'Inputs & Drivers'!$I$31 -> 234273.33
J93: Yr5 pre-exit | K93: =$G$26-K$87-'Inputs & Drivers'!$I$31 -> 415185.31 | L93: =$G$26-L$87-'Inputs & Drivers'!$I$31 -> 382501.52 | M93: =$G$26-M$87-'Inputs & Drivers'!$I$31 -> 349051.33 | N93: =$G$26-N$87-'Inputs & Drivers'!$I$31 -> 314862.29 | O93: =$G$26-O$87-'Inputs & Drivers'!$I$31 -> 279962.84
B94: GP / LP Waterfall | J94: Yr5 Loan Bal | K94: ='Inputs & Drivers'!$I$19+CUMPRINC(K86/12,'Inputs & Drivers'!$I$17*12,'Inputs & Drivers'!$I$19,1,60,0) -> 8098881.4 | L94: ='Inputs & Drivers'!$I$19+CUMPRINC(L86/12,'Inputs & Drivers'!$I$17*12,'Inputs & Drivers'!$I$19,1,60,0) -> 8160110.1 | M94: ='Inputs & Drivers'!$I$19+CUMPRINC(M86/12,'Inputs & Drivers'!$I$17*12,'Inputs & Drivers'!$I$19,1,60,0) -> 8218552.9 | N94: ='Inputs & Drivers'!$I$19+CUMPRINC(N86/12,'Inputs & Drivers'!$I$17*12,'Inputs & Drivers'!$I$19,1,60,0) -> 8274242.1 | O94: ='Inputs & Drivers'!$I$19+CUMPRINC(O86/12,'Inputs & Drivers'!$I$17*12,'Inputs & Drivers'!$I$19,1,60,0) -> 8327219.5
J95: Yr5 Total CF by Cap
B96: Equity Structure | J96: =$B88 -> 0.055 | K96: =K$93+($G$54/$J96)*(1-'Inputs & Drivers'!$I$29)-K$94 -> 13585878 | L96: =L$93+($G$54/$J96)*(1-'Inputs & Drivers'!$I$29)-L$94 -> 13491965 | M96: =M$93+($G$54/$J96)*(1-'Inputs & Drivers'!$I$29)-M$94 -> 13400072 | N96: =N$93+($G$54/$J96)*(1-'Inputs & Drivers'!$I$29)-N$94 -> 13310194 | O96: =O$93+($G$54/$J96)*(1-'Inputs & Drivers'!$I$29)-O$94 -> 13222317
C97: % | D97: Equity | J97: =$B89 -> 0.06 | K97: =K$93+($G$54/$J97)*(1-'Inputs & Drivers'!$I$29)-K$94 -> 11813413 | L97: =L$93+($G$54/$J97)*(1-'Inputs & Drivers'!$I$29)-L$94 -> 11719501 | M97: =M$93+($G$54/$J97)*(1-'Inputs & Drivers'!$I$29)-M$94 -> 11627608 | N97: =N$93+($G$54/$J97)*(1-'Inputs & Drivers'!$I$29)-N$94 -> 11537730 | O97: =O$93+($G$54/$J97)*(1-'Inputs & Drivers'!$I$29)-O$94 -> 11449853
B98: GP Equity | C98: ='Inputs & Drivers'!D79 -> 0.1 | D98: =C98*$C$7 -> 506500 | J98: =$B90 -> 0.065 | K98: =K$93+($G$54/$J98)*(1-'Inputs & Drivers'!$I$29)-K$94 -> 10313636 | L98: =L$93+($G$54/$J98)*(1-'Inputs & Drivers'!$I$29)-L$94 -> 10219723 | M98: =M$93+($G$54/$J98)*(1-'Inputs & Drivers'!$I$29)-M$94 -> 10127830 | N98: =N$93+($G$54/$J98)*(1-'Inputs & Drivers'!$I$29)-N$94 -> 10037952 | O98: =O$93+($G$54/$J98)*(1-'Inputs & Drivers'!$I$29)-O$94 -> 9950075.2
B99: LP Equity | C99: =1-C98 -> 0.9 | D99: =C99*$C$7 -> 4558500 | J99: =$B91 -> 0.07 | K99: =K$93+($G$54/$J99)*(1-'Inputs & Drivers'!$I$29)-K$94 -> 9028112.1 | L99: =L$93+($G$54/$J99)*(1-'Inputs & Drivers'!$I$29)-L$94 -> 8934199.6 | M99: =M$93+($G$54/$J99)*(1-'Inputs & Drivers'!$I$29)-M$94 -> 8842306.6 | N99: =N$93+($G$54/$J99)*(1-'Inputs & Drivers'!$I$29)-N$94 -> 8752428.3 | O99: =O$93+($G$54/$J99)*(1-'Inputs & Drivers'!$I$29)-O$94 -> 8664551.5
B100: Total Equity | C100: 1 | D100: =$C$7 -> 5065000 | J100: =$B92 -> 0.075 | K100: =K$93+($G$54/$J100)*(1-'Inputs & Drivers'!$I$29)-K$94 -> 7913991.5 | L100: =L$93+($G$54/$J100)*(1-'Inputs & Drivers'!$I$29)-L$94 -> 7820079 | M100: =M$93+($G$54/$J100)*(1-'Inputs & Drivers'!$I$29)-M$94 -> 7728186 | N100: =N$93+($G$54/$J100)*(1-'Inputs & Drivers'!$I$29)-N$94 -> 7638307.7 | O100: =O$93+($G$54/$J100)*(1-'Inputs & Drivers'!$I$29)-O$94 -> 7550430.9
B102: Preferred Return | C102: ='Inputs & Drivers'!D81 -> 0.08
B103: GP Promote (above pref) | C103: ='Inputs & Drivers'!D83 -> 0.25
B105: Annual Distribution Waterfall
C106: Year 1 | D106: Year 2 | E106: Year 3 | F106: Year 4 | G106: Year 5 | H106: Total
B107: Total Distributable Cash | C107: =C30 -> 202993.97 | D107: =D30 -> 226508.79 | E107: =E30 -> 260382.68 | F107: =F30 -> 303361.82 | G107: =G30+G59 -> 10847724 | H107: =SUM(C107:G107) -> 11840971
B109: Pref Accrual (8%) | C109: =$D$100*$C$102 -> 405200 | D109: =$D$100*$C$102 -> 405200 | E109: =$D$100*$C$102 -> 405200 | F109: =$D$100*$C$102 -> 405200 | G109: =$D$100*$C$102 -> 405200 | H109: =SUM(C109:G109) -> 2026000
B110: Cumulative Pref Owed | C110: =C109 -> 405200 | D110: =C110-C111+D109 -> 607406.03 | E110: =D110-D111+E109 -> 786097.24 | F110: =E110-E111+F109 -> 930914.57 | G110: =F110-F111+G109 -> 1032752.7
B111: Pref Paid | C111: =MIN(C110, MAX(C107,0)) -> 202993.97 | D111: =MIN(D110, MAX(D107,0)) -> 226508.79 | E111: =MIN(E110, MAX(E107,0)) -> 260382.68 | F111: =MIN(F110, MAX(F107,0)) -> 303361.82 | G111: =MIN(G110, MAX(G107,0)) -> 1032752.7 | H111: =SUM(C111:G111) -> 2026000
B112: Return of Capital | C112: =MIN(MAX(C107-C111,0), D100) -> 0 | D112: =MIN(MAX(D107-D111,0), D100-C112) -> 0 | E112: =MIN(MAX(E107-E111,0), D100-C112-D112) -> 0 | F112: =MIN(MAX(F107-F111,0), D100-C112-D112-E112) -> 0 | G112: =MIN(MAX(G107-G111,0), D100-C112-D112-E112-F112) -> 5065000 | H112: =SUM(C112:G112) -> 5065000
B113: Excess Cash Flow | C113: =MAX(C107-C111-C112,0) -> 0 | D113: =MAX(D107-D111-D112,0) -> 0 | E113: =MAX(E107-E111-E112,0) -> 0 | F113: =MAX(F107-F111-F112,0) -> 0 | G113: =MAX(G107-G111-G112,0) -> 4749970.8 | H113: =SUM(C113:G113) -> 4749970.8
B115: GP Distributions
B116: Pref (pro rata) | C116: =C111*$C$98 -> 20299.397 | D116: =D111*$C$98 -> 22650.879 | E116: =E111*$C$98 -> 26038.268 | F116: =F111*$C$98 -> 30336.182 | G116: =G111*$C$98 -> 103275.27 | H116: =SUM(C116:G116) -> 202600
B117: Return of Capital | C117: =C112*$C$98 -> 0 | D117: =D112*$C$98 -> 0 | E117: =E112*$C$98 -> 0 | F117: =F112*$C$98 -> 0 | G117: =G112*$C$98 -> 506500 | H117: =SUM(C117:G117) -> 506500
B118: Promote (25% of excess) | C118: =C113*$C$103 -> 0 | D118: =D113*$C$103 -> 0 | E118: =E113*$C$103 -> 0 | F118: =F113*$C$103 -> 0 | G118: =G113*$C$103 -> 1187492.7 | H118: =SUM(C118:G118) -> 1187492.7
B119: Pro Rata Share (excess) | C119: =C113*(1-$C$103)*$C$98 -> 0 | D119: =D113*(1-$C$103)*$C$98 -> 0 | E119: =E113*(1-$C$103)*$C$98 -> 0 | F119: =F113*(1-$C$103)*$C$98 -> 0 | G119: =G113*(1-$C$103)*$C$98 -> 356247.81 | H119: =SUM(C119:G119) -> 356247.81
B120: Total GP Distributions | C120: =SUM(C116:C119) -> 20299.397 | D120: =SUM(D116:D119) -> 22650.879 | E120: =SUM(E116:E119) -> 26038.268 | F120: =SUM(F116:F119) -> 30336.182 | G120: =SUM(G116:G119) -> 2153515.8 | H120: =SUM(H116:H119) -> 2252840.5
...

Sheet Claude Log
A1: Turn # | B1: Date | C1: User Request | D1: Action Taken | E1: Details | F1: Outcome
